Workbook

Sheet Luchenza
A1: SOUTHERN REGION WATER BOARD
A3: MONTHLY REPORTS - 2026/2027
A4: MULANJE ZONE
A5: MULANJE ZONE
A7: PARAMETERS | C7: UNITS | D7: APRIL | E7: MAY | F7: JUNE | G7: JULY | H7: AUGUST | I7: SEPTEMBER | J7: OCTOBER | K7: NOVEMBER | L7: DECEMBER | M7: JANUARY | N7: FEBRUARY | O7: MARCH | P7: TOTALS
A8: PRODUCTION
A9: Volume Produced | C9: m3 | D9: 13271 | E9: 16000 | F9: 16444 | P9: =SUM(D9:O9) -> 45715
A10: REVENUE WATER - POSTPAID
A11: Volume Billed Individuals | C11: m3 | D11: 4244 | E11: 4852 | F11: 7133 | P11: =SUM(D11:O11) -> 16229
A12: Volume Billed CWPs | C12: m3 | D12: 8 | E12: 27 | F12: 31 | P12: =SUM(D12:O12) -> 66
A13: Volume Billed Institutions | C13: m3 | D13: 8 | E13: 12 | F13: 12 | P13: =SUM(D13:O13) -> 32
A14: Volume Billed Commercial/Industrial | C14: m3 | D14: 23 | E14: 25 | F14: 19 | P14: =SUM(D14:O14) -> 67
A15: Total Volume Billed Post Paid | C15: m3 | D15: =SUM(D11:D14) -> 4283 | E15: =SUM(E11:E14) -> 4916 | F15: =SUM(F11:F14) -> 7195 | G15: =SUM(G11:G14) -> 0 | H15: =SUM(H11:H14) -> 0 | I15: =SUM(I11:I14) -> 0 | J15: =SUM(J11:J14) -> 0 | K15: =SUM(K11:K14) -> 0 | ... P15: =SUM(P11:P14) -> 16394
A16: REVENUE WATER - PREPAID
A17: Individuals | C17: m3 | D17: 4714 | E17: 5402 | F17: 4013 | P17: =SUM(D17:O17) -> 14129
A18: CWPs | C18: m3 | D18: 186 | E18: 246 | F18: 209 | P18: =SUM(D18:O18) -> 641
A19: Institutions | C19: m3 | D19: 167 | E19: 228 | F19: 137 | P19: =SUM(D19:O19) -> 532
A20: Commercial/Industrial | C20: m3 | D20: 203 | E20: 366 | F20: 220 | P20: =SUM(D20:O20) -> 789
A21: Total Volume Prepaid | C21: m3 | D21: =SUM(D17:D20) -> 5270 | E21: =SUM(E17:E20) -> 6242 | F21: =SUM(F17:F20) -> 4579 | G21: =SUM(G17:G20) -> 0 | H21: =SUM(H17:H20) -> 0 | I21: =SUM(I17:I20) -> 0 | J21: =SUM(J17:J20) -> 0 | K21: =SUM(K17:K20) -> 0 | ... P21: =SUM(P17:P20) -> 16091
A22: TOTAL REVENUE WATER | C22: m3 | D22: =D21+D15 -> 9553 | E22: =E21+E15 -> 11158 | F22: =F21+F15 -> 11774 | G22: =G21+G15 -> 0 | H22: =H21+H15 -> 0 | I22: =I21+I15 -> 0 | J22: =J21+J15 -> 0 | K22: =K21+K15 -> 0 | ... P22: =P21+P15 -> 32485
A24: Non-Revenue Water (NRW) | B24: Volume | C24: m3 | D24: =D9-D22 -> 3718 | E24: =E9-E22 -> 4842 | F24: =F9-F22 -> 4670 | G24: =G9-G22 -> 0 | H24: =H9-H22 -> 0 | I24: =I9-I22 -> 0 | J24: =J9-J22 -> 0 | K24: =K9-K22 -> 0 | ... P24: =P9-P22 -> 13230
B25: Percentage | C25: % | D25: =D24/D9 -> 0.28015975 | E25: =E24/E9 -> 0.302625 | F25: =F24/F9 -> 0.28399416 | G25: =G24/G9 -> #DIV/0! | H25: =H24/H9 -> #DIV/0! | I25: =I24/I9 -> #DIV/0! | J25: =J24/J9 -> #DIV/0! | K25: =K24/K9 -> #DIV/0! | ... P25: =P24/P9 -> 0.28940173
A26: OPERATING EXPENSES
A27: Chemicals
A28: Chemical | B28: Rate(MK/kg)
A29: Chlorine | B29: 5111.67 | C29: kg | D29: 35 | E29: 41 | F29: 42 | P29: =SUM(D29:O29) -> 118
C30: kg/mg litre | D30: =D29/(D9/1000) -> 2.6373295 | E30: =E29/(E9/1000) -> 2.5625 | F30: =F29/(F9/1000) -> 2.5541231 | G30: =G29/(G9/1000) -> #DIV/0! | H30: =H29/(H9/1000) -> #DIV/0! | I30: =I29/(I9/1000) -> #DIV/0! | J30: =J29/(J9/1000) -> #DIV/0! | K30: =K29/(K9/1000) -> #DIV/0! | ... N30: =N29/(N9/1000) -> #DIV/0! | P30: =P29/(P9/1000) -> 2.5812097
A31: Aluminium sulphate | B31: 1537 | C31: kg | P31: =SUM(D31:O31) -> 0
C32: kg/mg litre | D32: =D31/(D9/1000) -> 0 | E32: =E31/(E9/1000) -> 0 | F32: =F31/(F9/1000) -> 0 | G32: =G31/(G9/1000) -> #DIV/0! | H32: =H31/(H9/1000) -> #DIV/0! | I32: =I31/(I9/1000) -> #DIV/0! | J32: =J31/(J9/1000) -> #DIV/0! | K32: =K31/(K9/1000) -> #DIV/0! | ... N32: =N31/(N9/1000) -> #DIV/0! | P32: =P31/(P9/1000) -> 0
A33: Soda | B33: 1781.02 | C33: kg | P33: =SUM(D33:O33) -> 0
C34: kg/mg litre | D34: =D33/(D9/1000) -> 0 | E34: =E33/(E9/1000) -> 0 | F34: =F33/(F9/1000) -> 0 | G34: =G33/(G9/1000) -> #DIV/0! | H34: =H33/(H9/1000) -> #DIV/0! | I34: =I33/(I9/1000) -> #DIV/0! | J34: =J33/(J9/1000) -> #DIV/0! | K34: =K33/(K9/1000) -> #DIV/0! | ... N34: =N33/(N9/1000) -> #DIV/0! | P34: =P33/(P9/1000) -> 0
A35: Algae floc | B35: 5979.95 | C35: litres
C36: litres/mg litre
A37: Sud floc | B37: 5403.75 | C37: litres | P37: =SUM(D37:O37) -> 0
C38: litres/mg litre | D38: =D37/(D9/1000) -> 0 | E38: =E37/(E9/1000) -> 0 | F38: =F37/(F9/1000) -> 0 | G38: =G37/(G9/1000) -> #DIV/0! | H38: =H37/(H9/1000) -> #DIV/0! | I38: =I37/(I9/1000) -> #DIV/0! | J38: =J37/(J9/1000) -> #DIV/0! | K38: =K37/(K9/1000) -> #DIV/0! | ... N38: =N37/(N9/1000) -> #DIV/0! | P38: =P37/(P9/1000) -> 0
A39: Potasium permanganate | B39: 1950 | C39: kg | P39: =SUM(D39:O39) -> 0
C40: kg/mg litre | D40: =D39/(D9/1000) -> 0 | E40: =E39/(E9/1000) -> 0 | F40: =F39/(F9/1000) -> 0 | G40: =G39/(G9/1000) -> #DIV/0! | H40: =H39/(H9/1000) -> #DIV/0! | I40: =I39/(I9/1000) -> #DIV/0! | J40: =J39/(J9/1000) -> #DIV/0! | K40: =K39/(K9/1000) -> #DIV/0! | ... N40: =N39/(N9/1000) -> #DIV/0! | P40: =P39/(P9/1000) -> 0
A41: Cost of Chemicals | C41: Mk | D41: =(D29*$B29)+(D31*$B31)+(D33*$B33)+(D35*$B35)+(D37*$B37)+(D39*$B39) -> 178908.45 | E41: =(E29*$B29)+(E31*$B31)+(E33*$B33)+(E35*$B35)+(E37*$B37)+(E39*$B39) -> 209578.47 | F41: =(F29*$B29)+(F31*$B31)+(F33*$B33)+(F35*$B35)+(F37*$B37)+(F39*$B39) -> 214690.14 | G41: =(G29*$B29)+(G31*$B31)+(G33*$B33)+(G35*$B35)+(G37*$B37)+(G39*$B39) -> 0 | H41: =(H29*$B29)+(H31*$B31)+(H33*$B33)+(H35*$B35)+(H37*$B37)+(H39*$B39) -> 0 | I41: =(I29*$B29)+(I31*$B31)+(I33*$B33)+(I35*$B35)+(I37*$B37)+(I39*$B39) -> 0 | J41: =(J29*$B29)+(J31*$B31)+(J33*$B33)+(J35*$B35)+(J37*$B37)+(J39*$B39) -> 0 | K41: =(K29*$B29)+(K31*$B31)+(K33*$B33)+(K35*$B35)+(K37*$B37)+(K39*$B39) -> 0 | ... O41: =(O29*$B29)+(O31*$B31)+(O33*$B33)+(O35*$B35)+(O37*$B37)+(O39*$B39) -> 0 | P41: =SUM(D41:O41) -> 603177.06
A42: Cost/vol. Produced (chemicals) | C42: Mk/m3 | D42: =D41/D9 -> 13.481158 | E42: =E41/E9 -> 13.098654 | F42: =F41/F9 -> 13.055834 | G42: =G41/G9 -> #DIV/0! | H42: =H41/H9 -> #DIV/0! | I42: =I41/I9 -> #DIV/0! | J42: =J41/J9 -> #DIV/0! | K42: =K41/K9 -> #DIV/0! | ... P42: =P41/P9 -> 13.194292
A43: Power
A44: Power Usage | C44: Kw | D44: 8581.27 | E44: 8396 | F44: 7429.71 | P44: =SUM(D44:O44) -> 24406.98
A45: Power/ Vol. Produced | C45: Kw/m3 | D45: =D44/D9 -> 0.64661819 | E45: =E44/E9 -> 0.52475 | F45: =F44/F9 -> 0.4518189 | G45: =G44/G9 -> #DIV/0! | H45: =H44/H9 -> #DIV/0! | I45: =I44/I9 -> #DIV/0! | J45: =J44/J9 -> #DIV/0! | K45: =K44/K9 -> #DIV/0! | ... N45: =N44/N9 -> #DIV/0! | P45: =P44/P9 -> 0.53389435
A46: Cost of Power | C46: Mk | D46: =333.87*D44 -> 2865028.6 | E46: =333.87*E44 -> 2803172.5 | F46: =333.87*F44 -> 2480557.3 | G46: =333.87*G44 -> 0 | H46: =333.87*H44 -> 0 | I46: =333.87*I44 -> 0 | J46: =333.87*J44 -> 0 | K46: =333.87*K44 -> 0 | ... O46: =333.87*O44 -> 0 | P46: =SUM(D46:O46) -> 8148758.4
A47: Cost/vol. Produced | C47: Mk/m3 | D47: =D46/D9 -> 215.88642 | E47: =E46/E9 -> 175.19828 | F47: =F46/F9 -> 150.84878 | G47: =G46/G9 -> #DIV/0! | H47: =H46/H9 -> #DIV/0! | I47: =I46/I9 -> #DIV/0! | J47: =J46/J9 -> #DIV/0! | K47: =K46/K9 -> #DIV/0! | ... N47: =N46/N9 -> #DIV/0! | P47: =P46/P9 -> 178.25131
A48: Plant and Vehicle Maintenance
A49: Distances covered | C49: km | P49: =SUM(D49:O49) -> 0
A50: Fuel Used (litres) | C50: litres | D50: 97 | E50: 105 | F50: 69 | P50: =SUM(D50:O50) -> 271
A51: Cost of fuel | C51: Mk | D51: =6687*D50 -> 648639 | E51: =6687*E50 -> 702135 | F51: =6687*F50 -> 461403 | G51: =6687*G50 -> 0 | H51: =6687*H50 -> 0 | I51: =6687*I50 -> 0 | J51: =6687*J50 -> 0 | K51: =6687*K50 -> 0 | ... O51: =6687*O50 -> 0 | P51: =SUM(D51:O51) -> 1812177
A52: Maintenance | C52: Mk | P52: =SUM(D52:O52) -> 0
A53: Salaries and Wages
A54: Staff Costs | C54: MK | D54: 8457030.1 | E54: 9088969.9 | F54: 9088969.9 | P54: =SUM(D54:O54) -> 26634970
A55: Wages | C55: MK | D55: 2714571 | E55: 2585701.3 | F55: 2165156.5 | P55: =SUM(D55:O55) -> 7465428.8
A56: Other Overhead Costs | C56: MK | D56: 4604357.2 | E56: 1978316.5 | F56: 1840868.4 | P56: =SUM(D56:O56) -> 8423542.2
A57: Operating Costs
A58: Total Operating Costs | C58: MK | D58: =D41+D46+D51+D52+D54+D55+D56 -> 19468534 | E58: =E41+E46+E51+E52+E54+E55+E56 -> 17367874 | F58: =F41+F46+F51+F52+F54+F55+F56 -> 16251645 | G58: =G41+G46+G51+G52+G54+G55+G56 -> 0 | H58: =H41+H46+H51+H52+H54+H55+H56 -> 0 | I58: =I41+I46+I51+I52+I54+I55+I56 -> 0 | J58: =J41+J46+J51+J52+J54+J55+J56 -> 0 | K58: =K41+K46+K51+K52+K54+K55+K56 -> 0 | ... N58: =N41+N46+N51+N52+N54+N55+N56 -> 0 | P58: =SUM(D58:O58) -> 53088053
A59: Cost/Vol. Produced | C59: Mk/m3 | D59: =D58/D9 -> 1466.9983 | E59: =E58/E9 -> 1085.4921 | F59: =F58/F9 -> 988.30244 | G59: =G58/G9 -> #DIV/0! | H59: =H58/H9 -> #DIV/0! | I59: =I58/I9 -> #DIV/0! | J59: =J58/J9 -> #DIV/0! | K59: =K58/K9 -> #DIV/0! | ... N59: =N58/N9 -> #DIV/0! | P59: =P58/P9 -> 1161.283
A60: Cost/Vol. Billed | C60: Mk/m3 | D60: =D58/D22 -> 2037.9498 | E60: =E58/E22 -> 1556.54 | F60: =F58/F22 -> 1380.2994 | G60: =G58/G22 -> #DIV/0! | H60: =H58/H22 -> #DIV/0! | I60: =I58/I22 -> #DIV/0! | J60: =J58/J22 -> #DIV/0! | K60: =K58/K22 -> #DIV/0! | ... N60: =N58/N22 -> #DIV/0! | P60: =P58/P22 -> 1634.2328
A61: Permanent Staff Employed | C61: No | D61: 7 | E61: 7 | F61: 7 | P61: =O61 -> 0
A62: Staff/Vol.1000m3 of Volume Produced/hour (12 hour day) | C62: No/1000m3 | D62: =(D61*1000*31)/D9 -> 16.351443 | E62: =(E61*1000*31)/E9 -> 13.5625 | F62: =(F61*1000*31)/F9 -> 13.196303 | G62: =(G61*1000*31)/G9 -> #DIV/0! | H62: =(H61*1000*31)/H9 -> #DIV/0! | I62: =(I61*1000*31)/I9 -> #DIV/0! | J62: =(J61*1000*31)/J9 -> #DIV/0! | K62: =(K61*1000*31)/K9 -> #DIV/0! | ... N62: =(N61*1000*31)/N9 -> #DIV/0! | P62: =(P61*1000*31)/P9 -> 0
A63: Temporary Staff Employed | C63: No | D63: 17 | E63: 17 | F63: 17 | P63: =SUM(D63:O63) -> 51
A65: Water Connections and Disconnections
A66: New Individual Water Connections | B66: Brought Forward | C66: No | D66: 38 | E66: =D71 -> 50 | F66: =E71 -> 42 | G66: =F71 -> 43 | H66: =G71 -> 43 | I66: =H71 -> 43 | J66: =I71 -> 43 | K66: =J71 -> 43 | L66: =K71 -> 43 | ... N66: =M71 -> 43 | P66: =D66 -> 38
B67: Applied this Month | C67: No | D67: 22 | E67: 13 | F67: 19 | P67: =SUM(D67:O67) -> 54
B68: Done this Month Postpaid | C68: No | F68: 5 | P68: =SUM(D68:O68) -> 5
B69: Done this Month Prepaid | C69: No | D69: 10 | E69: 21 | F69: 13 | P69: =SUM(D69:O69) -> 44
B70: Total Done | C70: No | D70: =D68+D69 -> 10 | E70: =E68+E69 -> 21 | F70: =F68+F69 -> 18 | J70: =J68+J69 -> 0 | K70: =K68+K69 -> 0 | L70: =L68+L69 -> 0 | P70: =P68+P69 -> 49
B71: Carried Forward | C71: No | D71: =D66+D67-D70 -> 50 | E71: =E66+E67-E70 -> 42 | F71: =F66+F67-F70 -> 43 | G71: =G66+G67-G70 -> 43 | H71: =H66+H67-H70 -> 43 | I71: =I66+I67-I70 -> 43 | J71: =J66+J67-J70 -> 43 | K71: =K66+K67-K70 -> 43 | ... N71: =N66+N67-N70 -> 43 | P71: =P66+P67-P70 -> 43
A72: New Institutional Water Connections | B72: Brought Forward | C72: No | E72: =D77 -> 0 | F72: =E77 -> 0 | G72: =F77 -> 0 | H72: =G77 -> 0 | I72: =H77 -> 0 | P72: =D72 -> 0
B73: Applied this Month | C73: No | P73: =SUM(D73:O73) -> 0
B74: Done this Month Postpaid | C74: No | P74: =SUM(D74:O74) -> 0
B75: Done this Month Prepaid | C75: No | P75: =SUM(D75:O75) -> 0
B76: Total Done | C76: No | D76: =D74+D75 -> 0 | E76: =E74+E75 -> 0 | F76: =F74+F75 -> 0 | G76: =G74+G75 -> 0 | H76: =H74+H75 -> 0 | I76: =I74+I75 -> 0 | J76: =J74+J75 -> 0 | K76: =K74+K75 -> 0 | M76: =M74+M75 -> 0 | N76: =N74+N75 -> 0 | P76: =P74+P75 -> 0
B77: Carried Forward | C77: No | D77: =D72+D73-D76 -> 0 | E77: =E72+E73-E76 -> 0 | F77: =F72+F73-F76 -> 0 | G77: =G72+G73-G76 -> 0 | H77: =H72+H73-H76 -> 0 | I77: =I72+I73-I76 -> 0 | J77: =J72+J73-J76 -> 0 | K77: =K72+K73-K76 -> 0 | ... N77: =N72+N73-N76 -> 0 | P77: =P72+P73-P76 -> 0
A78: New Commercial/Industrial Water Connections | B78: Brought Forward | C78: No | E78: =D83 -> 0 | F78: =E83 -> 0 | G78: =F83 -> 0 | H78: =G83 -> 0 | I78: =H83 -> 0 | J78: =I83 -> 0 | K78: =J83 -> 0 | L78: =K83 -> 0 | ... N78: =M83 -> 0 | P78: =D78 -> 0
B79: Applied this Month | C79: No | P79: =SUM(D79:O79) -> 0
B80: Done this Month Postpaid | C80: No | P80: =SUM(D80:O80) -> 0
B81: Done this Month Prepaid | C81: No | P81: =SUM(D81:O81) -> 0
B82: Total Done | C82: No | D82: =D81+D80 -> 0 | E82: =E81+E80 -> 0 | F82: =F81+F80 -> 0 | G82: =G81+G80 -> 0 | H82: =H81+H80 -> 0 | I82: =I80+I81 -> 0 | J82: =J80+J81 -> 0 | K82: =K80+K81 -> 0 | M82: =M81+M80 -> 0 | N82: =N81+N80 -> 0 | P82: =P81+P80 -> 0
B83: Carried Forward | C83: No | D83: =D78+D79-D82 -> 0 | E83: =E78+E79-E82 -> 0 | F83: =F78+F79-F82 -> 0 | G83: =G78+G79-G82 -> 0 | H83: =H78+H79-H82 -> 0 | I83: =I78+I79-I82 -> 0 | J83: =J78+J79-J82 -> 0 | K83: =K78+K79-K82 -> 0 | ... N83: =N78+N79-N82 -> 0 | P83: =P78+P79-P82 -> 0
A84: New CWP | B84: Brought Forward | C84: No | E84: =D89 -> 0 | F84: =E89 -> 0 | G84: =F89 -> 0 | H84: =G89 -> 0 | P84: =D84 -> 0
B85: Applied this Month | C85: No | P85: =SUM(D85:O85) -> 0
B86: Done this Month Postpaid | C86: No | P86: =SUM(D86:O86) -> 0
B87: Done this Month Prepaid | C87: No | P87: =SUM(D87:O87) -> 0
B88: Total Done | C88: No | D88: =D86+D87 -> 0 | E88: =E86+E87 -> 0 | F88: =F86+F87 -> 0 | G88: =G86+G87 -> 0 | H88: =H86+H87 -> 0 | I88: =I86+I87 -> 0 | J88: =J86+J87 -> 0 | K88: =K86+K87 -> 0 | ... N88: =N86+N87 -> 0 | P88: =SUM(D88:O88) -> 0
B89: Carried Forward | C89: No | D89: =D84+D85-D88 -> 0 | E89: =E84+E85-E88 -> 0 | F89: =F84+F85-F88 -> 0 | G89: =G84+G85-G88 -> 0 | H89: =H84+H85-H88 -> 0 | I89: =I84+I85-I88 -> 0 | J89: =J84+J85-J88 -> 0 | K89: =K84+K85-K88 -> 0 | ... N89: =N84+N85-N88 -> 0 | P89: =P84+P85-P86-P87 -> 0
A90: Aggregated New Water connections | B90: Brought Forward | C90: No | D90: =D66+D72+D78+D84 -> 38 | E90: =E66+E72+E78+E84 -> 50 | F90: =F66+F72+F78+F84 -> 42 | G90: =G66+G72+G78+G84 -> 43 | H90: =H66+H72+H78+H84 -> 43 | I90: =I66+I72+I78+I84 -> 43 | J90: =J66+J72+J78+J84 -> 43 | K90: =K66+K72+K78+K84 -> 43 | ... N90: =N66+N72+N78+N84 -> 43 | P90: =D90 -> 38
B91: Applied this Month | C91: No | D91: =D67+D73+D79+D85 -> 22 | E91: =E67+E73+E79+E85 -> 13 | F91: =F67+F73+F79+F85 -> 19 | G91: =G67+G73+G79+G85 -> 0 | H91: =H67+H73+H79+H85 -> 0 | I91: =I67+I73+I79+I85 -> 0 | J91: =J67+J73+J79+J85 -> 0 | K91: =K67+K73+K79+K85 -> 0 | ... N91: =N67+N73+N79+N85 -> 0 | P91: =SUM(D91:O91) -> 54
B92: Done this Month Postpaid | C92: No | D92: =D68+D74+D80+D86 -> 0 | E92: =E68+E74+E80+E86 -> 0 | F92: =F68+F74+F80+F86 -> 5 | G92: =G68+G74+G80+G86 -> 0 | H92: =H68+H74+H80+H86 -> 0 | I92: =I68+I74+I80+I86 -> 0 | J92: =J68+J74+J80+J86 -> 0 | K92: =K68+K74+K80+K86 -> 0 | ... N92: =N68+N74+N80+N86 -> 0 | P92: =SUM(D92:O92) -> 5
B93: Done this Month Prepaid | D93: =D69+D75+D81+D87 -> 10 | E93: =E69+E75+E81+E87 -> 21 | F93: =F69+F75+F81+F87 -> 13 | G93: =G69+G75+G81+G87 -> 0 | H93: =H69+H75+H81+H87 -> 0 | I93: =I69+I75+I81+I87 -> 0 | J93: =J69+J75+J81+J87 -> 0 | K93: =K69+K75+K81+K87 -> 0 | ... N93: =N69+N75+N81+N87 -> 0 | P93: =SUM(D93:O93) -> 44
B94: Total Done | C94: No | D94: =D93+D92 -> 10 | E94: =E93+E92 -> 21 | F94: =F93+F92 -> 18 | G94: =G93+G92 -> 0 | H94: =H93+H92 -> 0 | I94: =I93+I92 -> 0 | J94: =J93+J92 -> 0 | K94: =K93+K92 -> 0 | ... N94: =N93+N92 -> 0 | P94: =P93+P92 -> 49
B95: Carried Forward | C95: No | D95: =D90+D91-D94 -> 50 | E95: =E90+E91-E94 -> 42 | F95: =F90+F91-F94 -> 43 | G95: =G90+G91-G94 -> 43 | H95: =H90+H91-H94 -> 43 | I95: =I90+I91-I94 -> 43 | J95: =J90+J91-J94 -> 43 | K95: =K90+K91-K94 -> 43 | ... N95: =N90+N91-N94 -> 43 | P95: =P90+P91-P94 -> 43
A97: Prepaid Metering
A98: Prepaid Meters Installed | C98: No | D98: 10 | E98: 21 | F98: 20 | P98: =SUM(D98:O98) -> 51
A100: Active and Disconnected Accounts
A101: Disconnected Individual Accounts | C101: No | D101: 868 | E101: 844 | F101: 820 | P101: =O101 -> 0
A102: Disconnected institutional Accounts | C102: No | D102: 11 | E102: 7 | F102: 7 | P102: =O102 -> 0
A103: Disconnected Commercial/Industrial Accounts | C103: No | D103: 17 | E103: 17 | F103: 17 | P103: =O103 -> 0
A104: Disconnected CWP | C104: No | D104: 23 | E104: 23 | F104: 23 | P104: =O104 -> 0
A105: Total Disconnected Accounts | C105: No | D105: =SUM(D101:D104) -> 919 | E105: =SUM(E101:E104) -> 891 | F105: =SUM(F101:F104) -> 867 | G105: =SUM(G101:G104) -> 0 | H105: =SUM(H101:H104) -> 0 | I105: =SUM(I101:I104) -> 0 | J105: =SUM(J101:J104) -> 0 | K105: =SUM(K101:K104) -> 0 | ... O105: =SUM(O101:O104) -> 0 | P105: =O105 -> 0
A106: Postpaid Consumers
...

Sheet Mulanje
A1: SOUTHERN REGION WATER BOARD
A3: MONTHLY REPORTS - 2026/2027
A4: MULANJE ZONE
A5: MULANJE ZONE
A7: PARAMETERS | C7: UNITS | D7: APRIL | E7: MAY | F7: JUNE | G7: JULY | H7: AUGUST | I7: SEPTEMBER | J7: OCTOBER | K7: NOVEMBER | L7: DECEMBER | M7: JANUARY | N7: FEBRUARY | O7: MARCH | P7: TOTALS
A8: PRODUCTION
A9: Volume Produced | C9: m3 | D9: 43194 | E9: 47903 | F9: 48675 | P9: =SUM(D9:O9) -> 139772
A10: REVENUE WATER - POSTPAID
A11: Volume Billed Individuals | C11: m3 | D11: 15725 | E11: 15973 | F11: 18757 | P11: =SUM(D11:O11) -> 50455
A12: Volume Billed CWPs | C12: m3 | D12: 813 | E12: 877 | F12: 1050 | P12: =SUM(D12:O12) -> 2740
A13: Volume Billed Institutions | C13: m3 | D13: 117 | E13: 85 | F13: 161 | P13: =SUM(D13:O13) -> 363
A14: Volume Billed Commercial/Industrial | C14: m3 | D14: 113 | E14: 240 | F14: 219 | P14: =SUM(D14:O14) -> 572
A15: Total Volume Billed Post Paid | C15: m3 | D15: =SUM(D11:D14) -> 16768 | E15: =SUM(E11:E14) -> 17175 | F15: =SUM(F11:F14) -> 20187 | G15: =SUM(G11:G14) -> 0 | H15: =SUM(H11:H14) -> 0 | I15: =SUM(I11:I14) -> 0 | J15: =SUM(J11:J14) -> 0 | K15: =SUM(K11:K14) -> 0 | ... P15: =SUM(P11:P14) -> 54130
A16: REVENUE WATER - PREPAID
A17: Individuals | C17: m3 | D17: 7965.53 | E17: 8716.5 | F17: 8365.2 | P17: =SUM(D17:O17) -> 25047.23
A18: CWPs | C18: m3 | P18: =SUM(D18:O18) -> 0
A19: Institutions | C19: m3 | D19: 5415.63 | E19: 6954.9 | F19: 5241.8 | P19: =SUM(D19:O19) -> 17612.33
A20: Commercial/Industrial | C20: m3 | D20: 714 | E20: 989 | F20: 916 | P20: =SUM(D20:O20) -> 2619
A21: Total Volume Prepaid | C21: m3 | D21: =SUM(D17:D20) -> 14095.16 | E21: =SUM(E17:E20) -> 16660.4 | F21: =SUM(F17:F20) -> 14523 | G21: =SUM(G17:G20) -> 0 | H21: =SUM(H17:H20) -> 0 | I21: =SUM(I17:I20) -> 0 | J21: =SUM(J17:J20) -> 0 | K21: =SUM(K17:K20) -> 0 | ... P21: =SUM(P17:P20) -> 45278.56
A22: TOTAL REVENUE WATER | C22: m3 | D22: =D21+D15 -> 30863.16 | E22: =E21+E15 -> 33835.4 | F22: =F21+F15 -> 34710 | G22: =G21+G15 -> 0 | H22: =H21+H15 -> 0 | I22: =I21+I15 -> 0 | J22: =J21+J15 -> 0 | K22: =K21+K15 -> 0 | ... P22: =P21+P15 -> 99408.56
A24: Non-Revenue Water (NRW) | B24: Volume | C24: m3 | D24: =D9-D22 -> 12330.84 | E24: =E9-E22 -> 14067.6 | F24: =F9-F22 -> 13965 | G24: =G9-G22 -> 0 | H24: =H9-H22 -> 0 | I24: =I9-I22 -> 0 | J24: =J9-J22 -> 0 | K24: =K9-K22 -> 0 | ... P24: =P9-P22 -> 40363.44
B25: Percentage | C25: % | D25: =D24/D9 -> 0.28547576 | E25: =E24/E9 -> 0.29366846 | F25: =F24/F9 -> 0.28690293 | G25: =G24/G9 -> #DIV/0! | H25: =H24/H9 -> #DIV/0! | I25: =I24/I9 -> #DIV/0! | J25: =J24/J9 -> #DIV/0! | K25: =K24/K9 -> #DIV/0! | ... P25: =P24/P9 -> 0.28878059
A26: OPERATING EXPENSES
A27: Chemicals
A28: Chemical | B28: Rate(MK/kg)
A29: Chlorine | B29: 5111.67 | C29: kg | D29: 90 | E29: 94 | F29: 97 | P29: =SUM(D29:O29) -> 281
C30: kg/mg litre | D30: =D29/(D9/1000) -> 2.0836227 | E30: =E29/(E9/1000) -> 1.9622988 | F30: =F29/(F9/1000) -> 1.9928095 | G30: =G29/(G9/1000) -> #DIV/0! | H30: =H29/(H9/1000) -> #DIV/0! | I30: =I29/(I9/1000) -> #DIV/0! | J30: =J29/(J9/1000) -> #DIV/0! | K30: =K29/(K9/1000) -> #DIV/0! | ... N30: =N29/(N9/1000) -> #DIV/0! | P30: =P29/(P9/1000) -> 2.010417
A31: Aluminium sulphate | B31: 1537 | C31: kg | P31: =SUM(D31:O31) -> 0
C32: kg/mg litre | D32: =D31/(D9/1000) -> 0 | E32: =E31/(E9/1000) -> 0 | F32: =F31/(F9/1000) -> 0 | G32: =G31/(G9/1000) -> #DIV/0! | H32: =H31/(H9/1000) -> #DIV/0! | I32: =I31/(I9/1000) -> #DIV/0! | J32: =J31/(J9/1000) -> #DIV/0! | K32: =K31/(K9/1000) -> #DIV/0! | ... N32: =N31/(N9/1000) -> #DIV/0! | P32: =P31/(P9/1000) -> 0
A33: Soda | B33: 1781.02 | C33: kg | P33: =SUM(D33:O33) -> 0
C34: kg/mg litre | D34: =D33/(D9/1000) -> 0 | E34: =E33/(E9/1000) -> 0 | F34: =F33/(F9/1000) -> 0 | G34: =G33/(G9/1000) -> #DIV/0! | H34: =H33/(H9/1000) -> #DIV/0! | I34: =I33/(I9/1000) -> #DIV/0! | J34: =J33/(J9/1000) -> #DIV/0! | K34: =K33/(K9/1000) -> #DIV/0! | ... N34: =N33/(N9/1000) -> #DIV/0! | P34: =P33/(P9/1000) -> 0
A35: Algae floc | B35: 5979.95 | C35: litres
C36: litres/mg litre
A37: Sud floc | B37: 5403.75 | C37: litres | P37: =SUM(D37:O37) -> 0
C38: litres/mg litre | D38: =D37/(D9/1000) -> 0 | E38: =E37/(E9/1000) -> 0 | F38: =F37/(F9/1000) -> 0 | G38: =G37/(G9/1000) -> #DIV/0! | H38: =H37/(H9/1000) -> #DIV/0! | I38: =I37/(I9/1000) -> #DIV/0! | J38: =J37/(J9/1000) -> #DIV/0! | K38: =K37/(K9/1000) -> #DIV/0! | ... N38: =N37/(N9/1000) -> #DIV/0! | P38: =P37/(P9/1000) -> 0
A39: Potasium permanganate | B39: 1950 | C39: kg | P39: =SUM(D39:O39) -> 0
C40: kg/mg litre | D40: =D39/(D9/1000) -> 0 | E40: =E39/(E9/1000) -> 0 | F40: =F39/(F9/1000) -> 0 | G40: =G39/(G9/1000) -> #DIV/0! | H40: =H39/(H9/1000) -> #DIV/0! | I40: =I39/(I9/1000) -> #DIV/0! | J40: =J39/(J9/1000) -> #DIV/0! | K40: =K39/(K9/1000) -> #DIV/0! | ... N40: =N39/(N9/1000) -> #DIV/0! | P40: =P39/(P9/1000) -> 0
A41: Cost of Chemicals | C41: Mk | D41: =(D29*$B29)+(D31*$B31)+(D33*$B33)+(D35*$B35)+(D37*$B37)+(D39*$B39) -> 460050.3 | E41: =(E29*$B29)+(E31*$B31)+(E33*$B33)+(E35*$B35)+(E37*$B37)+(E39*$B39) -> 480496.98 | F41: =(F29*$B29)+(F31*$B31)+(F33*$B33)+(F35*$B35)+(F37*$B37)+(F39*$B39) -> 495831.99 | G41: =(G29*$B29)+(G31*$B31)+(G33*$B33)+(G35*$B35)+(G37*$B37)+(G39*$B39) -> 0 | H41: =(H29*$B29)+(H31*$B31)+(H33*$B33)+(H35*$B35)+(H37*$B37)+(H39*$B39) -> 0 | I41: =(I29*$B29)+(I31*$B31)+(I33*$B33)+(I35*$B35)+(I37*$B37)+(I39*$B39) -> 0 | J41: =(J29*$B29)+(J31*$B31)+(J33*$B33)+(J35*$B35)+(J37*$B37)+(J39*$B39) -> 0 | K41: =(K29*$B29)+(K31*$B31)+(K33*$B33)+(K35*$B35)+(K37*$B37)+(K39*$B39) -> 0 | ... O41: =(O29*$B29)+(O31*$B31)+(O33*$B33)+(O35*$B35)+(O37*$B37)+(O39*$B39) -> 0 | P41: =SUM(D41:O41) -> 1436379.3
A42: Cost/vol. Produced (chemicals) | C42: Mk/m3 | D42: =D41/D9 -> 10.650792 | E42: =E41/E9 -> 10.030624 | F42: =F41/F9 -> 10.186584 | G42: =G41/G9 -> #DIV/0! | H42: =H41/H9 -> #DIV/0! | I42: =I41/I9 -> #DIV/0! | J42: =J41/J9 -> #DIV/0! | K42: =K41/K9 -> #DIV/0! | ... P42: =P41/P9 -> 10.276588
A43: Power
A44: Power Usage | C44: Kw | D44: 56 | E44: 60 | F44: 65 | P44: =SUM(D44:O44) -> 181
A45: Power/ Vol. Produced | C45: Kw/m3 | D45: =D44/D9 -> 0.0012964764 | E45: =E44/E9 -> 0.0012525312 | F45: =F44/F9 -> 0.0013353878 | G45: =G44/G9 -> #DIV/0! | H45: =H44/H9 -> #DIV/0! | J45: =J44/J9 -> #DIV/0! | L45: =L44/L9 -> #DIV/0! | M45: =M44/M9 -> #DIV/0! | N45: =N44/N9 -> #DIV/0! | P45: =P44/P9 -> 0.0012949661
A46: Cost of Power | C46: Mk | D46: =333.87*D44 -> 18696.72 | E46: =333.87*E44 -> 20032.2 | F46: =333.87*F44 -> 21701.55 | G46: =333.87*G44 -> 0 | H46: =333.87*H44 -> 0 | I46: =333.87*I44 -> 0 | J46: =333.87*J44 -> 0 | K46: =333.87*K44 -> 0 | ... O46: =333.87*O44 -> 0 | P46: =SUM(D46:O46) -> 60430.47
A47: Cost/vol. Produced | C47: Mk/m3 | D47: =D46/D9 -> 0.43285456 | E47: =E46/E9 -> 0.41818258 | F47: =F46/F9 -> 0.44584592 | G47: =G46/G9 -> #DIV/0! | H47: =H46/H9 -> #DIV/0! | I47: =I46/I9 -> #DIV/0! | J47: =J46/J9 -> #DIV/0! | K47: =K46/K9 -> #DIV/0! | ... P47: =P46/P9 -> 0.43235033
A48: Plant and Vehicle Maintenance
A49: Distances covered | C49: km | D49: 917 | E49: 717 | F49: 980 | P49: =SUM(D49:O49) -> 2614
A50: Fuel Used (litres) | C50: litres | D50: 111 | E50: 60 | F50: 90 | P50: =SUM(D50:O50) -> 261
A51: Cost of fuel | C51: Mk | D51: =6687*D50 -> 742257 | E51: =6687*E50 -> 401220 | F51: =6687*F50 -> 601830 | G51: =6687*G50 -> 0 | H51: =6687*H50 -> 0 | I51: =6687*I50 -> 0 | J51: =6687*J50 -> 0 | K51: =6687*K50 -> 0 | ... O51: =6687*O50 -> 0 | P51: =SUM(D51:O51) -> 1745307
A52: Maintenance | C52: Mk | P52: =SUM(D52:O52) -> 0
A53: Salaries and Wages
A54: Staff Costs | C54: MK | D54: 18900546 | E54: 19057154 | F54: 19057154 | P54: =SUM(D54:O54) -> 57014853
A55: Wages | C55: MK | D55: 2552049.2 | E55: 2715248.9 | F55: 3664989.1 | P55: =SUM(D55:O55) -> 8932287.1
A56: Other Overhead Costs | C56: MK | D56: 7925613.7 | E56: 3391330 | F56: 4903050 | P56: =SUM(D56:O56) -> 16219994
A57: Operating Costs
A58: Total Operating Costs | C58: MK | D58: =D41+D46+D51+D52+D54+D55+D56 -> 30599213 | E58: =E41+E46+E51+E52+E54+E55+E56 -> 26065482 | F58: =F41+F46+F51+F52+F54+F55+F56 -> 28744556 | G58: =G41+G46+G51+G52+G54+G55+G56 -> 0 | H58: =H41+H46+H51+H52+H54+H55+H56 -> 0 | I58: =I41+I46+I51+I52+I54+I55+I56 -> 0 | J58: =J41+J46+J51+J52+J54+J55+J56 -> 0 | K58: =K41+K46+K51+K52+K54+K55+K56 -> 0 | ... N58: =N41+N46+N51+N52+N54+N55+N56 -> 0 | P58: =SUM(D58:O58) -> 85409251
A59: Cost/Vol. Produced | C59: Mk/m3 | D59: =D58/D9 -> 708.4135 | E59: =E58/E9 -> 544.13046 | F59: =F58/F9 -> 590.54045 | G59: =G58/G9 -> #DIV/0! | H59: =H58/H9 -> #DIV/0! | I59: =I58/I9 -> #DIV/0! | J59: =J58/J9 -> #DIV/0! | K59: =K58/K9 -> #DIV/0! | ... N59: =N58/N9 -> #DIV/0! | P59: =P58/P9 -> 611.06123
A60: Cost/Vol. Billed | C60: Mk/m3 | D60: =D58/D22 -> 991.44783 | E60: =E58/E22 -> 770.36127 | F60: =F58/F22 -> 828.13472 | G60: =G58/G22 -> #DIV/0! | H60: =H58/H22 -> #DIV/0! | I60: =I58/I22 -> #DIV/0! | J60: =J58/J22 -> #DIV/0! | K60: =K58/K22 -> #DIV/0! | ... N60: =N58/N22 -> #DIV/0! | P60: =P58/P22 -> 859.17401
A61: Permanent Staff Employed | C61: No | D61: 9 | E61: 9 | F61: 9 | P61: =O61 -> 0
A62: Staff/Vol.1000m3 of Volume Produced/hour (12 hour day) | C62: No/1000m3 | D62: =(D61*1000*31)/D9 -> 6.4592304 | E62: =(E61*1000*31)/E9 -> 5.8242699 | F62: =(F61*1000*31)/F9 -> 5.7318952 | G62: =(G61*1000*31)/G9 -> #DIV/0! | H62: =(H61*1000*31)/H9 -> #DIV/0! | I62: =(I61*1000*31)/I9 -> #DIV/0! | J62: =(J61*1000*31)/J9 -> #DIV/0! | K62: =(K61*1000*31)/K9 -> #DIV/0! | ... N62: =(N61*1000*31)/N9 -> #DIV/0! | P62: =(P61*1000*31)/P9 -> 0
A63: Temporary Staff Employed | C63: No | D63: 22 | E63: 22 | F63: 22 | P63: =SUM(D63:O63) -> 66
A65: Water Connections and Disconnections
A66: New Individual Water Connections | B66: Brought Forward | C66: No | D66: 10 | E66: =D71 -> 38 | F66: =E71 -> 30 | G66: =F71 -> 20 | H66: =G71 -> 20 | I66: =H71 -> 20 | J66: =I71 -> 20 | K66: =J71 -> 20 | L66: =K71 -> 20 | ... O66: =N71 -> 20 | P66: =D66 -> 10
B67: Applied this Month | C67: No | D67: 30 | E67: 15 | F67: 25 | P67: =SUM(D67:O67) -> 70
B68: Done this Month Postpaid | C68: No | P68: =SUM(D68:O68) -> 0
B69: Done this Month Prepaid | C69: No | D69: 2 | E69: 23 | F69: 35 | P69: =SUM(D69:O69) -> 60
B70: Total Done | C70: No | D70: =D68+D69 -> 2 | E70: 23 | F70: =F68+F69 -> 35 | G70: =G68+G69 -> 0 | H70: =H68+H69 -> 0 | I70: =I68+I69 -> 0 | K70: =K68+K69 -> 0 | L70: =L68+L69 -> 0 | M70: =M68+M69 -> 0 | N70: =N68+N69 -> 0 | P70: =P68+P69 -> 60
B71: Carried Forward | C71: No | D71: =D66+D67-D70 -> 38 | E71: =E66+E67-E70 -> 30 | F71: =F66+F67-F70 -> 20 | G71: =G66+G67-G70 -> 20 | H71: =H66+H67-H70 -> 20 | I71: =I66+I67-I70 -> 20 | J71: =J66+J67-J70 -> 20 | K71: =K66+K67-K70 -> 20 | ... N71: =N66+N67-N70 -> 20 | P71: =P66+P67-P70 -> 20
A72: New Institutional Water Connections | B72: Brought Forward | C72: No | E72: =D77 -> 0 | F72: =E77 -> 0 | G72: =F77 -> 0 | H72: =G77 -> 0 | I72: =H77 -> 0 | P72: =D72 -> 0
B73: Applied this Month | C73: No | P73: =SUM(D73:O73) -> 0
B74: Done this Month Postpaid | C74: No | P74: =SUM(D74:O74) -> 0
B75: Done this Month Prepaid | C75: No | P75: =SUM(D75:O75) -> 0
B76: Total Done | C76: No | D76: =D74+D75 -> 0 | E76: =E74+E75 -> 0 | F76: =F74+F75 -> 0 | G76: =G74+G75 -> 0 | H76: =H74+H75 -> 0 | I76: =I74+I75 -> 0 | J76: =J74+J75 -> 0 | K76: =K74+K75 -> 0 | ... N76: =N74+N75 -> 0 | P76: =P74+P75 -> 0
B77: Carried Forward | C77: No | D77: =D72+D73-D76 -> 0 | E77: =E72+E73-E76 -> 0 | F77: =F72+F73-F76 -> 0 | G77: =G72+G73-G76 -> 0 | H77: =H72+H73-H76 -> 0 | I77: =I72+I73-I76 -> 0 | J77: =J72+J73-J76 -> 0 | K77: =K72+K73-K76 -> 0 | ... N77: =N72+N73-N76 -> 0 | P77: =P72+P73-P76 -> 0
A78: New Commercial/Industrial Water Connections | B78: Brought Forward | C78: No | E78: =D83 -> 0 | F78: =E83 -> 0 | G78: =F83 -> 0 | H78: =G83 -> 0 | I78: =H83 -> 0 | J78: =I83 -> 0 | K78: =J83 -> 0 | L78: =K83 -> 0 | ... N78: =M83 -> 0 | P78: =D78 -> 0
B79: Applied this Month | C79: No | P79: =SUM(D79:O79) -> 0
B80: Done this Month Postpaid | C80: No | P80: =SUM(D80:O80) -> 0
B81: Done this Month Prepaid | C81: No | P81: =SUM(D81:O81) -> 0
B82: Total Done | C82: No | D82: =D80+D81 -> 0 | E82: =E80+E81 -> 0 | F82: =F80+F81 -> 0 | G82: =G80+G81 -> 0 | H82: =H80+H81 -> 0 | I82: =I80+I81 -> 0 | J82: =J80+J81 -> 0 | K82: =K80+K81 -> 0 | ... N82: =N80+N81 -> 0 | P82: =P81+P80 -> 0
B83: Carried Forward | C83: No | D83: =D78+D79-D82 -> 0 | E83: =E78+E79-E82 -> 0 | F83: =F78+F79-F82 -> 0 | G83: =G78+G79-G82 -> 0 | H83: =H78+H79-H82 -> 0 | I83: =I78+I79-I82 -> 0 | J83: =J78+J79-J82 -> 0 | K83: =K78+K79-K82 -> 0 | ... N83: =N78+N79-N82 -> 0 | P83: =P78+P79-P82 -> 0
A84: New CWP | B84: Brought Forward | C84: No | E84: =D89 -> 0 | F84: =E89 -> 0 | G84: =F89 -> 0 | H84: =G89 -> 0 | P84: =D84 -> 0
B85: Applied this Month | C85: No | P85: =SUM(D85:O85) -> 0
B86: Done this Month Postpaid | C86: No | P86: =SUM(D86:O86) -> 0
B87: Done this Month Prepaid | C87: No | P87: =SUM(D87:O87) -> 0
B88: Total Done | C88: No | D88: =D86+D87 -> 0 | E88: =E86+E87 -> 0 | F88: =F86+F87 -> 0 | G88: =G86+G87 -> 0 | H88: =H86+H87 -> 0 | I88: =I86+I87 -> 0 | J88: =J86+J87 -> 0 | K88: =K86+K87 -> 0 | ... N88: =N86+N87 -> 0 | P88: =SUM(D88:O88) -> 0
B89: Carried Forward | C89: No | D89: =D84+D85-D88 -> 0 | E89: =E84+E85-E88 -> 0 | F89: =F84+F85-F88 -> 0 | G89: =G84+G85-G88 -> 0 | H89: =H84+H85-H88 -> 0 | I89: =I84+I85-I88 -> 0 | J89: =J84+J85-J88 -> 0 | K89: =K84+K85-K88 -> 0 | ... N89: =N84+N85-N88 -> 0 | P89: =P84+P85-P86-P87 -> 0
A90: Aggregated New Water connections | B90: Brought Forward | C90: No | D90: =D66+D72+D78+D84 -> 10 | E90: =E66+E72+E78+E84 -> 38 | F90: =F66+F72+F78+F84 -> 30 | G90: =G66+G72+G78+G84 -> 20 | H90: =H66+H72+H78+H84 -> 20 | I90: =I66+I72+I78+I84 -> 20 | J90: =J66+J72+J78+J84 -> 20 | K90: =K66+K72+K78+K84 -> 20 | ... N90: =N66+N72+N78+N84 -> 20 | P90: =D90 -> 10
B91: Applied this Month | C91: No | D91: =D67+D73+D79+D85 -> 30 | E91: =E67+E73+E79+E85 -> 15 | F91: =F67+F73+F79+F85 -> 25 | G91: =G67+G73+G79+G85 -> 0 | H91: =H67+H73+H79+H85 -> 0 | I91: =I67+I73+I79+I85 -> 0 | J91: =J67+J73+J79+J85 -> 0 | K91: =K67+K73+K79+K85 -> 0 | ... N91: =N67+N73+N79+N85 -> 0 | P91: =SUM(D91:O91) -> 70
B92: Done this Month Postpaid | C92: No | D92: =D68+D74+D80+D86 -> 0 | E92: =E68+E74+E80+E86 -> 0 | F92: =F68+F74+F80+F86 -> 0 | G92: =G68+G74+G80+G86 -> 0 | H92: =H68+H74+H80+H86 -> 0 | I92: =I68+I74+I80+I86 -> 0 | J92: =J68+J74+J80+J86 -> 0 | K92: =K68+K74+K80+K86 -> 0 | ... N92: =N68+N74+N80+N86 -> 0 | P92: =SUM(D92:O92) -> 0
B93: Done this Month Prepaid | D93: =D69+D75+D81+D87 -> 2 | E93: =E69+E75+E81+E87 -> 23 | F93: =F69+F75+F81+F87 -> 35 | G93: =G69+G75+G81+G87 -> 0 | H93: =H69+H75+H81+H87 -> 0 | I93: =I69+I75+I81+I87 -> 0 | J93: =J69+J75+J81+J87 -> 0 | K93: =K69+K75+K81+K87 -> 0 | ... N93: =N69+N75+N81+N87 -> 0 | P93: =SUM(D93:O93) -> 60
B94: Total Done | C94: No | D94: =D93+D92 -> 2 | E94: =E93+E92 -> 23 | F94: =F93+F92 -> 35 | G94: =G93+G92 -> 0 | H94: =H93+H92 -> 0 | I94: =I93+I92 -> 0 | J94: =J93+J92 -> 0 | K94: =K93+K92 -> 0 | ... N94: =N93+N92 -> 0 | P94: =P93+P92 -> 60
B95: Carried Forward | C95: No | D95: =D90+D91-D94 -> 38 | E95: =E90+E91-E94 -> 30 | F95: =F90+F91-F94 -> 20 | G95: =G90+G91-G94 -> 20 | H95: =H90+H91-H94 -> 20 | I95: =I90+I91-I94 -> 20 | J95: =J90+J91-J94 -> 20 | K95: =K90+K91-K94 -> 20 | ... N95: =N90+N91-N94 -> 20 | P95: =P90+P91-P94 -> 20
A97: Prepaid Metering
A98: Prepaid Meters Installed | C98: No | D98: 2 | E98: 23 | F98: 55 | P98: =SUM(D98:O98) -> 80
A100: Active and Disconnected Accounts
A101: Disconnected Individual Accounts | C101: No | D101: 675 | E101: 652 | F101: 672 | P101: =O101 -> 0
A102: Disconnected institutional Accounts | C102: No | D102: 25 | E102: 24 | F102: 24 | P102: =O102 -> 0
A103: Disconnected Commercial/Industrial Accounts | C103: No | D103: 70 | E103: 70 | F103: 70 | P103: =O103 -> 0
A104: Disconnected CWP | C104: No | D104: 16 | E104: 16 | F104: 16 | P104: =O104 -> 0
A105: Total Disconnected Accounts | C105: No | D105: =SUM(D101:D104) -> 786 | E105: =SUM(E101:E104) -> 762 | F105: =SUM(F101:F104) -> 782 | G105: =SUM(G101:G104) -> 0 | H105: =SUM(H101:H104) -> 0 | I105: =SUM(I101:I104) -> 0 | J105: =SUM(J101:J104) -> 0 | K105: =SUM(K101:K104) -> 0 | ... O105: =SUM(O101:O104) -> 0 | P105: =O105 -> 0
A106: Postpaid Consumers
...

Sheet Thyolo
A1: SOUTHERN REGION WATER BOARD
A3: MONTHLY REPORTS - 2026/2027
A4: MULANJE ZONE
A5: MULANJE ZONE
A7: PARAMETERS | C7: UNITS | D7: APRIL | E7: MAY | F7: JUNE | G7: JULY | H7: AUGUST | I7: SEPTEMBER | J7: OCTOBER | K7: NOVEMBER | L7: DECEMBER | M7: JANUARY | N7: FEBRUARY | O7: MARCH | P7: TOTALS
A8: PRODUCTION
A9: Volume Produced | C9: m3 | D9: 13500 | E9: 14160 | F9: 16850 | P9: =SUM(D9:O9) -> 44510
A10: REVENUE WATER - POSTPAID
A11: Volume Billed Individuals | C11: m3 | D11: 3924 | E11: 3444 | F11: 4557 | P11: =SUM(D11:O11) -> 11925
A12: Volume Billed CWPs | C12: m3 | D12: 4 | E12: 4 | F12: 4 | P12: =SUM(D12:O12) -> 12
A13: Volume Billed Institutions | C13: m3 | P13: =SUM(D13:O13) -> 0
A14: Volume Billed Commercial/Industrial | C14: m3 | D14: 29 | E14: 38 | F14: 26 | P14: =SUM(D14:O14) -> 93
A15: Total Volume Billed Post Paid | C15: m3 | D15: =SUM(D11:D14) -> 3957 | E15: =SUM(E11:E14) -> 3486 | F15: =SUM(F11:F14) -> 4587 | G15: =SUM(G11:G14) -> 0 | H15: =SUM(H11:H14) -> 0 | I15: =SUM(I11:I14) -> 0 | J15: =SUM(J11:J14) -> 0 | K15: =SUM(K11:K14) -> 0 | ... P15: =SUM(P11:P14) -> 12030
A16: REVENUE WATER - PREPAID
A17: Individuals | C17: m3 | D17: 4440 | E17: 3436.8 | F17: 4922 | P17: =SUM(D17:O17) -> 12798.8
A18: CWPs | C18: m3 | D18: 10 | E18: 2 | F18: 10 | P18: =SUM(D18:O18) -> 22
A19: Institutions | C19: m3 | D19: 313 | E19: 1866 | F19: 774 | P19: =SUM(D19:O19) -> 2953
A20: Commercial/Industrial | C20: m3 | D20: 214 | E20: 372 | F20: 389 | P20: =SUM(D20:O20) -> 975
A21: Total Volume Prepaid | C21: m3 | D21: =SUM(D17:D20) -> 4977 | E21: =SUM(E17:E20) -> 5676.8 | F21: =SUM(F17:F20) -> 6095 | G21: =SUM(G17:G20) -> 0 | H21: =SUM(H17:H20) -> 0 | I21: =SUM(I17:I20) -> 0 | J21: =SUM(J17:J20) -> 0 | K21: =SUM(K17:K20) -> 0 | ... P21: =SUM(P17:P20) -> 16748.8
A22: TOTAL REVENUE WATER | C22: m3 | D22: =D21+D15 -> 8934 | E22: =E21+E15 -> 9162.8 | F22: =F21+F15 -> 10682 | G22: =G21+G15 -> 0 | H22: =H21+H15 -> 0 | I22: =I21+I15 -> 0 | J22: =J21+J15 -> 0 | K22: =K21+K15 -> 0 | ... P22: =P21+P15 -> 28778.8
A24: Non-Revenue Water (NRW) | B24: Volume | C24: m3 | D24: =D9-D22 -> 4566 | E24: =E9-E22 -> 4997.2 | F24: =F9-F22 -> 6168 | G24: =G9-G22 -> 0 | H24: =H9-H22 -> 0 | I24: =I9-I22 -> 0 | J24: =J9-J22 -> 0 | K24: =K9-K22 -> 0 | ... P24: =P9-P22 -> 15731.2
B25: Percentage | C25: % | D25: =D24/D9 -> 0.33822222 | E25: =E24/E9 -> 0.3529096 | F25: =F24/F9 -> 0.36605341 | G25: =G24/G9 -> #DIV/0! | H25: =H24/H9 -> #DIV/0! | I25: =I24/I9 -> #DIV/0! | J25: =J24/J9 -> #DIV/0! | K25: =K24/K9 -> #DIV/0! | ... P25: =P24/P9 -> 0.35343069
A26: OPERATING EXPENSES
A27: Chemicals
A28: Chemical | B28: Rate(MK/kg)
A29: Chlorine | B29: 5111.67 | C29: kg | D29: 80 | E29: 60 | F29: 80 | P29: =SUM(D29:O29) -> 220
C30: kg/mg litre | D30: =D29/(D9/1000) -> 5.9259259 | E30: =E29/(E9/1000) -> 4.2372881 | F30: =F29/(F9/1000) -> 4.7477745 | G30: =G29/(G9/1000) -> #DIV/0! | H30: =H29/(H9/1000) -> #DIV/0! | I30: =I29/(I9/1000) -> #DIV/0! | J30: =J29/(J9/1000) -> #DIV/0! | K30: =K29/(K9/1000) -> #DIV/0! | ... N30: =N29/(N9/1000) -> #DIV/0! | P30: =P29/(P9/1000) -> 4.9427095
A31: Aluminium sulphate | B31: 1537 | C31: kg | P31: =SUM(D31:O31) -> 0
C32: kg/mg litre | D32: =D31/(D9/1000) -> 0 | E32: =E31/(E9/1000) -> 0 | F32: =F31/(F9/1000) -> 0 | G32: =G31/(G9/1000) -> #DIV/0! | H32: =H31/(H9/1000) -> #DIV/0! | I32: =I31/(I9/1000) -> #DIV/0! | J32: =J31/(J9/1000) -> #DIV/0! | K32: =K31/(K9/1000) -> #DIV/0! | ... N32: =N31/(N9/1000) -> #DIV/0! | P32: =P31/(P9/1000) -> 0
A33: Soda | B33: 1781.02 | C33: kg | P33: =SUM(D33:O33) -> 0
C34: kg/mg litre | D34: =D33/(D9/1000) -> 0 | E34: =E33/(E9/1000) -> 0 | F34: =F33/(F9/1000) -> 0 | G34: =G33/(G9/1000) -> #DIV/0! | H34: =H33/(H9/1000) -> #DIV/0! | I34: =I33/(I9/1000) -> #DIV/0! | J34: =J33/(J9/1000) -> #DIV/0! | K34: =K33/(K9/1000) -> #DIV/0! | ... N34: =N33/(N9/1000) -> #DIV/0! | P34: =P33/(P9/1000) -> 0
A35: Algae floc | B35: 5979.95 | C35: litres | D35: 84 | E35: 54 | F35: 81
C36: litres/mg litre | D36: =D35/(D15/1000) -> 21.228203 | E36: =E35/(E15/1000) -> 15.490534 | F36: =F35/(F15/1000) -> 17.6586 | G36: =G35/(G15/1000) -> #DIV/0! | H36: =H35/(H15/1000) -> #DIV/0! | I36: =I35/(I15/1000) -> #DIV/0! | J36: =J35/(J15/1000) -> #DIV/0! | K36: =K35/(K15/1000) -> #DIV/0! | ... N36: =N35/(N15/1000) -> #DIV/0! | P36: =P35/(P15/1000) -> 0
A37: Sud floc | B37: 5403.75 | C37: litres | P37: =SUM(D37:O37) -> 0
C38: litres/mg litre | D38: =D37/(D9/1000) -> 0 | E38: =E37/(E9/1000) -> 0 | F38: =F37/(F9/1000) -> 0 | G38: =G37/(G9/1000) -> #DIV/0! | H38: =H37/(H9/1000) -> #DIV/0! | I38: =I37/(I9/1000) -> #DIV/0! | J38: =J37/(J9/1000) -> #DIV/0! | K38: =K37/(K9/1000) -> #DIV/0! | ... N38: =N37/(N9/1000) -> #DIV/0! | P38: =P37/(P9/1000) -> 0
A39: Potasium permanganate | B39: 1950 | C39: kg | P39: =SUM(D39:O39) -> 0
C40: kg/mg litre | D40: =D39/(D9/1000) -> 0 | E40: =E39/(E9/1000) -> 0 | F40: =F39/(F9/1000) -> 0 | G40: =G39/(G9/1000) -> #DIV/0! | H40: =H39/(H9/1000) -> #DIV/0! | I40: =I39/(I9/1000) -> #DIV/0! | J40: =J39/(J9/1000) -> #DIV/0! | K40: =K39/(K9/1000) -> #DIV/0! | ... N40: =N39/(N9/1000) -> #DIV/0! | P40: =P39/(P9/1000) -> 0
A41: Cost of Chemicals | C41: Mk | D41: =(D29*$B29)+(D31*$B31)+(D33*$B33)+(D35*$B35)+(D37*$B37)+(D39*$B39) -> 911249.4 | E41: =(E29*$B29)+(E31*$B31)+(E33*$B33)+(E35*$B35)+(E37*$B37)+(E39*$B39) -> 629617.5 | F41: =(F29*$B29)+(F31*$B31)+(F33*$B33)+(F35*$B35)+(F37*$B37)+(F39*$B39) -> 893309.55 | G41: =(G29*$B29)+(G31*$B31)+(G33*$B33)+(G35*$B35)+(G37*$B37)+(G39*$B39) -> 0 | H41: =(H29*$B29)+(H31*$B31)+(H33*$B33)+(H35*$B35)+(H37*$B37)+(H39*$B39) -> 0 | I41: =(I29*$B29)+(I31*$B31)+(I33*$B33)+(I35*$B35)+(I37*$B37)+(I39*$B39) -> 0 | J41: =(J29*$B29)+(J31*$B31)+(J33*$B33)+(J35*$B35)+(J37*$B37)+(J39*$B39) -> 0 | K41: =(K29*$B29)+(K31*$B31)+(K33*$B33)+(K35*$B35)+(K37*$B37)+(K39*$B39) -> 0 | ... O41: =(O29*$B29)+(O31*$B31)+(O33*$B33)+(O35*$B35)+(O37*$B37)+(O39*$B39) -> 0 | P41: =SUM(D41:O41) -> 2434176.5
A42: Cost/vol. Produced (chemicals) | C42: Mk/m3 | D42: =D41/D9 -> 67.499956 | E42: =E41/E9 -> 44.464513 | F42: =F41/F9 -> 53.015404 | G42: =G41/G9 -> #DIV/0! | H42: =H41/H9 -> #DIV/0! | I42: =I41/I9 -> #DIV/0! | J42: =J41/J9 -> #DIV/0! | K42: =K41/K9 -> #DIV/0! | ... P42: =P41/P9 -> 54.688305
A43: Power
A44: Power Usage | C44: Kw | D44: 32000 | E44: 32000 | F44: 32000 | P44: =SUM(D44:O44) -> 96000
A45: Power/ Vol. Produced | C45: Kw/m3 | D45: =D44/D9 -> 2.3703704 | E45: =E44/E9 -> 2.259887 | F45: =F44/F9 -> 1.8991098 | G45: =G44/G9 -> #DIV/0! | H45: =H44/H9 -> #DIV/0! | I45: =I44/I9 -> #DIV/0! | J45: =J44/J9 -> #DIV/0! | K45: =K44/K9 -> #DIV/0! | ... N45: =N44/N9 -> #DIV/0! | P45: =P44/P9 -> 2.1568187
A46: Cost of Power | C46: Mk | D46: =333.87*D44 -> 10683840 | E46: =1.165*(14100+(E44*119.1)) -> 4456474.5 | F46: =1.165*(14100+(F44*119.1)) -> 4456474.5 | G46: =1.165*(14100+(G44*119.1)) -> 16426.5 | H46: =1.165*(14100+(H44*119.1)) -> 16426.5 | I46: =1.165*(14100+(I44*119.1)) -> 16426.5 | J46: =1.165*(14100+(J44*119.1)) -> 16426.5 | K46: =1.165*(14100+(K44*119.1)) -> 16426.5 | L46: =1.165*(14100+(L44*119.1)) -> 16426.5 | ... N46: =1.165*(14100+(N44*119.1)) -> 16426.5 | P46: =SUM(D46:O46) -> 19728201
A47: Cost/vol. Produced | C47: Mk/m3 | D47: =D46/D9 -> 791.39556 | E47: =E46/E9 -> 314.72278 | F47: =F46/F9 -> 264.4792 | G47: =G46/G9 -> #DIV/0! | H47: =H46/H9 -> #DIV/0! | I47: =I46/I9 -> #DIV/0! | J47: =J46/J9 -> #DIV/0! | K47: =K46/K9 -> #DIV/0! | ... N47: =N46/N9 -> #DIV/0! | P47: =P46/P9 -> 443.23076
A48: Plant and Vehicle Maintenance
A49: Distances covered | C49: km | P49: =SUM(D49:O49) -> 0
A50: Fuel Used (litres) | C50: litres | P50: =SUM(D50:O50) -> 0
A51: Cost of fuel | C51: Mk | D51: =D50*2734 -> 0 | E51: =E50*2734 -> 0 | F51: =F50*2734 -> 0 | G51: =G50*2734 -> 0 | J51: =J50*2734 -> 0 | L51: =L50*2734 -> 0 | P51: =SUM(D51:O51) -> 0
A52: Maintenance | C52: Mk | P52: =SUM(D52:O52) -> 0
A53: Salaries and Wages
A54: Staff Costs | C54: MK | D54: 12607528 | E54: 12936772 | F54: 12936772 | P54: =SUM(D54:O54) -> 38481071
A55: Wages | C55: MK | D55: 2714571 | E55: 2585701.3 | F55: 3664734.6 | P55: =SUM(D55:O55) -> 8965006.9
A56: Other Overhead Costs | C56: MK | D56: 4923595 | E56: 3137787 | F56: 1559000 | P56: =SUM(D56:O56) -> 9620382
A57: Operating Costs
A58: Total Operating Costs | C58: MK | D58: =D41+D46+D51+D52+D54+D55+D56 -> 31840783 | E58: =E41+E46+E51+E52+E54+E55+E56 -> 23746352 | F58: =F41+F46+F51+F52+F54+F55+F56 -> 23510290 | G58: =G41+G46+G51+G52+G54+G55+G56 -> 16426.5 | H58: =H41+H46+H51+H52+H54+H55+H56 -> 16426.5 | I58: =I41+I46+I51+I52+I54+I55+I56 -> 16426.5 | J58: =J41+J46+J51+J52+J54+J55+J56 -> 16426.5 | K58: =K41+K46+K51+K52+K54+K55+K56 -> 16426.5 | ... N58: =N41+N46+N51+N52+N54+N55+N56 -> 16426.5 | P58: =SUM(D58:O58) -> 79228837
A59: Cost/Vol. Produced | C59: Mk/m3 | D59: =D58/D9 -> 2358.5765 | E59: =E58/E9 -> 1677.0023 | F59: =F58/F9 -> 1395.2695 | G59: =G58/G9 -> #DIV/0! | H59: =H58/H9 -> #DIV/0! | I59: =I58/I9 -> #DIV/0! | J59: =J58/J9 -> #DIV/0! | K59: =K58/K9 -> #DIV/0! | ... N59: =N58/N9 -> #DIV/0! | P59: =P58/P9 -> 1780.0233
A60: Cost/Vol. Billed | C60: Mk/m3 | D60: =D58/D22 -> 3564.0008 | E60: =E58/E22 -> 2591.6043 | F60: =F58/F22 -> 2200.9259 | G60: =G58/G22 -> #DIV/0! | H60: =H58/H22 -> #DIV/0! | I60: =I58/I22 -> #DIV/0! | J60: =J58/J22 -> #DIV/0! | K60: =K58/K22 -> #DIV/0! | ... N60: =N58/N22 -> #DIV/0! | P60: =P58/P22 -> 2753.0278
A61: Permanent Staff Employed | C61: No | D61: 9 | E61: 9 | F61: 9 | P61: =O61 -> 0
A62: Staff/Vol.1000m3 of Volume Produced/hour (12 hour day) | C62: No/1000m3 | D62: =(D61*1000*31)/D9 -> 20.666667 | E62: =(E61*1000*31)/E9 -> 19.70339 | F62: =(F61*1000*31)/F9 -> 16.557864 | G62: =(G61*1000*31)/G9 -> #DIV/0! | H62: =(H61*1000*31)/H9 -> #DIV/0! | I62: =(I61*1000*31)/I9 -> #DIV/0! | J62: =(J61*1000*31)/J9 -> #DIV/0! | K62: =(K61*1000*31)/K9 -> #DIV/0! | ... N62: =(N61*1000*31)/N9 -> #DIV/0! | P62: =(P61*1000*31)/P9 -> 0
A63: Temporary Staff Employed | C63: No | D63: 19 | E63: 19 | F63: 19 | P63: =SUM(D63:O63) -> 57
A65: Water Connections and Disconnections
A66: New Individual Water Connections | B66: Brought Forward | C66: No | D66: 8 | E66: =D71 -> 10 | F66: =E71 -> 10 | G66: =F71 -> 16 | H66: =G71 -> 16 | I66: =H71 -> 16 | J66: =I71 -> 16 | K66: =J71 -> 16 | L66: =K71 -> 16 | ... N66: =M71 -> 16 | P66: =D66 -> 8
B67: Applied this Month | C67: No | D67: 12 | E67: 12 | F67: 20 | P67: =SUM(D67:O67) -> 44
B68: Done this Month Postpaid | C68: No | E68: 1 | F68: 1 | P68: =SUM(D68:O68) -> 2
B69: Done this Month Prepaid | C69: No | D69: 10 | E69: 11 | F69: 13 | P69: =SUM(D69:O69) -> 34
B70: Total Done | C70: No | D70: =D68+D69 -> 10 | E70: =E68+E69 -> 12 | F70: =F68+F69 -> 14 | G70: =G68+G69 -> 0 | I70: =I68+I69 -> 0 | J70: =J68+J69 -> 0 | K70: =K68+K69 -> 0 | L70: =L68+L69 -> 0 | M70: =M68+M69 -> 0 | N70: =N68+N69 -> 0 | P70: =P68+P69 -> 36
B71: Carried Forward | C71: No | D71: =D66+D67-D70 -> 10 | E71: =E66+E67-E70 -> 10 | F71: =F66+F67-F70 -> 16 | G71: =G66+G67-G70 -> 16 | H71: =H66+H67-H70 -> 16 | I71: =I66+I67-I70 -> 16 | J71: =J66+J67-J70 -> 16 | K71: =K66+K67-K70 -> 16 | ... N71: =N66+N67-N70 -> 16 | P71: =P66+P67-P70 -> 16
A72: New Institutional Water Connections | B72: Brought Forward | C72: No | E72: =D77 -> 0 | F72: =E77 -> 0 | G72: =F77 -> 0 | H72: =G77 -> 0 | I72: =H77 -> 0 | P72: =D72 -> 0
B73: Applied this Month | C73: No | P73: =SUM(D73:O73) -> 0
B74: Done this Month Postpaid | C74: No | P74: =SUM(D74:O74) -> 0
B75: Done this Month Prepaid | C75: No | P75: =SUM(D75:O75) -> 0
B76: Total Done | C76: No | D76: =D74+D75 -> 0 | E76: =E74+E75 -> 0 | F76: =F74+F75 -> 0 | G76: =G74+G75 -> 0 | H76: =H74+H75 -> 0 | I76: =I74+I75 -> 0 | J76: =J74+J75 -> 0 | K76: =K74+K75 -> 0 | M76: =M74+M75 -> 0 | N76: =N74+N75 -> 0 | P76: =P74+P75 -> 0
B77: Carried Forward | C77: No | D77: =D72+D73-D76 -> 0 | E77: =E72+E73-E76 -> 0 | F77: =F72+F73-F76 -> 0 | G77: =G72+G73-G76 -> 0 | H77: =H72+H73-H76 -> 0 | I77: =I72+I73-I76 -> 0 | J77: =J72+J73-J76 -> 0 | K77: =K72+K73-K76 -> 0 | ... N77: =N72+N73-N76 -> 0 | P77: =P72+P73-P76 -> 0
A78: New Commercial/Industrial Water Connections | B78: Brought Forward | C78: No | E78: =D83 -> 0 | F78: =E83 -> 0 | G78: =F83 -> 0 | H78: =G83 -> 0 | I78: =H83 -> 0 | J78: =I83 -> 0 | K78: =J83 -> 0 | L78: =K83 -> 0 | ... N78: =M83 -> 0 | P78: =D78 -> 0
B79: Applied this Month | C79: No | P79: =SUM(D79:O79) -> 0
B80: Done this Month Postpaid | C80: No | P80: =SUM(D80:O80) -> 0
B81: Done this Month Prepaid | C81: No | P81: =SUM(D81:O81) -> 0
B82: Total Done | C82: No | D82: =D81+D80 -> 0 | E82: =E81+E80 -> 0 | F82: =F81+F80 -> 0 | G82: =G81+G80 -> 0 | H82: =H81+H80 -> 0 | I82: =I80+I81 -> 0 | J82: =J80+J81 -> 0 | K82: =K80+K81 -> 0 | M82: =M81+M80 -> 0 | N82: =N81+N80 -> 0 | P82: =P81+P80 -> 0
B83: Carried Forward | C83: No | D83: =D78+D79-D82 -> 0 | E83: =E78+E79-E82 -> 0 | F83: =F78+F79-F82 -> 0 | G83: =G78+G79-G82 -> 0 | H83: =H78+H79-H82 -> 0 | I83: =I78+I79-I82 -> 0 | J83: =J78+J79-J82 -> 0 | K83: =K78+K79-K82 -> 0 | ... N83: =N78+N79-N82 -> 0 | P83: =P78+P79-P82 -> 0
A84: New CWP | B84: Brought Forward | C84: No | E84: =D89 -> 0 | F84: =E89 -> 0 | G84: =F89 -> 0 | H84: =G89 -> 0 | P84: =D84 -> 0
B85: Applied this Month | C85: No | P85: =SUM(D85:O85) -> 0
B86: Done this Month Postpaid | C86: No | P86: =SUM(D86:O86) -> 0
B87: Done this Month Prepaid | C87: No | P87: =SUM(D87:O87) -> 0
B88: Total Done | C88: No | D88: =D86+D87 -> 0 | E88: =E86+E87 -> 0 | F88: =F86+F87 -> 0 | G88: =G86+G87 -> 0 | H88: =H86+H87 -> 0 | I88: =I86+I87 -> 0 | J88: =J86+J87 -> 0 | K88: =K86+K87 -> 0 | ... N88: =N86+N87 -> 0 | P88: =SUM(D88:O88) -> 0
B89: Carried Forward | C89: No | D89: =D84+D85-D88 -> 0 | E89: =E84+E85-E88 -> 0 | F89: =F84+F85-F88 -> 0 | G89: =G84+G85-G88 -> 0 | H89: =H84+H85-H88 -> 0 | I89: =I84+I85-I88 -> 0 | J89: =J84+J85-J88 -> 0 | K89: =K84+K85-K88 -> 0 | ... N89: =N84+N85-N88 -> 0 | P89: =P84+P85-P86-P87 -> 0
A90: Aggregated New Water connections | B90: Brought Forward | C90: No | D90: =D66+D72+D78+D84 -> 8 | E90: =E66+E72+E78+E84 -> 10 | F90: =F66+F72+F78+F84 -> 10 | G90: =G66+G72+G78+G84 -> 16 | H90: =H66+H72+H78+H84 -> 16 | I90: =I66+I72+I78+I84 -> 16 | J90: =J66+J72+J78+J84 -> 16 | K90: =K66+K72+K78+K84 -> 16 | ... N90: =N66+N72+N78+N84 -> 16 | P90: =D90 -> 8
B91: Applied this Month | C91: No | D91: =D67+D73+D79+D85 -> 12 | E91: =E67+E73+E79+E85 -> 12 | F91: =F67+F73+F79+F85 -> 20 | G91: =G67+G73+G79+G85 -> 0 | H91: =H67+H73+H79+H85 -> 0 | I91: =I67+I73+I79+I85 -> 0 | J91: =J67+J73+J79+J85 -> 0 | K91: =K67+K73+K79+K85 -> 0 | ... N91: =N67+N73+N79+N85 -> 0 | P91: =SUM(D91:O91) -> 44
B92: Done this Month Postpaid | C92: No | D92: =D68+D74+D80+D86 -> 0 | E92: =E68+E74+E80+E86 -> 1 | F92: =F68+F74+F80+F86 -> 1 | G92: =G68+G74+G80+G86 -> 0 | H92: =H68+H74+H80+H86 -> 0 | I92: =I68+I74+I80+I86 -> 0 | J92: =J68+J74+J80+J86 -> 0 | K92: =K68+K74+K80+K86 -> 0 | ... N92: =N68+N74+N80+N86 -> 0 | P92: =SUM(D92:O92) -> 2
B93: Done this Month Prepaid | D93: =D69+D75+D81+D87 -> 10 | E93: =E69+E75+E81+E87 -> 11 | F93: =F69+F75+F81+F87 -> 13 | G93: =G69+G75+G81+G87 -> 0 | H93: =H69+H75+H81+H87 -> 0 | I93: =I69+I75+I81+I87 -> 0 | J93: =J69+J75+J81+J87 -> 0 | K93: =K69+K75+K81+K87 -> 0 | ... N93: =N69+N75+N81+N87 -> 0 | P93: =SUM(D93:O93) -> 34
B94: Total Done | C94: No | D94: =D93+D92 -> 10 | E94: =E93+E92 -> 12 | F94: =F93+F92 -> 14 | G94: =G93+G92 -> 0 | H94: =H93+H92 -> 0 | I94: =I93+I92 -> 0 | J94: =J93+J92 -> 0 | K94: =K93+K92 -> 0 | ... N94: =N93+N92 -> 0 | P94: =P93+P92 -> 36
B95: Carried Forward | C95: No | D95: =D90+D91-D94 -> 10 | E95: =E90+E91-E94 -> 10 | F95: =F90+F91-F94 -> 16 | G95: =G90+G91-G94 -> 16 | H95: =H90+H91-H94 -> 16 | I95: =I90+I91-I94 -> 16 | J95: =J90+J91-J94 -> 16 | K95: =K90+K91-K94 -> 16 | ... P95: =P90+P91-P94 -> 16
A97: Prepaid Metering
A98: Prepaid Meters Installed | C98: No | D98: 10 | E98: 16 | F98: 19 | P98: =SUM(D98:O98) -> 45
A100: Active and Disconnected Accounts
A101: Disconnected Individual Accounts | C101: No | D101: 556 | E101: 553 | F101: 553 | P101: =O101 -> 0
A102: Disconnected institutional Accounts | C102: No | D102: 13 | E102: 13 | F102: 13 | P102: =O102 -> 0
A103: Disconnected Commercial/Industrial Accounts | C103: No | D103: 13 | E103: 13 | F103: 13 | P103: =O103 -> 0
A104: Disconnected CWP | C104: No | D104: 16 | E104: 16 | F104: 16 | P104: =O104 -> 0
A105: Total Disconnected Accounts | C105: No | D105: =SUM(D101:D104) -> 598 | E105: =SUM(E101:E104) -> 595 | F105: =SUM(F101:F104) -> 595 | G105: =SUM(G101:G104) -> 0 | H105: =SUM(H101:H104) -> 0 | I105: =SUM(I101:I104) -> 0 | J105: =SUM(J101:J104) -> 0 | K105: =SUM(K101:K104) -> 0 | ... O105: =SUM(O101:O104) -> 0 | P105: =O105 -> 0
A106: Postpaid Consumers
...

Sheet Muloza
A1: SOUTHERN REGION WATER BOARD
A3: MONTHLY REPORTS - 2026/2027
A4: MULANJE ZONE
A5: MULANJE ZONE
A7: PARAMETERS | C7: UNITS | D7: APRIL | E7: MAY | F7: JUNE | G7: JULY | H7: AUGUST | I7: SEPTEMBER | J7: OCTOBER | K7: NOVEMBER | L7: DECEMBER | M7: JANUARY | N7: FEBRUARY | O7: MARCH | P7: TOTALS
A8: PRODUCTION
A9: Volume Produced | C9: m3 | D9: 11073 | E9: 9222 | F9: 8783 | P9: =SUM(D9:O9) -> 29078
A10: REVENUE WATER - POSTPAID
A11: Volume Billed Individuals | C11: m3 | D11: 2780 | E11: 2655 | F11: 3160 | P11: =SUM(D11:O11) -> 8595
A12: Volume Billed CWPs | C12: m3 | D12: 17 | E12: 14 | F12: 6 | P12: =SUM(D12:O12) -> 37
A13: Volume Billed Institutions | C13: m3 | P13: =SUM(D13:O13) -> 0
A14: Volume Billed Commercial/Industrial | C14: m3 | D14: 18 | E14: 8 | F14: 8 | P14: =SUM(D14:O14) -> 34
A15: Total Volume Billed Post Paid | C15: m3 | D15: =SUM(D11:D14) -> 2815 | E15: =SUM(E11:E14) -> 2677 | F15: =SUM(F11:F14) -> 3174 | G15: =SUM(G11:G14) -> 0 | H15: =SUM(H11:H14) -> 0 | I15: =SUM(I11:I14) -> 0 | J15: =SUM(J11:J14) -> 0 | K15: =SUM(K11:K14) -> 0 | ... P15: =SUM(P11:P14) -> 8666
A16: REVENUE WATER - PREPAID
A17: Individuals | C17: m3 | D17: 3079 | E17: 3325 | F17: 3028 | P17: =SUM(D17:O17) -> 9432
A18: CWPs | C18: m3 | D18: 26 | E18: 25 | F18: 9 | P18: =SUM(D18:O18) -> 60
A19: Institutions | C19: m3 | D19: 91 | E19: 116 | F19: 78 | P19: =SUM(D19:O19) -> 285
A20: Commercial/Industrial | C20: m3 | D20: 177 | E20: 283 | F20: 63 | P20: =SUM(D20:O20) -> 523
A21: Total Volume Prepaid | C21: m3 | D21: =SUM(D17:D20) -> 3373 | E21: =SUM(E17:E20) -> 3749 | F21: =SUM(F17:F20) -> 3178 | G21: =SUM(G17:G20) -> 0 | H21: =SUM(H17:H20) -> 0 | I21: =SUM(I17:I20) -> 0 | J21: =SUM(J17:J20) -> 0 | K21: =SUM(K17:K20) -> 0 | ... P21: =SUM(P17:P20) -> 10300
A22: TOTAL REVENUE WATER | C22: m3 | D22: =D21+D15 -> 6188 | E22: =E21+E15 -> 6426 | F22: =F21+F15 -> 6352 | G22: =G21+G15 -> 0 | H22: =H21+H15 -> 0 | I22: =I21+I15 -> 0 | J22: =J21+J15 -> 0 | K22: =K21+K15 -> 0 | ... P22: =P21+P15 -> 18966
A24: Non-Revenue Water (NRW) | B24: Volume | C24: m3 | D24: =D9-D22 -> 4885 | E24: =E9-E22 -> 2796 | F24: =F9-F22 -> 2431 | G24: =G9-G22 -> 0 | H24: =H9-H22 -> 0 | I24: =I9-I22 -> 0 | J24: =J9-J22 -> 0 | K24: =K9-K22 -> 0 | ... P24: =P9-P22 -> 10112
B25: Percentage | C25: % | D25: =D24/D9 -> 0.44116319 | E25: =E24/E9 -> 0.30318803 | F25: =F24/F9 -> 0.2767847 | G25: =G24/G9 -> #DIV/0! | H25: =H24/H9 -> #DIV/0! | I25: =I24/I9 -> #DIV/0! | J25: =J24/J9 -> #DIV/0! | K25: =K24/K9 -> #DIV/0! | ... P25: =P24/P9 -> 0.34775432
A26: OPERATING EXPENSES
A27: Chemicals
A28: Chemical | B28: Rate(MK/kg)
A29: Chlorine | B29: 5111.67 | C29: kg | D29: 15 | E29: 15 | F29: 15 | P29: =SUM(D29:O29) -> 45
C30: kg/mg litre | D30: =D29/(D9/1000) -> 1.3546464 | E30: =E29/(E9/1000) -> 1.6265452 | F30: =F29/(F9/1000) -> 1.7078447 | G30: =G29/(G9/1000) -> #DIV/0! | H30: =H29/(H9/1000) -> #DIV/0! | I30: =I29/(I9/1000) -> #DIV/0! | J30: =J29/(J9/1000) -> #DIV/0! | K30: =K29/(K9/1000) -> #DIV/0! | ... N30: =N29/(N9/1000) -> #DIV/0! | P30: =P29/(P9/1000) -> 1.5475617
A31: Aluminium sulphate | B31: 1537 | C31: kg | P31: =SUM(D31:O31) -> 0
C32: kg/mg litre | D32: =D31/(D9/1000) -> 0 | E32: =E31/(E9/1000) -> 0 | F32: =F31/(F9/1000) -> 0 | G32: =G31/(G9/1000) -> #DIV/0! | H32: =H31/(H9/1000) -> #DIV/0! | I32: =I31/(I9/1000) -> #DIV/0! | J32: =J31/(J9/1000) -> #DIV/0! | K32: =K31/(K9/1000) -> #DIV/0! | ... N32: =N31/(N9/1000) -> #DIV/0! | P32: =P31/(P9/1000) -> 0
A33: Soda | B33: 1781.02 | C33: kg | P33: =SUM(D33:O33) -> 0
C34: kg/mg litre | D34: =D33/(D9/1000) -> 0 | E34: =E33/(E9/1000) -> 0 | F34: =F33/(F9/1000) -> 0 | G34: =G33/(G9/1000) -> #DIV/0! | H34: =H33/(H9/1000) -> #DIV/0! | I34: =I33/(I9/1000) -> #DIV/0! | J34: =J33/(J9/1000) -> #DIV/0! | K34: =K33/(K9/1000) -> #DIV/0! | ... N34: =N33/(N9/1000) -> #DIV/0! | P34: =P33/(P9/1000) -> 0
A35: Algae floc | B35: 5979.95 | C35: litres
C36: litres/mg litre
A37: Sud floc | B37: 5403.75 | C37: litres | P37: =SUM(D37:O37) -> 0
C38: litres/mg litre | D38: =D37/(D9/1000) -> 0 | E38: =E37/(E9/1000) -> 0 | F38: =F37/(F9/1000) -> 0 | G38: =G37/(G9/1000) -> #DIV/0! | H38: =H37/(H9/1000) -> #DIV/0! | I38: =I37/(I9/1000) -> #DIV/0! | J38: =J37/(J9/1000) -> #DIV/0! | K38: =K37/(K9/1000) -> #DIV/0! | ... N38: =N37/(N9/1000) -> #DIV/0! | P38: =P37/(P9/1000) -> 0
A39: Potasium permanganate | B39: 1950 | C39: kg | P39: =SUM(D39:O39) -> 0
C40: kg/mg litre | D40: =D39/(D9/1000) -> 0 | E40: =E39/(E9/1000) -> 0 | F40: =F39/(F9/1000) -> 0 | G40: =G39/(G9/1000) -> #DIV/0! | H40: =H39/(H9/1000) -> #DIV/0! | I40: =I39/(I9/1000) -> #DIV/0! | J40: =J39/(J9/1000) -> #DIV/0! | K40: =K39/(K9/1000) -> #DIV/0! | ... N40: =N39/(N9/1000) -> #DIV/0! | P40: =P39/(P9/1000) -> 0
A41: Cost of Chemicals | C41: Mk | D41: =(D29*$B29)+(D31*$B31)+(D33*$B33)+(D35*$B35)+(D37*$B37)+(D39*$B39) -> 76675.05 | E41: =(E29*$B29)+(E31*$B31)+(E33*$B33)+(E35*$B35)+(E37*$B37)+(E39*$B39) -> 76675.05 | F41: =(F29*$B29)+(F31*$B31)+(F33*$B33)+(F35*$B35)+(F37*$B37)+(F39*$B39) -> 76675.05 | G41: =(G29*$B29)+(G31*$B31)+(G33*$B33)+(G35*$B35)+(G37*$B37)+(G39*$B39) -> 0 | H41: =(H29*$B29)+(H31*$B31)+(H33*$B33)+(H35*$B35)+(H37*$B37)+(H39*$B39) -> 0 | I41: =(I29*$B29)+(I31*$B31)+(I33*$B33)+(I35*$B35)+(I37*$B37)+(I39*$B39) -> 0 | J41: =(J29*$B29)+(J31*$B31)+(J33*$B33)+(J35*$B35)+(J37*$B37)+(J39*$B39) -> 0 | K41: =(K29*$B29)+(K31*$B31)+(K33*$B33)+(K35*$B35)+(K37*$B37)+(K39*$B39) -> 0 | ... N41: =(N29*$B29)+(N31*$B31)+(N33*$B33)+(N35*$B35)+(N37*$B37)+(N39*$B39) -> 0 | P41: =SUM(D41:O41) -> 230025.15
A42: Cost/vol. Produced (chemicals) | C42: Mk/m3 | D42: =D41/D9 -> 6.9245056 | E42: =E41/E9 -> 8.3143624 | F42: =F41/F9 -> 8.7299385 | G42: =G41/G9 -> #DIV/0! | H42: =H41/H9 -> #DIV/0! | I42: =I41/I9 -> #DIV/0! | J42: =J41/J9 -> #DIV/0! | K42: =K41/K9 -> #DIV/0! | ... P42: =P41/P9 -> 7.9106249
A43: Power
A44: Power Usage | C44: Kw | D44: 11957 | E44: 12037 | F44: 11285 | P44: =SUM(D44:O44) -> 35279
A45: Power/ Vol. Produced | C45: Kw/m3 | D45: =D44/D9 -> 1.0798338 | E45: =E44/E9 -> 1.3052483 | F45: =F44/F9 -> 1.2848685 | G45: =G44/G9 -> #DIV/0! | H45: =H44/H9 -> #DIV/0! | I45: =I44/I9 -> #DIV/0! | J45: =J44/J9 -> #DIV/0! | K45: =K44/K9 -> #DIV/0! | ... N45: =N44/N9 -> #DIV/0! | P45: =P44/P9 -> 1.213254
A46: Cost of Power | C46: Mk | D46: =333.87*D44 -> 3992083.6 | E46: =333.87*E44 -> 4018793.2 | F46: =333.87*F44 -> 3767723 | G46: =333.87*G44 -> 0 | H46: =333.87*H44 -> 0 | I46: =333.87*I44 -> 0 | J46: =333.87*J44 -> 0 | K46: =333.87*K44 -> 0 | ... O46: =333.87*O44 -> 0 | P46: =SUM(D46:O46) -> 11778600
A47: Cost/vol. Produced | C47: Mk/m3 | D47: =D46/D9 -> 360.52412 | E47: =E46/E9 -> 435.78326 | F47: =F46/F9 -> 428.97904 | G47: =G46/G9 -> #DIV/0! | H47: =H46/H9 -> #DIV/0! | I47: =I46/I9 -> #DIV/0! | J47: =J46/J9 -> #DIV/0! | K47: =K46/K9 -> #DIV/0! | ... P47: =P46/P9 -> 405.06912
A48: Plant and Vehicle Maintenance
A49: Distances covered | C49: km | P49: =SUM(D49:O49) -> 0
A50: Fuel Used (litres) | C50: litres | P50: =SUM(D50:O50) -> 0
A51: Cost of fuel | C51: Mk | D51: =D50*2734 -> 0 | F51: =F50*2734 -> 0 | G51: =G50*2734 -> 0 | H51: =H50*2734 -> 0 | I51: =I50*2734 -> 0 | J51: =J50*2734 -> 0 | K51: =K50*2734 -> 0 | P51: =SUM(D51:O51) -> 0
A52: Maintenance | C52: Mk | P52: =SUM(D52:O52) -> 0
A53: Salaries and Wages
A54: Staff Costs | C54: MK | D54: 5462710.1 | E54: 5681145.1 | F54: 5681145.1 | P54: =SUM(D54:O54) -> 16825000
A55: Wages | C55: MK | D55: 1357285.5 | E55: 1292850.6 | F55: 1194309.1 | P55: =SUM(D55:O55) -> 3844445.3
A56: Other Overhead Costs | C56: MK | D56: 2355175.8 | E56: 3533909 | F56: 869260 | P56: =SUM(D56:O56) -> 6758344.8
A57: Operating Costs
A58: Total Operating Costs | C58: MK | D58: =D41+D46+D51+D52+D54+D55+D56 -> 13243930 | E58: =E41+E46+E51+E52+E54+E55+E56 -> 14603373 | F58: =F41+F46+F51+F52+F54+F55+F56 -> 11589112 | G58: =G41+G46+G51+G52+G54+G55+G56 -> 0 | H58: =H41+H46+H51+H52+H54+H55+H56 -> 0 | I58: =I41+I46+I51+I52+I54+I55+I56 -> 0 | J58: =J41+J46+J51+J52+J54+J55+J56 -> 0 | K58: =K41+K46+K51+K52+K54+K55+K56 -> 0 | ... N58: =N41+N46+N51+N52+N54+N55+N56 -> 0 | P58: =SUM(D58:O58) -> 39436415
A59: Cost/Vol. Produced | C59: Mk/m3 | D59: =D58/D9 -> 1196.0562 | E59: =E58/E9 -> 1583.5364 | F59: =F58/F9 -> 1319.4936 | G59: =G58/G9 -> #DIV/0! | H59: =H58/H9 -> #DIV/0! | I59: =I58/I9 -> #DIV/0! | J59: =J58/J9 -> #DIV/0! | K59: =K58/K9 -> #DIV/0! | ... N59: =N58/N9 -> #DIV/0! | P59: =P58/P9 -> 1356.2286
A60: Cost/Vol. Billed | C60: Mk/m3 | D60: =D58/D22 -> 2140.2602 | E60: =E58/E22 -> 2272.5448 | F60: =F58/F22 -> 1824.4824 | G60: =G58/G22 -> #DIV/0! | H60: =H58/H22 -> #DIV/0! | I60: =I58/I22 -> #DIV/0! | J60: =J58/J22 -> #DIV/0! | K60: =K58/K22 -> #DIV/0! | ... N60: =N58/N22 -> #DIV/0! | P60: =P58/P22 -> 2079.3217
A61: Permanent Staff Employed | C61: No | D61: 6 | E61: 6 | F61: 6 | P61: =O61 -> 0
A62: Staff/Vol.1000m3 of Volume Produced/hour (12 hour day) | C62: No/1000m3 | D62: =(D61*1000*31)/D9 -> 16.797616 | E62: =(E61*1000*31)/E9 -> 20.169161 | F62: =(F61*1000*31)/F9 -> 21.177274 | G62: =(G61*1000*31)/G9 -> #DIV/0! | H62: =(H61*1000*31)/H9 -> #DIV/0! | I62: =(I61*1000*31)/I9 -> #DIV/0! | J62: =(J61*1000*31)/J9 -> #DIV/0! | K62: =(K61*1000*31)/K9 -> #DIV/0! | ... N62: =(N61*1000*31)/N9 -> #DIV/0! | P62: =(P61*1000*31)/P9 -> 0
A63: Temporary Staff Employed | C63: No | D63: 10 | E63: 13 | F63: 15 | P63: =SUM(D63:O63) -> 38
A65: Water Connections and Disconnections
A66: New Individual Water Connections | B66: Brought Forward | C66: No | D66: 52 | E66: =D71 -> 49 | F66: =E71 -> 58 | G66: =F71 -> 65 | H66: =G71 -> 65 | I66: =H71 -> 65 | J66: =I71 -> 65 | K66: =J71 -> 65 | L66: =K71 -> 65 | ... O66: =N71 -> 65 | P66: =D66 -> 52
B67: Applied this Month | C67: No | D67: 1 | E67: 12 | F67: 16 | P67: =SUM(D67:O67) -> 29
B68: Done this Month Postpaid | C68: No | F68: 1 | P68: =SUM(D68:O68) -> 1
B69: Done this Month Prepaid | C69: No | D69: 4 | E69: 3 | F69: 8 | P69: =SUM(D69:O69) -> 15
B70: Total Done | C70: No | D70: =D68+D69 -> 4 | E70: =E68+E69 -> 3 | F70: =F68+F69 -> 9 | G70: =G68+G69 -> 0 | I70: =I68+I69 -> 0 | J70: =J68+J69 -> 0 | K70: =K68+K69 -> 0 | L70: =L68+L69 -> 0 | M70: =M68+M69 -> 0 | N70: =N68+N69 -> 0 | P70: =P68+P69 -> 16
B71: Carried Forward | C71: No | D71: =D66+D67-D70 -> 49 | E71: =E66+E67-E70 -> 58 | F71: =F66+F67-F70 -> 65 | G71: =G66+G67-G70 -> 65 | H71: =H66+H67-H70 -> 65 | I71: =I66+I67-I70 -> 65 | J71: =J66+J67-J70 -> 65 | K71: =K66+K67-K70 -> 65 | ... N71: =N66+N67-N70 -> 65 | P71: =P66+P67-P70 -> 65
A72: New Institutional Water Connections | B72: Brought Forward | C72: No | E72: =D77 -> 1 | F72: =E77 -> 0 | G72: =F77 -> 0 | H72: =G77 -> 0 | I72: =H77 -> 0 | P72: =D72 -> 0
B73: Applied this Month | C73: No | D73: 1 | P73: =SUM(D73:O73) -> 1
B74: Done this Month Postpaid | C74: No | P74: =SUM(D74:O74) -> 0
B75: Done this Month Prepaid | C75: No | E75: 1 | P75: =SUM(D75:O75) -> 1
B76: Total Done | C76: No | D76: =D74+D75 -> 0 | E76: =E74+E75 -> 1 | F76: =F74+F75 -> 0 | G76: =G74+G75 -> 0 | H76: =H74+H75 -> 0 | K76: =K74+K75 -> 0 | M76: =M74+M75 -> 0 | N76: =N74+N75 -> 0 | P76: =P74+P75 -> 1
B77: Carried Forward | C77: No | D77: =D72+D73-D76 -> 1 | E77: =E72+E73-E76 -> 0 | F77: =F72+F73-F76 -> 0 | G77: =G72+G73-G76 -> 0 | H77: =H72+H73-H76 -> 0 | J77: =J72+J73-J76 -> 0 | K77: =K72+K73-K76 -> 0 | L77: =L72+L73-L76 -> 0 | M77: =M72+M73-M76 -> 0 | N77: =N72+N73-N76 -> 0 | P77: =P72+P73-P76 -> 0
A78: New Commercial/Industrial Water Connections | B78: Brought Forward | C78: No | D78: 6 | E78: =D83 -> 6 | F78: =E83 -> 7 | H78: =G83 -> 0 | I78: =H83 -> 0 | J78: =I83 -> 0 | K78: =J83 -> 0 | L78: =K83 -> 0 | M78: =L83 -> 0 | N78: =M83 -> 0 | P78: =D78 -> 6
B79: Applied this Month | C79: No | E79: 1 | P79: =SUM(D79:O79) -> 1
B80: Done this Month Postpaid | C80: No | P80: =SUM(D80:O80) -> 0
B81: Done this Month Prepaid | C81: No | P81: =SUM(D81:O81) -> 0
B82: Total Done | C82: No | D82: =D81+D80 -> 0 | E82: =E81+E80 -> 0 | F82: =F81+F80 -> 0 | I82: =I80+I81 -> 0 | J82: =J80+J81 -> 0 | K82: =K80+K81 -> 0 | M82: =M81+M80 -> 0 | N82: =N81+N80 -> 0 | P82: =P81+P80 -> 0
B83: Carried Forward | C83: No | D83: =D78+D79-D82 -> 6 | E83: =E78+E79-E82 -> 7 | F83: =F78+F79-F82 -> 7 | G83: =G78+G79-G82 -> 0 | H83: =H78+H79-H82 -> 0 | I83: =I78+I79-I82 -> 0 | J83: =J78+J79-J82 -> 0 | K83: =K78+K79-K82 -> 0 | ... N83: =N78+N79-N82 -> 0 | P83: =P78+P79-P82 -> 7
A84: New CWP | B84: Brought Forward | C84: No | E84: =D89 -> 0 | F84: =E89 -> 0 | G84: =F89 -> 0 | H84: =G89 -> 0 | P84: =D84 -> 0
B85: Applied this Month | C85: No | P85: =SUM(D85:O85) -> 0
B86: Done this Month Postpaid | C86: No | P86: =SUM(D86:O86) -> 0
B87: Done this Month Prepaid | C87: No | P87: =SUM(D87:O87) -> 0
B88: Total Done | C88: No | D88: =D86+D87 -> 0 | E88: =E86+E87 -> 0 | F88: =F86+F87 -> 0 | G88: =G86+G87 -> 0 | I88: =I86+I87 -> 0 | J88: =J86+J87 -> 0 | K88: =K86+K87 -> 0 | L88: =L86+L87 -> 0 | M88: =M86+M87 -> 0 | N88: =N86+N87 -> 0 | P88: =SUM(D88:O88) -> 0
B89: Carried Forward | C89: No | D89: =D84+D85-D88 -> 0 | E89: =E84+E85-E88 -> 0 | F89: =F84+F85-F88 -> 0 | G89: =G84+G85-G88 -> 0 | H89: =H87+H88 -> 0 | I89: =I84+I85-I88 -> 0 | J89: =J84+J85-J88 -> 0 | K89: =K84+K85-K88 -> 0 | L89: =L84+L85-L88 -> 0 | M89: =M84+M85-M88 -> 0 | N89: =N84+N85-N88 -> 0 | P89: =P84+P85-P86-P87 -> 0
A90: Aggregated New Water connections | B90: Brought Forward | C90: No | D90: =D66+D72+D78+D84 -> 58 | E90: =E66+E72+E78+E84 -> 56 | F90: =F66+F72+F78+F84 -> 65 | G90: =G66+G72+G78+G84 -> 65 | H90: =H66+H72+H78+H84 -> 65 | I90: =I66+I72+I78+I84 -> 65 | J90: =J66+J72+J78+J84 -> 65 | K90: =K66+K72+K78+K84 -> 65 | ... N90: =N66+N72+N78+N84 -> 65 | P90: =D90 -> 58
B91: Applied this Month | C91: No | D91: =D67+D73+D79+D85 -> 2 | E91: =E67+E73+E79+E85 -> 13 | F91: =F67+F73+F79+F85 -> 16 | G91: =G67+G73+G79+G85 -> 0 | H91: =H67+H73+H79+H85 -> 0 | I91: =I67+I73+I79+I85 -> 0 | J91: =J67+J73+J79+J85 -> 0 | K91: =K67+K73+K79+K85 -> 0 | ... N91: =N67+N73+N79+N85 -> 0 | P91: =SUM(D91:O91) -> 31
B92: Done this Month Postpaid | C92: No | D92: =D68+D74+D80+D86 -> 0 | E92: =E68+E74+E80+E86 -> 0 | F92: =F68+F74+F80+F86 -> 1 | G92: =G68+G74+G80+G86 -> 0 | H92: =H68+H74+H80+H86 -> 0 | I92: =I68+I74+I80+I86 -> 0 | J92: =J68+J74+J80+J86 -> 0 | K92: =K68+K74+K80+K86 -> 0 | ... N92: =N68+N74+N80+N86 -> 0 | P92: =SUM(D92:O92) -> 1
B93: Done this Month Prepaid | D93: =D69+D75+D81+D87 -> 4 | E93: =E69+E75+E81+E87 -> 4 | F93: =F69+F75+F81+F87 -> 8 | G93: =G69+G75+G81+G87 -> 0 | H93: =H69+H75+H81+H87 -> 0 | I93: =I69+I75+I81+I87 -> 0 | J93: =J69+J75+J81+J87 -> 0 | K93: =K69+K75+K81+K87 -> 0 | ... N93: =N69+N75+N81+N87 -> 0 | P93: =SUM(D93:O93) -> 16
B94: Total Done | C94: No | D94: =D93+D92 -> 4 | E94: =E93+E92 -> 4 | F94: =F93+F92 -> 9 | G94: =G93+G92 -> 0 | H94: =H93+H92 -> 0 | I94: =I93+I92 -> 0 | J94: =J93+J92 -> 0 | K94: =K93+K92 -> 0 | ... N94: =N93+N92 -> 0 | P94: =P93+P92 -> 17
B95: Carried Forward | C95: No | D95: =D90+D91-D94 -> 56 | E95: =E90+E91-E94 -> 65 | F95: =F90+F91-F94 -> 72 | G95: =G90+G91-G94 -> 65 | H95: =H90+H91-H94 -> 65 | I95: =I90+I91-I94 -> 65 | J95: =J90+J91-J94 -> 65 | K95: =K90+K91-K94 -> 65 | ... P95: =P90+P91-P94 -> 72
A97: Prepaid Metering
A98: Prepaid Meters Installed | C98: No | D98: 4 | E98: 13 | F98: 19 | I98: =I93 -> 0 | K98: =K93 -> 0
A100: Active and Disconnected Accounts
A101: Disconnected Individual Accounts | C101: No | D101: 420 | E101: 420 | F101: 398 | P101: =O101 -> 0
A102: Disconnected institutional Accounts | C102: No | D102: 18 | E102: 18 | F102: 6 | P102: =O102 -> 0
A103: Disconnected Commercial/Industrial Accounts | C103: No | D103: 70 | E103: 70 | F103: 70 | P103: =O103 -> 0
A104: Disconnected CWP | C104: No | E104: 0 | F104: 0 | P104: =O104 -> 0
A105: Total Disconnected Accounts | C105: No | D105: =SUM(D101:D104) -> 508 | E105: =SUM(E101:E104) -> 508 | F105: =SUM(F101:F104) -> 474 | G105: =SUM(G101:G104) -> 0 | H105: =SUM(H101:H104) -> 0 | I105: =SUM(I101:I104) -> 0 | J105: =SUM(J101:J104) -> 0 | K105: =SUM(K101:K104) -> 0 | ... O105: =SUM(O101:O104) -> 0 | P105: =O105 -> 0
A106: Postpaid Consumers
...

Sheet MUST
A1: SOUTHERN REGION WATER BOARD
A3: MONTHLY REPORTS - 2026/2027
A4: MULANJE ZONE
A5: MULANJE ZONE
A7: PARAMETERS | C7: UNITS | D7: APRIL | E7: MAY | F7: JUNE | G7: JULY | H7: AUGUST | I7: SEPTEMBER | J7: OCTOBER | K7: NOVEMBER | L7: DECEMBER | M7: JANUARY | N7: FEBRUARY | O7: MARCH | P7: TOTALS
A8: PRODUCTION
A9: Volume Produced | C9: m3 | D9: 18871 | E9: 23837 | F9: 17677 | P9: =SUM(D9:O9) -> 60385
A10: REVENUE WATER - POSTPAID
A11: Volume Billed Individuals | C11: m3 | D11: 770 | E11: 748 | F11: 933 | P11: =SUM(D11:O11) -> 2451
A12: Volume Billed CWPs | C12: m3 | P12: =SUM(D12:O12) -> 0
A13: Volume Billed Institutions | C13: m3 | E13: 14 | F13: 58 | P13: =SUM(D13:O13) -> 72
A14: Volume Billed Commercial/Industrial | C14: m3 | P14: =SUM(D14:O14) -> 0
A15: Total Volume Billed Post Paid | C15: m3 | D15: =SUM(D11:D14) -> 770 | E15: =SUM(E11:E14) -> 762 | F15: =SUM(F11:F14) -> 991 | G15: =SUM(G11:G14) -> 0 | H15: =SUM(H11:H14) -> 0 | I15: =SUM(I11:I14) -> 0 | J15: =SUM(J11:J14) -> 0 | K15: =SUM(K11:K14) -> 0 | ... P15: =SUM(P11:P14) -> 2523
A16: REVENUE WATER - PREPAID
A17: Individuals | C17: m3 | D17: 2282 | E17: 2841 | F17: 1408 | P17: =SUM(D17:O17) -> 6531
A18: CWPs | C18: m3 | P18: =SUM(D18:O18) -> 0
A19: Institutions | C19: m3 | D19: 11520 | E19: 13810 | F19: 10798 | P19: =SUM(D19:O19) -> 36128
A20: Commercial/Industrial | C20: m3 | D20: 854 | E20: 1621 | F20: 113 | P20: =SUM(D20:O20) -> 2588
A21: Total Volume Prepaid | C21: m3 | D21: =SUM(D17:D20) -> 14656 | E21: =SUM(E17:E20) -> 18272 | F21: =SUM(F17:F20) -> 12319 | G21: =SUM(G17:G20) -> 0 | H21: =SUM(H17:H20) -> 0 | I21: =SUM(I17:I20) -> 0 | J21: =SUM(J17:J20) -> 0 | K21: =SUM(K17:K20) -> 0 | ... P21: =SUM(P17:P20) -> 45247
A22: TOTAL REVENUE WATER | C22: m3 | D22: =D21+D15 -> 15426 | E22: =E21+E15 -> 19034 | F22: =F21+F15 -> 13310 | G22: =G21+G15 -> 0 | H22: =H21+H15 -> 0 | I22: =I21+I15 -> 0 | J22: =J21+J15 -> 0 | K22: =K21+K15 -> 0 | ... P22: =P21+P15 -> 47770
A24: Non-Revenue Water (NRW) | B24: Volume | C24: m3 | D24: =D9-D22 -> 3445 | E24: =E9-E22 -> 4803 | F24: =F9-F22 -> 4367 | G24: =G9-G22 -> 0 | H24: =H9-H22 -> 0 | I24: =I9-I22 -> 0 | J24: =J9-J22 -> 0 | K24: =K9-K22 -> 0 | ... P24: =P9-P22 -> 12615
B25: Percentage | C25: % | D25: =D24/D9 -> 0.18255524 | E25: =E24/E9 -> 0.20149348 | F25: =F24/F9 -> 0.24704418 | G25: =G24/G9 -> #DIV/0! | H25: =H24/H9 -> #DIV/0! | I25: =I24/I9 -> #DIV/0! | J25: =J24/J9 -> #DIV/0! | K25: =K24/K9 -> #DIV/0! | ... P25: =P24/P9 -> 0.2089095
A26: OPERATING EXPENSES
A27: Chemicals
A28: Chemical | B28: Rate(MK/kg)
A29: Chlorine | B29: 5111.67 | C29: kg | D29: 19 | E29: 22 | F29: 15 | P29: =SUM(D29:O29) -> 56
C30: kg/mg litre | D30: =D29/(D9/1000) -> 1.0068359 | E30: =E29/(E9/1000) -> 0.92293493 | F30: =F29/(F9/1000) -> 0.84856028 | G30: =G29/(G9/1000) -> #DIV/0! | H30: =H29/(H9/1000) -> #DIV/0! | I30: =I29/(I9/1000) -> #DIV/0! | J30: =J29/(J9/1000) -> #DIV/0! | K30: =K29/(K9/1000) -> #DIV/0! | ... N30: =N29/(N9/1000) -> #DIV/0! | P30: =P29/(P9/1000) -> 0.92738263
A31: Aluminium sulphate | B31: 1537 | C31: kg | P31: =SUM(D31:O31) -> 0
C32: kg/mg litre | D32: =D31/(D9/1000) -> 0 | E32: =E31/(E9/1000) -> 0 | F32: =F31/(F9/1000) -> 0 | G32: =G31/(G9/1000) -> #DIV/0! | H32: =H31/(H9/1000) -> #DIV/0! | I32: =I31/(I9/1000) -> #DIV/0! | J32: =J31/(J9/1000) -> #DIV/0! | K32: =K31/(K9/1000) -> #DIV/0! | ... N32: =N31/(N9/1000) -> #DIV/0! | P32: =P31/(P9/1000) -> 0
A33: Soda | B33: 1781.02 | C33: kg | P33: =SUM(D33:O33) -> 0
C34: kg/mg litre | D34: =D33/(D9/1000) -> 0 | E34: =E33/(E9/1000) -> 0 | F34: =F33/(F9/1000) -> 0 | G34: =G33/(G9/1000) -> #DIV/0! | H34: =H33/(H9/1000) -> #DIV/0! | I34: =I33/(I9/1000) -> #DIV/0! | J34: =J33/(J9/1000) -> #DIV/0! | K34: =K33/(K9/1000) -> #DIV/0! | ... N34: =N33/(N9/1000) -> #DIV/0! | P34: =P33/(P9/1000) -> 0
A35: Algae floc | B35: 5979.95 | C35: litres
C36: litres/mg litre
A37: Sud floc | B37: 5403.75 | C37: litres | P37: =SUM(D37:O37) -> 0
C38: litres/mg litre | D38: =D37/(D9/1000) -> 0 | E38: =E37/(E9/1000) -> 0 | F38: =F37/(F9/1000) -> 0 | G38: =G37/(G9/1000) -> #DIV/0! | H38: =H37/(H9/1000) -> #DIV/0! | I38: =I37/(I9/1000) -> #DIV/0! | J38: =J37/(J9/1000) -> #DIV/0! | K38: =K37/(K9/1000) -> #DIV/0! | ... N38: =N37/(N9/1000) -> #DIV/0! | P38: =P37/(P9/1000) -> 0
A39: Potasium permanganate | B39: 1950 | C39: kg | P39: =SUM(D39:O39) -> 0
C40: kg/mg litre | D40: =D39/(D9/1000) -> 0 | E40: =E39/(E9/1000) -> 0 | F40: =F39/(F9/1000) -> 0 | G40: =G39/(G9/1000) -> #DIV/0! | H40: =H39/(H9/1000) -> #DIV/0! | I40: =I39/(I9/1000) -> #DIV/0! | J40: =J39/(J9/1000) -> #DIV/0! | K40: =K39/(K9/1000) -> #DIV/0! | ... N40: =N39/(N9/1000) -> #DIV/0! | P40: =P39/(P9/1000) -> 0
A41: Cost of Chemicals | C41: Mk | D41: =(D29*$B29)+(D31*$B31)+(D33*$B33)+(D35*$B35)+(D37*$B37)+(D39*$B39) -> 97121.73 | E41: =(E29*$B29)+(E31*$B31)+(E33*$B33)+(E35*$B35)+(E37*$B37)+(E39*$B39) -> 112456.74 | F41: =(F29*$B29)+(F31*$B31)+(F33*$B33)+(F35*$B35)+(F37*$B37)+(F39*$B39) -> 76675.05 | G41: =(G29*$B29)+(G31*$B31)+(G33*$B33)+(G35*$B35)+(G37*$B37)+(G39*$B39) -> 0 | H41: =(H29*$B29)+(H31*$B31)+(H33*$B33)+(H35*$B35)+(H37*$B37)+(H39*$B39) -> 0 | I41: =(I29*$B29)+(I31*$B31)+(I33*$B33)+(I35*$B35)+(I37*$B37)+(I39*$B39) -> 0 | J41: =(J29*$B29)+(J31*$B31)+(J33*$B33)+(J35*$B35)+(J37*$B37)+(J39*$B39) -> 0 | K41: =(K29*$B29)+(K31*$B31)+(K33*$B33)+(K35*$B35)+(K37*$B37)+(K39*$B39) -> 0 | ... O41: =(O29*$B29)+(O31*$B31)+(O33*$B33)+(O35*$B35)+(O37*$B37)+(O39*$B39) -> 0 | P41: =SUM(D41:O41) -> 286253.52
A42: Cost/vol. Produced (chemicals) | C42: Mk/m3 | D42: =D41/D9 -> 5.1466128 | E42: =E41/E9 -> 4.7177388 | F42: =F41/F9 -> 4.3375601 | G42: =G41/G9 -> #DIV/0! | H42: =H41/H9 -> #DIV/0! | I42: =I41/I9 -> #DIV/0! | J42: =J41/J9 -> #DIV/0! | K42: =K41/K9 -> #DIV/0! | ... P42: =P41/P9 -> 4.740474
A43: Power
A44: Power Usage | C44: Kw | D44: 14230 | E44: 14230 | F44: 6390 | P44: =SUM(D44:O44) -> 34850
A45: Power/ Vol. Produced | C45: Kw/m3 | D45: =D44/D9 -> 0.75406709 | E45: 0.5969711 | F45: =F44/F9 -> 0.36148668 | G45: =G44/G9 -> #DIV/0! | H45: =H44/H9 -> #DIV/0! | I45: =I44/I9 -> #DIV/0! | J45: =J44/J9 -> #DIV/0! | K45: =K44/K9 -> #DIV/0! | L45: =L44/L9 -> #DIV/0! | M45: =M44/M9 -> #DIV/0! | P45: =P44/P9 -> 0.57713008
A46: Cost of Power | C46: Mk | D46: =333.87*D44 -> 4750970.1 | E46: =333.87*E44 -> 4750970.1 | F46: =333.87*F44 -> 2133429.3 | G46: =333.87*G44 -> 0 | H46: =333.87*H44 -> 0 | I46: =333.87*I44 -> 0 | J46: =333.87*J44 -> 0 | K46: =333.87*K44 -> 0 | ... O46: =333.87*O44 -> 0 | P46: =SUM(D46:O46) -> 11635370
A47: Cost/vol. Produced | C47: Mk/m3 | D47: =D46/D9 -> 251.76038 | E47: =E46/E9 -> 199.31074 | F47: =F46/F9 -> 120.68956 | G47: =G46/G9 -> #DIV/0! | H47: =H46/H9 -> #DIV/0! | I47: =I46/I9 -> #DIV/0! | J47: =J46/J9 -> #DIV/0! | K47: =K46/K9 -> #DIV/0! | ... P47: =P46/P9 -> 192.68642
A48: Plant and Vehicle Maintenance
A49: Distances covered | C49: km | P49: =SUM(D49:O49) -> 0
A50: Fuel Used (litres) | C50: litres | P50: =SUM(D50:O50) -> 0
A51: Cost of fuel | C51: Mk | E51: =2734*E50 -> 0 | F51: =2734*F50 -> 0 | M51: =2734*M50 -> 0 | P51: =SUM(D51:O51) -> 0
A52: Maintenance | C52: Mk | P52: =SUM(D52:O52) -> 0
A53: Salaries and Wages
A54: Staff Costs | C54: MK | D54: 9377117.4 | E54: 9459007.2 | F54: 9459007.2 | P54: =SUM(D54:O54) -> 28295132
A55: Wages | C55: MK | F55: 3158418.6 | P55: =SUM(D55:O55) -> 3158418.6
A56: Other Overhead Costs | C56: MK | D56: 8454058.9 | E56: 8691498 | F56: 2815642.1 | P56: =SUM(D56:O56) -> 19961199
A57: Operating Costs
A58: Total Operating Costs | C58: MK | D58: =D41+D46+D51+D52+D54+D55+D56 -> 22679268 | E58: =E41+E46+E51+E52+E54+E55+E56 -> 23013932 | F58: =F41+F46+F51+F52+F54+F55+F56 -> 17643172 | G58: =G41+G46+G51+G52+G54+G55+G56 -> 0 | H58: =H41+H46+H51+H52+H54+H55+H56 -> 0 | I58: =I41+I46+I51+I52+I54+I55+I56 -> 0 | J58: =J41+J46+J51+J52+J54+J55+J56 -> 0 | K58: =K41+K46+K51+K52+K54+K55+K56 -> 0 | ... N58: =N41+N46+N51+N52+N54+N55+N56 -> 0 | P58: =SUM(D58:O58) -> 63336373
A59: Cost/Vol. Produced | C59: Mk/m3 | D59: =D58/D9 -> 1201.8053 | E59: =E58/E9 -> 965.47099 | F59: =F58/F9 -> 998.08635 | G59: =G58/G9 -> #DIV/0! | H59: =H58/H9 -> #DIV/0! | I59: =I58/I9 -> #DIV/0! | J59: =J58/J9 -> #DIV/0! | K59: =K58/K9 -> #DIV/0! | ... N59: =N58/N9 -> #DIV/0! | P59: =P58/P9 -> 1048.8759
A60: Cost/Vol. Billed | C60: Mk/m3 | D60: =D58/D22 -> 1470.1976 | E60: =E58/E22 -> 1209.0959 | F60: =F58/F22 -> 1325.5577 | G60: =G58/G22 -> #DIV/0! | H60: =H58/H22 -> #DIV/0! | I60: =I58/I22 -> #DIV/0! | J60: =J58/J22 -> #DIV/0! | K60: =K58/K22 -> #DIV/0! | ... N60: =N58/N22 -> #DIV/0! | P60: =P58/P22 -> 1325.8608
A61: Permanent Staff Employed | C61: No | D61: 4 | E61: 4 | F61: 4 | P61: =O61 -> 0
A62: Staff/Vol.1000m3 of Volume Produced/hour (12 hour day) | C62: No/1000m3 | D62: =(D61*1000*31)/D9 -> 6.5709289 | E62: =(E61*1000*31)/E9 -> 5.2019969 | F62: =(F61*1000*31)/F9 -> 7.0147649 | G62: =(G61*1000*31)/G9 -> #DIV/0! | H62: =(H61*1000*31)/H9 -> #DIV/0! | I62: =(I61*1000*31)/I9 -> #DIV/0! | J62: =(J61*1000*31)/J9 -> #DIV/0! | K62: =(K61*1000*31)/K9 -> #DIV/0! | ... N62: =(N61*1000*31)/N9 -> #DIV/0! | P62: =(P61*1000*31)/P9 -> 0
A63: Temporary Staff Employed | C63: No | D63: 14 | E63: 14 | F63: 14 | P63: =SUM(D63:O63) -> 42
A65: Water Connections and Disconnections
A66: New Individual Water Connections | B66: Brought Forward | C66: No | D66: 1 | E66: =D71 -> 1 | F66: =E71 -> 4 | G66: =F71 -> 3 | H66: =G71 -> 3 | I66: =H71 -> 3 | J66: =I71 -> 3 | K66: =J71 -> 3 | L66: =K71 -> 3 | ... O66: =N71 -> 3 | P66: =D66 -> 1
B67: Applied this Month | C67: No | D67: 4 | E67: 5 | F67: 8 | P67: =SUM(D67:O67) -> 17
B68: Done this Month Postpaid | C68: No | E68: 2 | F68: 9 | P68: =SUM(D68:O68) -> 11
B69: Done this Month Prepaid | C69: No | D69: 4 | E69: 0 | F69: 0 | P69: =SUM(D69:O69) -> 4
B70: Total Done | C70: No | D70: 4 | E70: =E68+E69 -> 2 | F70: =F68+F69 -> 9 | P70: =P68+P69 -> 15
B71: Carried Forward | C71: No | D71: =D66+D67-D70 -> 1 | E71: =E66+E67-E70 -> 4 | F71: =F66+F67-F70 -> 3 | G71: =G66+G67-G70 -> 3 | H71: =H66+H67-H70 -> 3 | I71: =I66+I67-I70 -> 3 | J71: =J66+J67-J70 -> 3 | K71: =K66+K67-K70 -> 3 | ... N71: =N66+N67-N70 -> 3 | P71: =P66+P67-P70 -> 3
A72: New Institutional Water Connections | B72: Brought Forward | C72: No | E72: =D77 -> 1 | F72: =E77 -> 0 | G72: =F77 -> 0 | I72: =H77 -> 0 | P72: =D72 -> 0
B73: Applied this Month | C73: No | D73: 1 | P73: =SUM(D73:O73) -> 1
B74: Done this Month Postpaid | C74: No | E74: 1 | P74: =SUM(D74:O74) -> 1
B75: Done this Month Prepaid | C75: No | P75: =SUM(D75:O75) -> 0
B76: Total Done | C76: No | D76: =D74+D75 -> 0 | E76: =E74+E75 -> 1 | F76: =F74+F75 -> 0 | G76: =G74+G75 -> 0 | H76: =H74+H75 -> 0 | I76: =I74+I75 -> 0 | J76: =J74+J75 -> 0 | K76: =K74+K75 -> 0 | M76: =M74+M75 -> 0 | N76: =N74+N75 -> 0 | P76: =P74+P75 -> 1
B77: Carried Forward | C77: No | D77: =D72+D73-D76 -> 1 | E77: =E72+E73-E76 -> 0 | F77: =F72+F73-F76 -> 0 | G77: =G72+G73-G76 -> 0 | H77: =H72+H73-H76 -> 0 | I77: =I72+I73-I76 -> 0 | J77: =J72+J73-J76 -> 0 | K77: =K72+K73-K76 -> 0 | ... N77: =N72+N73-N76 -> 0 | P77: =P72+P73-P76 -> 0
A78: New Commercial/Industrial Water Connections | B78: Brought Forward | C78: No | E78: =D83 -> 0 | F78: =E83 -> 0 | G78: =F83 -> 0 | H78: =G83 -> 0 | I78: =H83 -> 0 | J78: =I83 -> 0 | K78: =J83 -> 0 | L78: =K83 -> 0 | ... N78: =M83 -> 0 | P78: =D78 -> 0
B79: Applied this Month | C79: No | P79: =SUM(D79:O79) -> 0
B80: Done this Month Postpaid | C80: No | P80: =SUM(D80:O80) -> 0
B81: Done this Month Prepaid | C81: No | P81: =SUM(D81:O81) -> 0
B82: Total Done | C82: No | D82: =D81+D80 -> 0 | E82: =E81+E80 -> 0 | F82: =F81+F80 -> 0 | G82: =G81+G80 -> 0 | H82: =H81+H80 -> 0 | I82: =I80+I81 -> 0 | J82: =J80+J81 -> 0 | K82: =K80+K81 -> 0 | M82: =M81+M80 -> 0 | N82: =N81+N80 -> 0 | P82: =P81+P80 -> 0
B83: Carried Forward | C83: No | D83: =D78+D79-D82 -> 0 | E83: =E78+E79-E82 -> 0 | F83: =F78+F79-F82 -> 0 | G83: =G78+G79-G82 -> 0 | H83: =H78+H79-H82 -> 0 | I83: =I78+I79-I82 -> 0 | J83: =J78+J79-J82 -> 0 | K83: =K78+K79-K82 -> 0 | ... N83: =N78+N79-N82 -> 0 | P83: =P78+P79-P82 -> 0
A84: New CWP | B84: Brought Forward | C84: No | E84: =D89 -> 0 | F84: =E89 -> 0 | G84: =F89 -> 0 | H84: =G89 -> 0 | P84: =D84 -> 0
B85: Applied this Month | C85: No | P85: =SUM(D85:O85) -> 0
B86: Done this Month Postpaid | C86: No | P86: =SUM(D86:O86) -> 0
B87: Done this Month Prepaid | C87: No | P87: =SUM(D87:O87) -> 0
B88: Total Done | C88: No | D88: =D86+D87 -> 0 | E88: =E86+E87 -> 0 | F88: =F86+F87 -> 0 | G88: =G86+G87 -> 0 | H88: =H86+H87 -> 0 | I88: =I86+I87 -> 0 | J88: =J86+J87 -> 0 | K88: =K86+K87 -> 0 | ... N88: =N86+N87 -> 0 | P88: =SUM(D88:O88) -> 0
B89: Carried Forward | C89: No | D89: =D84+D85-D88 -> 0 | E89: =E84+E85-E88 -> 0 | F89: =F84+F85-F88 -> 0 | G89: =G84+G85-G88 -> 0 | H89: =H84+H85-H88 -> 0 | I89: =I84+I85-I88 -> 0 | J89: =J84+J85-J88 -> 0 | K89: =K84+K85-K88 -> 0 | ... N89: =N84+N85-N88 -> 0 | P89: =P84+P85-P86-P87 -> 0
A90: Aggregated New Water connections | B90: Brought Forward | C90: No | D90: =D66+D72+D78+D84 -> 1 | E90: =E66+E72+E78+E84 -> 2 | F90: =F66+F72+F78+F84 -> 4 | G90: =G66+G72+G78+G84 -> 3 | H90: =H66+H72+H78+H84 -> 3 | I90: =I66+I72+I78+I84 -> 3 | J90: =J66+J72+J78+J84 -> 3 | K90: =K66+K72+K78+K84 -> 3 | ... N90: =N66+N72+N78+N84 -> 3 | P90: =D90 -> 1
B91: Applied this Month | C91: No | D91: =D67+D73+D79+D85 -> 5 | E91: =E67+E73+E79+E85 -> 5 | F91: =F67+F73+F79+F85 -> 8 | G91: =G67+G73+G79+G85 -> 0 | H91: =H67+H73+H79+H85 -> 0 | I91: =I67+I73+I79+I85 -> 0 | J91: =J67+J73+J79+J85 -> 0 | K91: =K67+K73+K79+K85 -> 0 | ... N91: =N67+N73+N79+N85 -> 0 | P91: =SUM(D91:O91) -> 18
B92: Done this Month Postpaid | C92: No | D92: =D68+D74+D80+D86 -> 0 | E92: =E68+E74+E80+E86 -> 3 | F92: =F68+F74+F80+F86 -> 9 | G92: =G68+G74+G80+G86 -> 0 | H92: =H68+H74+H80+H86 -> 0 | I92: =I68+I74+I80+I86 -> 0 | J92: =J68+J74+J80+J86 -> 0 | K92: =K68+K74+K80+K86 -> 0 | ... N92: =N68+N74+N80+N86 -> 0 | P92: =SUM(D92:O92) -> 12
B93: Done this Month Prepaid | D93: =D69+D75+D81+D87 -> 4 | E93: =E69+E75+E81+E87 -> 0 | F93: =F69+F75+F81+F87 -> 0 | G93: =G69+G75+G81+G87 -> 0 | H93: =H69+H75+H81+H87 -> 0 | I93: =I69+I75+I81+I87 -> 0 | J93: =J69+J75+J81+J87 -> 0 | K93: =K69+K75+K81+K87 -> 0 | ... N93: =N69+N75+N81+N87 -> 0 | P93: =SUM(D93:O93) -> 4
B94: Total Done | C94: No | D94: =D93+D92 -> 4 | E94: =E93+E92 -> 3 | F94: =F93+F92 -> 9 | G94: =G93+G92 -> 0 | H94: =H93+H92 -> 0 | I94: =I93+I92 -> 0 | J94: =J93+J92 -> 0 | K94: =K93+K92 -> 0 | ... N94: =N93+N92 -> 0 | P94: =P93+P92 -> 16
B95: Carried Forward | C95: No | D95: =D90+D91-D94 -> 2 | E95: =E90+E91-E94 -> 4 | F95: =F90+F91-F94 -> 3 | G95: =G90+G91-G94 -> 3 | H95: =H90+H91-H94 -> 3 | I95: =I90+I91-I94 -> 3 | J95: =J90+J91-J94 -> 3 | K95: =K90+K91-K94 -> 3 | ... N95: =N90+N91-N94 -> 3 | P95: =P90+P91-P94 -> 3
A97: Prepaid Metering
A98: Prepaid Meters Installed | C98: No | D98: 4 | P98: =SUM(D98:O98) -> 4
A100: Active and Disconnected Accounts
A101: Disconnected Individual Accounts | C101: No | D101: 12 | E101: 12 | F101: 12 | P101: =O101 -> 0
A102: Disconnected institutional Accounts | C102: No | D102: 1 | E102: 1 | F102: 1 | P102: =O102 -> 0
A103: Disconnected Commercial/Industrial Accounts | C103: No | D103: 11 | E103: 11 | F103: 11 | P103: =O103 -> 0
A104: Disconnected CWP | C104: No | P104: =O104 -> 0
A105: Total Disconnected Accounts | C105: No | D105: =SUM(D101:D104) -> 24 | E105: =SUM(E101:E104) -> 24 | F105: =SUM(F101:F104) -> 24 | G105: =SUM(G101:G104) -> 0 | H105: =SUM(H101:H104) -> 0 | I105: =SUM(I101:I104) -> 0 | J105: =SUM(J101:J104) -> 0 | K105: =SUM(K101:K104) -> 0 | ... O105: =SUM(O101:O104) -> 0 | P105: =O105 -> 0
A106: Postpaid Consumers
...

Sheet Phalombe
A1: SOUTHERN REGION WATER BOARD
A3: MONTHLY REPORTS - 2026/2027
A4: MULANJE ZONE
A5: MULANJE ZONE
A7: PARAMETERS | C7: UNITS | D7: APRIL | E7: MAY | F7: JUNE | G7: JULY | H7: AUGUST | I7: SEPTEMBER | J7: OCTOBER | K7: NOVEMBER | L7: DECEMBER | M7: JANUARY | N7: FEBRUARY | O7: MARCH | P7: TOTALS
A8: PRODUCTION
A9: Volume Produced | C9: m3 | D9: 8721 | E9: 8182 | F9: 9627 | P9: =SUM(D9:O9) -> 26530
A10: REVENUE WATER - POSTPAID
A11: Volume Billed Individuals | C11: m3 | D11: 2418 | E11: 2324 | F11: 2959 | P11: =SUM(D11:O11) -> 7701
A12: Volume Billed CWPs | C12: m3 | P12: =SUM(D12:O12) -> 0
A13: Volume Billed Institutions | C13: m3 | P13: =SUM(D13:O13) -> 0
A14: Volume Billed Commercial/Industrial | C14: m3 | D14: 4 | E14: 5 | F14: 4 | P14: =SUM(D14:O14) -> 13
A15: Total Volume Billed Post Paid | C15: m3 | D15: =SUM(D11:D14) -> 2422 | E15: =SUM(E11:E14) -> 2329 | F15: =SUM(F11:F14) -> 2963 | G15: =SUM(G11:G14) -> 0 | H15: =SUM(H11:H14) -> 0 | I15: =SUM(I11:I14) -> 0 | J15: =SUM(J11:J14) -> 0 | K15: =SUM(K11:K14) -> 0 | ... P15: =SUM(P11:P14) -> 7714
A16: REVENUE WATER - PREPAID
A17: Individuals | C17: m3 | D17: 3726.5 | E17: 3179 | F17: 2942 | P17: =SUM(D17:O17) -> 9847.5
A18: CWPs | C18: m3 | D18: 40.4 | E18: 50 | F18: 50 | P18: =SUM(D18:O18) -> 140.4
A19: Institutions | C19: m3 | D19: 157.6 | E19: 66 | F19: 744.3 | P19: =SUM(D19:O19) -> 967.9
A20: Commercial/Industrial | C20: m3 | D20: 111 | E20: 77 | F20: 159.9 | P20: =SUM(D20:O20) -> 347.9
A21: Total Volume Prepaid | C21: m3 | D21: =SUM(D17:D20) -> 4035.5 | E21: =SUM(E17:E20) -> 3372 | F21: =SUM(F17:F20) -> 3896.2 | G21: =SUM(G17:G20) -> 0 | H21: =SUM(H17:H20) -> 0 | I21: =SUM(I17:I20) -> 0 | J21: =SUM(J17:J20) -> 0 | K21: =SUM(K17:K20) -> 0 | ... P21: =SUM(P17:P20) -> 11303.7
A22: TOTAL REVENUE WATER | C22: m3 | D22: =D21+D15 -> 6457.5 | E22: =E21+E15 -> 5701 | F22: =F21+F15 -> 6859.2 | G22: =G21+G15 -> 0 | H22: =H21+H15 -> 0 | I22: =I21+I15 -> 0 | J22: =J21+J15 -> 0 | K22: =K21+K15 -> 0 | ... P22: =P21+P15 -> 19017.7
A24: Non-Revenue Water (NRW) | B24: Volume | C24: m3 | D24: =D9-D22 -> 2263.5 | E24: =E9-E22 -> 2481 | F24: =F9-F22 -> 2767.8 | G24: =G9-G22 -> 0 | H24: =H9-H22 -> 0 | I24: =I9-I22 -> 0 | J24: =J9-J22 -> 0 | K24: =K9-K22 -> 0 | ... P24: =P9-P22 -> 7512.3
B25: Percentage | C25: % | D25: =D24/D9 -> 0.25954592 | E25: =E24/E9 -> 0.30322659 | F25: =F24/F9 -> 0.2875039 | G25: =G24/G9 -> #DIV/0! | H25: =H24/H9 -> #DIV/0! | I25: =I24/I9 -> #DIV/0! | J25: =J24/J9 -> #DIV/0! | K25: =K24/K9 -> #DIV/0! | ... P25: =P24/P9 -> 0.28316246
A26: OPERATING EXPENSES
A27: Chemicals
A28: Chemical | B28: Rate(MK/kg)
A29: Chlorine | B29: 5111.67 | C29: kg | D29: 24 | E29: 24 | F29: 24 | P29: =SUM(D29:O29) -> 72
C30: kg/mg litre | D30: =D29/(D9/1000) -> 2.751978 | E30: =E29/(E9/1000) -> 2.9332681 | F30: =F29/(F9/1000) -> 2.4929885 | G30: =G29/(G9/1000) -> #DIV/0! | H30: =H29/(H9/1000) -> #DIV/0! | I30: =I29/(I9/1000) -> #DIV/0! | J30: =J29/(J9/1000) -> #DIV/0! | K30: =K29/(K9/1000) -> #DIV/0! | ... N30: =N29/(N9/1000) -> #DIV/0! | P30: =P29/(P9/1000) -> 2.7139088
A31: Aluminium sulphate | B31: 1537 | C31: kg | P31: =SUM(D31:O31) -> 0
C32: kg/mg litre | D32: =D31/(D9/1000) -> 0 | E32: =E31/(E9/1000) -> 0 | F32: =F31/(F9/1000) -> 0 | G32: =G31/(G9/1000) -> #DIV/0! | H32: =H31/(H9/1000) -> #DIV/0! | I32: =I31/(I9/1000) -> #DIV/0! | J32: =J31/(J9/1000) -> #DIV/0! | K32: =K31/(K9/1000) -> #DIV/0! | ... N32: =N31/(N9/1000) -> #DIV/0! | P32: =P31/(P9/1000) -> 0
A33: Soda | B33: 1781.02 | C33: kg | P33: =SUM(D33:O33) -> 0
C34: kg/mg litre | D34: =D33/(D9/1000) -> 0 | E34: =E33/(E9/1000) -> 0 | F34: =F33/(F9/1000) -> 0 | G34: =G33/(G9/1000) -> #DIV/0! | H34: =H33/(H9/1000) -> #DIV/0! | I34: =I33/(I9/1000) -> #DIV/0! | J34: =J33/(J9/1000) -> #DIV/0! | K34: =K33/(K9/1000) -> #DIV/0! | ... N34: =N33/(N9/1000) -> #DIV/0! | P34: =P33/(P9/1000) -> 0
A35: Algae floc | B35: 5979.95 | C35: litres
C36: litres/mg litre
A37: Sud floc | B37: 5403.75 | C37: litres | P37: =SUM(D37:O37) -> 0
C38: litres/mg litre | D38: =D37/(D9/1000) -> 0 | E38: =E37/(E9/1000) -> 0 | F38: =F37/(F9/1000) -> 0 | G38: =G37/(G9/1000) -> #DIV/0! | H38: =H37/(H9/1000) -> #DIV/0! | I38: =I37/(I9/1000) -> #DIV/0! | J38: =J37/(J9/1000) -> #DIV/0! | K38: =K37/(K9/1000) -> #DIV/0! | ... N38: =N37/(N9/1000) -> #DIV/0! | P38: =P37/(P9/1000) -> 0
A39: Potasium permanganate | B39: 1950 | C39: kg | P39: =SUM(D39:O39) -> 0
C40: kg/mg litre | D40: =D39/(D9/1000) -> 0 | E40: =E39/(E9/1000) -> 0 | F40: =F39/(F9/1000) -> 0 | G40: =G39/(G9/1000) -> #DIV/0! | H40: =H39/(H9/1000) -> #DIV/0! | I40: =I39/(I9/1000) -> #DIV/0! | J40: =J39/(J9/1000) -> #DIV/0! | K40: =K39/(K9/1000) -> #DIV/0! | ... N40: =N39/(N9/1000) -> #DIV/0! | P40: =P39/(P9/1000) -> 0
A41: Cost of Chemicals | C41: Mk | D41: =(D29*$B29)+(D31*$B31)+(D33*$B33)+(D35*$B35)+(D37*$B37)+(D39*$B39) -> 122680.08 | E41: =(E29*$B29)+(E31*$B31)+(E33*$B33)+(E35*$B35)+(E37*$B37)+(E39*$B39) -> 122680.08 | F41: =(F29*$B29)+(F31*$B31)+(F33*$B33)+(F35*$B35)+(F37*$B37)+(F39*$B39) -> 122680.08 | G41: =(G29*$B29)+(G31*$B31)+(G33*$B33)+(G35*$B35)+(G37*$B37)+(G39*$B39) -> 0 | H41: =(H29*$B29)+(H31*$B31)+(H33*$B33)+(H35*$B35)+(H37*$B37)+(H39*$B39) -> 0 | I41: =(I29*$B29)+(I31*$B31)+(I33*$B33)+(I35*$B35)+(I37*$B37)+(I39*$B39) -> 0 | J41: =(J29*$B29)+(J31*$B31)+(J33*$B33)+(J35*$B35)+(J37*$B37)+(J39*$B39) -> 0 | K41: =(K29*$B29)+(K31*$B31)+(K33*$B33)+(K35*$B35)+(K37*$B37)+(K39*$B39) -> 0 | ... O41: =(O29*$B29)+(O31*$B31)+(O33*$B33)+(O35*$B35)+(O37*$B37)+(O39*$B39) -> 0 | P41: =SUM(D41:O41) -> 368040.24
A42: Cost/vol. Produced (chemicals) | C42: Mk/m3 | D42: =D41/D9 -> 14.067203 | E42: =E41/E9 -> 14.993899 | F42: =F41/F9 -> 12.743334 | G42: =G41/G9 -> #DIV/0! | H42: =H41/H9 -> #DIV/0! | I42: =I41/I9 -> #DIV/0! | J42: =J41/J9 -> #DIV/0! | K42: =K41/K9 -> #DIV/0! | ... P42: =P41/P9 -> 13.872606
A43: Power
A44: Power Usage | C44: Kw | D44: 50 | E44: 60 | F44: 55 | P44: =SUM(D44:O44) -> 165
A45: Power/ Vol. Produced | C45: Kw/m3 | D45: =D44/D9 -> 0.0057332875 | E45: =E44/E9 -> 0.0073331704 | F45: =F44/F9 -> 0.0057130986 | G45: =G44/G9 -> #DIV/0! | H45: =H44/H9 -> #DIV/0! | I45: =I44/I9 -> #DIV/0! | J45: =J44/J9 -> #DIV/0! | K45: =K44/K9 -> #DIV/0! | ... N45: =N44/N9 -> #DIV/0! | P45: =P44/P9 -> 0.0062193743
A46: Cost of Power | C46: Mk | D46: =295.56*D44 -> 14778 | E46: =295.56*E44 -> 17733.6 | F46: =295.56*F44 -> 16255.8 | G46: =295.56*G44 -> 0 | H46: =295.56*H44 -> 0 | I46: =295.56*I44 -> 0 | J46: =295.56*J44 -> 0 | K46: =295.56*K44 -> 0 | ... O46: =295.56*O44 -> 0 | P46: =SUM(D46:O46) -> 48767.4
A47: Cost/vol. Produced | C47: Mk/m3 | D47: =D46/D9 -> 1.6945304 | E47: =E46/E9 -> 2.1673918 | F47: =F46/F9 -> 1.6885634 | G47: =G46/G9 -> #DIV/0! | H47: =H46/H9 -> #DIV/0! | I47: =I46/I9 -> #DIV/0! | J47: =J46/J9 -> #DIV/0! | K47: =K46/K9 -> #DIV/0! | ... P47: =P46/P9 -> 1.8381983
A48: Plant and Vehicle Maintenance
A49: Distances covered | C49: km | P49: =SUM(D49:O49) -> 0
A50: Fuel Used (litres) | C50: litres | P50: =SUM(D50:O50) -> 0
A51: Cost of fuel | C51: Mk | D51: =D49*2530 -> 0 | P51: =SUM(D51:O51) -> 0
A52: Maintenance | C52: Mk | P52: =SUM(D52:O52) -> 0
A53: Salaries and Wages
A54: Staff Costs | C54: MK | D54: 5094517.1 | E54: 5070265 | F54: 5070265 | P54: =SUM(D54:O54) -> 15235047
A55: Wages | C55: MK | D55: 1357285.5 | E55: 1292850.6 | F55: 1725879 | P55: =SUM(D55:O55) -> 4376015.1
A56: Other Overhead Costs | C56: MK | D56: 2661609.5 | E56: 3242091.5 | P56: =SUM(D56:O56) -> 5903701.1
A57: Operating Costs
A58: Total Operating Costs | C58: MK | D58: =D41+D46+D51+D52+D54+D55+D56 -> 9250870.3 | E58: =E41+E46+E51+E52+E54+E55+E56 -> 9745620.8 | F58: =F41+F46+F51+F52+F54+F55+F56 -> 6935079.9 | G58: =G41+G46+G51+G52+G54+G55+G56 -> 0 | H58: =H41+H46+H51+H52+H54+H55+H56 -> 0 | I58: =I41+I46+I51+I52+I54+I55+I56 -> 0 | J58: =J41+J46+J51+J52+J54+J55+J56 -> 0 | K58: =K41+K46+K51+K52+K54+K55+K56 -> 0 | ... N58: =N41+N46+N51+N52+N54+N55+N56 -> 0 | P58: =SUM(D58:O58) -> 25931571
A59: Cost/Vol. Produced | C59: Mk/m3 | D59: =D58/D9 -> 1060.758 | E59: =E58/E9 -> 1191.105 | F59: =F58/F9 -> 720.37809 | G59: =G58/G9 -> #DIV/0! | H59: =H58/H9 -> #DIV/0! | I59: =I58/I9 -> #DIV/0! | J59: =J58/J9 -> #DIV/0! | K59: =K58/K9 -> #DIV/0! | ... N59: =N58/N9 -> #DIV/0! | P59: =P58/P9 -> 977.44331
A60: Cost/Vol. Billed | C60: Mk/m3 | D60: =D58/D22 -> 1432.5777 | E60: =E58/E22 -> 1709.4581 | F60: =F58/F22 -> 1011.0625 | G60: =G58/G22 -> #DIV/0! | H60: =H58/H22 -> #DIV/0! | I60: =I58/I22 -> #DIV/0! | J60: =J58/J22 -> #DIV/0! | K60: =K58/K22 -> #DIV/0! | ... N60: =N58/N22 -> #DIV/0! | P60: =P58/P22 -> 1363.5493
A61: Permanent Staff Employed | C61: No | D61: 4 | E61: 4 | F61: 4 | P61: =O61 -> 0
A62: Staff/Vol.1000m3 of Volume Produced/hour (12 hour day) | C62: No/1000m3 | D62: =(D61*1000*31)/D9 -> 14.218553 | E62: =(E61*1000*31)/E9 -> 15.155219 | F62: =(F61*1000*31)/F9 -> 12.88044 | G62: =(G61*1000*31)/G9 -> #DIV/0! | H62: =(H61*1000*31)/H9 -> #DIV/0! | I62: =(I61*1000*31)/I9 -> #DIV/0! | J62: =(J61*1000*31)/J9 -> #DIV/0! | K62: =(K61*1000*31)/K9 -> #DIV/0! | ... N62: =(N61*1000*31)/N9 -> #DIV/0! | P62: =(P61*1000*31)/P9 -> 0
A63: Temporary Staff Employed | C63: No | D63: 12 | E63: 12 | F63: 12 | P63: =SUM(D63:O63) -> 36
A65: Water Connections and Disconnections
A66: New Individual Water Connections | B66: Brought Forward | C66: No | D66: 38 | E66: =D71 -> 35 | F66: =E71 -> 42 | G66: =F71 -> 40 | H66: =G71 -> 40 | I66: =H71 -> 40 | J66: =I71 -> 40 | K66: =J71 -> 40 | L66: =K71 -> 40 | ... O66: =N71 -> 40 | P66: =D66 -> 38
B67: Applied this Month | C67: No | D67: 3 | E67: 7 | F67: 6 | P67: =SUM(D67:O67) -> 16
B68: Done this Month Postpaid | C68: No | P68: =SUM(D68:O68) -> 0
B69: Done this Month Prepaid | C69: No | D69: 6 | F69: 8 | P69: =SUM(D69:O69) -> 14
B70: Total Done | C70: No | D70: 6 | E70: =E68+E69 -> 0 | F70: =F68+F69 -> 8 | G70: =G68+G69 -> 0 | I70: =I68+I69 -> 0 | J70: =J68+J69 -> 0 | K70: =K68+K69 -> 0 | L70: =L68+L69 -> 0 | M70: =M68+M69 -> 0 | N70: =N68+N69 -> 0 | P70: =P68+P69 -> 14
B71: Carried Forward | C71: No | D71: =D66+D67-D70 -> 35 | E71: =E66+E67-E70 -> 42 | F71: =F66+F67-F70 -> 40 | G71: =G66+G67-G70 -> 40 | H71: =H66+H67-H70 -> 40 | I71: =I66+I67-I70 -> 40 | J71: =J66+J67-J70 -> 40 | K71: =K66+K67-K70 -> 40 | ... N71: =N66+N67-N70 -> 40 | P71: =P66+P67-P70 -> 40
A72: New Institutional Water Connections | B72: Brought Forward | C72: No | E72: =D77 -> 0 | F72: =E77 -> 0 | G72: =F77 -> 0 | H72: =G77 -> 0 | P72: =D72 -> 0
B73: Applied this Month | C73: No | P73: =SUM(D73:O73) -> 0
B74: Done this Month Postpaid | C74: No | P74: =SUM(D74:O74) -> 0
B75: Done this Month Prepaid | C75: No | P75: =SUM(D75:O75) -> 0
B76: Total Done | C76: No | D76: =D74+D75 -> 0 | E76: =E74+E75 -> 0 | F76: =F74+F75 -> 0 | G76: =G74+G75 -> 0 | H76: =H74+H75 -> 0 | I76: =I74+I75 -> 0 | J76: =J74+J75 -> 0 | K76: =K74+K75 -> 0 | M76: =M74+M75 -> 0 | N76: =N74+N75 -> 0 | P76: =P74+P75 -> 0
B77: Carried Forward | C77: No | D77: =D72+D73-D76 -> 0 | E77: =E72+E73-E76 -> 0 | F77: =F72+F73-F76 -> 0 | G77: =G72+G73-G76 -> 0 | H77: =H72+H73-H76 -> 0 | I77: =I72+I73-I76 -> 0 | J77: =J72+J73-J76 -> 0 | K77: =K72+K73-K76 -> 0 | ... N77: =N72+N73-N76 -> 0 | P77: =P72+P73-P76 -> 0
A78: New Commercial/Industrial Water Connections | B78: Brought Forward | C78: No | F78: =E83 -> 0 | H78: =G83 -> 0 | I78: =H83 -> 0 | J78: =I83 -> 0 | K78: =J83 -> 0 | L78: =K83 -> 0 | M78: =L83 -> 0 | N78: =M83 -> 0 | P78: =D78 -> 0
B79: Applied this Month | C79: No | P79: =SUM(D79:O79) -> 0
B80: Done this Month Postpaid | C80: No | P80: =SUM(D80:O80) -> 0
B81: Done this Month Prepaid | C81: No | P81: =SUM(D81:O81) -> 0
B82: Total Done | C82: No | D82: =D81+D80 -> 0 | E82: =E81+E80 -> 0 | F82: =F81+F80 -> 0 | G82: =G81+G80 -> 0 | H82: =H81+H80 -> 0 | I82: =I80+I81 -> 0 | J82: =J80+J81 -> 0 | K82: =K80+K81 -> 0 | M82: =M81+M80 -> 0 | N82: =N81+N80 -> 0 | P82: =P81+P80 -> 0
B83: Carried Forward | C83: No | D83: =D78+D79-D82 -> 0 | E83: =E78+E79-E82 -> 0 | F83: =F78+F79-F82 -> 0 | G83: =G78+G79-G82 -> 0 | H83: =H78+H79-H82 -> 0 | I83: =I78+I79-I82 -> 0 | J83: =J78+J79-J82 -> 0 | K83: =K78+K79-K82 -> 0 | ... N83: =N78+N79-N82 -> 0 | P83: =P78+P79-P82 -> 0
A84: New CWP | B84: Brought Forward | C84: No | E84: =D89 -> 0 | F84: =E89 -> 0 | G84: =F89 -> 0 | H84: =G89 -> 0 | P84: =D84 -> 0
B85: Applied this Month | C85: No | P85: =SUM(D85:O85) -> 0
B86: Done this Month Postpaid | C86: No | P86: =SUM(D86:O86) -> 0
B87: Done this Month Prepaid | C87: No | P87: =SUM(D87:O87) -> 0
B88: Total Done | C88: No | D88: =D86+D87 -> 0 | E88: =E86+E87 -> 0 | F88: =F86+F87 -> 0 | G88: =G86+G87 -> 0 | H88: =H86+H87 -> 0 | I88: =I86+I87 -> 0 | J88: =J86+J87 -> 0 | K88: =K86+K87 -> 0 | ... N88: =N86+N87 -> 0 | P88: =SUM(D88:O88) -> 0
B89: Carried Forward | C89: No | D89: =D84+D85-D88 -> 0 | E89: =E84+E85-E88 -> 0 | F89: =F84+F85-F88 -> 0 | G89: =G84+G85-G88 -> 0 | H89: =H84+H85-H88 -> 0 | I89: =I84+I85-I88 -> 0 | J89: =J84+J85-J88 -> 0 | K89: =K84+K85-K88 -> 0 | ... N89: =N84+N85-N88 -> 0 | P89: =P84+P85-P86-P87 -> 0
A90: Aggregated New Water connections | B90: Brought Forward | C90: No | D90: =D66+D72+D78+D84 -> 38 | E90: =E66+E72+E78+E84 -> 35 | F90: =F66+F72+F78+F84 -> 42 | G90: =G66+G72+G78+G84 -> 40 | H90: =H66+H72+H78+H84 -> 40 | I90: =I66+I72+I78+I84 -> 40 | J90: =J66+J72+J78+J84 -> 40 | K90: =K66+K72+K78+K84 -> 40 | ... N90: =N66+N72+N78+N84 -> 40 | P90: =D90 -> 38
B91: Applied this Month | C91: No | D91: =D67+D73+D79+D85 -> 3 | E91: =E67+E73+E79+E85 -> 7 | F91: =F67+F73+F79+F85 -> 6 | G91: =G67+G73+G79+G85 -> 0 | H91: =H67+H73+H79+H85 -> 0 | I91: =I67+I73+I79+I85 -> 0 | J91: =J67+J73+J79+J85 -> 0 | K91: =K67+K73+K79+K85 -> 0 | ... N91: =N67+N73+N79+N85 -> 0 | P91: =SUM(D91:O91) -> 16
B92: Done this Month Postpaid | C92: No | D92: =D68+D74+D80+D86 -> 0 | E92: =E68+E74+E80+E86 -> 0 | F92: =F68+F74+F80+F86 -> 0 | G92: =G68+G74+G80+G86 -> 0 | H92: =H68+H74+H80+H86 -> 0 | I92: =I68+I74+I80+I86 -> 0 | J92: =J68+J74+J80+J86 -> 0 | K92: =K68+K74+K80+K86 -> 0 | ... N92: =N68+N74+N80+N86 -> 0 | P92: =SUM(D92:O92) -> 0
B93: Done this Month Prepaid | D93: =D69+D75+D81+D87 -> 6 | E93: =E69+E75+E81+E87 -> 0 | F93: =F69+F75+F81+F87 -> 8 | G93: =G69+G75+G81+G87 -> 0 | H93: =H69+H75+H81+H87 -> 0 | I93: =I69+I75+I81+I87 -> 0 | J93: =J69+J75+J81+J87 -> 0 | K93: =K69+K75+K81+K87 -> 0 | ... N93: =N69+N75+N81+N87 -> 0 | P93: =SUM(D93:O93) -> 14
B94: Total Done | C94: No | D94: =D93+D92 -> 6 | E94: =E93+E92 -> 0 | F94: =F93+F92 -> 8 | G94: =G93+G92 -> 0 | H94: =H93+H92 -> 0 | I94: =I93+I92 -> 0 | J94: =J93+J92 -> 0 | K94: =K93+K92 -> 0 | ... N94: =N93+N92 -> 0 | P94: =P93+P92 -> 14
B95: Carried Forward | C95: No | D95: =D90+D91-D94 -> 35 | E95: =E90+E91-E94 -> 42 | F95: =F90+F91-F94 -> 40 | G95: =G90+G91-G94 -> 40 | H95: =H90+H91-H94 -> 40 | I95: =I90+I91-I94 -> 40 | J95: =J90+J91-J94 -> 40 | K95: =K90+K91-K94 -> 40 | ... P95: =P90+P91-P94 -> 40
A97: Prepaid Metering
A98: Prepaid Meters Installed | C98: No | D98: 6 | E98: 4 | F98: 16
A100: Active and Disconnected Accounts
A101: Disconnected Individual Accounts | C101: No | D101: 219 | E101: 199 | F101: 196 | P101: =O101 -> 0
A102: Disconnected institutional Accounts | C102: No | D102: 14 | E102: 13 | F102: 13 | P102: =O102 -> 0
A103: Disconnected Commercial/Industrial Accounts | C103: No | D103: 25 | E103: 25 | F103: 25 | P103: =O103 -> 0
A104: Disconnected CWP | C104: No | E104: 0 | P104: =O104 -> 0
A105: Total Disconnected Accounts | C105: No | D105: =SUM(D101:D104) -> 258 | E105: =SUM(E101:E104) -> 237 | F105: =SUM(F101:F104) -> 234 | G105: =SUM(G101:G104) -> 0 | H105: =SUM(H101:H104) -> 0 | I105: =SUM(I101:I104) -> 0 | J105: =SUM(J101:J104) -> 0 | K105: =SUM(K101:K104) -> 0 | ... O105: =SUM(O101:O104) -> 0 | P105: =O105 -> 0
A106: Postpaid Consumers
...

Sheet Mikolongwe
A1: SOUTHERN REGION WATER BOARD
A3: MONTHLY REPORTS - 2026/2027
A4: MULANJE ZONE
A5: MULANJE ZONE
A7: PARAMETERS | C7: UNITS | D7: APRIL | E7: MAY | F7: JUNE | G7: JULY | H7: AUGUST | I7: SEPTEMBER | J7: OCTOBER | K7: NOVEMBER | L7: DECEMBER | M7: JANUARY | N7: FEBRUARY | O7: MARCH | P7: TOTALS
A8: PRODUCTION
A9: Volume Produced | C9: m3 | D9: 802 | E9: 981 | F9: 607 | P9: =SUM(D9:O9) -> 2390
A10: REVENUE WATER - POSTPAID
A11: Volume Billed Individuals | C11: m3 | P11: =SUM(D11:O11) -> 0
A12: Volume Billed CWPs | C12: m3 | P12: =SUM(D12:O12) -> 0
A13: Volume Billed Institutions | C13: m3 | P13: =SUM(D13:O13) -> 0
A14: Volume Billed Commercial/Industrial | C14: m3 | P14: =SUM(D14:O14) -> 0
A15: Total Volume Billed Post Paid | C15: m3 | D15: =SUM(D11:D14) -> 0 | E15: =SUM(E11:E14) -> 0 | F15: =SUM(F11:F14) -> 0 | G15: =SUM(G11:G14) -> 0 | H15: =SUM(H11:H14) -> 0 | I15: =SUM(I11:I14) -> 0 | J15: =SUM(J11:J14) -> 0 | K15: =SUM(K11:K14) -> 0 | ... P15: =SUM(P11:P14) -> 0
A16: REVENUE WATER - PREPAID
A17: Individuals | C17: m3 | D17: 271 | E17: 212 | F17: 201 | P17: =SUM(D17:O17) -> 684
A18: CWPs | C18: m3 | P18: =SUM(D18:O18) -> 0
A19: Institutions | C19: m3 | D19: 401 | E19: 577 | F19: 274 | P19: =SUM(D19:O19) -> 1252
A20: Commercial/Industrial | C20: m3 | D20: 5 | E20: 10 | P20: =SUM(D20:O20) -> 15
A21: Total Volume Prepaid | C21: m3 | D21: =SUM(D17:D20) -> 677 | E21: =SUM(E17:E20) -> 799 | F21: =SUM(F17:F20) -> 475 | G21: =SUM(G17:G20) -> 0 | H21: =SUM(H17:H20) -> 0 | I21: =SUM(I17:I20) -> 0 | J21: =SUM(J17:J20) -> 0 | K21: =SUM(K17:K20) -> 0 | ... P21: =SUM(P17:P20) -> 1951
A22: TOTAL REVENUE WATER | C22: m3 | D22: =D21+D15 -> 677 | E22: =E21+E15 -> 799 | F22: =F21+F15 -> 475 | G22: =G21+G15 -> 0 | H22: =H21+H15 -> 0 | I22: =I21+I15 -> 0 | J22: =J21+J15 -> 0 | K22: =K21+K15 -> 0 | ... P22: =P21+P15 -> 1951
A24: Non-Revenue Water (NRW) | B24: Volume | C24: m3 | D24: =D9-D22 -> 125 | E24: =E9-E22 -> 182 | F24: =F9-F22 -> 132 | G24: =G9-G22 -> 0 | H24: =H9-H22 -> 0 | I24: =I9-I22 -> 0 | J24: =J9-J22 -> 0 | K24: =K9-K22 -> 0 | ... P24: =P9-P22 -> 439
B25: Percentage | C25: % | D25: =D24/D9 -> 0.15586035 | E25: =E24/E9 -> 0.18552497 | F25: =F24/F9 -> 0.21746293 | G25: =G24/G9 -> #DIV/0! | H25: =H24/H9 -> #DIV/0! | I25: =I24/I9 -> #DIV/0! | J25: =J24/J9 -> #DIV/0! | K25: =K24/K9 -> #DIV/0! | ... P25: =P24/P9 -> 0.18368201
A26: OPERATING EXPENSES
A27: Chemicals
A28: Chemical | B28: Rate(MK/kg)
A29: Chlorine | B29: 5111.67 | C29: kg | D29: 5 | E29: 5 | F29: 4 | P29: =SUM(D29:O29) -> 14
C30: kg/mg litre | D30: =D29/(D9/1000) -> 6.234414 | E30: =E29/(E9/1000) -> 5.09684 | F30: =F29/(F9/1000) -> 6.5897858 | G30: =G29/(G9/1000) -> #DIV/0! | H30: =H29/(H9/1000) -> #DIV/0! | I30: =I29/(I9/1000) -> #DIV/0! | J30: =J29/(J9/1000) -> #DIV/0! | K30: =K29/(K9/1000) -> #DIV/0! | ... N30: =N29/(N9/1000) -> #DIV/0! | P30: =P29/(P9/1000) -> 5.8577406
A31: Aluminium sulphate | B31: 1537 | C31: kg | P31: =SUM(D31:O31) -> 0
C32: kg/mg litre | D32: =D31/(D9/1000) -> 0 | E32: =E31/(E9/1000) -> 0 | F32: =F31/(F9/1000) -> 0 | G32: =G31/(G9/1000) -> #DIV/0! | H32: =H31/(H9/1000) -> #DIV/0! | I32: =I31/(I9/1000) -> #DIV/0! | J32: =J31/(J9/1000) -> #DIV/0! | K32: =K31/(K9/1000) -> #DIV/0! | ... N32: =N31/(N9/1000) -> #DIV/0! | P32: =P31/(P9/1000) -> 0
A33: Soda | B33: 1781.02 | C33: kg | P33: =SUM(D33:O33) -> 0
C34: kg/mg litre | D34: =D33/(D9/1000) -> 0 | E34: =E33/(E9/1000) -> 0 | F34: =F33/(F9/1000) -> 0 | G34: =G33/(G9/1000) -> #DIV/0! | H34: =H33/(H9/1000) -> #DIV/0! | I34: =I33/(I9/1000) -> #DIV/0! | J34: =J33/(J9/1000) -> #DIV/0! | K34: =K33/(K9/1000) -> #DIV/0! | ... N34: =N33/(N9/1000) -> #DIV/0! | P34: =P33/(P9/1000) -> 0
A35: Algae floc | B35: 5979.95 | C35: litres
C36: litres/mg litre
A37: Sud floc | B37: 5403.75 | C37: litres | P37: =SUM(D37:O37) -> 0
C38: litres/mg litre | D38: =D37/(D9/1000) -> 0 | E38: =E37/(E9/1000) -> 0 | F38: =F37/(F9/1000) -> 0 | G38: =G37/(G9/1000) -> #DIV/0! | H38: =H37/(H9/1000) -> #DIV/0! | I38: =I37/(I9/1000) -> #DIV/0! | J38: =J37/(J9/1000) -> #DIV/0! | K38: =K37/(K9/1000) -> #DIV/0! | ... N38: =N37/(N9/1000) -> #DIV/0! | P38: =P37/(P9/1000) -> 0
A39: Potasium permanganate | B39: 1950 | C39: kg | P39: =SUM(D39:O39) -> 0
C40: kg/mg litre | D40: =D39/(D9/1000) -> 0 | E40: =E39/(E9/1000) -> 0 | F40: =F39/(F9/1000) -> 0 | G40: =G39/(G9/1000) -> #DIV/0! | H40: =H39/(H9/1000) -> #DIV/0! | I40: =I39/(I9/1000) -> #DIV/0! | J40: =J39/(J9/1000) -> #DIV/0! | K40: =K39/(K9/1000) -> #DIV/0! | ... N40: =N39/(N9/1000) -> #DIV/0! | P40: =P39/(P9/1000) -> 0
A41: Cost of Chemicals | C41: Mk | D41: =(D29*$B29)+(D31*$B31)+(D33*$B33)+(D35*$B35)+(D37*$B37)+(D39*$B39) -> 25558.35 | E41: =(E29*$B29)+(E31*$B31)+(E33*$B33)+(E35*$B35)+(E37*$B37)+(E39*$B39) -> 25558.35 | F41: =(F29*$B29)+(F31*$B31)+(F33*$B33)+(F35*$B35)+(F37*$B37)+(F39*$B39) -> 20446.68 | G41: =(G29*$B29)+(G31*$B31)+(G33*$B33)+(G35*$B35)+(G37*$B37)+(G39*$B39) -> 0 | H41: =(H29*$B29)+(H31*$B31)+(H33*$B33)+(H35*$B35)+(H37*$B37)+(H39*$B39) -> 0 | I41: =(I29*$B29)+(I31*$B31)+(I33*$B33)+(I35*$B35)+(I37*$B37)+(I39*$B39) -> 0 | J41: =(J29*$B29)+(J31*$B31)+(J33*$B33)+(J35*$B35)+(J37*$B37)+(J39*$B39) -> 0 | K41: =(K29*$B29)+(K31*$B31)+(K33*$B33)+(K35*$B35)+(K37*$B37)+(K39*$B39) -> 0 | ... O41: =(O29*$B29)+(O31*$B31)+(O33*$B33)+(O35*$B35)+(O37*$B37)+(O39*$B39) -> 0 | P41: =SUM(D41:O41) -> 71563.38
A42: Cost/vol. Produced (chemicals) | C42: Mk/m3 | D42: =D41/D9 -> 31.868267 | E42: =E41/E9 -> 26.053364 | F42: =F41/F9 -> 33.684811 | G42: =G41/G9 -> #DIV/0! | H42: =H41/H9 -> #DIV/0! | I42: =I41/I9 -> #DIV/0! | J42: =J41/J9 -> #DIV/0! | K42: =K41/K9 -> #DIV/0! | ... P42: =P41/P9 -> 29.942837
A43: Power
A44: Power Usage | C44: Kw | D44: 386 | E44: 685 | F44: 422 | P44: =SUM(D44:O44) -> 1493
A45: Power/ Vol. Produced | C45: Kw/m3 | D45: =D44/D9 -> 0.48129676 | E45: =E44/E9 -> 0.69826707 | F45: =F44/F9 -> 0.69522241 | G45: =G44/G9 -> #DIV/0! | H45: =H44/H9 -> #DIV/0! | I45: =I44/I9 -> #DIV/0! | J45: =J44/J9 -> #DIV/0! | K45: =K44/K9 -> #DIV/0! | ... N45: =N44/N9 -> #DIV/0! | P45: =P44/P9 -> 0.62468619
A46: Cost of Power | C46: Mk | D46: =333.87*D44 -> 128873.82 | E46: =333.87*E44 -> 228700.95 | F46: =333.87*F44 -> 140893.14 | G46: =333.87*G44 -> 0 | H46: =333.87*H44 -> 0 | I46: =333.87*I44 -> 0 | J46: =333.87*J44 -> 0 | K46: =333.87*K44 -> 0 | ... O46: =333.87*O44 -> 0 | P46: =SUM(D46:O46) -> 498467.91
A47: Cost/vol. Produced | C47: Mk/m3 | D47: =D46/D9 -> 160.69055 | E47: =E46/E9 -> 233.13043 | F47: =F46/F9 -> 232.1139 | G47: =G46/G9 -> #DIV/0! | H47: =H46/H9 -> #DIV/0! | I47: =I46/I9 -> #DIV/0! | J47: =J46/J9 -> #DIV/0! | K47: =K46/K9 -> #DIV/0! | ... N47: =N46/N9 -> #DIV/0! | P47: =P46/P9 -> 208.56398
A48: Plant and Vehicle Maintenance
A49: Distances covered | C49: km | P49: =SUM(D49:O49) -> 0
A50: Fuel Used (litres) | C50: litres | P50: =SUM(D50:O50) -> 0
A51: Cost of fuel | C51: Mk | P51: =SUM(D51:O51) -> 0
A52: Maintenance | C52: Mk | P52: =SUM(D52:O52) -> 0
A53: Salaries and Wages
A54: Staff Costs | C54: MK | D54: 962553.49 | E54: 1097996.6 | F54: 1097996.6 | P54: =SUM(D54:O54) -> 3158546.6
A55: Wages | C55: MK | E55: 423499.96 | F55: 454462.08 | P55: =SUM(D55:O55) -> 877962.04
A56: Other Overhead Costs | C56: MK | E56: 250000 | P56: =SUM(D56:O56) -> 250000
A57: Operating Costs
A58: Total Operating Costs | C58: MK | D58: =D41+D46+D51+D52+D54+D55+D56 -> 1116985.7 | E58: =E41+E46+E51+E52+E54+E55+E56 -> 2025755.8 | F58: =F41+F46+F51+F52+F54+F55+F56 -> 1713798.5 | G58: =G41+G46+G51+G52+G54+G55+G56 -> 0 | H58: =H41+H46+H51+H52+H54+H55+H56 -> 0 | I58: =I41+I46+I51+I52+I54+I55+I56 -> 0 | J58: =J41+J46+J51+J52+J54+J55+J56 -> 0 | K58: =K41+K46+K51+K52+K54+K55+K56 -> 0 | ... N58: =N41+N46+N51+N52+N54+N55+N56 -> 0 | P58: =SUM(D58:O58) -> 4856540
A59: Cost/Vol. Produced | C59: Mk/m3 | D59: =D58/D9 -> 1392.7502 | E59: =E58/E9 -> 2064.9907 | F59: =F58/F9 -> 2823.3912 | G59: =G58/G9 -> #DIV/0! | H59: =H58/H9 -> #DIV/0! | I59: =I58/I9 -> #DIV/0! | J59: =J58/J9 -> #DIV/0! | K59: =K58/K9 -> #DIV/0! | ... N59: =N58/N9 -> #DIV/0! | P59: =P58/P9 -> 2032.0251
A60: Cost/Vol. Billed | C60: Mk/m3 | D60: =D58/D22 -> 1649.905 | E60: =E58/E22 -> 2535.364 | F60: =F58/F22 -> 3607.9968 | G60: =G58/G22 -> #DIV/0! | H60: =H58/H22 -> #DIV/0! | I60: =I58/I22 -> #DIV/0! | J60: =J58/J22 -> #DIV/0! | K60: =K58/K22 -> #DIV/0! | ... N60: =N58/N22 -> #DIV/0! | P60: =P58/P22 -> 2489.2568
A61: Permanent Staff Employed | C61: No | P61: =O61 -> 0
A62: Staff/Vol.1000m3 of Volume Produced/hour (12 hour day) | C62: No/1000m3 | D62: =(D61*1000*31)/D9 -> 0 | E62: =(E61*1000*31)/E9 -> 0 | F62: =(F61*1000*31)/F9 -> 0 | G62: =(G61*1000*31)/G9 -> #DIV/0! | H62: =(H61*1000*31)/H9 -> #DIV/0! | I62: =(I61*1000*31)/I9 -> #DIV/0! | J62: =(J61*1000*31)/J9 -> #DIV/0! | K62: =(K61*1000*31)/K9 -> #DIV/0! | ... N62: =(N61*1000*31)/N9 -> #DIV/0! | P62: =(P61*1000*31)/P9 -> 0
A63: Temporary Staff Employed | C63: No | D63: 4 | E63: 4 | F63: 4 | P63: =SUM(D63:O63) -> 12
A65: Water Connections and Disconnections
A66: New Individual Water Connections | B66: Brought Forward | C66: No | E66: =D71 -> 0 | F66: =E71 -> 0 | G66: =F71 -> 0 | H66: =G71 -> 0 | I66: =H71 -> 0 | J66: =I71 -> 0 | K66: =J71 -> 0 | L66: =K71 -> 0 | ... O66: =N71 -> 0 | P66: =D66 -> 0
B67: Applied this Month | C67: No | P67: =SUM(D67:O67) -> 0
B68: Done this Month Postpaid | C68: No | P68: =SUM(D68:O68) -> 0
B69: Done this Month Prepaid | C69: No | P69: =SUM(D69:O69) -> 0
B70: Total Done | C70: No | D70: =D68+D69 -> 0 | E70: =E68+E69 -> 0 | F70: =F68+F69 -> 0 | G70: =G68+G69 -> 0 | H70: =H68+H69 -> 0 | I70: =I68+I69 -> 0 | J70: =J68+J69 -> 0 | K70: =K68+K69 -> 0 | P70: =P68+P69 -> 0
B71: Carried Forward | C71: No | D71: =D66+D67-D70 -> 0 | E71: =E66+E67-E70 -> 0 | F71: =F66+F67-F70 -> 0 | G71: =G66+G67-G70 -> 0 | H71: =H66+H67-H70 -> 0 | I71: =I66+I67-I70 -> 0 | J71: =J66+J67-J70 -> 0 | K71: =K66+K67-K70 -> 0 | ... P71: =P66+P67-P70 -> 0
A72: New Institutional Water Connections | B72: Brought Forward | C72: No | E72: =D77 -> 0 | F72: =E77 -> 0 | G72: =F77 -> 0 | H72: =G77 -> 0 | I72: =H77 -> 0 | P72: =D72 -> 0
B73: Applied this Month | C73: No | P73: =SUM(D73:O73) -> 0
B74: Done this Month Postpaid | C74: No | P74: =SUM(D74:O74) -> 0
B75: Done this Month Prepaid | C75: No | P75: =SUM(D75:O75) -> 0
B76: Total Done | C76: No | D76: =D74+D75 -> 0 | E76: =E74+E75 -> 0 | F76: =F74+F75 -> 0 | G76: =G74+G75 -> 0 | H76: =H74+H75 -> 0 | I76: =I74+I75 -> 0 | J76: =J74+J75 -> 0 | K76: =K74+K75 -> 0 | M76: =M74+M75 -> 0 | N76: =N74+N75 -> 0 | P76: =P74+P75 -> 0
B77: Carried Forward | C77: No | D77: =D72+D73-D76 -> 0 | E77: =E72+E73-E76 -> 0 | F77: =F72+F73-F76 -> 0 | G77: =G72+G73-G76 -> 0 | H77: =H72+H73-H76 -> 0 | I77: =I72+I73-I76 -> 0 | J77: =J72+J73-J76 -> 0 | K77: =K72+K73-K76 -> 0 | ... P77: =P72+P73-P76 -> 0
A78: New Commercial/Industrial Water Connections | B78: Brought Forward | C78: No | E78: =D83 -> 0 | F78: =E83 -> 0 | G78: =F83 -> 0 | H78: =G83 -> 0 | I78: =H83 -> 0 | J78: =I83 -> 0 | K78: =J83 -> 0 | L78: =K83 -> 0 | ... O78: =N83 -> 0 | P78: =D78 -> 0
B79: Applied this Month | C79: No | P79: =SUM(D79:O79) -> 0
B80: Done this Month Postpaid | C80: No | P80: =SUM(D80:O80) -> 0
B81: Done this Month Prepaid | C81: No | P81: =SUM(D81:O81) -> 0
B82: Total Done | C82: No | D82: =D81+D80 -> 0 | E82: =E81+E80 -> 0 | F82: =F81+F80 -> 0 | G82: =G81+G80 -> 0 | H82: =H81+H80 -> 0 | I82: =I80+I81 -> 0 | J82: =J80+J81 -> 0 | K82: =K80+K81 -> 0 | M82: =M81+M80 -> 0 | N82: =N81+N80 -> 0 | P82: =P81+P80 -> 0
B83: Carried Forward | C83: No | D83: =D78+D79-D82 -> 0 | E83: =E78+E79-E82 -> 0 | F83: =F78+F79-F82 -> 0 | G83: =G78+G79-G82 -> 0 | H83: =H78+H79-H82 -> 0 | I83: =I78+I79-I82 -> 0 | J83: =J78+J79-J82 -> 0 | K83: =K78+K79-K82 -> 0 | ... P83: =P78+P79-P82 -> 0
A84: New CWP | B84: Brought Forward | C84: No | E84: =D89 -> 0 | F84: =E89 -> 0 | G84: =F89 -> 0 | H84: =G89 -> 0 | P84: =D84 -> 0
B85: Applied this Month | C85: No | P85: =SUM(D85:O85) -> 0
B86: Done this Month Postpaid | C86: No | P86: =SUM(D86:O86) -> 0
B87: Done this Month Prepaid | C87: No | P87: =SUM(D87:O87) -> 0
B88: Total Done | C88: No | D88: =D86+D87 -> 0 | E88: =E86+E87 -> 0 | F88: =F86+F87 -> 0 | G88: =G86+G87 -> 0 | H88: =H86+H87 -> 0 | I88: =I86+I87 -> 0 | J88: =J86+J87 -> 0 | K88: =K86+K87 -> 0 | ... O88: =O86+O87 -> 0 | P88: =SUM(D88:O88) -> 0
B89: Carried Forward | C89: No | D89: =D84+D85-D88 -> 0 | E89: =E84+E85-E88 -> 0 | F89: =F84+F85-F88 -> 0 | G89: =G84+G85-G88 -> 0 | H89: =H84+H85-H88 -> 0 | I89: =I84+I85-I88 -> 0 | J89: =J84+J85-J88 -> 0 | K89: =K84+K85-K88 -> 0 | ... O89: =O84+O85-O88 -> 0 | P89: =P84+P85-P86-P87 -> 0
A90: Aggregated New Water connections | B90: Brought Forward | C90: No | D90: =D66+D72+D78+D84 -> 0 | E90: =E66+E72+E78+E84 -> 0 | F90: =F66+F72+F78+F84 -> 0 | G90: =G66+G72+G78+G84 -> 0 | H90: =H66+H72+H78+H84 -> 0 | I90: =I66+I72+I78+I84 -> 0 | J90: =J66+J72+J78+J84 -> 0 | K90: =K66+K72+K78+K84 -> 0 | ... O90: =O66+O72+O78+O84 -> 0 | P90: =D90 -> 0
B91: Applied this Month | C91: No | D91: =D67+D73+D79+D85 -> 0 | E91: =E67+E73+E79+E85 -> 0 | F91: =F67+F73+F79+F85 -> 0 | G91: =G67+G73+G79+G85 -> 0 | H91: =H67+H73+H79+H85 -> 0 | I91: =I67+I73+I79+I85 -> 0 | J91: =J67+J73+J79+J85 -> 0 | K91: =K67+K73+K79+K85 -> 0 | ... O91: =O67+O73+O79+O85 -> 0 | P91: =SUM(D91:O91) -> 0
B92: Done this Month Postpaid | C92: No | D92: =D68+D74+D80+D86 -> 0 | E92: =E68+E74+E80+E86 -> 0 | F92: =F68+F74+F80+F86 -> 0 | G92: =G68+G74+G80+G86 -> 0 | H92: =H68+H74+H80+H86 -> 0 | I92: =I68+I74+I80+I86 -> 0 | J92: =J68+J74+J80+J86 -> 0 | K92: =K68+K74+K80+K86 -> 0 | ... O92: =O68+O74+O80+O86 -> 0 | P92: =SUM(D92:O92) -> 0
B93: Done this Month Prepaid | D93: =D69+D75+D81+D87 -> 0 | E93: =E69+E75+E81+E87 -> 0 | F93: =F69+F75+F81+F87 -> 0 | G93: =G69+G75+G81+G87 -> 0 | H93: =H69+H75+H81+H87 -> 0 | I93: =I69+I75+I81+I87 -> 0 | J93: =J69+J75+J81+J87 -> 0 | K93: =K69+K75+K81+K87 -> 0 | ... O93: =O69+O75+O81+O87 -> 0 | P93: =SUM(D93:O93) -> 0
B94: Total Done | C94: No | D94: =D93+D92 -> 0 | E94: =E93+E92 -> 0 | F94: =F93+F92 -> 0 | G94: =G93+G92 -> 0 | H94: =H93+H92 -> 0 | I94: =I93+I92 -> 0 | J94: =J93+J92 -> 0 | K94: =K93+K92 -> 0 | ... P94: =P93+P92 -> 0
B95: Carried Forward | C95: No | D95: =D90+D91-D94 -> 0 | E95: =E90+E91-E94 -> 0 | F95: =F90+F91-F94 -> 0 | G95: =G90+G91-G94 -> 0 | H95: =H90+H91-H94 -> 0 | I95: =I90+I91-I94 -> 0 | J95: =J90+J91-J94 -> 0 | K95: =K90+K91-K94 -> 0 | ... P95: =P90+P91-P94 -> 0
A97: Prepaid Metering
A98: Prepaid Meters Installed | C98: No | P98: =SUM(D98:O98) -> 0
A100: Active and Disconnected Accounts
A101: Disconnected Individual Accounts | C101: No | D101: 14 | E101: 14 | F101: 14 | P101: =O101 -> 0
A102: Disconnected institutional Accounts | C102: No | P102: =O102 -> 0
A103: Disconnected Commercial/Industrial Accounts | C103: No | D103: 2 | E103: 2 | F103: 2 | P103: =O103 -> 0
A104: Disconnected CWP | C104: No | P104: =O104 -> 0
A105: Total Disconnected Accounts | C105: No | D105: =SUM(D101:D104) -> 16 | E105: =SUM(E101:E104) -> 16 | F105: =SUM(F101:F104) -> 16 | G105: =SUM(G101:G104) -> 0 | H105: =SUM(H101:H104) -> 0 | I105: =SUM(I101:I104) -> 0 | J105: =SUM(J101:J104) -> 0 | K105: =SUM(K101:K104) -> 0 | ... O105: =SUM(O101:O104) -> 0 | P105: =O105 -> 0
A106: Postpaid Consumers
...

Sheet Migowi
A1: SOUTHERN REGION WATER BOARD
A3: MONTHLY REPORTS - 2026/2027
A4: MULANJE ZONE
A5: MULANJE ZONE
A7: PARAMETERS | C7: UNITS | D7: APRIL | E7: MAY | F7: JUNE | G7: JULY | H7: AUGUST | I7: SEPTEMBER | J7: OCTOBER | K7: NOVEMBER | L7: DECEMBER | M7: JANUARY | N7: FEBRUARY | O7: MARCH | P7: TOTALS
A8: PRODUCTION
A9: Volume Produced | C9: m3 | D9: 1150 | E9: 937 | F9: 889 | P9: =SUM(D9:O9) -> 2976
A10: REVENUE WATER - POSTPAID
A11: Volume Billed Individuals | C11: m3 | P11: =SUM(D11:O11) -> 0
A12: Volume Billed CWPs | C12: m3 | P12: =SUM(D12:O12) -> 0
A13: Volume Billed Institutions | C13: m3 | P13: =SUM(D13:O13) -> 0
A14: Volume Billed Commercial/Industrial | C14: m3 | P14: =SUM(D14:O14) -> 0
A15: Total Volume Billed Post Paid | C15: m3 | D15: =SUM(D11:D14) -> 0 | E15: =SUM(E11:E14) -> 0 | F15: =SUM(F11:F14) -> 0 | G15: =SUM(G11:G14) -> 0 | H15: =SUM(H11:H14) -> 0 | I15: =SUM(I11:I14) -> 0 | J15: =SUM(J11:J14) -> 0 | K15: =SUM(K11:K14) -> 0 | ... P15: =SUM(P11:P14) -> 0
A16: REVENUE WATER - PREPAID
A17: Individuals | C17: m3 | D17: 930 | E17: 801 | F17: 733 | P17: =SUM(D17:O17) -> 2464
A18: CWPs | C18: m3 | P18: =SUM(D18:O18) -> 0
A19: Institutions | C19: m3 | P19: =SUM(D19:O19) -> 0
A20: Commercial/Industrial | C20: m3 | P20: =SUM(D20:O20) -> 0
A21: Total Volume Prepaid | C21: m3 | D21: =SUM(D17:D20) -> 930 | E21: =SUM(E17:E20) -> 801 | F21: =SUM(F17:F20) -> 733 | G21: =SUM(G17:G20) -> 0 | H21: =SUM(H17:H20) -> 0 | I21: =SUM(I17:I20) -> 0 | J21: =SUM(J17:J20) -> 0 | K21: =SUM(K17:K20) -> 0 | ... P21: =SUM(P17:P20) -> 2464
A22: TOTAL REVENUE WATER | C22: m3 | D22: =D21+D15 -> 930 | E22: =E21+E15 -> 801 | F22: =F21+F15 -> 733 | G22: =G21+G15 -> 0 | H22: =H21+H15 -> 0 | I22: =I21+I15 -> 0 | J22: =J21+J15 -> 0 | K22: =K21+K15 -> 0 | ... P22: =P21+P15 -> 2464
A24: Non-Revenue Water (NRW) | B24: Volume | C24: m3 | D24: =D9-D22 -> 220 | E24: =E9-E22 -> 136 | F24: =F9-F22 -> 156 | G24: =G9-G22 -> 0 | H24: =H9-H22 -> 0 | I24: =I9-I22 -> 0 | J24: =J9-J22 -> 0 | K24: =K9-K22 -> 0 | ... P24: =P9-P22 -> 512
B25: Percentage | C25: % | D25: =D24/D9 -> 0.19130435 | E25: =E24/E9 -> 0.14514408 | F25: =F24/F9 -> 0.17547807 | G25: =G24/G9 -> #DIV/0! | H25: =H24/H9 -> #DIV/0! | I25: =I24/I9 -> #DIV/0! | J25: =J24/J9 -> #DIV/0! | K25: =K24/K9 -> #DIV/0! | ... P25: =P24/P9 -> 0.17204301
A26: OPERATING EXPENSES
A27: Chemicals
A28: Chemical | B28: Rate(MK/kg)
A29: Chlorine | B29: 5111.67 | C29: kg | D29: 1 | E29: 1 | F29: 1 | P29: =SUM(D29:O29) -> 3
C30: kg/mg litre | D30: =D29/(D9/1000) -> 0.86956522 | E30: =E29/(E9/1000) -> 1.0672359 | F30: =F29/(F9/1000) -> 1.1248594 | G30: =G29/(G9/1000) -> #DIV/0! | H30: =H29/(H9/1000) -> #DIV/0! | I30: =I29/(I9/1000) -> #DIV/0! | J30: =J29/(J9/1000) -> #DIV/0! | K30: =K29/(K9/1000) -> #DIV/0! | ... N30: =N29/(N9/1000) -> #DIV/0! | P30: =P29/(P9/1000) -> 1.0080645
A31: Aluminium sulphate | B31: 1537 | C31: kg | P31: =SUM(D31:O31) -> 0
C32: kg/mg litre | D32: =D31/(D9/1000) -> 0 | E32: =E31/(E9/1000) -> 0 | F32: =F31/(F9/1000) -> 0 | G32: =G31/(G9/1000) -> #DIV/0! | H32: =H31/(H9/1000) -> #DIV/0! | I32: =I31/(I9/1000) -> #DIV/0! | J32: =J31/(J9/1000) -> #DIV/0! | K32: =K31/(K9/1000) -> #DIV/0! | ... N32: =N31/(N9/1000) -> #DIV/0! | P32: =P31/(P9/1000) -> 0
A33: Soda | B33: 1781.02 | C33: kg | P33: =SUM(D33:O33) -> 0
C34: kg/mg litre | D34: =D33/(D9/1000) -> 0 | E34: =E33/(E9/1000) -> 0 | F34: =F33/(F9/1000) -> 0 | G34: =G33/(G9/1000) -> #DIV/0! | H34: =H33/(H9/1000) -> #DIV/0! | I34: =I33/(I9/1000) -> #DIV/0! | J34: =J33/(J9/1000) -> #DIV/0! | K34: =K33/(K9/1000) -> #DIV/0! | ... N34: =N33/(N9/1000) -> #DIV/0! | P34: =P33/(P9/1000) -> 0
A35: Algae floc | B35: 5979.95 | C35: litres
C36: litres/mg litre
A37: Sud floc | B37: 5403.75 | C37: litres | P37: =SUM(D37:O37) -> 0
C38: litres/mg litre | D38: =D37/(D9/1000) -> 0 | E38: =E37/(E9/1000) -> 0 | F38: =F37/(F9/1000) -> 0 | G38: =G37/(G9/1000) -> #DIV/0! | H38: =H37/(H9/1000) -> #DIV/0! | I38: =I37/(I9/1000) -> #DIV/0! | J38: =J37/(J9/1000) -> #DIV/0! | K38: =K37/(K9/1000) -> #DIV/0! | ... N38: =N37/(N9/1000) -> #DIV/0! | P38: =P37/(P9/1000) -> 0
A39: Potasium permanganate | B39: 1950 | C39: kg | P39: =SUM(D39:O39) -> 0
C40: kg/mg litre | D40: =D39/(D9/1000) -> 0 | E40: =E39/(E9/1000) -> 0 | F40: =F39/(F9/1000) -> 0 | G40: =G39/(G9/1000) -> #DIV/0! | H40: =H39/(H9/1000) -> #DIV/0! | I40: =I39/(I9/1000) -> #DIV/0! | J40: =J39/(J9/1000) -> #DIV/0! | K40: =K39/(K9/1000) -> #DIV/0! | ... N40: =N39/(N9/1000) -> #DIV/0! | P40: =P39/(P9/1000) -> 0
A41: Cost of Chemicals | C41: Mk | D41: =(D29*$B29)+(D31*$B31)+(D33*$B33)+(D35*$B35)+(D37*$B37)+(D39*$B39) -> 5111.67 | E41: =(E29*$B29)+(E31*$B31)+(E33*$B33)+(E35*$B35)+(E37*$B37)+(E39*$B39) -> 5111.67 | F41: =(F29*$B29)+(F31*$B31)+(F33*$B33)+(F35*$B35)+(F37*$B37)+(F39*$B39) -> 5111.67 | G41: =(G29*$B29)+(G31*$B31)+(G33*$B33)+(G35*$B35)+(G37*$B37)+(G39*$B39) -> 0 | H41: =(H29*$B29)+(H31*$B31)+(H33*$B33)+(H35*$B35)+(H37*$B37)+(H39*$B39) -> 0 | I41: =(I29*$B29)+(I31*$B31)+(I33*$B33)+(I35*$B35)+(I37*$B37)+(I39*$B39) -> 0 | J41: =(J29*$B29)+(J31*$B31)+(J33*$B33)+(J35*$B35)+(J37*$B37)+(J39*$B39) -> 0 | K41: =(K29*$B29)+(K31*$B31)+(K33*$B33)+(K35*$B35)+(K37*$B37)+(K39*$B39) -> 0 | ... O41: =(O29*$B29)+(O31*$B31)+(O33*$B33)+(O35*$B35)+(O37*$B37)+(O39*$B39) -> 0 | P41: =SUM(D41:O41) -> 15335.01
A42: Cost/vol. Produced (chemicals) | C42: Mk/m3 | D42: =D41/D9 -> 4.4449304 | E42: =E41/E9 -> 5.4553575 | F42: =F41/F9 -> 5.74991 | G42: =G41/G9 -> #DIV/0! | H42: =H41/H9 -> #DIV/0! | I42: =I41/I9 -> #DIV/0! | J42: =J41/J9 -> #DIV/0! | K42: =K41/K9 -> #DIV/0! | ... P42: =P41/P9 -> 5.1528931
A43: Power
A44: Power Usage | C44: Kw | D44: 1000 | E44: 500 | F44: 433 | P44: =SUM(D44:O44) -> 1933
A45: Power/ Vol. Produced | C45: Kw/m3 | D45: =D44/D9 -> 0.86956522 | E45: =E44/E9 -> 0.53361793 | F45: =F44/F9 -> 0.48706412 | G45: =G44/G9 -> #DIV/0! | H45: =H44/H9 -> #DIV/0! | I45: =I44/I9 -> #DIV/0! | J45: =J44/J9 -> #DIV/0! | K45: =K44/K9 -> #DIV/0! | ... N45: =N44/N9 -> #DIV/0! | P45: =P44/P9 -> 0.64952957
A46: Cost of Power | C46: Mk | D46: =333.87*D44 -> 333870 | E46: =333.87*E44 -> 166935 | F46: =333.87*F44 -> 144565.71 | G46: =333.87*G44 -> 0 | H46: =333.87*H44 -> 0 | I46: =333.87*I44 -> 0 | J46: =333.87*J44 -> 0 | K46: =333.87*K44 -> 0 | ... O46: =333.87*O44 -> 0 | P46: =SUM(D46:O46) -> 645370.71
A47: Cost/vol. Produced | C47: Mk/m3 | D47: =D46/D9 -> 290.32174 | E47: =E46/E9 -> 178.15902 | F47: =F46/F9 -> 162.6161 | G47: =G46/G9 -> #DIV/0! | H47: =H46/H9 -> #DIV/0! | I47: =I46/I9 -> #DIV/0! | J47: =J46/J9 -> #DIV/0! | K47: =K46/K9 -> #DIV/0! | ... N47: =N46/N9 -> #DIV/0! | P47: =P46/P9 -> 216.85844
A48: Plant and Vehicle Maintenance
A49: Distances covered | C49: km | P49: =SUM(D49:O49) -> 0
A50: Fuel Used (litres) | C50: litres | P50: =SUM(D50:O50) -> 0
A51: Cost of fuel | C51: Mk | P51: =SUM(D51:O51) -> 0
A52: Maintenance | C52: Mk | P52: =SUM(D52:O52) -> 0
A53: Salaries and Wages
A54: Staff Costs | C54: MK | P54: =SUM(D54:O54) -> 0
A55: Wages | C55: MK | E55: 1285672.5 | P55: =SUM(D55:O55) -> 1285672.5
A56: Other Overhead Costs | C56: MK | P56: =SUM(D56:O56) -> 0
A57: Operating Costs
A58: Total Operating Costs | C58: MK | D58: =D41+D46+D51+D52+D54+D55+D56 -> 338981.67 | E58: =E41+E46+E51+E52+E54+E55+E56 -> 1457719.2 | F58: =F41+F46+F51+F52+F54+F55+F56 -> 149677.38 | G58: =G41+G46+G51+G52+G54+G55+G56 -> 0 | H58: =H41+H46+H51+H52+H54+H55+H56 -> 0 | I58: =I41+I46+I51+I52+I54+I55+I56 -> 0 | J58: =J41+J46+J51+J52+J54+J55+J56 -> 0 | K58: =K41+K46+K51+K52+K54+K55+K56 -> 0 | ... N58: =N41+N46+N51+N52+N54+N55+N56 -> 0 | P58: =SUM(D58:O58) -> 1946378.2
A59: Cost/Vol. Produced | C59: Mk/m3 | D59: =D58/D9 -> 294.76667 | E59: =E58/E9 -> 1555.7302 | F59: =F58/F9 -> 168.36601 | G59: =G58/G9 -> #DIV/0! | H59: =H58/H9 -> #DIV/0! | I59: =I58/I9 -> #DIV/0! | J59: =J58/J9 -> #DIV/0! | K59: =K58/K9 -> #DIV/0! | ... N59: =N58/N9 -> #DIV/0! | P59: =P58/P9 -> 654.02494
A60: Cost/Vol. Billed | C60: Mk/m3 | D60: =D58/D22 -> 364.49642 | E60: =E58/E22 -> 1819.8741 | F60: =F58/F22 -> 204.19834 | G60: =G58/G22 -> #DIV/0! | H60: =H58/H22 -> #DIV/0! | I60: =I58/I22 -> #DIV/0! | J60: =J58/J22 -> #DIV/0! | K60: =K58/K22 -> #DIV/0! | ... N60: =N58/N22 -> #DIV/0! | P60: =P58/P22 -> 789.92623
A61: Permanent Staff Employed | C61: No | P61: =O61 -> 0
A62: Staff/Vol.1000m3 of Volume Produced/hour (12 hour day) | C62: No/1000m3 | D62: =(D61*1000*31)/D9 -> 0 | E62: =(E61*1000*31)/E9 -> 0 | F62: =(F61*1000*31)/F9 -> 0 | G62: =(G61*1000*31)/G9 -> #DIV/0! | H62: =(H61*1000*31)/H9 -> #DIV/0! | I62: =(I61*1000*31)/I9 -> #DIV/0! | J62: =(J61*1000*31)/J9 -> #DIV/0! | K62: =(K61*1000*31)/K9 -> #DIV/0! | ... N62: =(N61*1000*31)/N9 -> #DIV/0! | P62: =(P61*1000*31)/P9 -> 0
A63: Temporary Staff Employed | C63: No | D63: 2 | E63: 2 | F63: 2 | P63: =SUM(D63:O63) -> 6
A65: Water Connections and Disconnections
A66: New Individual Water Connections | B66: Brought Forward | C66: No | E66: =D71 -> 0 | F66: =E71 -> 0 | G66: =F71 -> 0 | H66: =G71 -> 0 | I66: =H71 -> 0 | J66: =I71 -> 0 | K66: =J71 -> 0 | L66: =K71 -> 0 | ... O66: =N71 -> 0 | P66: =D66 -> 0
B67: Applied this Month | C67: No | P67: =SUM(D67:O67) -> 0
B68: Done this Month Postpaid | C68: No | P68: =SUM(D68:O68) -> 0
B69: Done this Month Prepaid | C69: No | P69: =SUM(D69:O69) -> 0
B70: Total Done | C70: No | D70: =D68+D69 -> 0 | E70: =E68+E69 -> 0 | F70: =F68+F69 -> 0 | G70: =G68+G69 -> 0 | H70: =H68+H69 -> 0 | I70: =I68+I69 -> 0 | J70: =J68+J69 -> 0 | K70: =K68+K69 -> 0 | P70: =P68+P69 -> 0
B71: Carried Forward | C71: No | D71: =D66+D67-D70 -> 0 | E71: =E66+E67-E70 -> 0 | F71: =F66+F67-F70 -> 0 | G71: =G66+G67-G70 -> 0 | H71: =H66+H67-H70 -> 0 | I71: =I66+I67-I70 -> 0 | J71: =J66+J67-J70 -> 0 | K71: =K66+K67-K70 -> 0 | ... P71: =P66+P67-P70 -> 0
A72: New Institutional Water Connections | B72: Brought Forward | C72: No | E72: =D77 -> 0 | F72: =E77 -> 0 | G72: =F77 -> 0 | H72: =G77 -> 0 | I72: =H77 -> 0 | P72: =D72 -> 0
B73: Applied this Month | C73: No | P73: =SUM(D73:O73) -> 0
B74: Done this Month Postpaid | C74: No | P74: =SUM(D74:O74) -> 0
B75: Done this Month Prepaid | C75: No | P75: =SUM(D75:O75) -> 0
B76: Total Done | C76: No | D76: =D74+D75 -> 0 | E76: =E74+E75 -> 0 | F76: =F74+F75 -> 0 | G76: =G74+G75 -> 0 | H76: =H74+H75 -> 0 | I76: =I74+I75 -> 0 | J76: =J74+J75 -> 0 | K76: =K74+K75 -> 0 | M76: =M74+M75 -> 0 | N76: =N74+N75 -> 0 | P76: =P74+P75 -> 0
B77: Carried Forward | C77: No | D77: =D72+D73-D76 -> 0 | E77: =E72+E73-E76 -> 0 | F77: =F72+F73-F76 -> 0 | G77: =G72+G73-G76 -> 0 | H77: =H72+H73-H76 -> 0 | I77: =I72+I73-I76 -> 0 | J77: =J72+J73-J76 -> 0 | K77: =K72+K73-K76 -> 0 | ... P77: =P72+P73-P76 -> 0
A78: New Commercial/Industrial Water Connections | B78: Brought Forward | C78: No | E78: =D83 -> 0 | F78: =E83 -> 0 | G78: =F83 -> 0 | H78: =G83 -> 0 | I78: =H83 -> 0 | J78: =I83 -> 0 | K78: =J83 -> 0 | L78: =K83 -> 0 | ... O78: =N83 -> 0 | P78: =D78 -> 0
B79: Applied this Month | C79: No | P79: =SUM(D79:O79) -> 0
B80: Done this Month Postpaid | C80: No | P80: =SUM(D80:O80) -> 0
B81: Done this Month Prepaid | C81: No | P81: =SUM(D81:O81) -> 0
B82: Total Done | C82: No | D82: =D81+D80 -> 0 | E82: =E81+E80 -> 0 | F82: =F81+F80 -> 0 | G82: =G81+G80 -> 0 | H82: =H81+H80 -> 0 | I82: =I80+I81 -> 0 | J82: =J80+J81 -> 0 | K82: =K80+K81 -> 0 | M82: =M81+M80 -> 0 | N82: =N81+N80 -> 0 | P82: =P81+P80 -> 0
B83: Carried Forward | C83: No | D83: =D78+D79-D82 -> 0 | E83: =E78+E79-E82 -> 0 | F83: =F78+F79-F82 -> 0 | G83: =G78+G79-G82 -> 0 | H83: =H78+H79-H82 -> 0 | I83: =I78+I79-I82 -> 0 | J83: =J78+J79-J82 -> 0 | K83: =K78+K79-K82 -> 0 | ... P83: =P78+P79-P82 -> 0
A84: New CWP | B84: Brought Forward | C84: No | E84: =D89 -> 0 | F84: =E89 -> 0 | G84: =F89 -> 0 | H84: =G89 -> 0 | P84: =D84 -> 0
B85: Applied this Month | C85: No | P85: =SUM(D85:O85) -> 0
B86: Done this Month Postpaid | C86: No | P86: =SUM(D86:O86) -> 0
B87: Done this Month Prepaid | C87: No | P87: =SUM(D87:O87) -> 0
B88: Total Done | C88: No | D88: =D86+D87 -> 0 | E88: =E86+E87 -> 0 | F88: =F86+F87 -> 0 | G88: =G86+G87 -> 0 | H88: =H86+H87 -> 0 | I88: =I86+I87 -> 0 | J88: =J86+J87 -> 0 | K88: =K86+K87 -> 0 | ... O88: =O86+O87 -> 0 | P88: =SUM(D88:O88) -> 0
B89: Carried Forward | C89: No | D89: =D84+D85-D88 -> 0 | E89: =E84+E85-E88 -> 0 | F89: =F84+F85-F88 -> 0 | G89: =G84+G85-G88 -> 0 | H89: =H84+H85-H88 -> 0 | I89: =I84+I85-I88 -> 0 | J89: =J84+J85-J88 -> 0 | K89: =K84+K85-K88 -> 0 | ... O89: =O84+O85-O88 -> 0 | P89: =P84+P85-P86-P87 -> 0
A90: Aggregated New Water connections | B90: Brought Forward | C90: No | D90: =D66+D72+D78+D84 -> 0 | E90: =E66+E72+E78+E84 -> 0 | F90: =F66+F72+F78+F84 -> 0 | G90: =G66+G72+G78+G84 -> 0 | H90: =H66+H72+H78+H84 -> 0 | I90: =I66+I72+I78+I84 -> 0 | J90: =J66+J72+J78+J84 -> 0 | K90: =K66+K72+K78+K84 -> 0 | ... O90: =O66+O72+O78+O84 -> 0 | P90: =D90 -> 0
B91: Applied this Month | C91: No | D91: =D67+D73+D79+D85 -> 0 | E91: =E67+E73+E79+E85 -> 0 | F91: =F67+F73+F79+F85 -> 0 | G91: =G67+G73+G79+G85 -> 0 | H91: =H67+H73+H79+H85 -> 0 | I91: =I67+I73+I79+I85 -> 0 | J91: =J67+J73+J79+J85 -> 0 | K91: =K67+K73+K79+K85 -> 0 | ... O91: =O67+O73+O79+O85 -> 0 | P91: =SUM(D91:O91) -> 0
B92: Done this Month Postpaid | C92: No | D92: =D68+D74+D80+D86 -> 0 | E92: =E68+E74+E80+E86 -> 0 | F92: =F68+F74+F80+F86 -> 0 | G92: =G68+G74+G80+G86 -> 0 | H92: =H68+H74+H80+H86 -> 0 | I92: =I68+I74+I80+I86 -> 0 | J92: =J68+J74+J80+J86 -> 0 | K92: =K68+K74+K80+K86 -> 0 | ... O92: =O68+O74+O80+O86 -> 0 | P92: =SUM(D92:O92) -> 0
B93: Done this Month Prepaid | D93: =D69+D75+D81+D87 -> 0 | E93: =E69+E75+E81+E87 -> 0 | F93: =F69+F75+F81+F87 -> 0 | G93: =G69+G75+G81+G87 -> 0 | H93: =H69+H75+H81+H87 -> 0 | I93: =I69+I75+I81+I87 -> 0 | J93: =J69+J75+J81+J87 -> 0 | K93: =K69+K75+K81+K87 -> 0 | ... O93: =O69+O75+O81+O87 -> 0 | P93: =SUM(D93:O93) -> 0
B94: Total Done | C94: No | D94: =D93+D92 -> 0 | E94: =E93+E92 -> 0 | F94: =F93+F92 -> 0 | G94: =G93+G92 -> 0 | H94: =H93+H92 -> 0 | I94: =I93+I92 -> 0 | J94: =J93+J92 -> 0 | K94: =K93+K92 -> 0 | ... P94: =P93+P92 -> 0
B95: Carried Forward | C95: No | D95: =D90+D91-D94 -> 0 | E95: =E90+E91-E94 -> 0 | F95: =F90+F91-F94 -> 0 | G95: =G90+G91-G94 -> 0 | H95: =H90+H91-H94 -> 0 | I95: =I90+I91-I94 -> 0 | J95: =J90+J91-J94 -> 0 | K95: =K90+K91-K94 -> 0 | ... P95: =P90+P91-P94 -> 0
A97: Prepaid Metering
A98: Prepaid Meters Installed | C98: No | P98: =SUM(D98:O98) -> 0
A100: Active and Disconnected Accounts
A101: Disconnected Individual Accounts | C101: No | P101: =O101 -> 0
A102: Disconnected institutional Accounts | C102: No | P102: =O102 -> 0
A103: Disconnected Commercial/Industrial Accounts | C103: No | P103: =O103 -> 0
A104: Disconnected CWP | C104: No | P104: =O104 -> 0
A105: Total Disconnected Accounts | C105: No | D105: =SUM(D101:D104) -> 0 | E105: =SUM(E101:E104) -> 0 | F105: =SUM(F101:F104) -> 0 | G105: =SUM(G101:G104) -> 0 | H105: =SUM(H101:H104) -> 0 | I105: =SUM(I101:I104) -> 0 | J105: =SUM(J101:J104) -> 0 | K105: =SUM(K101:K104) -> 0 | ... O105: =SUM(O101:O104) -> 0 | P105: =O105 -> 0
A106: Postpaid Consumers
...

Sheet Nkando
A1: SOUTHERN REGION WATER BOARD
A3: MONTHLY REPORTS - 2026/2027
A4: MULANJE ZONE
A5: MULANJE ZONE
A7: PARAMETERS | C7: UNITS | D7: APRIL | E7: MAY | F7: JUNE | G7: JULY | H7: AUGUST | I7: SEPTEMBER | J7: OCTOBER | K7: NOVEMBER | L7: DECEMBER | M7: JANUARY | N7: FEBRUARY | O7: MARCH | P7: TOTALS
A8: PRODUCTION
A9: Volume Produced | C9: m3 | D9: 2150 | E9: 2312 | F9: 2100 | P9: =SUM(D9:O9) -> 6562
A10: REVENUE WATER - POSTPAID
A11: Volume Billed Individuals | C11: m3 | P11: =SUM(D11:O11) -> 0
A12: Volume Billed CWPs | C12: m3 | P12: =SUM(D12:O12) -> 0
A13: Volume Billed Institutions | C13: m3 | P13: =SUM(D13:O13) -> 0
A14: Volume Billed Commercial/Industrial | C14: m3 | P14: =SUM(D14:O14) -> 0
A15: Total Volume Billed Post Paid | C15: m3 | D15: =SUM(D11:D14) -> 0 | F15: =SUM(F11:F14) -> 0 | G15: =SUM(G11:G14) -> 0 | H15: =SUM(H11:H14) -> 0 | I15: =SUM(I11:I14) -> 0 | J15: =SUM(J11:J14) -> 0 | K15: =SUM(K11:K14) -> 0 | L15: =SUM(L11:L14) -> 0 | M15: =SUM(M11:M14) -> 0 | ... P15: =SUM(P11:P14) -> 0
A16: REVENUE WATER - PREPAID
A17: Individuals | C17: m3 | D17: 1566 | E17: 1735.1 | F17: 1566.8 | P17: =SUM(D17:O17) -> 4867.9
A18: CWPs | C18: m3 | D18: 12 | E18: 4 | F18: 4 | P18: =SUM(D18:O18) -> 20
A19: Institutions | C19: m3 | D19: 18 | E19: 22 | F19: 14 | P19: =SUM(D19:O19) -> 54
A20: Commercial/Industrial | C20: m3 | D20: 47 | E20: 39 | F20: 27 | P20: =SUM(D20:O20) -> 113
A21: Total Volume Prepaid | C21: m3 | D21: =SUM(D17:D20) -> 1643 | E21: =SUM(E17:E20) -> 1800.1 | F21: =SUM(F17:F20) -> 1611.8 | G21: =SUM(G17:G20) -> 0 | H21: =SUM(H17:H20) -> 0 | I21: =SUM(I17:I20) -> 0 | J21: =SUM(J17:J20) -> 0 | K21: =SUM(K17:K20) -> 0 | ... P21: =SUM(P17:P20) -> 5054.9
A22: TOTAL REVENUE WATER | C22: m3 | D22: =D21+D15 -> 1643 | E22: =E21+E15 -> 1800.1 | F22: =F21+F15 -> 1611.8 | G22: =G21+G15 -> 0 | H22: =H21+H15 -> 0 | I22: =I21+I15 -> 0 | J22: =J21+J15 -> 0 | K22: =K21+K15 -> 0 | ... P22: =P21+P15 -> 5054.9
A24: Non-Revenue Water (NRW) | B24: Volume | C24: m3 | D24: =D9-D22 -> 507 | E24: =E9-E22 -> 511.9 | F24: =F9-F22 -> 488.2 | G24: =G9-G22 -> 0 | H24: =H9-H22 -> 0 | I24: =I9-I22 -> 0 | J24: =J9-J22 -> 0 | K24: =K9-K22 -> 0 | ... P24: =P9-P22 -> 1507.1
B25: Percentage | C25: % | D25: =D24/D9 -> 0.23581395 | E25: =E24/E9 -> 0.22141003 | F25: =F24/F9 -> 0.23247619 | G25: =G24/G9 -> #DIV/0! | H25: =H24/H9 -> #DIV/0! | I25: =I24/I9 -> #DIV/0! | J25: =J24/J9 -> #DIV/0! | K25: =K24/K9 -> #DIV/0! | ... P25: =P24/P9 -> 0.22967083
A26: OPERATING EXPENSES
A27: Chemicals
A28: Chemical | B28: Rate(MK/kg)
A29: Chlorine | B29: 5111.67 | C29: kg | D29: 6 | E29: 6 | F29: 5 | P29: =SUM(D29:O29) -> 17
C30: kg/mg litre | D30: =D29/(D9/1000) -> 2.7906977 | E30: =E29/(E9/1000) -> 2.5951557 | F30: =F29/(F9/1000) -> 2.3809524 | G30: =G29/(G9/1000) -> #DIV/0! | H30: =H29/(H9/1000) -> #DIV/0! | I30: =I29/(I9/1000) -> #DIV/0! | J30: =J29/(J9/1000) -> #DIV/0! | K30: =K29/(K9/1000) -> #DIV/0! | ... N30: =N29/(N9/1000) -> #DIV/0! | P30: =P29/(P9/1000) -> 2.5906736
A31: Aluminium sulphate | B31: 1537 | C31: kg | P31: =SUM(D31:O31) -> 0
C32: kg/mg litre | D32: =D31/(D9/1000) -> 0 | E32: =E31/(E9/1000) -> 0 | F32: =F31/(F9/1000) -> 0 | G32: =G31/(G9/1000) -> #DIV/0! | H32: =H31/(H9/1000) -> #DIV/0! | I32: =I31/(I9/1000) -> #DIV/0! | J32: =J31/(J9/1000) -> #DIV/0! | K32: =K31/(K9/1000) -> #DIV/0! | ... N32: =N31/(N9/1000) -> #DIV/0! | P32: =P31/(P9/1000) -> 0
A33: Soda | B33: 1781.02 | C33: kg | P33: =SUM(D33:O33) -> 0
C34: kg/mg litre | D34: =D33/(D9/1000) -> 0 | E34: =E33/(E9/1000) -> 0 | F34: =F33/(F9/1000) -> 0 | G34: =G33/(G9/1000) -> #DIV/0! | H34: =H33/(H9/1000) -> #DIV/0! | I34: =I33/(I9/1000) -> #DIV/0! | J34: =J33/(J9/1000) -> #DIV/0! | K34: =K33/(K9/1000) -> #DIV/0! | ... N34: =N33/(N9/1000) -> #DIV/0! | P34: =P33/(P9/1000) -> 0
A35: Algae floc | B35: 5979.95 | C35: litres
C36: litres/mg litre
A37: Sud floc | B37: 5403.75 | C37: litres | P37: =SUM(D37:O37) -> 0
C38: litres/mg litre | D38: =D37/(D9/1000) -> 0 | E38: =E37/(E9/1000) -> 0 | F38: =F37/(F9/1000) -> 0 | G38: =G37/(G9/1000) -> #DIV/0! | H38: =H37/(H9/1000) -> #DIV/0! | I38: =I37/(I9/1000) -> #DIV/0! | J38: =J37/(J9/1000) -> #DIV/0! | K38: =K37/(K9/1000) -> #DIV/0! | ... N38: =N37/(N9/1000) -> #DIV/0! | P38: =P37/(P9/1000) -> 0
A39: Potasium permanganate | B39: 1950 | C39: kg | P39: =SUM(D39:O39) -> 0
C40: kg/mg litre | D40: =D39/(D9/1000) -> 0 | E40: =E39/(E9/1000) -> 0 | F40: =F39/(F9/1000) -> 0 | G40: =G39/(G9/1000) -> #DIV/0! | H40: =H39/(H9/1000) -> #DIV/0! | I40: =I39/(I9/1000) -> #DIV/0! | J40: =J39/(J9/1000) -> #DIV/0! | K40: =K39/(K9/1000) -> #DIV/0! | ... N40: =N39/(N9/1000) -> #DIV/0! | P40: =P39/(P9/1000) -> 0
A41: Cost of Chemicals | C41: Mk | D41: =(D29*$B29)+(D31*$B31)+(D33*$B33)+(D35*$B35)+(D37*$B37)+(D39*$B39) -> 30670.02 | E41: =(E29*$B29)+(E31*$B31)+(E33*$B33)+(E35*$B35)+(E37*$B37)+(E39*$B39) -> 30670.02 | F41: =(F29*$B29)+(F31*$B31)+(F33*$B33)+(F35*$B35)+(F37*$B37)+(F39*$B39) -> 25558.35 | G41: =(G29*$B29)+(G31*$B31)+(G33*$B33)+(G35*$B35)+(G37*$B37)+(G39*$B39) -> 0 | H41: =(H29*$B29)+(H31*$B31)+(H33*$B33)+(H35*$B35)+(H37*$B37)+(H39*$B39) -> 0 | I41: =(I29*$B29)+(I31*$B31)+(I33*$B33)+(I35*$B35)+(I37*$B37)+(I39*$B39) -> 0 | J41: =(J29*$B29)+(J31*$B31)+(J33*$B33)+(J35*$B35)+(J37*$B37)+(J39*$B39) -> 0 | K41: =(K29*$B29)+(K31*$B31)+(K33*$B33)+(K35*$B35)+(K37*$B37)+(K39*$B39) -> 0 | ... O41: =(O29*$B29)+(O31*$B31)+(O33*$B33)+(O35*$B35)+(O37*$B37)+(O39*$B39) -> 0 | P41: =SUM(D41:O41) -> 86898.39
A42: Cost/vol. Produced (chemicals) | C42: Mk/m3 | D42: =D41/D9 -> 14.265126 | E42: =E41/E9 -> 13.26558 | F42: =F41/F9 -> 12.170643 | G42: =G41/G9 -> #DIV/0! | H42: =H41/H9 -> #DIV/0! | I42: =I41/I9 -> #DIV/0! | J42: =J41/J9 -> #DIV/0! | K42: =K41/K9 -> #DIV/0! | ... P42: =P41/P9 -> 13.242668
A43: Power
A44: Power Usage | C44: Kw | D44: 2096 | E44: 1348 | F44: 599 | P44: =SUM(D44:O44) -> 4043
A45: Power/ Vol. Produced | C45: Kw/m3 | D45: =D44/D9 -> 0.97488372 | E45: =E44/E9 -> 0.58304498 | F45: =F44/F9 -> 0.2852381 | G45: =G44/G9 -> #DIV/0! | H45: =H44/H9 -> #DIV/0! | I45: =I44/I9 -> #DIV/0! | J45: =J44/J9 -> #DIV/0! | K45: =K44/K9 -> #DIV/0! | ... N45: =N44/N9 -> #DIV/0! | P45: =P44/P9 -> 0.61612313
A46: Cost of Power | C46: Mk | D46: =333.87*D44 -> 699791.52 | E46: =333.87*E44 -> 450056.76 | F46: =333.87*F44 -> 199988.13 | G46: =333.87*G44 -> 0 | H46: =333.87*H44 -> 0 | I46: =333.87*I44 -> 0 | J46: =333.87*J44 -> 0 | K46: =333.87*K44 -> 0 | ... O46: =333.87*O44 -> 0 | P46: =SUM(D46:O46) -> 1349836.4
A47: Cost/vol. Produced | C47: Mk/m3 | D47: =D46/D9 -> 325.48443 | E47: =E46/E9 -> 194.66123 | F47: =F46/F9 -> 95.232443 | G47: =G46/G9 -> #DIV/0! | H47: =H46/H9 -> #DIV/0! | I47: =I46/I9 -> #DIV/0! | J47: =J46/J9 -> #DIV/0! | K47: =K46/K9 -> #DIV/0! | ... P47: =P46/P9 -> 205.70503
A48: Plant and Vehicle Maintenance
A49: Distances covered | C49: km | P49: =SUM(D49:O49) -> 0
A50: Fuel Used (litres) | C50: litres | P50: =SUM(D50:O50) -> 0
A51: Cost of fuel | C51: Mk | P51: =SUM(D51:O51) -> 0
A52: Maintenance | C52: Mk | P52: =SUM(D52:O52) -> 0
A53: Salaries and Wages
A54: Staff Costs | C54: MK | P54: =SUM(D54:O54) -> 0
A55: Wages | C55: MK | E55: 1285672.5 | F55: 1116013.9 | P55: =SUM(D55:O55) -> 2401686.4
A56: Other Overhead Costs | C56: MK | P56: =SUM(D56:O56) -> 0
A57: Operating Costs
A58: Total Operating Costs | C58: MK | D58: =D41+D46+D51+D52+D54+D55+D56 -> 730461.54 | E58: =E41+E46+E51+E52+E54+E55+E56 -> 1766399.3 | F58: =F41+F46+F51+F52+F54+F55+F56 -> 1341560.4 | G58: =G41+G46+G51+G52+G54+G55+G56 -> 0 | H58: =H41+H46+H51+H52+H54+H55+H56 -> 0 | I58: =I41+I46+I51+I52+I54+I55+I56 -> 0 | J58: =J41+J46+J51+J52+J54+J55+J56 -> 0 | K58: =K41+K46+K51+K52+K54+K55+K56 -> 0 | ... N58: =N41+N46+N51+N52+N54+N55+N56 -> 0 | P58: =SUM(D58:O58) -> 3838421.2
A59: Cost/Vol. Produced | C59: Mk/m3 | D59: =D58/D9 -> 339.74955 | E59: =E58/E9 -> 764.01353 | F59: =F58/F9 -> 638.83829 | G59: =G58/G9 -> #DIV/0! | H59: =H58/H9 -> #DIV/0! | I59: =I58/I9 -> #DIV/0! | J59: =J58/J9 -> #DIV/0! | K59: =K58/K9 -> #DIV/0! | ... N59: =N58/N9 -> #DIV/0! | P59: =P58/P9 -> 584.94685
A60: Cost/Vol. Billed | C60: Mk/m3 | D60: =D58/D22 -> 444.5901 | E60: =E58/E22 -> 981.27842 | F60: =F58/F22 -> 832.33677 | G60: =G58/G22 -> #DIV/0! | H60: =H58/H22 -> #DIV/0! | I60: =I58/I22 -> #DIV/0! | J60: =J58/J22 -> #DIV/0! | K60: =K58/K22 -> #DIV/0! | ... N60: =N58/N22 -> #DIV/0! | P60: =P58/P22 -> 759.34662
A61: Permanent Staff Employed | C61: No | D61: 5 | E61: 5 | F61: 5 | P61: =O61 -> 0
A62: Staff/Vol.1000m3 of Volume Produced/hour (12 hour day) | C62: No/1000m3 | D62: =(D61*1000*31)/D9 -> 72.093023 | E62: =(E61*1000*31)/E9 -> 67.041522 | F62: =(F61*1000*31)/F9 -> 73.809524 | G62: =(G61*1000*31)/G9 -> #DIV/0! | H62: =(H61*1000*31)/H9 -> #DIV/0! | I62: =(I61*1000*31)/I9 -> #DIV/0! | J62: =(J61*1000*31)/J9 -> #DIV/0! | K62: =(K61*1000*31)/K9 -> #DIV/0! | ... N62: =(N61*1000*31)/N9 -> #DIV/0! | P62: =(P61*1000*31)/P9 -> 0
A63: Temporary Staff Employed | C63: No | D63: 2 | E63: 2 | F63: 2 | P63: =SUM(D63:O63) -> 6
A65: Water Connections and Disconnections
A66: New Individual Water Connections | B66: Brought Forward | C66: No | D66: 6 | E66: =D71 -> 6 | F66: =E71 -> 10 | G66: =F71 -> 4 | H66: =G71 -> 4 | I66: =H71 -> 4 | J66: =I71 -> 4 | K66: =J71 -> 4 | L66: =K71 -> 4 | ... O66: =N71 -> 4 | P66: =D66 -> 6
B67: Applied this Month | C67: No | E67: 4 | F67: 3 | P67: =SUM(D67:O67) -> 7
B68: Done this Month Postpaid | C68: No | P68: =SUM(D68:O68) -> 0
B69: Done this Month Prepaid | C69: No | F69: 9 | P69: =SUM(D69:O69) -> 9
B70: Total Done | C70: No | D70: =D68+D69 -> 0 | E70: =E68+E69 -> 0 | F70: =F68+F69 -> 9 | G70: =G68+G69 -> 0 | H70: =H68+H69 -> 0 | M70: =M68+M69 -> 0 | P70: =P68+P69 -> 9
B71: Carried Forward | C71: No | D71: =D66+D67-D70 -> 6 | E71: =E66+E67-E70 -> 10 | F71: =F66+F67-F70 -> 4 | G71: =G66+G67-G70 -> 4 | H71: =H66+H67-H70 -> 4 | I71: =I66+I67-I70 -> 4 | J71: =J66+J67-J70 -> 4 | K71: =K66+K67-K70 -> 4 | ... N71: =N66+N67-N70 -> 4 | P71: =P66+P67-P70 -> 4
A72: New Institutional Water Connections | B72: Brought Forward | C72: No | E72: =D77 -> 0 | F72: =E77 -> 0 | G72: =F77 -> 0 | H72: =G77 -> 0 | I72: =H77 -> 0 | P72: =D72 -> 0
B73: Applied this Month | C73: No | P73: =SUM(D73:O73) -> 0
B74: Done this Month Postpaid | C74: No | P74: =SUM(D74:O74) -> 0
B75: Done this Month Prepaid | C75: No | P75: =SUM(D75:O75) -> 0
B76: Total Done | C76: No | D76: =D74+D75 -> 0 | E76: =E74+E75 -> 0 | F76: =F74+F75 -> 0 | G76: =G74+G75 -> 0 | H76: =H74+H75 -> 0 | I76: =I74+I75 -> 0 | J76: =J74+J75 -> 0 | K76: =K74+K75 -> 0 | M76: =M74+M75 -> 0 | N76: =N74+N75 -> 0 | P76: =P74+P75 -> 0
B77: Carried Forward | C77: No | D77: =D72+D73-D76 -> 0 | E77: =E72+E73-E76 -> 0 | F77: =F72+F73-F76 -> 0 | G77: =G72+G73-G76 -> 0 | H77: =H72+H73-H76 -> 0 | I77: =I72+I73-I76 -> 0 | J77: =J72+J73-J76 -> 0 | K77: =K72+K73-K76 -> 0 | ... N77: =N72+N73-N76 -> 0 | P77: =P72+P73-P76 -> 0
A78: New Commercial/Industrial Water Connections | B78: Brought Forward | C78: No | E78: =D83 -> 0 | F78: =E83 -> 0 | G78: =F83 -> 0 | H78: =G83 -> 0 | I78: =H83 -> 0 | J78: =I83 -> 0 | K78: =J83 -> 0 | L78: =K83 -> 0 | ... N78: =M83 -> 0 | P78: =D78 -> 0
B79: Applied this Month | C79: No | P79: =SUM(D79:O79) -> 0
B80: Done this Month Postpaid | C80: No | P80: =SUM(D80:O80) -> 0
B81: Done this Month Prepaid | C81: No | P81: =SUM(D81:O81) -> 0
B82: Total Done | C82: No | D82: =D81+D80 -> 0 | E82: =E81+E80 -> 0 | F82: =F81+F80 -> 0 | G82: =G81+G80 -> 0 | H82: =H81+H80 -> 0 | I82: =I80+I81 -> 0 | J82: =J80+J81 -> 0 | K82: =K80+K81 -> 0 | M82: =M81+M80 -> 0 | N82: =N81+N80 -> 0 | P82: =P81+P80 -> 0
B83: Carried Forward | C83: No | D83: =D78+D79-D82 -> 0 | E83: =E78+E79-E82 -> 0 | F83: =F78+F79-F82 -> 0 | G83: =G78+G79-G82 -> 0 | H83: =H78+H79-H82 -> 0 | I83: =I78+I79-I82 -> 0 | J83: =J78+J79-J82 -> 0 | K83: =K78+K79-K82 -> 0 | ... N83: =N78+N79-N82 -> 0 | P83: =P78+P79-P82 -> 0
A84: New CWP | B84: Brought Forward | C84: No | E84: =D89 -> 0 | F84: =E89 -> 0 | G84: =F89 -> 0 | H84: =G89 -> 0 | P84: =D84 -> 0
B85: Applied this Month | C85: No | P85: =SUM(D85:O85) -> 0
B86: Done this Month Postpaid | C86: No | P86: =SUM(D86:O86) -> 0
B87: Done this Month Prepaid | C87: No | P87: =SUM(D87:O87) -> 0
B88: Total Done | C88: No | D88: =D86+D87 -> 0 | E88: =E86+E87 -> 0 | F88: =F86+F87 -> 0 | G88: =G86+G87 -> 0 | H88: =H86+H87 -> 0 | I88: =I86+I87 -> 0 | J88: =J86+J87 -> 0 | K88: =K86+K87 -> 0 | ... N88: =N86+N87 -> 0 | P88: =SUM(D88:O88) -> 0
B89: Carried Forward | C89: No | D89: =D84+D85-D88 -> 0 | E89: =E84+E85-E88 -> 0 | F89: =F84+F85-F88 -> 0 | G89: =G84+G85-G88 -> 0 | H89: =H84+H85-H88 -> 0 | I89: =I84+I85-I88 -> 0 | J89: =J84+J85-J88 -> 0 | K89: =K84+K85-K88 -> 0 | ... N89: =N84+N85-N88 -> 0 | P89: =P84+P85-P86-P87 -> 0
A90: Aggregated New Water connections | B90: Brought Forward | C90: No | D90: =D66+D72+D78+D84 -> 6 | E90: =E66+E72+E78+E84 -> 6 | F90: =F66+F72+F78+F84 -> 10 | G90: =G66+G72+G78+G84 -> 4 | H90: =H66+H72+H78+H84 -> 4 | I90: =I66+I72+I78+I84 -> 4 | J90: =J66+J72+J78+J84 -> 4 | K90: =K66+K72+K78+K84 -> 4 | ... N90: =N66+N72+N78+N84 -> 4 | P90: =D90 -> 6
B91: Applied this Month | C91: No | D91: =D67+D73+D79+D85 -> 0 | E91: =E67+E73+E79+E85 -> 4 | F91: =F67+F73+F79+F85 -> 3 | G91: =G67+G73+G79+G85 -> 0 | H91: =H67+H73+H79+H85 -> 0 | I91: =I67+I73+I79+I85 -> 0 | J91: =J67+J73+J79+J85 -> 0 | K91: =K67+K73+K79+K85 -> 0 | ... N91: =N67+N73+N79+N85 -> 0 | P91: =SUM(D91:O91) -> 7
B92: Done this Month Postpaid | C92: No | D92: =D68+D74+D80+D86 -> 0 | E92: =E68+E74+E80+E86 -> 0 | F92: =F68+F74+F80+F86 -> 0 | G92: =G68+G74+G80+G86 -> 0 | H92: =H68+H74+H80+H86 -> 0 | I92: =I68+I74+I80+I86 -> 0 | J92: =J68+J74+J80+J86 -> 0 | K92: =K68+K74+K80+K86 -> 0 | ... N92: =N68+N74+N80+N86 -> 0 | P92: =SUM(D92:O92) -> 0
B93: Done this Month Prepaid | D93: =D69+D75+D81+D87 -> 0 | E93: =E69+E75+E81+E87 -> 0 | F93: =F69+F75+F81+F87 -> 9 | G93: =G69+G75+G81+G87 -> 0 | H93: =H69+H75+H81+H87 -> 0 | I93: =I69+I75+I81+I87 -> 0 | J93: =J69+J75+J81+J87 -> 0 | K93: =K69+K75+K81+K87 -> 0 | ... N93: =N69+N75+N81+N87 -> 0 | P93: =SUM(D93:O93) -> 9
B94: Total Done | C94: No | D94: =D93+D92 -> 0 | E94: =E93+E92 -> 0 | F94: =F93+F92 -> 9 | G94: =G93+G92 -> 0 | H94: =H93+H92 -> 0 | I94: =I93+I92 -> 0 | J94: =J93+J92 -> 0 | K94: =K93+K92 -> 0 | ... N94: =N93+N92 -> 0 | P94: =P93+P92 -> 9
B95: Carried Forward | C95: No | D95: =D90+D91-D94 -> 6 | E95: =E90+E91-E94 -> 10 | F95: =F90+F91-F94 -> 4 | G95: =G90+G91-G94 -> 4 | H95: =H90+H91-H94 -> 4 | I95: =I90+I91-I94 -> 4 | J95: =J90+J91-J94 -> 4 | K95: =K90+K91-K94 -> 4 | ... P95: =P90+P91-P94 -> 4
A97: Prepaid Metering
A98: Prepaid Meters Installed | C98: No | P98: =SUM(D98:O98) -> 0
A100: Active and Disconnected Accounts
A101: Disconnected Individual Accounts | C101: No | D101: 13 | E101: 13 | F101: 12 | P101: =O101 -> 0
A102: Disconnected institutional Accounts | C102: No | D102: 5 | E102: 5 | F102: 5 | P102: =O102 -> 0
A103: Disconnected Commercial/Industrial Accounts | C103: No | D103: 5 | E103: 5 | F103: 5 | P103: =O103 -> 0
A104: Disconnected CWP | C104: No | D104: 11 | E104: 11 | F104: 11 | P104: =O104 -> 0
A105: Total Disconnected Accounts | C105: No | D105: =SUM(D101:D104) -> 34 | E105: =SUM(E101:E104) -> 34 | F105: =SUM(F101:F104) -> 33 | G105: =SUM(G101:G104) -> 0 | H105: =SUM(H101:H104) -> 0 | I105: =SUM(I101:I104) -> 0 | J105: =SUM(J101:J104) -> 0 | K105: =SUM(K101:K104) -> 0 | ... O105: =SUM(O101:O104) -> 0 | P105: =O105 -> 0
A106: Postpaid Consumers
...

Sheet Zone Monthly
A1: SOUTHERN REGION WATER BOARD
A3: MONTHLY REPORTS - 2024/2025
A4: MULANJEZONE
A5: MULANJE ZONE
A7: PARAMETERS | C7: UNITS | D7: APRIL | E7: MAY | F7: JUNE | G7: JULY | H7: AUGUST | I7: SEPTEMBER | J7: OCTOBER | K7: NOVEMBER | L7: DECEMBER | M7: JANUARY | N7: FEBRUARY | O7: MARCH | P7: TOTALS
A8: PRODUCTION
A9: Volume Produced | C9: m3 | D9: =Mulanje!D9+Luchenza!D9+Thyolo!D9+Muloza!D9+MUST!D9+Phalombe!D9+Mikolongwe!D9+Migowi!D9+Nkando!D9 -> 112732 | E9: =Mulanje!E9+Luchenza!E9+Thyolo!E9+Muloza!E9+MUST!E9+Phalombe!E9+Mikolongwe!E9+Migowi!E9+Nkando!E9 -> 123534 | F9: =Mulanje!F9+Luchenza!F9+Thyolo!F9+Muloza!F9+MUST!F9+Phalombe!F9+Mikolongwe!F9+Migowi!F9+Nkando!F9 -> 121652 | G9: =Mulanje!G9+Luchenza!G9+Thyolo!G9+Muloza!G9+MUST!G9+Phalombe!G9+Mikolongwe!G9+Migowi!G9+Nkando!G9 -> 0 | H9: =Mulanje!H9+Luchenza!H9+Thyolo!H9+Muloza!H9+MUST!H9+Phalombe!H9+Mikolongwe!H9+Migowi!H9+Nkando!H9 -> 0 | I9: =Mulanje!I9+Luchenza!I9+Thyolo!I9+Muloza!I9+MUST!I9+Phalombe!I9+Mikolongwe!I9+Migowi!I9+Nkando!I9 -> 0 | J9: =Mulanje!J9+Luchenza!J9+Thyolo!J9+Muloza!J9+MUST!J9+Phalombe!J9+Mikolongwe!J9+Migowi!J9+Nkando!J9 -> 0 | K9: =Mulanje!K9+Luchenza!K9+Thyolo!K9+Muloza!K9+MUST!K9+Phalombe!K9+Mikolongwe!K9+Migowi!K9+Nkando!K9 -> 0 | ... O9: =Mulanje!O9+Luchenza!O9+Thyolo!O9+Muloza!O9+MUST!O9+Phalombe!O9+Mikolongwe!O9+Migowi!O9+Nkando!O9 -> 0 | P9: =SUM(D9:O9) -> 357918
A10: REVENUE WATER - POSTPAID
A11: Volume Billed Individuals | C11: m3 | D11: =Mulanje!D11+Luchenza!D11+Thyolo!D11+Muloza!D11+MUST!D11+Phalombe!D11+Mikolongwe!D11+Migowi!D11+Nkando!D11 -> 29861 | E11: =Mulanje!E11+Luchenza!E11+Thyolo!E11+Muloza!E11+MUST!E11+Phalombe!E11+Mikolongwe!E11+Migowi!E11+Nkando!E11 -> 29996 | F11: =Mulanje!F11+Luchenza!F11+Thyolo!F11+Muloza!F11+MUST!F11+Phalombe!F11+Mikolongwe!F11+Migowi!F11+Nkando!F11 -> 37499 | G11: =Mulanje!G11+Luchenza!G11+Thyolo!G11+Muloza!G11+MUST!G11+Phalombe!G11+Mikolongwe!G11+Migowi!G11+Nkando!G11 -> 0 | H11: =Mulanje!H11+Luchenza!H11+Thyolo!H11+Muloza!H11+MUST!H11+Phalombe!H11+Mikolongwe!H11+Migowi!H11+Nkando!H11 -> 0 | I11: =Mulanje!I11+Luchenza!I11+Thyolo!I11+Muloza!I11+MUST!I11+Phalombe!I11+Mikolongwe!I11+Migowi!I11+Nkando!I11 -> 0 | J11: =Mulanje!J11+Luchenza!J11+Thyolo!J11+Muloza!J11+MUST!J11+Phalombe!J11+Mikolongwe!J11+Migowi!J11+Nkando!J11 -> 0 | K11: =Mulanje!K11+Luchenza!K11+Thyolo!K11+Muloza!K11+MUST!K11+Phalombe!K11+Mikolongwe!K11+Migowi!K11+Nkando!K11 -> 0 | ... O11: =Mulanje!O11+Luchenza!O11+Thyolo!O11+Muloza!O11+MUST!O11+Phalombe!O11+Mikolongwe!O11+Migowi!O11+Nkando!O11 -> 0 | P11: =SUM(D11:O11) -> 97356
A12: Volume Billed CWPs | C12: m3 | D12: =Mulanje!D12+Luchenza!D12+Thyolo!D12+Muloza!D12+MUST!D12+Phalombe!D12+Mikolongwe!D12+Migowi!D12+Nkando!D12 -> 842 | E12: =Mulanje!E12+Luchenza!E12+Thyolo!E12+Muloza!E12+MUST!E12+Phalombe!E12+Mikolongwe!E12+Migowi!E12+Nkando!E12 -> 922 | F12: =Mulanje!F12+Luchenza!F12+Thyolo!F12+Muloza!F12+MUST!F12+Phalombe!F12+Mikolongwe!F12+Migowi!F12+Nkando!F12 -> 1091 | G12: =Mulanje!G12+Luchenza!G12+Thyolo!G12+Muloza!G12+MUST!G12+Phalombe!G12+Mikolongwe!G12+Migowi!G12+Nkando!G12 -> 0 | H12: =Mulanje!H12+Luchenza!H12+Thyolo!H12+Muloza!H12+MUST!H12+Phalombe!H12+Mikolongwe!H12+Migowi!H12+Nkando!H12 -> 0 | I12: =Mulanje!I12+Luchenza!I12+Thyolo!I12+Muloza!I12+MUST!I12+Phalombe!I12+Mikolongwe!I12+Migowi!I12+Nkando!I12 -> 0 | J12: =Mulanje!J12+Luchenza!J12+Thyolo!J12+Muloza!J12+MUST!J12+Phalombe!J12+Mikolongwe!J12+Migowi!J12+Nkando!J12 -> 0 | K12: =Mulanje!K12+Luchenza!K12+Thyolo!K12+Muloza!K12+MUST!K12+Phalombe!K12+Mikolongwe!K12+Migowi!K12+Nkando!K12 -> 0 | ... O12: =Mulanje!O12+Luchenza!O12+Thyolo!O12+Muloza!O12+MUST!O12+Phalombe!O12+Mikolongwe!O12+Migowi!O12+Nkando!O12 -> 0 | P12: =SUM(D12:O12) -> 2855
A13: Volume Billed Institutions | C13: m3 | D13: =Mulanje!D13+Luchenza!D13+Thyolo!D13+Muloza!D13+MUST!D13+Phalombe!D13+Mikolongwe!D13+Migowi!D13+Nkando!D13 -> 125 | E13: =Mulanje!E13+Luchenza!E13+Thyolo!E13+Muloza!E13+MUST!E13+Phalombe!E13+Mikolongwe!E13+Migowi!E13+Nkando!E13 -> 111 | F13: =Mulanje!F13+Luchenza!F13+Thyolo!F13+Muloza!F13+MUST!F13+Phalombe!F13+Mikolongwe!F13+Migowi!F13+Nkando!F13 -> 231 | G13: =Mulanje!G13+Luchenza!G13+Thyolo!G13+Muloza!G13+MUST!G13+Phalombe!G13+Mikolongwe!G13+Migowi!G13+Nkando!G13 -> 0 | H13: =Mulanje!H13+Luchenza!H13+Thyolo!H13+Muloza!H13+MUST!H13+Phalombe!H13+Mikolongwe!H13+Migowi!H13+Nkando!H13 -> 0 | I13: =Mulanje!I13+Luchenza!I13+Thyolo!I13+Muloza!I13+MUST!I13+Phalombe!I13+Mikolongwe!I13+Migowi!I13+Nkando!I13 -> 0 | J13: =Mulanje!J13+Luchenza!J13+Thyolo!J13+Muloza!J13+MUST!J13+Phalombe!J13+Mikolongwe!J13+Migowi!J13+Nkando!J13 -> 0 | K13: =Mulanje!K13+Luchenza!K13+Thyolo!K13+Muloza!K13+MUST!K13+Phalombe!K13+Mikolongwe!K13+Migowi!K13+Nkando!K13 -> 0 | ... O13: =Mulanje!O13+Luchenza!O13+Thyolo!O13+Muloza!O13+MUST!O13+Phalombe!O13+Mikolongwe!O13+Migowi!O13+Nkando!O13 -> 0 | P13: =SUM(D13:O13) -> 467
A14: Volume Billed Commercial/Industrial | C14: m3 | D14: =Mulanje!D14+Luchenza!D14+Thyolo!D14+Muloza!D14+MUST!D14+Phalombe!D14+Mikolongwe!D14+Migowi!D14+Nkando!D14 -> 187 | E14: =Mulanje!E14+Luchenza!E14+Thyolo!E14+Muloza!E14+MUST!E14+Phalombe!E14+Mikolongwe!E14+Migowi!E14+Nkando!E14 -> 316 | F14: =Mulanje!F14+Luchenza!F14+Thyolo!F14+Muloza!F14+MUST!F14+Phalombe!F14+Mikolongwe!F14+Migowi!F14+Nkando!F14 -> 276 | G14: =Mulanje!G14+Luchenza!G14+Thyolo!G14+Muloza!G14+MUST!G14+Phalombe!G14+Mikolongwe!G14+Migowi!G14+Nkando!G14 -> 0 | H14: =Mulanje!H14+Luchenza!H14+Thyolo!H14+Muloza!H14+MUST!H14+Phalombe!H14+Mikolongwe!H14+Migowi!H14+Nkando!H14 -> 0 | I14: =Mulanje!I14+Luchenza!I14+Thyolo!I14+Muloza!I14+MUST!I14+Phalombe!I14+Mikolongwe!I14+Migowi!I14+Nkando!I14 -> 0 | J14: =Mulanje!J14+Luchenza!J14+Thyolo!J14+Muloza!J14+MUST!J14+Phalombe!J14+Mikolongwe!J14+Migowi!J14+Nkando!J14 -> 0 | K14: =Mulanje!K14+Luchenza!K14+Thyolo!K14+Muloza!K14+MUST!K14+Phalombe!K14+Mikolongwe!K14+Migowi!K14+Nkando!K14 -> 0 | ... O14: =Mulanje!O14+Luchenza!O14+Thyolo!O14+Muloza!O14+MUST!O14+Phalombe!O14+Mikolongwe!O14+Migowi!O14+Nkando!O14 -> 0 | P14: =SUM(D14:O14) -> 779
A15: Total Volume Billed Post Paid | C15: m3 | D15: =SUM(D11:D14) -> 31015 | E15: =SUM(E11:E14) -> 31345 | F15: =SUM(F11:F14) -> 39097 | G15: =SUM(G11:G14) -> 0 | H15: =SUM(H11:H14) -> 0 | I15: =SUM(I11:I14) -> 0 | J15: =SUM(J11:J14) -> 0 | K15: =SUM(K11:K14) -> 0 | ... P15: =SUM(P11:P14) -> 101457
A16: REVENUE WATER - PREPAID
A17: Individuals | C17: m3 | D17: =Mulanje!D17+Luchenza!D17+Thyolo!D17+Muloza!D17+MUST!D17+Phalombe!D17+Mikolongwe!D17+Migowi!D17+Nkando!D17 -> 28974.03 | E17: =Mulanje!E17+Luchenza!E17+Thyolo!E17+Muloza!E17+MUST!E17+Phalombe!E17+Mikolongwe!E17+Migowi!E17+Nkando!E17 -> 29648.4 | F17: =Mulanje!F17+Luchenza!F17+Thyolo!F17+Muloza!F17+MUST!F17+Phalombe!F17+Mikolongwe!F17+Migowi!F17+Nkando!F17 -> 27179 | G17: =Mulanje!G17+Luchenza!G17+Thyolo!G17+Muloza!G17+MUST!G17+Phalombe!G17+Mikolongwe!G17+Migowi!G17+Nkando!G17 -> 0 | H17: =Mulanje!H17+Luchenza!H17+Thyolo!H17+Muloza!H17+MUST!H17+Phalombe!H17+Mikolongwe!H17+Migowi!H17+Nkando!H17 -> 0 | I17: =Mulanje!I17+Luchenza!I17+Thyolo!I17+Muloza!I17+MUST!I17+Phalombe!I17+Mikolongwe!I17+Migowi!I17+Nkando!I17 -> 0 | J17: =Mulanje!J17+Luchenza!J17+Thyolo!J17+Muloza!J17+MUST!J17+Phalombe!J17+Mikolongwe!J17+Migowi!J17+Nkando!J17 -> 0 | K17: =Mulanje!K17+Luchenza!K17+Thyolo!K17+Muloza!K17+MUST!K17+Phalombe!K17+Mikolongwe!K17+Migowi!K17+Nkando!K17 -> 0 | ... O17: =Mulanje!O17+Luchenza!O17+Thyolo!O17+Muloza!O17+MUST!O17+Phalombe!O17+Mikolongwe!O17+Migowi!O17+Nkando!O17 -> 0 | P17: =SUM(D17:O17) -> 85801.43
A18: CWPs | C18: m3 | D18: =Mulanje!D18+Luchenza!D18+Thyolo!D18+Muloza!D18+MUST!D18+Phalombe!D18+Mikolongwe!D18+Migowi!D18+Nkando!D18 -> 274.4 | E18: =Mulanje!E18+Luchenza!E18+Thyolo!E18+Muloza!E18+MUST!E18+Phalombe!E18+Mikolongwe!E18+Migowi!E18+Nkando!E18 -> 327 | F18: =Mulanje!F18+Luchenza!F18+Thyolo!F18+Muloza!F18+MUST!F18+Phalombe!F18+Mikolongwe!F18+Migowi!F18+Nkando!F18 -> 282 | G18: =Mulanje!G18+Luchenza!G18+Thyolo!G18+Muloza!G18+MUST!G18+Phalombe!G18+Mikolongwe!G18+Migowi!G18+Nkando!G18 -> 0 | H18: =Mulanje!H18+Luchenza!H18+Thyolo!H18+Muloza!H18+MUST!H18+Phalombe!H18+Mikolongwe!H18+Migowi!H18+Nkando!H18 -> 0 | I18: =Mulanje!I18+Luchenza!I18+Thyolo!I18+Muloza!I18+MUST!I18+Phalombe!I18+Mikolongwe!I18+Migowi!I18+Nkando!I18 -> 0 | J18: =Mulanje!J18+Luchenza!J18+Thyolo!J18+Muloza!J18+MUST!J18+Phalombe!J18+Mikolongwe!J18+Migowi!J18+Nkando!J18 -> 0 | K18: =Mulanje!K18+Luchenza!K18+Thyolo!K18+Muloza!K18+MUST!K18+Phalombe!K18+Mikolongwe!K18+Migowi!K18+Nkando!K18 -> 0 | ... O18: =Mulanje!O18+Luchenza!O18+Thyolo!O18+Muloza!O18+MUST!O18+Phalombe!O18+Mikolongwe!O18+Migowi!O18+Nkando!O18 -> 0 | P18: =SUM(D18:O18) -> 883.4
A19: Institutions | C19: m3 | D19: =Mulanje!D19+Luchenza!D19+Thyolo!D19+Muloza!D19+MUST!D19+Phalombe!D19+Mikolongwe!D19+Migowi!D19+Nkando!D19 -> 18083.23 | E19: =Mulanje!E19+Luchenza!E19+Thyolo!E19+Muloza!E19+MUST!E19+Phalombe!E19+Mikolongwe!E19+Migowi!E19+Nkando!E19 -> 23639.9 | F19: =Mulanje!F19+Luchenza!F19+Thyolo!F19+Muloza!F19+MUST!F19+Phalombe!F19+Mikolongwe!F19+Migowi!F19+Nkando!F19 -> 18061.1 | G19: =Mulanje!G19+Luchenza!G19+Thyolo!G19+Muloza!G19+MUST!G19+Phalombe!G19+Mikolongwe!G19+Migowi!G19+Nkando!G19 -> 0 | H19: =Mulanje!H19+Luchenza!H19+Thyolo!H19+Muloza!H19+MUST!H19+Phalombe!H19+Mikolongwe!H19+Migowi!H19+Nkando!H19 -> 0 | I19: =Mulanje!I19+Luchenza!I19+Thyolo!I19+Muloza!I19+MUST!I19+Phalombe!I19+Mikolongwe!I19+Migowi!I19+Nkando!I19 -> 0 | J19: =Mulanje!J19+Luchenza!J19+Thyolo!J19+Muloza!J19+MUST!J19+Phalombe!J19+Mikolongwe!J19+Migowi!J19+Nkando!J19 -> 0 | K19: =Mulanje!K19+Luchenza!K19+Thyolo!K19+Muloza!K19+MUST!K19+Phalombe!K19+Mikolongwe!K19+Migowi!K19+Nkando!K19 -> 0 | ... O19: =Mulanje!O19+Luchenza!O19+Thyolo!O19+Muloza!O19+MUST!O19+Phalombe!O19+Mikolongwe!O19+Migowi!O19+Nkando!O19 -> 0 | P19: =SUM(D19:O19) -> 59784.23
A20: Commercial/Industrial | C20: m3 | D20: =Mulanje!D20+Luchenza!D20+Thyolo!D20+Muloza!D20+MUST!D20+Phalombe!D20+Mikolongwe!D20+Migowi!D20+Nkando!D20 -> 2325 | E20: =Mulanje!E20+Luchenza!E20+Thyolo!E20+Muloza!E20+MUST!E20+Phalombe!E20+Mikolongwe!E20+Migowi!E20+Nkando!E20 -> 3757 | F20: =Mulanje!F20+Luchenza!F20+Thyolo!F20+Muloza!F20+MUST!F20+Phalombe!F20+Mikolongwe!F20+Migowi!F20+Nkando!F20 -> 1887.9 | G20: =Mulanje!G20+Luchenza!G20+Thyolo!G20+Muloza!G20+MUST!G20+Phalombe!G20+Mikolongwe!G20+Migowi!G20+Nkando!G20 -> 0 | H20: =Mulanje!H20+Luchenza!H20+Thyolo!H20+Muloza!H20+MUST!H20+Phalombe!H20+Mikolongwe!H20+Migowi!H20+Nkando!H20 -> 0 | I20: =Mulanje!I20+Luchenza!I20+Thyolo!I20+Muloza!I20+MUST!I20+Phalombe!I20+Mikolongwe!I20+Migowi!I20+Nkando!I20 -> 0 | J20: =Mulanje!J20+Luchenza!J20+Thyolo!J20+Muloza!J20+MUST!J20+Phalombe!J20+Mikolongwe!J20+Migowi!J20+Nkando!J20 -> 0 | K20: =Mulanje!K20+Luchenza!K20+Thyolo!K20+Muloza!K20+MUST!K20+Phalombe!K20+Mikolongwe!K20+Migowi!K20+Nkando!K20 -> 0 | ... O20: =Mulanje!O20+Luchenza!O20+Thyolo!O20+Muloza!O20+MUST!O20+Phalombe!O20+Mikolongwe!O20+Migowi!O20+Nkando!O20 -> 0 | P20: =SUM(D20:O20) -> 7969.9
A21: Total Volume Prepaid | C21: m3 | D21: =SUM(D17:D20) -> 49656.66 | E21: =SUM(E17:E20) -> 57372.3 | F21: =SUM(F17:F20) -> 47410 | G21: =SUM(G17:G20) -> 0 | H21: =SUM(H17:H20) -> 0 | I21: =SUM(I17:I20) -> 0 | J21: =SUM(J17:J20) -> 0 | K21: =SUM(K17:K20) -> 0 | ... P21: =SUM(P17:P20) -> 154438.96
A22: TOTAL REVENUE WATER | C22: m3 | D22: =D21+D15 -> 80671.66 | E22: =E21+E15 -> 88717.3 | F22: =F21+F15 -> 86507 | G22: =G21+G15 -> 0 | H22: =H21+H15 -> 0 | I22: =I21+I15 -> 0 | J22: =J21+J15 -> 0 | K22: =K21+K15 -> 0 | ... P22: =P21+P15 -> 255895.96
A24: Non-Revenue Water (NRW) | B24: Volume | C24: m3 | D24: =D9-D22 -> 32060.34 | E24: =E9-E22 -> 34816.7 | F24: =F9-F22 -> 35145 | G24: =G9-G22 -> 0 | H24: =H9-H22 -> 0 | I24: =I9-I22 -> 0 | J24: =J9-J22 -> 0 | K24: =K9-K22 -> 0 | ... P24: =P9-P22 -> 102022.04
B25: Percentage | C25: % | D25: =D24/D9 -> 0.28439432 | E25: =E24/E9 -> 0.28183901 | F25: =F24/F9 -> 0.28889784 | G25: =G24/G9 -> #DIV/0! | H25: =H24/H9 -> #DIV/0! | I25: =I24/I9 -> #DIV/0! | J25: =J24/J9 -> #DIV/0! | K25: =K24/K9 -> #DIV/0! | ... P25: =P24/P9 -> 0.28504305
A26: OPERATING EXPENSES
A27: Chemicals
A28: Chemical | B28: Rate(MK/kg)
A29: Chlorine | B29: 5111.67 | C29: kg | D29: =Mulanje!D29+Luchenza!D29+Thyolo!D29+Muloza!D29+MUST!D29+Phalombe!D29+Mikolongwe!D29+Migowi!D29+Nkando!D29 -> 275 | E29: =Mulanje!E29+Luchenza!E29+Thyolo!E29+Muloza!E29+MUST!E29+Phalombe!E29+Mikolongwe!E29+Migowi!E29+Nkando!E29 -> 268 | F29: =Mulanje!F29+Luchenza!F29+Thyolo!F29+Muloza!F29+MUST!F29+Phalombe!F29+Mikolongwe!F29+Migowi!F29+Nkando!F29 -> 283 | G29: =Mulanje!G29+Luchenza!G29+Thyolo!G29+Muloza!G29+MUST!G29+Phalombe!G29+Mikolongwe!G29+Migowi!G29+Nkando!G29 -> 0 | H29: =Mulanje!H29+Luchenza!H29+Thyolo!H29+Muloza!H29+MUST!H29+Phalombe!H29+Mikolongwe!H29+Migowi!H29+Nkando!H29 -> 0 | I29: =Mulanje!I29+Luchenza!I29+Thyolo!I29+Muloza!I29+MUST!I29+Phalombe!I29+Mikolongwe!I29+Migowi!I29+Nkando!I29 -> 0 | J29: =Mulanje!J29+Luchenza!J29+Thyolo!J29+Muloza!J29+MUST!J29+Phalombe!J29+Mikolongwe!J29+Migowi!J29+Nkando!J29 -> 0 | K29: =Mulanje!K29+Luchenza!K29+Thyolo!K29+Muloza!K29+MUST!K29+Phalombe!K29+Mikolongwe!K29+Migowi!K29+Nkando!K29 -> 0 | ... O29: =Mulanje!O29+Luchenza!O29+Thyolo!O29+Muloza!O29+MUST!O29+Phalombe!O29+Mikolongwe!O29+Migowi!O29+Nkando!O29 -> 0 | P29: =SUM(D29:O29) -> 826
C30: kg/mg litre | D30: =D29/(D9/1000) -> 2.4394138 | E30: =E29/(E9/1000) -> 2.1694432 | F30: =F29/(F9/1000) -> 2.3263078 | G30: =G29/(G9/1000) -> #DIV/0! | H30: =H29/(H9/1000) -> #DIV/0! | I30: =I29/(I9/1000) -> #DIV/0! | J30: =J29/(J9/1000) -> #DIV/0! | K30: =K29/(K9/1000) -> #DIV/0! | ... P30: =P29/(P9/1000) -> 2.3077912
A31: Aluminium sulphate | B31: 1537 | C31: kg | D31: =Mulanje!D31+Luchenza!D31+Thyolo!D31+Muloza!D31+MUST!D31+Phalombe!D31+Mikolongwe!D31+Migowi!D31 -> 0 | E31: =Mulanje!E31+Luchenza!E31+Thyolo!E31+Muloza!E31+MUST!E31+Phalombe!E31+Mikolongwe!E31+Migowi!E31 -> 0 | F31: =Mulanje!F31+Luchenza!F31+Thyolo!F31+Muloza!F31+MUST!F31+Phalombe!F31+Mikolongwe!F31+Migowi!F31 -> 0 | G31: =Mulanje!G31+Luchenza!G31+Thyolo!G31+Muloza!G31+MUST!G31+Phalombe!G31+Mikolongwe!G31+Migowi!G31 -> 0 | H31: =Mulanje!H31+Luchenza!H31+Thyolo!H31+Muloza!H31+MUST!H31+Phalombe!H31+Mikolongwe!H31+Migowi!H31 -> 0 | I31: =Mulanje!I31+Luchenza!I31+Thyolo!I31+Muloza!I31+MUST!I31+Phalombe!I31+Mikolongwe!I31+Migowi!I31 -> 0 | J31: =Mulanje!J31+Luchenza!J31+Thyolo!J31+Muloza!J31+MUST!J31+Phalombe!J31+Mikolongwe!J31+Migowi!J31 -> 0 | K31: =Mulanje!K31+Luchenza!K31+Thyolo!K31+Muloza!K31+MUST!K31+Phalombe!K31+Mikolongwe!K31+Migowi!K31 -> 0 | L31: =Mulanje!L31+Luchenza!L31+Thyolo!L31+Muloza!L31+MUST!L31+Phalombe!L31+Mikolongwe!L31+Migowi!L31 -> 0 | M31: =Mulanje!M31+Luchenza!M31+Thyolo!M31+Muloza!M31+MUST!M31+Phalombe!M31+Mikolongwe!M31+Migowi!M31+Nkando!M31 -> 0 | N31: =Mulanje!N31+Luchenza!N31+Thyolo!N31+Muloza!N31+MUST!N31+Phalombe!N31+Mikolongwe!N31+Migowi!N31+Nkando!N31 -> 0 | O31: =Mulanje!O31+Luchenza!O31+Thyolo!O31+Muloza!O31+MUST!O31+Phalombe!O31+Mikolongwe!O31+Migowi!O31+Nkando!O31 -> 0 | P31: =SUM(D31:O31) -> 0
C32: kg/mg litre | D32: =D31/(D9/1000) -> 0 | E32: =E31/(E9/1000) -> 0 | F32: =F31/(F9/1000) -> 0 | G32: =G31/(G9/1000) -> #DIV/0! | H32: =H31/(H9/1000) -> #DIV/0! | I32: =I31/(I9/1000) -> #DIV/0! | J32: =J31/(J9/1000) -> #DIV/0! | K32: =K31/(K9/1000) -> #DIV/0! | ... P32: =P31/(P9/1000) -> 0
A33: Soda | B33: 1781.02 | C33: kg | D33: =Mulanje!D33+Luchenza!D33+Thyolo!D33+Muloza!D33+MUST!D33+Phalombe!D33+Mikolongwe!D33+Migowi!D33 -> 0 | E33: =Mulanje!E33+Luchenza!E33+Thyolo!E33+Muloza!E33+MUST!E33+Phalombe!E33+Mikolongwe!E33+Migowi!E33 -> 0 | F33: =Mulanje!F33+Luchenza!F33+Thyolo!F33+Muloza!F33+MUST!F33+Phalombe!F33+Mikolongwe!F33+Migowi!F33 -> 0 | G33: =Mulanje!G33+Luchenza!G33+Thyolo!G33+Muloza!G33+MUST!G33+Phalombe!G33+Mikolongwe!G33+Migowi!G33 -> 0 | H33: =Mulanje!H33+Luchenza!H33+Thyolo!H33+Muloza!H33+MUST!H33+Phalombe!H33+Mikolongwe!H33+Migowi!H33 -> 0 | I33: =Mulanje!I33+Luchenza!I33+Thyolo!I33+Muloza!I33+MUST!I33+Phalombe!I33+Mikolongwe!I33+Migowi!I33 -> 0 | J33: =Mulanje!J33+Luchenza!J33+Thyolo!J33+Muloza!J33+MUST!J33+Phalombe!J33+Mikolongwe!J33+Migowi!J33 -> 0 | K33: =Mulanje!K33+Luchenza!K33+Thyolo!K33+Muloza!K33+MUST!K33+Phalombe!K33+Mikolongwe!K33+Migowi!K33 -> 0 | L33: =Mulanje!L33+Luchenza!L33+Thyolo!L33+Muloza!L33+MUST!L33+Phalombe!L33+Mikolongwe!L33+Migowi!L33 -> 0 | M33: =Mulanje!M33+Luchenza!M33+Thyolo!M33+Muloza!M33+MUST!M33+Phalombe!M33+Mikolongwe!M33+Migowi!M33+Nkando!M33 -> 0 | N33: =Mulanje!N33+Luchenza!N33+Thyolo!N33+Muloza!N33+MUST!N33+Phalombe!N33+Mikolongwe!N33+Migowi!N33+Nkando!N33 -> 0 | O33: =Mulanje!O33+Luchenza!O33+Thyolo!O33+Muloza!O33+MUST!O33+Phalombe!O33+Mikolongwe!O33+Migowi!O33+Nkando!O33 -> 0 | P33: =SUM(D33:O33) -> 0
C34: kg/mg litre | D34: =D33/(D9/1000) -> 0 | E34: =E33/(E9/1000) -> 0 | F34: =F33/(F9/1000) -> 0 | G34: =G33/(G9/1000) -> #DIV/0! | H34: =H33/(H9/1000) -> #DIV/0! | I34: =I33/(I9/1000) -> #DIV/0! | J34: =J33/(J9/1000) -> #DIV/0! | K34: =K33/(K9/1000) -> #DIV/0! | ... P34: =P33/(P9/1000) -> 0
A35: Algae floc | B35: 5979.95 | C35: litres | D35: =Mulanje!D35+Luchenza!D35+Thyolo!D35+Muloza!D35+MUST!D35+Phalombe!D35+Mikolongwe!D35+Migowi!D35 -> 84 | E35: =Mulanje!E35+Luchenza!E35+Thyolo!E35+Muloza!E35+MUST!E35+Phalombe!E35+Mikolongwe!E35+Migowi!E35 -> 54 | F35: =Mulanje!F35+Luchenza!F35+Thyolo!F35+Muloza!F35+MUST!F35+Phalombe!F35+Mikolongwe!F35+Migowi!F35 -> 81 | G35: =Mulanje!G35+Luchenza!G35+Thyolo!G35+Muloza!G35+MUST!G35+Phalombe!G35+Mikolongwe!G35+Migowi!G35 -> 0 | H35: =Mulanje!H35+Luchenza!H35+Thyolo!H35+Muloza!H35+MUST!H35+Phalombe!H35+Mikolongwe!H35+Migowi!H35 -> 0 | I35: =Mulanje!I35+Luchenza!I35+Thyolo!I35+Muloza!I35+MUST!I35+Phalombe!I35+Mikolongwe!I35+Migowi!I35 -> 0 | J35: =Mulanje!J35+Luchenza!J35+Thyolo!J35+Muloza!J35+MUST!J35+Phalombe!J35+Mikolongwe!J35+Migowi!J35 -> 0 | K35: =Mulanje!K35+Luchenza!K35+Thyolo!K35+Muloza!K35+MUST!K35+Phalombe!K35+Mikolongwe!K35+Migowi!K35 -> 0 | L35: =Mulanje!L35+Luchenza!L35+Thyolo!L35+Muloza!L35+MUST!L35+Phalombe!L35+Mikolongwe!L35+Migowi!L35 -> 0 | M35: =Mulanje!M35+Luchenza!M35+Thyolo!M35+Muloza!M35+MUST!M35+Phalombe!M35+Mikolongwe!M35+Migowi!M35+Nkando!M35 -> 0 | N35: =Mulanje!N35+Luchenza!N35+Thyolo!N35+Muloza!N35+MUST!N35+Phalombe!N35+Mikolongwe!N35+Migowi!N35+Nkando!N35 -> 0 | O35: =Mulanje!O35+Luchenza!O35+Thyolo!O35+Muloza!O35+MUST!O35+Phalombe!O35+Mikolongwe!O35+Migowi!O35+Nkando!O35 -> 0
C36: litres/mg litre
A37: Sud floc | B37: 5403.75 | C37: litres | D37: =Mulanje!D37+Luchenza!D37+Thyolo!D37+Muloza!D37+MUST!D37+Phalombe!D37+Mikolongwe!D37+Migowi!D37 -> 0 | E37: =Mulanje!E37+Luchenza!E37+Thyolo!E37+Muloza!E37+MUST!E37+Phalombe!E37+Mikolongwe!E37+Migowi!E37 -> 0 | F37: =Mulanje!F37+Luchenza!F37+Thyolo!F37+Muloza!F37+MUST!F37+Phalombe!F37+Mikolongwe!F37+Migowi!F37 -> 0 | G37: =Mulanje!G37+Luchenza!G37+Thyolo!G37+Muloza!G37+MUST!G37+Phalombe!G37+Mikolongwe!G37+Migowi!G37 -> 0 | H37: =Mulanje!H37+Luchenza!H37+Thyolo!H37+Muloza!H37+MUST!H37+Phalombe!H37+Mikolongwe!H37+Migowi!H37 -> 0 | I37: =Mulanje!I37+Luchenza!I37+Thyolo!I37+Muloza!I37+MUST!I37+Phalombe!I37+Mikolongwe!I37+Migowi!I37 -> 0 | J37: =Mulanje!J37+Luchenza!J37+Thyolo!J37+Muloza!J37+MUST!J37+Phalombe!J37+Mikolongwe!J37+Migowi!J37 -> 0 | K37: =Mulanje!K37+Luchenza!K37+Thyolo!K37+Muloza!K37+MUST!K37+Phalombe!K37+Mikolongwe!K37+Migowi!K37 -> 0 | L37: =Mulanje!L37+Luchenza!L37+Thyolo!L37+Muloza!L37+MUST!L37+Phalombe!L37+Mikolongwe!L37+Migowi!L37 -> 0 | M37: =Mulanje!M37+Luchenza!M37+Thyolo!M37+Muloza!M37+MUST!M37+Phalombe!M37+Mikolongwe!M37+Migowi!M37+Nkando!M37 -> 0 | N37: =Mulanje!N37+Luchenza!N37+Thyolo!N37+Muloza!N37+MUST!N37+Phalombe!N37+Mikolongwe!N37+Migowi!N37+Nkando!N37 -> 0 | O37: =Mulanje!O37+Luchenza!O37+Thyolo!O37+Muloza!O37+MUST!O37+Phalombe!O37+Mikolongwe!O37+Migowi!O37+Nkando!O37 -> 0 | P37: =SUM(D37:O37) -> 0
C38: litres/mg litre | D38: =D37/(D9/1000) -> 0 | E38: =E37/(E9/1000) -> 0 | F38: =F37/(F9/1000) -> 0 | G38: =G37/(G9/1000) -> #DIV/0! | H38: =H37/(H9/1000) -> #DIV/0! | I38: =I37/(I9/1000) -> #DIV/0! | J38: =J37/(J9/1000) -> #DIV/0! | K38: =K37/(K9/1000) -> #DIV/0! | ... P38: =P37/(P9/1000) -> 0
A39: Potasium permanganate | B39: 1950 | C39: kg | D39: =Mulanje!D39+Luchenza!D39+Thyolo!D39+Muloza!D39+MUST!D39+Phalombe!D39+Mikolongwe!D39+Migowi!D39 -> 0 | E39: =Mulanje!E39+Luchenza!E39+Thyolo!E39+Muloza!E39+MUST!E39+Phalombe!E39+Mikolongwe!E39+Migowi!E39 -> 0 | F39: =Mulanje!F39+Luchenza!F39+Thyolo!F39+Muloza!F39+MUST!F39+Phalombe!F39+Mikolongwe!F39+Migowi!F39 -> 0 | G39: =Mulanje!G39+Luchenza!G39+Thyolo!G39+Muloza!G39+MUST!G39+Phalombe!G39+Mikolongwe!G39+Migowi!G39 -> 0 | H39: =Mulanje!H39+Luchenza!H39+Thyolo!H39+Muloza!H39+MUST!H39+Phalombe!H39+Mikolongwe!H39+Migowi!H39 -> 0 | I39: =Mulanje!I39+Luchenza!I39+Thyolo!I39+Muloza!I39+MUST!I39+Phalombe!I39+Mikolongwe!I39+Migowi!I39 -> 0 | J39: =Mulanje!J39+Luchenza!J39+Thyolo!J39+Muloza!J39+MUST!J39+Phalombe!J39+Mikolongwe!J39+Migowi!J39 -> 0 | K39: =Mulanje!K39+Luchenza!K39+Thyolo!K39+Muloza!K39+MUST!K39+Phalombe!K39+Mikolongwe!K39+Migowi!K39 -> 0 | L39: =Mulanje!L39+Luchenza!L39+Thyolo!L39+Muloza!L39+MUST!L39+Phalombe!L39+Mikolongwe!L39+Migowi!L39 -> 0 | M39: =Mulanje!M39+Luchenza!M39+Thyolo!M39+Muloza!M39+MUST!M39+Phalombe!M39+Mikolongwe!M39+Migowi!M39+Nkando!M39 -> 0 | N39: =Mulanje!N39+Luchenza!N39+Thyolo!N39+Muloza!N39+MUST!N39+Phalombe!N39+Mikolongwe!N39+Migowi!N39+Nkando!N39 -> 0 | O39: =Mulanje!O39+Luchenza!O39+Thyolo!O39+Muloza!O39+MUST!O39+Phalombe!O39+Mikolongwe!O39+Migowi!O39+Nkando!O39 -> 0 | P39: =SUM(D39:O39) -> 0
C40: kg/mg litre | D40: =D39/(D9/1000) -> 0 | E40: =E39/(E9/1000) -> 0 | F40: =F39/(F9/1000) -> 0 | G40: =G39/(G9/1000) -> #DIV/0! | H40: =H39/(H9/1000) -> #DIV/0! | I40: =I39/(I9/1000) -> #DIV/0! | J40: =J39/(J9/1000) -> #DIV/0! | K40: =K39/(K9/1000) -> #DIV/0! | ... P40: =P39/(P9/1000) -> 0
A41: Cost of Chemicals | C41: Mk | D41: =(D29*$B29)+(D31*$B31)+(D33*$B33)+(D35*$B35)+(D37*$B37)+(D39*$B39) -> 1908025.1 | E41: =(E29*$B29)+(E31*$B31)+(E33*$B33)+(E35*$B35)+(E37*$B37)+(E39*$B39) -> 1692844.9 | F41: =(F29*$B29)+(F31*$B31)+(F33*$B33)+(F35*$B35)+(F37*$B37)+(F39*$B39) -> 1930978.6 | G41: =(G29*$B29)+(G31*$B31)+(G33*$B33)+(G35*$B35)+(G37*$B37)+(G39*$B39) -> 0 | H41: =(H29*$B29)+(H31*$B31)+(H33*$B33)+(H35*$B35)+(H37*$B37)+(H39*$B39) -> 0 | I41: =(I29*$B29)+(I31*$B31)+(I33*$B33)+(I35*$B35)+(I37*$B37)+(I39*$B39) -> 0 | J41: =(J29*$B29)+(J31*$B31)+(J33*$B33)+(J35*$B35)+(J37*$B37)+(J39*$B39) -> 0 | K41: =(K29*$B29)+(K31*$B31)+(K33*$B33)+(K35*$B35)+(K37*$B37)+(K39*$B39) -> 0 | ... O41: =(O29*$B29)+(O31*$B31)+(O33*$B33)+(O35*$B35)+(O37*$B37)+(O39*$B39) -> 0 | P41: =SUM(D41:O41) -> 5531848.5
A42: Cost/vol. Produced (chemicals) | C42: Mk/m3 | D42: =D41/D9 -> 16.925319 | E42: =E41/E9 -> 13.703473 | F42: =F41/F9 -> 15.87297 | G42: =G41/G9 -> #DIV/0! | H42: =H41/H9 -> #DIV/0! | I42: =I41/I9 -> #DIV/0! | J42: =J41/J9 -> #DIV/0! | K42: =K41/K9 -> #DIV/0! | ... P42: =P41/P9 -> 15.455631
A43: Power
A44: Power Usage | C44: Kw | D44: =Mulanje!D44+Luchenza!D44+Thyolo!D44+Muloza!D44+MUST!D44+Phalombe!D44+Mikolongwe!D44+Migowi!D44+Nkando!D44 -> 70356.27 | E44: =Mulanje!E44+Luchenza!E44+Thyolo!E44+Muloza!E44+MUST!E44+Phalombe!E44+Mikolongwe!E44+Migowi!E44+Nkando!E44 -> 69316 | F44: =Mulanje!F44+Luchenza!F44+Thyolo!F44+Muloza!F44+MUST!F44+Phalombe!F44+Mikolongwe!F44+Migowi!F44+Nkando!F44 -> 58678.71 | G44: =Mulanje!G44+Luchenza!G44+Thyolo!G44+Muloza!G44+MUST!G44+Phalombe!G44+Mikolongwe!G44+Migowi!G44+Nkando!G44 -> 0 | H44: =Mulanje!H44+Luchenza!H44+Thyolo!H44+Muloza!H44+MUST!H44+Phalombe!H44+Mikolongwe!H44+Migowi!H44+Nkando!H44 -> 0 | I44: =Mulanje!I44+Luchenza!I44+Thyolo!I44+Muloza!I44+MUST!I44+Phalombe!I44+Mikolongwe!I44+Migowi!I44+Nkando!I44 -> 0 | J44: =Mulanje!J44+Luchenza!J44+Thyolo!J44+Muloza!J44+MUST!J44+Phalombe!J44+Mikolongwe!J44+Migowi!J44+Nkando!J44 -> 0 | K44: =Mulanje!K44+Luchenza!K44+Thyolo!K44+Muloza!K44+MUST!K44+Phalombe!K44+Mikolongwe!K44+Migowi!K44+Nkando!K44 -> 0 | ... O44: =Mulanje!O44+Luchenza!O44+Thyolo!O44+Muloza!O44+MUST!O44+Phalombe!O44+Mikolongwe!O44+Migowi!O44+Nkando!O44 -> 0 | P44: =SUM(D44:O44) -> 198350.98
A45: Power/ Vol. Produced | C45: Kw/m3 | D45: =D44/D9 -> 0.62410203 | E45: =E44/E9 -> 0.56110868 | F45: =F44/F9 -> 0.48234891 | G45: =G44/G9 -> #DIV/0! | H45: =H44/H9 -> #DIV/0! | I45: =I44/I9 -> #DIV/0! | J45: =J44/J9 -> #DIV/0! | K45: =K44/K9 -> #DIV/0! | ... P45: =P44/P9 -> 0.55417995
A46: Cost of Power | C46: Mk | D46: =Mulanje!D46+Luchenza!D46+Thyolo!D46+Muloza!D46+MUST!D46+Phalombe!D46+Mikolongwe!D46+Migowi!D46+Nkando!D46 -> 23487932 | E46: =Mulanje!E46+Luchenza!E46+Thyolo!E46+Muloza!E46+MUST!E46+Phalombe!E46+Mikolongwe!E46+Migowi!E46+Nkando!E46 -> 16912869 | F46: =Mulanje!F46+Luchenza!F46+Thyolo!F46+Muloza!F46+MUST!F46+Phalombe!F46+Mikolongwe!F46+Migowi!F46+Nkando!F46 -> 13361588 | G46: =Mulanje!G46+Luchenza!G46+Thyolo!G46+Muloza!G46+MUST!G46+Phalombe!G46+Mikolongwe!G46+Migowi!G46+Nkando!G46 -> 16426.5 | H46: =Mulanje!H46+Luchenza!H46+Thyolo!H46+Muloza!H46+MUST!H46+Phalombe!H46+Mikolongwe!H46+Migowi!H46+Nkando!H46 -> 16426.5 | I46: =Mulanje!I46+Luchenza!I46+Thyolo!I46+Muloza!I46+MUST!I46+Phalombe!I46+Mikolongwe!I46+Migowi!I46+Nkando!I46 -> 16426.5 | J46: =Mulanje!J46+Luchenza!J46+Thyolo!J46+Muloza!J46+MUST!J46+Phalombe!J46+Mikolongwe!J46+Migowi!J46+Nkando!J46 -> 16426.5 | K46: =Mulanje!K46+Luchenza!K46+Thyolo!K46+Muloza!K46+MUST!K46+Phalombe!K46+Mikolongwe!K46+Migowi!K46+Nkando!K46 -> 16426.5 | ... P46: =Mulanje!P46+Luchenza!P46+Thyolo!P46+Muloza!P46+MUST!P46+Phalombe!P46+Mikolongwe!P46+Migowi!P46+Nkando!P46 -> 53893802
A47: Cost/vol. Produced | C47: Mk/m3 | D47: =D46/D9 -> 208.35195 | E47: =E46/E9 -> 136.90861 | F47: =F46/F9 -> 109.83451 | G47: =G46/G9 -> #DIV/0! | H47: =H46/H9 -> #DIV/0! | I47: =I46/I9 -> #DIV/0! | J47: =J46/J9 -> #DIV/0! | K47: =K46/K9 -> #DIV/0! | ... P47: =P46/P9 -> 150.57583
A48: Plant and Vehicle Maintenance
A49: Distances covered | C49: km | D49: =Mulanje!D49+Luchenza!D49+Thyolo!D49+Muloza!D49+MUST!D49+Phalombe!D49+Mikolongwe!D49+Migowi!D49+Nkando!D49 -> 917 | E49: =Mulanje!E49+Luchenza!E49+Thyolo!E49+Muloza!E49+MUST!E49+Phalombe!E49+Mikolongwe!E49+Migowi!E49+Nkando!E49 -> 717 | F49: =Mulanje!F49+Luchenza!F49+Thyolo!F49+Muloza!F49+MUST!F49+Phalombe!F49+Mikolongwe!F49+Migowi!F49+Nkando!F49 -> 980 | G49: =Mulanje!G49+Luchenza!G49+Thyolo!G49+Muloza!G49+MUST!G49+Phalombe!G49+Mikolongwe!G49+Migowi!G49+Nkando!G49 -> 0 | H49: =Mulanje!H49+Luchenza!H49+Thyolo!H49+Muloza!H49+MUST!H49+Phalombe!H49+Mikolongwe!H49+Migowi!H49+Nkando!H49 -> 0 | I49: =Mulanje!I49+Luchenza!I49+Thyolo!I49+Muloza!I49+MUST!I49+Phalombe!I49+Mikolongwe!I49+Migowi!I49+Nkando!I49 -> 0 | J49: =Mulanje!J49+Luchenza!J49+Thyolo!J49+Muloza!J49+MUST!J49+Phalombe!J49+Mikolongwe!J49+Migowi!J49+Nkando!J49 -> 0 | K49: =Mulanje!K49+Luchenza!K49+Thyolo!K49+Muloza!K49+MUST!K49+Phalombe!K49+Mikolongwe!K49+Migowi!K49+Nkando!K49 -> 0 | ... O49: =Mulanje!O49+Luchenza!O49+Thyolo!O49+Muloza!O49+MUST!O49+Phalombe!O49+Mikolongwe!O49+Migowi!O49+Nkando!O49 -> 0 | P49: =SUM(D49:O49) -> 2614
A50: Fuel Used (litres) | C50: litres | D50: =Mulanje!D50+Luchenza!D50+Thyolo!D50+Muloza!D50+MUST!D50+Phalombe!D50+Mikolongwe!D50+Migowi!D50+Nkando!D50 -> 208 | E50: =Mulanje!E50+Luchenza!E50+Thyolo!E50+Muloza!E50+MUST!E50+Phalombe!E50+Mikolongwe!E50+Migowi!E50+Nkando!E50 -> 165 | F50: =Mulanje!F50+Luchenza!F50+Thyolo!F50+Muloza!F50+MUST!F50+Phalombe!F50+Mikolongwe!F50+Migowi!F50+Nkando!F50 -> 159 | G50: =Mulanje!G50+Luchenza!G50+Thyolo!G50+Muloza!G50+MUST!G50+Phalombe!G50+Mikolongwe!G50+Migowi!G50+Nkando!G50 -> 0 | H50: =Mulanje!H50+Luchenza!H50+Thyolo!H50+Muloza!H50+MUST!H50+Phalombe!H50+Mikolongwe!H50+Migowi!H50+Nkando!H50 -> 0 | I50: =Mulanje!I50+Luchenza!I50+Thyolo!I50+Muloza!I50+MUST!I50+Phalombe!I50+Mikolongwe!I50+Migowi!I50+Nkando!I50 -> 0 | J50: =Mulanje!J50+Luchenza!J50+Thyolo!J50+Muloza!J50+MUST!J50+Phalombe!J50+Mikolongwe!J50+Migowi!J50+Nkando!J50 -> 0 | K50: =Mulanje!K50+Luchenza!K50+Thyolo!K50+Muloza!K50+MUST!K50+Phalombe!K50+Mikolongwe!K50+Migowi!K50+Nkando!K50 -> 0 | ... O50: =Mulanje!O50+Luchenza!O50+Thyolo!O50+Muloza!O50+MUST!O50+Phalombe!O50+Mikolongwe!O50+Migowi!O50+Nkando!O50 -> 0 | P50: =SUM(D50:O50) -> 532
A51: Cost of fuel | C51: Mk | D51: =Mulanje!D51+Luchenza!D51+Thyolo!D51+Muloza!D51+MUST!D51+Phalombe!D51+Mikolongwe!D51+Migowi!D51+Nkando!D51 -> 1390896 | E51: =Mulanje!E51+Luchenza!E51+Thyolo!E51+Muloza!E51+MUST!E51+Phalombe!E51+Mikolongwe!E51+Migowi!E51+Nkando!E51 -> 1103355 | F51: =Mulanje!F51+Luchenza!F51+Thyolo!F51+Muloza!F51+MUST!F51+Phalombe!F51+Mikolongwe!F51+Migowi!F51+Nkando!F51 -> 1063233 | G51: =Mulanje!G51+Luchenza!G51+Thyolo!G51+Muloza!G51+MUST!G51+Phalombe!G51+Mikolongwe!G51+Migowi!G51+Nkando!G51 -> 0 | H51: =Mulanje!H51+Luchenza!H51+Thyolo!H51+Muloza!H51+MUST!H51+Phalombe!H51+Mikolongwe!H51+Migowi!H51+Nkando!H51 -> 0 | I51: =Mulanje!I51+Luchenza!I51+Thyolo!I51+Muloza!I51+MUST!I51+Phalombe!I51+Mikolongwe!I51+Migowi!I51+Nkando!I51 -> 0 | J51: =Mulanje!J51+Luchenza!J51+Thyolo!J51+Muloza!J51+MUST!J51+Phalombe!J51+Mikolongwe!J51+Migowi!J51+Nkando!J51 -> 0 | K51: =Mulanje!K51+Luchenza!K51+Thyolo!K51+Muloza!K51+MUST!K51+Phalombe!K51+Mikolongwe!K51+Migowi!K51+Nkando!K51 -> 0 | ... O51: =Mulanje!O51+Luchenza!O51+Thyolo!O51+Muloza!O51+MUST!O51+Phalombe!O51+Mikolongwe!O51+Migowi!O51+Nkando!O51 -> 0 | P51: =SUM(D51:O51) -> 3557484
A52: Maintenance | C52: Mk | D52: =Mulanje!D52+Luchenza!D52+Thyolo!D52+Muloza!D52+MUST!D52+Phalombe!D52+Mikolongwe!D52+Migowi!D52+Nkando!D52 -> 0 | E52: =Mulanje!E52+Luchenza!E52+Thyolo!E52+Muloza!E52+MUST!E52+Phalombe!E52+Mikolongwe!E52+Migowi!E52+Nkando!E52 -> 0 | F52: =Mulanje!F52+Luchenza!F52+Thyolo!F52+Muloza!F52+MUST!F52+Phalombe!F52+Mikolongwe!F52+Migowi!F52+Nkando!F52 -> 0 | G52: =Mulanje!G52+Luchenza!G52+Thyolo!G52+Muloza!G52+MUST!G52+Phalombe!G52+Mikolongwe!G52+Migowi!G52+Nkando!G52 -> 0 | H52: =Mulanje!H52+Luchenza!H52+Thyolo!H52+Muloza!H52+MUST!H52+Phalombe!H52+Mikolongwe!H52+Migowi!H52+Nkando!H52 -> 0 | I52: =Mulanje!I52+Luchenza!I52+Thyolo!I52+Muloza!I52+MUST!I52+Phalombe!I52+Mikolongwe!I52+Migowi!I52+Nkando!I52 -> 0 | J52: =Mulanje!J52+Luchenza!J52+Thyolo!J52+Muloza!J52+MUST!J52+Phalombe!J52+Mikolongwe!J52+Migowi!J52+Nkando!J52 -> 0 | K52: =Mulanje!K52+Luchenza!K52+Thyolo!K52+Muloza!K52+MUST!K52+Phalombe!K52+Mikolongwe!K52+Migowi!K52+Nkando!K52 -> 0 | ... O52: =Mulanje!O52+Luchenza!O52+Thyolo!O52+Muloza!O52+MUST!O52+Phalombe!O52+Mikolongwe!O52+Migowi!O52+Nkando!O52 -> 0 | P52: =SUM(D52:O52) -> 0
A53: Salaries and Wages
A54: Staff Costs | C54: MK | D54: =Mulanje!D54+Luchenza!D54+Thyolo!D54+Muloza!D54+MUST!D54+Phalombe!D54+Mikolongwe!D54+Migowi!D54+Nkando!D54 -> 60862002 | E54: =Mulanje!E54+Luchenza!E54+Thyolo!E54+Muloza!E54+MUST!E54+Phalombe!E54+Mikolongwe!E54+Migowi!E54+Nkando!E54 -> 62391309 | F54: =Mulanje!F54+Luchenza!F54+Thyolo!F54+Muloza!F54+MUST!F54+Phalombe!F54+Mikolongwe!F54+Migowi!F54+Nkando!F54 -> 62391309 | G54: =Mulanje!G54+Luchenza!G54+Thyolo!G54+Muloza!G54+MUST!G54+Phalombe!G54+Mikolongwe!G54+Migowi!G54+Nkando!G54 -> 0 | H54: =Mulanje!H54+Luchenza!H54+Thyolo!H54+Muloza!H54+MUST!H54+Phalombe!H54+Mikolongwe!H54+Migowi!H54+Nkando!H54 -> 0 | I54: =Mulanje!I54+Luchenza!I54+Thyolo!I54+Muloza!I54+MUST!I54+Phalombe!I54+Mikolongwe!I54+Migowi!I54+Nkando!I54 -> 0 | J54: =Mulanje!J54+Luchenza!J54+Thyolo!J54+Muloza!J54+MUST!J54+Phalombe!J54+Mikolongwe!J54+Migowi!J54+Nkando!J54 -> 0 | K54: =Mulanje!K54+Luchenza!K54+Thyolo!K54+Muloza!K54+MUST!K54+Phalombe!K54+Mikolongwe!K54+Migowi!K54+Nkando!K54 -> 0 | ... O54: =Mulanje!O54+Luchenza!O54+Thyolo!O54+Muloza!O54+MUST!O54+Phalombe!O54+Mikolongwe!O54+Migowi!O54+Nkando!O54 -> 0 | P54: =SUM(D54:O54) -> 1.8564462e+08
A55: Wages | C55: MK | D55: =Mulanje!D55+Luchenza!D55+Thyolo!D55+Muloza!D55+MUST!D55+Phalombe!D55+Mikolongwe!D55+Migowi!D55+Nkando!D55 -> 10695762 | E55: =Mulanje!E55+Luchenza!E55+Thyolo!E55+Muloza!E55+MUST!E55+Phalombe!E55+Mikolongwe!E55+Migowi!E55+Nkando!E55 -> 13467198 | F55: =Mulanje!F55+Luchenza!F55+Thyolo!F55+Muloza!F55+MUST!F55+Phalombe!F55+Mikolongwe!F55+Migowi!F55+Nkando!F55 -> 17143963 | G55: =Mulanje!G55+Luchenza!G55+Thyolo!G55+Muloza!G55+MUST!G55+Phalombe!G55+Mikolongwe!G55+Migowi!G55+Nkando!G55 -> 0 | H55: =Mulanje!H55+Luchenza!H55+Thyolo!H55+Muloza!H55+MUST!H55+Phalombe!H55+Mikolongwe!H55+Migowi!H55+Nkando!H55 -> 0 | I55: =Mulanje!I55+Luchenza!I55+Thyolo!I55+Muloza!I55+MUST!I55+Phalombe!I55+Mikolongwe!I55+Migowi!I55+Nkando!I55 -> 0 | J55: =Mulanje!J55+Luchenza!J55+Thyolo!J55+Muloza!J55+MUST!J55+Phalombe!J55+Mikolongwe!J55+Migowi!J55+Nkando!J55 -> 0 | K55: =Mulanje!K55+Luchenza!K55+Thyolo!K55+Muloza!K55+MUST!K55+Phalombe!K55+Mikolongwe!K55+Migowi!K55+Nkando!K55 -> 0 | ... O55: =Mulanje!O55+Luchenza!O55+Thyolo!O55+Muloza!O55+MUST!O55+Phalombe!O55+Mikolongwe!O55+Migowi!O55+Nkando!O55 -> 0 | P55: =SUM(D55:O55) -> 41306923
A56: Other Overhead Costs | C56: MK | D56: =Mulanje!D56+Luchenza!D56+Thyolo!D56+Muloza!D56+MUST!D56+Phalombe!D56+Mikolongwe!D56+Migowi!D56+Nkando!D56 -> 30924410 | E56: =Mulanje!E56+Luchenza!E56+Thyolo!E56+Muloza!E56+MUST!E56+Phalombe!E56+Mikolongwe!E56+Migowi!E56+Nkando!E56 -> 24224932 | F56: =Mulanje!F56+Luchenza!F56+Thyolo!F56+Muloza!F56+MUST!F56+Phalombe!F56+Mikolongwe!F56+Migowi!F56+Nkando!F56 -> 11987821 | G56: =Mulanje!G56+Luchenza!G56+Thyolo!G56+Muloza!G56+MUST!G56+Phalombe!G56+Mikolongwe!G56+Migowi!G56+Nkando!G56 -> 0 | H56: =Mulanje!H56+Luchenza!H56+Thyolo!H56+Muloza!H56+MUST!H56+Phalombe!H56+Mikolongwe!H56+Migowi!H56+Nkando!H56 -> 0 | I56: =Mulanje!I56+Luchenza!I56+Thyolo!I56+Muloza!I56+MUST!I56+Phalombe!I56+Mikolongwe!I56+Migowi!I56+Nkando!I56 -> 0 | J56: =Mulanje!J56+Luchenza!J56+Thyolo!J56+Muloza!J56+MUST!J56+Phalombe!J56+Mikolongwe!J56+Migowi!J56+Nkando!J56 -> 0 | K56: =Mulanje!K56+Luchenza!K56+Thyolo!K56+Muloza!K56+MUST!K56+Phalombe!K56+Mikolongwe!K56+Migowi!K56+Nkando!K56 -> 0 | ... O56: =Mulanje!O56+Luchenza!O56+Thyolo!O56+Muloza!O56+MUST!O56+Phalombe!O56+Mikolongwe!O56+Migowi!O56+Nkando!O56 -> 0 | P56: =SUM(D56:O56) -> 67137163
A57: Operating Costs
A58: Total Operating Costs | C58: MK | D58: =D41+D46+D51+D52+D54+D55+D56 -> 1.2926903e+08 | E58: =E41+E46+E51+E52+E54+E55+E56 -> 1.1979251e+08 | F58: =F41+F46+F51+F52+F54+F55+F56 -> 1.0787889e+08 | G58: =G41+G46+G51+G52+G54+G55+G56 -> 16426.5 | H58: =H41+H46+H51+H52+H54+H55+H56 -> 16426.5 | I58: =I41+I46+I51+I52+I54+I55+I56 -> 16426.5 | J58: =J41+J46+J51+J52+J54+J55+J56 -> 16426.5 | K58: =K41+K46+K51+K52+K54+K55+K56 -> 16426.5 | ... O58: =O41+O46+O51+O52+O54+O55+O56 -> 0 | P58: =SUM(D58:O58) -> 3.5707184e+08
A59: Cost/Vol. Produced | C59: Mk/m3 | D59: =D58/D9 -> 1146.6933 | E59: =E58/E9 -> 969.71285 | F59: =F58/F9 -> 886.78273 | G59: =G58/G9 -> #DIV/0! | H59: =H58/H9 -> #DIV/0! | I59: =I58/I9 -> #DIV/0! | J59: =J58/J9 -> #DIV/0! | K59: =K58/K9 -> #DIV/0! | ... P59: =P58/P9 -> 997.63588
A60: Cost/Vol. Billed | C60: Mk/m3 | D60: =D58/D22 -> 1602.4094 | E60: =E58/E22 -> 1350.2722 | F60: =F58/F22 -> 1247.0539 | G60: =G58/G22 -> #DIV/0! | H60: =H58/H22 -> #DIV/0! | I60: =I58/I22 -> #DIV/0! | J60: =J58/J22 -> #DIV/0! | K60: =K58/K22 -> #DIV/0! | ... P60: =P58/P22 -> 1395.379
A61: Permanent Staff Employed | C61: No | D61: =Mulanje!D61+Luchenza!D61+Thyolo!D61+Muloza!D61+MUST!D61+Phalombe!D61+Mikolongwe!D61+Migowi!D61+Nkando!D61 -> 44 | E61: =Mulanje!E61+Luchenza!E61+Thyolo!E61+Muloza!E61+MUST!E61+Phalombe!E61+Mikolongwe!E61+Migowi!E61+Nkando!E61 -> 44 | F61: =Mulanje!F61+Luchenza!F61+Thyolo!F61+Muloza!F61+MUST!F61+Phalombe!F61+Mikolongwe!F61+Migowi!F61+Nkando!F61 -> 44 | G61: =Mulanje!G61+Luchenza!G61+Thyolo!G61+Muloza!G61+MUST!G61+Phalombe!G61+Mikolongwe!G61+Migowi!G61+Nkando!G61 -> 0 | H61: =Mulanje!H61+Luchenza!H61+Thyolo!H61+Muloza!H61+MUST!H61+Phalombe!H61+Mikolongwe!H61+Migowi!H61+Nkando!H61 -> 0 | I61: =Mulanje!I61+Luchenza!I61+Thyolo!I61+Muloza!I61+MUST!I61+Phalombe!I61+Mikolongwe!I61+Migowi!I61+Nkando!I61 -> 0 | J61: =Mulanje!J61+Luchenza!J61+Thyolo!J61+Muloza!J61+MUST!J61+Phalombe!J61+Mikolongwe!J61+Migowi!J61+Nkando!J61 -> 0 | K61: =Mulanje!K61+Luchenza!K61+Thyolo!K61+Muloza!K61+MUST!K61+Phalombe!K61+Mikolongwe!K61+Migowi!K61+Nkando!K61 -> 0 | ... O61: =Mulanje!O61+Luchenza!O61+Thyolo!O61+Muloza!O61+MUST!O61+Phalombe!O61+Mikolongwe!O61+Migowi!O61+Nkando!O61 -> 0 | P61: =O61 -> 0
A62: Staff/Vol.1000m3 of Volume Produced/hour (12 hour day) | C62: No/1000m3 | D62: =(D61*1000*31)/D9 -> 12.099493 | E62: =(E61*1000*31)/E9 -> 11.041495 | F62: =(F61*1000*31)/F9 -> 11.212311 | G62: =(G61*1000*31)/G9 -> #DIV/0! | H62: =(H61*1000*31)/H9 -> #DIV/0! | I62: =(I61*1000*31)/I9 -> #DIV/0! | J62: =(J61*1000*31)/J9 -> #DIV/0! | K62: =(K61*1000*31)/K9 -> #DIV/0! | ... P62: =(P61*1000*31)/P9 -> 0
A63: Temporary Staff Employed | C63: No | D63: =Mulanje!D63+Luchenza!D63+Thyolo!D63+Muloza!D63+MUST!D63+Phalombe!D63+Mikolongwe!D63+Migowi!D63+Nkando!D63 -> 102 | E63: =Mulanje!E63+Luchenza!E63+Thyolo!E63+Muloza!E63+MUST!E63+Phalombe!E63+Mikolongwe!E63+Migowi!E63+Nkando!E63 -> 105 | F63: =Mulanje!F63+Luchenza!F63+Thyolo!F63+Muloza!F63+MUST!F63+Phalombe!F63+Mikolongwe!F63+Migowi!F63+Nkando!F63 -> 107 | G63: =Mulanje!G63+Luchenza!G63+Thyolo!G63+Muloza!G63+MUST!G63+Phalombe!G63+Mikolongwe!G63+Migowi!G63+Nkando!G63 -> 0 | H63: =Mulanje!H63+Luchenza!H63+Thyolo!H63+Muloza!H63+MUST!H63+Phalombe!H63+Mikolongwe!H63+Migowi!H63+Nkando!H63 -> 0 | I63: =Mulanje!I63+Luchenza!I63+Thyolo!I63+Muloza!I63+MUST!I63+Phalombe!I63+Mikolongwe!I63+Migowi!I63+Nkando!I63 -> 0 | J63: =Mulanje!J63+Luchenza!J63+Thyolo!J63+Muloza!J63+MUST!J63+Phalombe!J63+Mikolongwe!J63+Migowi!J63+Nkando!J63 -> 0 | K63: =Mulanje!K63+Luchenza!K63+Thyolo!K63+Muloza!K63+MUST!K63+Phalombe!K63+Mikolongwe!K63+Migowi!K63+Nkando!K63 -> 0 | ... O63: =Mulanje!O63+Luchenza!O63+Thyolo!O63+Muloza!O63+MUST!O63+Phalombe!O63+Mikolongwe!O63+Migowi!O63+Nkando!O63 -> 0 | P63: =SUM(D63:O63) -> 314
A65: Water Connections and Disconnections
A66: New Individual Water Connections | B66: Brought Forward | C66: No | D66: =Mulanje!D66+Luchenza!D66+Thyolo!D66+Muloza!D66+MUST!D66+Phalombe!D66+Mikolongwe!D66+Migowi!D66+Nkando!D66 -> 153 | E66: =Mulanje!E66+Luchenza!E66+Thyolo!E66+Muloza!E66+MUST!E66+Phalombe!E66+Mikolongwe!E66+Migowi!E66+Nkando!E66 -> 189 | F66: =Mulanje!F66+Luchenza!F66+Thyolo!F66+Muloza!F66+MUST!F66+Phalombe!F66+Mikolongwe!F66+Migowi!F66+Nkando!F66 -> 196 | G66: =Mulanje!G66+Luchenza!G66+Thyolo!G66+Muloza!G66+MUST!G66+Phalombe!G66+Mikolongwe!G66+Migowi!G66+Nkando!G66 -> 191 | H66: =Mulanje!H66+Luchenza!H66+Thyolo!H66+Muloza!H66+MUST!H66+Phalombe!H66+Mikolongwe!H66+Migowi!H66+Nkando!H66 -> 191 | I66: =Mulanje!I66+Luchenza!I66+Thyolo!I66+Muloza!I66+MUST!I66+Phalombe!I66+Mikolongwe!I66+Migowi!I66+Nkando!I66 -> 191 | J66: =Mulanje!J66+Luchenza!J66+Thyolo!J66+Muloza!J66+MUST!J66+Phalombe!J66+Mikolongwe!J66+Migowi!J66+Nkando!J66 -> 191 | K66: =Mulanje!K66+Luchenza!K66+Thyolo!K66+Muloza!K66+MUST!K66+Phalombe!K66+Mikolongwe!K66+Migowi!K66+Nkando!K66 -> 191 | ... O66: =Mulanje!O66+Luchenza!O66+Thyolo!O66+Muloza!O66+MUST!O66+Phalombe!O66+Mikolongwe!O66+Migowi!O66+Nkando!O66 -> 132 | P66: =D66 -> 153
B67: Applied this Month | C67: No | D67: =Mulanje!D67+Luchenza!D67+Thyolo!D67+Muloza!D67+MUST!D67+Phalombe!D67+Mikolongwe!D67+Migowi!D67+Nkando!D67 -> 72 | E67: =Mulanje!E67+Luchenza!E67+Thyolo!E67+Muloza!E67+MUST!E67+Phalombe!E67+Mikolongwe!E67+Migowi!E67+Nkando!E67 -> 68 | F67: =Mulanje!F67+Luchenza!F67+Thyolo!F67+Muloza!F67+MUST!F67+Phalombe!F67+Mikolongwe!F67+Migowi!F67+Nkando!F67 -> 97 | G67: =Mulanje!G67+Luchenza!G67+Thyolo!G67+Muloza!G67+MUST!G67+Phalombe!G67+Mikolongwe!G67+Migowi!G67+Nkando!G67 -> 0 | H67: =Mulanje!H67+Luchenza!H67+Thyolo!H67+Muloza!H67+MUST!H67+Phalombe!H67+Mikolongwe!H67+Migowi!H67+Nkando!H67 -> 0 | I67: =Mulanje!I67+Luchenza!I67+Thyolo!I67+Muloza!I67+MUST!I67+Phalombe!I67+Mikolongwe!I67+Migowi!I67+Nkando!I67 -> 0 | J67: =Mulanje!J67+Luchenza!J67+Thyolo!J67+Muloza!J67+MUST!J67+Phalombe!J67+Mikolongwe!J67+Migowi!J67+Nkando!J67 -> 0 | K67: =Mulanje!K67+Luchenza!K67+Thyolo!K67+Muloza!K67+MUST!K67+Phalombe!K67+Mikolongwe!K67+Migowi!K67+Nkando!K67 -> 0 | ... O67: =Mulanje!O67+Luchenza!O67+Thyolo!O67+Muloza!O67+MUST!O67+Phalombe!O67+Mikolongwe!O67+Migowi!O67+Nkando!O67 -> 0 | P67: =SUM(D67:O67) -> 237
B68: Done this Month Postpaid | C68: No | D68: =Mulanje!D68+Luchenza!D68+Thyolo!D68+Muloza!D68+MUST!D68+Phalombe!D68+Mikolongwe!D68+Migowi!D68+Nkando!D68 -> 0 | E68: =Mulanje!E68+Luchenza!E68+Thyolo!E68+Muloza!E68+MUST!E68+Phalombe!E68+Mikolongwe!E68+Migowi!E68+Nkando!E68 -> 3 | F68: =Mulanje!F68+Luchenza!F68+Thyolo!F68+Muloza!F68+MUST!F68+Phalombe!F68+Mikolongwe!F68+Migowi!F68+Nkando!F68 -> 16 | G68: =Mulanje!G68+Luchenza!G68+Thyolo!G68+Muloza!G68+MUST!G68+Phalombe!G68+Mikolongwe!G68+Migowi!G68+Nkando!G68 -> 0 | H68: =Mulanje!H68+Luchenza!H68+Thyolo!H68+Muloza!H68+MUST!H68+Phalombe!H68+Mikolongwe!H68+Migowi!H68+Nkando!H68 -> 0 | I68: =Mulanje!I68+Luchenza!I68+Thyolo!I68+Muloza!I68+MUST!I68+Phalombe!I68+Mikolongwe!I68+Migowi!I68+Nkando!I68 -> 0 | J68: =Mulanje!J68+Luchenza!J68+Thyolo!J68+Muloza!J68+MUST!J68+Phalombe!J68+Mikolongwe!J68+Migowi!J68+Nkando!J68 -> 0 | K68: =Mulanje!K68+Luchenza!K68+Thyolo!K68+Muloza!K68+MUST!K68+Phalombe!K68+Mikolongwe!K68+Migowi!K68+Nkando!K68 -> 0 | ... O68: =Mulanje!O68+Luchenza!O68+Thyolo!O68+Muloza!O68+MUST!O68+Phalombe!O68+Mikolongwe!O68+Migowi!O68+Nkando!O68 -> 0 | P68: =SUM(D68:O68) -> 19
B69: Done this Month Prepaid | C69: No | D69: =Mulanje!D69+Luchenza!D69+Thyolo!D69+Muloza!D69+MUST!D69+Phalombe!D69+Mikolongwe!D69+Migowi!D69+Nkando!D69 -> 36 | E69: =Mulanje!E69+Luchenza!E69+Thyolo!E69+Muloza!E69+MUST!E69+Phalombe!E69+Mikolongwe!E69+Migowi!E69+Nkando!E69 -> 58 | F69: =Mulanje!F69+Luchenza!F69+Thyolo!F69+Muloza!F69+MUST!F69+Phalombe!F69+Mikolongwe!F69+Migowi!F69+Nkando!F69 -> 86 | G69: =Mulanje!G69+Luchenza!G69+Thyolo!G69+Muloza!G69+MUST!G69+Phalombe!G69+Mikolongwe!G69+Migowi!G69+Nkando!G69 -> 0 | H69: =Mulanje!H69+Luchenza!H69+Thyolo!H69+Muloza!H69+MUST!H69+Phalombe!H69+Mikolongwe!H69+Migowi!H69+Nkando!H69 -> 0 | I69: =Mulanje!I69+Luchenza!I69+Thyolo!I69+Muloza!I69+MUST!I69+Phalombe!I69+Mikolongwe!I69+Migowi!I69+Nkando!I69 -> 0 | J69: =Mulanje!J69+Luchenza!J69+Thyolo!J69+Muloza!J69+MUST!J69+Phalombe!J69+Mikolongwe!J69+Migowi!J69+Nkando!J69 -> 0 | K69: =Mulanje!K69+Luchenza!K69+Thyolo!K69+Muloza!K69+MUST!K69+Phalombe!K69+Mikolongwe!K69+Migowi!K69+Nkando!K69 -> 0 | ... O69: =Mulanje!O69+Luchenza!O69+Thyolo!O69+Muloza!O69+MUST!O69+Phalombe!O69+Mikolongwe!O69+Migowi!O69+Nkando!O69 -> 0 | P69: =SUM(D69:O69) -> 180
B70: Total Done | C70: No | D70: =Mulanje!D70+Luchenza!D70+Thyolo!D70+Muloza!D70+MUST!D70+Phalombe!D70+Mikolongwe!D70+Migowi!D70+Nkando!D70 -> 36 | E70: =Mulanje!E70+Luchenza!E70+Thyolo!E70+Muloza!E70+MUST!E70+Phalombe!E70+Mikolongwe!E70+Migowi!E70+Nkando!E70 -> 61 | F70: =Mulanje!F70+Luchenza!F70+Thyolo!F70+Muloza!F70+MUST!F70+Phalombe!F70+Mikolongwe!F70+Migowi!F70+Nkando!F70 -> 102 | G70: =Mulanje!G70+Luchenza!G70+Thyolo!G70+Muloza!G70+MUST!G70+Phalombe!G70+Mikolongwe!G70+Migowi!G70+Nkando!G70 -> 0 | H70: =Mulanje!H70+Luchenza!H70+Thyolo!H70+Muloza!H70+MUST!H70+Phalombe!H70+Mikolongwe!H70+Migowi!H70+Nkando!H70 -> 0 | I70: =Mulanje!I70+Luchenza!I70+Thyolo!I70+Muloza!I70+MUST!I70+Phalombe!I70+Mikolongwe!I70+Migowi!I70+Nkando!I70 -> 0 | J70: =Mulanje!J70+Luchenza!J70+Thyolo!J70+Muloza!J70+MUST!J70+Phalombe!J70+Mikolongwe!J70+Migowi!J70+Nkando!J70 -> 0 | K70: =Mulanje!K70+Luchenza!K70+Thyolo!K70+Muloza!K70+MUST!K70+Phalombe!K70+Mikolongwe!K70+Migowi!K70+Nkando!K70 -> 0 | ... O70: =Mulanje!O70+Luchenza!O70+Thyolo!O70+Muloza!O70+MUST!O70+Phalombe!O70+Mikolongwe!O70+Migowi!O70+Nkando!O70 -> 0 | P70: =P68+P69 -> 199
B71: Carried Forward | C71: No | D71: =Mulanje!D71+Luchenza!D71+Thyolo!D71+Muloza!D71+MUST!D71+Phalombe!D71+Mikolongwe!D71+Migowi!D71+Nkando!D71 -> 189 | E71: =Mulanje!E71+Luchenza!E71+Thyolo!E71+Muloza!E71+MUST!E71+Phalombe!E71+Mikolongwe!E71+Migowi!E71+Nkando!E71 -> 196 | F71: =Mulanje!F71+Luchenza!F71+Thyolo!F71+Muloza!F71+MUST!F71+Phalombe!F71+Mikolongwe!F71+Migowi!F71+Nkando!F71 -> 191 | G71: =Mulanje!G71+Luchenza!G71+Thyolo!G71+Muloza!G71+MUST!G71+Phalombe!G71+Mikolongwe!G71+Migowi!G71+Nkando!G71 -> 191 | H71: =Mulanje!H71+Luchenza!H71+Thyolo!H71+Muloza!H71+MUST!H71+Phalombe!H71+Mikolongwe!H71+Migowi!H71+Nkando!H71 -> 191 | I71: =Mulanje!I71+Luchenza!I71+Thyolo!I71+Muloza!I71+MUST!I71+Phalombe!I71+Mikolongwe!I71+Migowi!I71+Nkando!I71 -> 191 | J71: =Mulanje!J71+Luchenza!J71+Thyolo!J71+Muloza!J71+MUST!J71+Phalombe!J71+Mikolongwe!J71+Migowi!J71+Nkando!J71 -> 191 | K71: =Mulanje!K71+Luchenza!K71+Thyolo!K71+Muloza!K71+MUST!K71+Phalombe!K71+Mikolongwe!K71+Migowi!K71+Nkando!K71 -> 191 | ... O71: =Mulanje!O71+Luchenza!O71+Thyolo!O71+Muloza!O71+MUST!O71+Phalombe!O71+Mikolongwe!O71+Migowi!O71+Nkando!O71 -> 0 | P71: =P66+P67-P70 -> 191
A72: New Institutional Water Connections | B72: Brought Forward | C72: No | D72: =Mulanje!D72+Luchenza!D72+Thyolo!D72+Muloza!D72+MUST!D72+Phalombe!D72+Mikolongwe!D72+Migowi!D72+Nkando!D72 -> 0 | E72: =Mulanje!E72+Luchenza!E72+Thyolo!E72+Muloza!E72+MUST!E72+Phalombe!E72+Mikolongwe!E72+Migowi!E72+Nkando!E72 -> 2 | F72: =Mulanje!F72+Luchenza!F72+Thyolo!F72+Muloza!F72+MUST!F72+Phalombe!F72+Mikolongwe!F72+Migowi!F72+Nkando!F72 -> 0 | G72: =Mulanje!G72+Luchenza!G72+Thyolo!G72+Muloza!G72+MUST!G72+Phalombe!G72+Mikolongwe!G72+Migowi!G72+Nkando!G72 -> 0 | H72: =Mulanje!H72+Luchenza!H72+Thyolo!H72+Muloza!H72+MUST!H72+Phalombe!H72+Mikolongwe!H72+Migowi!H72+Nkando!H72 -> 0 | I72: =Mulanje!I72+Luchenza!I72+Thyolo!I72+Muloza!I72+MUST!I72+Phalombe!I72+Mikolongwe!I72+Migowi!I72+Nkando!I72 -> 0 | J72: =Mulanje!J72+Luchenza!J72+Thyolo!J72+Muloza!J72+MUST!J72+Phalombe!J72+Mikolongwe!J72+Migowi!J72+Nkando!J72 -> 0 | K72: =Mulanje!K72+Luchenza!K72+Thyolo!K72+Muloza!K72+MUST!K72+Phalombe!K72+Mikolongwe!K72+Migowi!K72+Nkando!K72 -> 0 | ... O72: =Mulanje!O72+Luchenza!O72+Thyolo!O72+Muloza!O72+MUST!O72+Phalombe!O72+Mikolongwe!O72+Migowi!O72+Nkando!O72 -> 0 | P72: =D72 -> 0
B73: Applied this Month | C73: No | D73: =Mulanje!D73+Luchenza!D73+Thyolo!D73+Muloza!D73+MUST!D73+Phalombe!D73+Mikolongwe!D73+Migowi!D73+Nkando!D73 -> 2 | E73: =Mulanje!E73+Luchenza!E73+Thyolo!E73+Muloza!E73+MUST!E73+Phalombe!E73+Mikolongwe!E73+Migowi!E73+Nkando!E73 -> 0 | F73: =Mulanje!F73+Luchenza!F73+Thyolo!F73+Muloza!F73+MUST!F73+Phalombe!F73+Mikolongwe!F73+Migowi!F73+Nkando!F73 -> 0 | G73: =Mulanje!G73+Luchenza!G73+Thyolo!G73+Muloza!G73+MUST!G73+Phalombe!G73+Mikolongwe!G73+Migowi!G73+Nkando!G73 -> 0 | H73: =Mulanje!H73+Luchenza!H73+Thyolo!H73+Muloza!H73+MUST!H73+Phalombe!H73+Mikolongwe!H73+Migowi!H73+Nkando!H73 -> 0 | I73: =Mulanje!I73+Luchenza!I73+Thyolo!I73+Muloza!I73+MUST!I73+Phalombe!I73+Mikolongwe!I73+Migowi!I73+Nkando!I73 -> 0 | J73: =Mulanje!J73+Luchenza!J73+Thyolo!J73+Muloza!J73+MUST!J73+Phalombe!J73+Mikolongwe!J73+Migowi!J73+Nkando!J73 -> 0 | K73: =Mulanje!K73+Luchenza!K73+Thyolo!K73+Muloza!K73+MUST!K73+Phalombe!K73+Mikolongwe!K73+Migowi!K73+Nkando!K73 -> 0 | ... O73: =Mulanje!O73+Luchenza!O73+Thyolo!O73+Muloza!O73+MUST!O73+Phalombe!O73+Mikolongwe!O73+Migowi!O73+Nkando!O73 -> 0 | P73: =SUM(D73:O73) -> 2
B74: Done this Month Postpaid | C74: No | D74: =Mulanje!D74+Luchenza!D74+Thyolo!D74+Muloza!D74+MUST!D74+Phalombe!D74+Mikolongwe!D74+Migowi!D74+Nkando!D74 -> 0 | E74: =Mulanje!E74+Luchenza!E74+Thyolo!E74+Muloza!E74+MUST!E74+Phalombe!E74+Mikolongwe!E74+Migowi!E74+Nkando!E74 -> 1 | F74: =Mulanje!F74+Luchenza!F74+Thyolo!F74+Muloza!F74+MUST!F74+Phalombe!F74+Mikolongwe!F74+Migowi!F74+Nkando!F74 -> 0 | G74: =Mulanje!G74+Luchenza!G74+Thyolo!G74+Muloza!G74+MUST!G74+Phalombe!G74+Mikolongwe!G74+Migowi!G74+Nkando!G74 -> 0 | H74: =Mulanje!H74+Luchenza!H74+Thyolo!H74+Muloza!H74+MUST!H74+Phalombe!H74+Mikolongwe!H74+Migowi!H74+Nkando!H74 -> 0 | I74: =Mulanje!I74+Luchenza!I74+Thyolo!I74+Muloza!I74+MUST!I74+Phalombe!I74+Mikolongwe!I74+Migowi!I74+Nkando!I74 -> 0 | J74: =Mulanje!J74+Luchenza!J74+Thyolo!J74+Muloza!J74+MUST!J74+Phalombe!J74+Mikolongwe!J74+Migowi!J74+Nkando!J74 -> 0 | K74: =Mulanje!K74+Luchenza!K74+Thyolo!K74+Muloza!K74+MUST!K74+Phalombe!K74+Mikolongwe!K74+Migowi!K74+Nkando!K74 -> 0 | ... O74: =Mulanje!O74+Luchenza!O74+Thyolo!O74+Muloza!O74+MUST!O74+Phalombe!O74+Mikolongwe!O74+Migowi!O74+Nkando!O74 -> 0 | P74: =SUM(D74:O74) -> 1
B75: Done this Month Prepaid | C75: No | D75: =Mulanje!D75+Luchenza!D75+Thyolo!D75+Muloza!D75+MUST!D75+Phalombe!D75+Mikolongwe!D75+Migowi!D75+Nkando!D75 -> 0 | E75: =Mulanje!E75+Luchenza!E75+Thyolo!E75+Muloza!E75+MUST!E75+Phalombe!E75+Mikolongwe!E75+Migowi!E75+Nkando!E75 -> 1 | F75: =Mulanje!F75+Luchenza!F75+Thyolo!F75+Muloza!F75+MUST!F75+Phalombe!F75+Mikolongwe!F75+Migowi!F75+Nkando!F75 -> 0 | G75: =Mulanje!G75+Luchenza!G75+Thyolo!G75+Muloza!G75+MUST!G75+Phalombe!G75+Mikolongwe!G75+Migowi!G75+Nkando!G75 -> 0 | H75: =Mulanje!H75+Luchenza!H75+Thyolo!H75+Muloza!H75+MUST!H75+Phalombe!H75+Mikolongwe!H75+Migowi!H75+Nkando!H75 -> 0 | I75: =Mulanje!I75+Luchenza!I75+Thyolo!I75+Muloza!I75+MUST!I75+Phalombe!I75+Mikolongwe!I75+Migowi!I75+Nkando!I75 -> 0 | J75: =Mulanje!J75+Luchenza!J75+Thyolo!J75+Muloza!J75+MUST!J75+Phalombe!J75+Mikolongwe!J75+Migowi!J75+Nkando!J75 -> 0 | K75: =Mulanje!K75+Luchenza!K75+Thyolo!K75+Muloza!K75+MUST!K75+Phalombe!K75+Mikolongwe!K75+Migowi!K75+Nkando!K75 -> 0 | ... O75: =Mulanje!O75+Luchenza!O75+Thyolo!O75+Muloza!O75+MUST!O75+Phalombe!O75+Mikolongwe!O75+Migowi!O75+Nkando!O75 -> 0
B76: Total Done | C76: No | D76: =Mulanje!D76+Luchenza!D76+Thyolo!D76+Muloza!D76+MUST!D76+Phalombe!D76+Mikolongwe!D76+Migowi!D76+Nkando!D76 -> 0 | E76: =Mulanje!E76+Luchenza!E76+Thyolo!E76+Muloza!E76+MUST!E76+Phalombe!E76+Mikolongwe!E76+Migowi!E76+Nkando!E76 -> 2 | F76: =Mulanje!F76+Luchenza!F76+Thyolo!F76+Muloza!F76+MUST!F76+Phalombe!F76+Mikolongwe!F76+Migowi!F76+Nkando!F76 -> 0 | G76: =Mulanje!G76+Luchenza!G76+Thyolo!G76+Muloza!G76+MUST!G76+Phalombe!G76+Mikolongwe!G76+Migowi!G76+Nkando!G76 -> 0 | H76: =Mulanje!H76+Luchenza!H76+Thyolo!H76+Muloza!H76+MUST!H76+Phalombe!H76+Mikolongwe!H76+Migowi!H76+Nkando!H76 -> 0 | I76: =Mulanje!I76+Luchenza!I76+Thyolo!I76+Muloza!I76+MUST!I76+Phalombe!I76+Mikolongwe!I76+Migowi!I76+Nkando!I76 -> 0 | J76: =Mulanje!J76+Luchenza!J76+Thyolo!J76+Muloza!J76+MUST!J76+Phalombe!J76+Mikolongwe!J76+Migowi!J76+Nkando!J76 -> 0 | K76: =Mulanje!K76+Luchenza!K76+Thyolo!K76+Muloza!K76+MUST!K76+Phalombe!K76+Mikolongwe!K76+Migowi!K76+Nkando!K76 -> 0 | ... O76: =Mulanje!O76+Luchenza!O76+Thyolo!O76+Muloza!O76+MUST!O76+Phalombe!O76+Mikolongwe!O76+Migowi!O76+Nkando!O76 -> 0 | P76: =P74+P75 -> 1
B77: Carried Forward | C77: No | D77: =Mulanje!D77+Luchenza!D77+Thyolo!D77+Muloza!D77+MUST!D77+Phalombe!D77+Mikolongwe!D77+Migowi!D77+Nkando!D77 -> 2 | E77: =Mulanje!E77+Luchenza!E77+Thyolo!E77+Muloza!E77+MUST!E77+Phalombe!E77+Mikolongwe!E77+Migowi!E77+Nkando!E77 -> 0 | F77: =Mulanje!F77+Luchenza!F77+Thyolo!F77+Muloza!F77+MUST!F77+Phalombe!F77+Mikolongwe!F77+Migowi!F77+Nkando!F77 -> 0 | G77: =Mulanje!G77+Luchenza!G77+Thyolo!G77+Muloza!G77+MUST!G77+Phalombe!G77+Mikolongwe!G77+Migowi!G77+Nkando!G77 -> 0 | H77: =Mulanje!H77+Luchenza!H77+Thyolo!H77+Muloza!H77+MUST!H77+Phalombe!H77+Mikolongwe!H77+Migowi!H77+Nkando!H77 -> 0 | I77: =Mulanje!I77+Luchenza!I77+Thyolo!I77+Muloza!I77+MUST!I77+Phalombe!I77+Mikolongwe!I77+Migowi!I77+Nkando!I77 -> 0 | J77: =Mulanje!J77+Luchenza!J77+Thyolo!J77+Muloza!J77+MUST!J77+Phalombe!J77+Mikolongwe!J77+Migowi!J77+Nkando!J77 -> 0 | K77: =Mulanje!K77+Luchenza!K77+Thyolo!K77+Muloza!K77+MUST!K77+Phalombe!K77+Mikolongwe!K77+Migowi!K77+Nkando!K77 -> 0 | ... O77: =Mulanje!O77+Luchenza!O77+Thyolo!O77+Muloza!O77+MUST!O77+Phalombe!O77+Mikolongwe!O77+Migowi!O77+Nkando!O77 -> 0 | P77: =P73+P74-P76 -> 2
A78: New Commercial/Industrial Water Connections | B78: Brought Forward | C78: No | D78: =Mulanje!D78+Luchenza!D78+Thyolo!D78+Muloza!D78+MUST!D78+Phalombe!D78+Mikolongwe!D78+Migowi!D78+Nkando!D78 -> 6 | E78: =Mulanje!E78+Luchenza!E78+Thyolo!E78+Muloza!E78+MUST!E78+Phalombe!E78+Mikolongwe!E78+Migowi!E78+Nkando!E78 -> 6 | F78: =Mulanje!F78+Luchenza!F78+Thyolo!F78+Muloza!F78+MUST!F78+Phalombe!F78+Mikolongwe!F78+Migowi!F78+Nkando!F78 -> 7 | G78: =Mulanje!G78+Luchenza!G78+Thyolo!G78+Muloza!G78+MUST!G78+Phalombe!G78+Mikolongwe!G78+Migowi!G78+Nkando!G78 -> 0 | H78: =Mulanje!H78+Luchenza!H78+Thyolo!H78+Muloza!H78+MUST!H78+Phalombe!H78+Mikolongwe!H78+Migowi!H78+Nkando!H78 -> 0 | I78: =Mulanje!I78+Luchenza!I78+Thyolo!I78+Muloza!I78+MUST!I78+Phalombe!I78+Mikolongwe!I78+Migowi!I78+Nkando!I78 -> 0 | J78: =Mulanje!J78+Luchenza!J78+Thyolo!J78+Muloza!J78+MUST!J78+Phalombe!J78+Mikolongwe!J78+Migowi!J78+Nkando!J78 -> 0 | K78: =Mulanje!K78+Luchenza!K78+Thyolo!K78+Muloza!K78+MUST!K78+Phalombe!K78+Mikolongwe!K78+Migowi!K78+Nkando!K78 -> 0 | ... O78: =Mulanje!O78+Luchenza!O78+Thyolo!O78+Muloza!O78+MUST!O78+Phalombe!O78+Mikolongwe!O78+Migowi!O78+Nkando!O78 -> 0 | P78: =D78 -> 6
B79: Applied this Month | C79: No | D79: =Mulanje!D79+Luchenza!D79+Thyolo!D79+Muloza!D79+MUST!D79+Phalombe!D79+Mikolongwe!D79+Migowi!D79+Nkando!D79 -> 0 | E79: =Mulanje!E79+Luchenza!E79+Thyolo!E79+Muloza!E79+MUST!E79+Phalombe!E79+Mikolongwe!E79+Migowi!E79+Nkando!E79 -> 1 | F79: =Mulanje!F79+Luchenza!F79+Thyolo!F79+Muloza!F79+MUST!F79+Phalombe!F79+Mikolongwe!F79+Migowi!F79+Nkando!F79 -> 0 | G79: =Mulanje!G79+Luchenza!G79+Thyolo!G79+Muloza!G79+MUST!G79+Phalombe!G79+Mikolongwe!G79+Migowi!G79+Nkando!G79 -> 0 | H79: =Mulanje!H79+Luchenza!H79+Thyolo!H79+Muloza!H79+MUST!H79+Phalombe!H79+Mikolongwe!H79+Migowi!H79+Nkando!H79 -> 0 | I79: =Mulanje!I79+Luchenza!I79+Thyolo!I79+Muloza!I79+MUST!I79+Phalombe!I79+Mikolongwe!I79+Migowi!I79+Nkando!I79 -> 0 | J79: =Mulanje!J79+Luchenza!J79+Thyolo!J79+Muloza!J79+MUST!J79+Phalombe!J79+Mikolongwe!J79+Migowi!J79+Nkando!J79 -> 0 | K79: =Mulanje!K79+Luchenza!K79+Thyolo!K79+Muloza!K79+MUST!K79+Phalombe!K79+Mikolongwe!K79+Migowi!K79+Nkando!K79 -> 0 | ... O79: =Mulanje!O79+Luchenza!O79+Thyolo!O79+Muloza!O79+MUST!O79+Phalombe!O79+Mikolongwe!O79+Migowi!O79+Nkando!O79 -> 0 | P79: =SUM(D79:O79) -> 1
B80: Done this Month Postpaid | C80: No | D80: =Mulanje!D80+Luchenza!D80+Thyolo!D80+Muloza!D80+MUST!D80+Phalombe!D80+Mikolongwe!D80+Migowi!D80+Nkando!D80 -> 0 | E80: =Mulanje!E80+Luchenza!E80+Thyolo!E80+Muloza!E80+MUST!E80+Phalombe!E80+Mikolongwe!E80+Migowi!E80+Nkando!E80 -> 0 | F80: =Mulanje!F80+Luchenza!F80+Thyolo!F80+Muloza!F80+MUST!F80+Phalombe!F80+Mikolongwe!F80+Migowi!F80+Nkando!F80 -> 0 | G80: =Mulanje!G80+Luchenza!G80+Thyolo!G80+Muloza!G80+MUST!G80+Phalombe!G80+Mikolongwe!G80+Migowi!G80+Nkando!G80 -> 0 | H80: =Mulanje!H80+Luchenza!H80+Thyolo!H80+Muloza!H80+MUST!H80+Phalombe!H80+Mikolongwe!H80+Migowi!H80+Nkando!H80 -> 0 | I80: =Mulanje!I80+Luchenza!I80+Thyolo!I80+Muloza!I80+MUST!I80+Phalombe!I80+Mikolongwe!I80+Migowi!I80+Nkando!I80 -> 0 | J80: =Mulanje!J80+Luchenza!J80+Thyolo!J80+Muloza!J80+MUST!J80+Phalombe!J80+Mikolongwe!J80+Migowi!J80+Nkando!J80 -> 0 | K80: =Mulanje!K80+Luchenza!K80+Thyolo!K80+Muloza!K80+MUST!K80+Phalombe!K80+Mikolongwe!K80+Migowi!K80+Nkando!K80 -> 0 | ... O80: =Mulanje!O80+Luchenza!O80+Thyolo!O80+Muloza!O80+MUST!O80+Phalombe!O80+Mikolongwe!O80+Migowi!O80+Nkando!O80 -> 0
B81: Done this Month Prepaid | C81: No | D81: =Mulanje!D81+Luchenza!D81+Thyolo!D81+Muloza!D81+MUST!D81+Phalombe!D81+Mikolongwe!D81+Migowi!D81+Nkando!D81 -> 0 | E81: =Mulanje!E81+Luchenza!E81+Thyolo!E81+Muloza!E81+MUST!E81+Phalombe!E81+Mikolongwe!E81+Migowi!E81+Nkando!E81 -> 0 | F81: =Mulanje!F81+Luchenza!F81+Thyolo!F81+Muloza!F81+MUST!F81+Phalombe!F81+Mikolongwe!F81+Migowi!F81+Nkando!F81 -> 0 | G81: =Mulanje!G81+Luchenza!G81+Thyolo!G81+Muloza!G81+MUST!G81+Phalombe!G81+Mikolongwe!G81+Migowi!G81+Nkando!G81 -> 0 | H81: =Mulanje!H81+Luchenza!H81+Thyolo!H81+Muloza!H81+MUST!H81+Phalombe!H81+Mikolongwe!H81+Migowi!H81+Nkando!H81 -> 0 | I81: =Mulanje!I81+Luchenza!I81+Thyolo!I81+Muloza!I81+MUST!I81+Phalombe!I81+Mikolongwe!I81+Migowi!I81+Nkando!I81 -> 0 | J81: =Mulanje!J81+Luchenza!J81+Thyolo!J81+Muloza!J81+MUST!J81+Phalombe!J81+Mikolongwe!J81+Migowi!J81+Nkando!J81 -> 0 | K81: =Mulanje!K81+Luchenza!K81+Thyolo!K81+Muloza!K81+MUST!K81+Phalombe!K81+Mikolongwe!K81+Migowi!K81+Nkando!K81 -> 0 | ... O81: =Mulanje!O81+Luchenza!O81+Thyolo!O81+Muloza!O81+MUST!O81+Phalombe!O81+Mikolongwe!O81+Migowi!O81+Nkando!O81 -> 0 | P81: =SUM(D81:O81) -> 0
B82: Total Done | C82: No | D82: =Mulanje!D82+Luchenza!D82+Thyolo!D82+Muloza!D82+MUST!D82+Phalombe!D82+Mikolongwe!D82+Migowi!D82+Nkando!D82 -> 0 | E82: =Mulanje!E82+Luchenza!E82+Thyolo!E82+Muloza!E82+MUST!E82+Phalombe!E82+Mikolongwe!E82+Migowi!E82+Nkando!E82 -> 0 | F82: =Mulanje!F82+Luchenza!F82+Thyolo!F82+Muloza!F82+MUST!F82+Phalombe!F82+Mikolongwe!F82+Migowi!F82+Nkando!F82 -> 0 | G82: =Mulanje!G82+Luchenza!G82+Thyolo!G82+Muloza!G82+MUST!G82+Phalombe!G82+Mikolongwe!G82+Migowi!G82+Nkando!G82 -> 0 | H82: =Mulanje!H82+Luchenza!H82+Thyolo!H82+Muloza!H82+MUST!H82+Phalombe!H82+Mikolongwe!H82+Migowi!H82+Nkando!H82 -> 0 | I82: =Mulanje!I82+Luchenza!I82+Thyolo!I82+Muloza!I82+MUST!I82+Phalombe!I82+Mikolongwe!I82+Migowi!I82+Nkando!I82 -> 0 | J82: =Mulanje!J82+Luchenza!J82+Thyolo!J82+Muloza!J82+MUST!J82+Phalombe!J82+Mikolongwe!J82+Migowi!J82+Nkando!J82 -> 0 | K82: =Mulanje!K82+Luchenza!K82+Thyolo!K82+Muloza!K82+MUST!K82+Phalombe!K82+Mikolongwe!K82+Migowi!K82+Nkando!K82 -> 0 | ... O82: =Mulanje!O82+Luchenza!O82+Thyolo!O82+Muloza!O82+MUST!O82+Phalombe!O82+Mikolongwe!O82+Migowi!O82+Nkando!O82 -> 0 | P82: =P81+P80 -> 0
