Workbook

Sheet Mangochi
A1: SOUTHERN REGION WATER BOARD
A3: MONTHLY REPORTS - 2025/2026
A4: MANGOCHI ZONE
A5: MANGOCHI ZONE
A7: PARAMETERS | C7: UNITS | D7: APRIL | E7: MAY | F7: JUNE | G7: JULY | H7: AUGUST | I7: SEPTEMBER | J7: OCTOBER | K7: NOVEMBER | L7: DECEMBER | M7: JANUARY | N7: FEBRUARY | O7: MARCH | P7: TOTALS
A8: PRODUCTION
A9: Volume Produced | C9: m3 | D9: 155427 | E9: 150181 | P9: =SUM(D9:O9) -> 305608
A10: REVENUE WATER - POSTPAID
A11: Volume Billed Individuals | C11: m3 | D11: 54507 | E11: 59377 | P11: =SUM(D11:O11) -> 113884
A12: Volume Billed CWPs | C12: m3 | P12: =SUM(D12:O12) -> 0
A13: Volume Billed Institutions | C13: m3 | D13: 105 | E13: 199 | P13: =SUM(D13:O13) -> 304
A14: Volume Billed Commercial/Industrial | C14: m3 | D14: 64 | E14: 79 | P14: =SUM(D14:O14) -> 143
A15: Total Volume Billed Post Paid | C15: m3 | D15: =SUM(D11:D14) -> 54676 | E15: =SUM(E11:E14) -> 59655 | F15: =SUM(F11:F14) -> 0 | G15: =SUM(G11:G14) -> 0 | H15: =SUM(H11:H14) -> 0 | I15: =SUM(I11:I14) -> 0 | J15: =SUM(J11:J14) -> 0 | K15: =SUM(K11:K14) -> 0 | ... P15: =SUM(P11:P14) -> 114331
A16: REVENUE WATER - PREPAID
A17: Individuals | C17: m3 | D17: 25311.5 | E17: 29446.1 | P17: =SUM(D17:O17) -> 54757.6
A18: CWPs | C18: m3 | D18: 4819.3 | E18: 4389.2 | P18: =SUM(D18:O18) -> 9208.5
A19: Institutions | C19: m3 | D19: 5386.9 | E19: 5468 | P19: =SUM(D19:O19) -> 10854.9
A20: Commercial/Industrial | C20: m3 | D20: 1783.5 | E20: 2548.1 | P20: =SUM(D20:O20) -> 4331.6
A21: Total Volume Prepaid | C21: m3 | D21: =SUM(D17:D20) -> 37301.2 | E21: =SUM(E17:E20) -> 41851.4 | F21: =SUM(F17:F20) -> 0 | G21: =SUM(G17:G20) -> 0 | H21: =SUM(H17:H20) -> 0 | I21: =SUM(I17:I20) -> 0 | J21: =SUM(J17:J20) -> 0 | K21: =SUM(K17:K20) -> 0 | ... P21: =SUM(P17:P20) -> 79152.6
A22: TOTAL REVENUE WATER | C22: m3 | D22: =D21+D15 -> 91977.2 | E22: =E21+E15 -> 101506.4 | F22: =F21+F15 -> 0 | G22: =G21+G15 -> 0 | H22: =H21+H15 -> 0 | I22: =I21+I15 -> 0 | J22: =J21+J15 -> 0 | K22: =K21+K15 -> 0 | ... P22: =P21+P15 -> 193483.6
A24: Non-Revenue Water (NRW) | B24: Volume | C24: m3 | D24: =D9-D22 -> 63449.8 | E24: =E9-E22 -> 48674.6 | F24: =F9-F22 -> 0 | G24: =G9-G22 -> 0 | H24: =H9-H22 -> 0 | I24: =I9-I22 -> 0 | J24: =J9-J22 -> 0 | K24: =K9-K22 -> 0 | ... P24: =P9-P22 -> 112124.4
B25: Percentage | C25: % | D25: =D24/D9 -> 0.40822894 | E25: =E24/E9 -> 0.32410625 | F25: =F24/F9 -> #DIV/0! | G25: =G24/G9 -> #DIV/0! | H25: =H24/H9 -> #DIV/0! | I25: =I24/I9 -> #DIV/0! | J25: =J24/J9 -> #DIV/0! | K25: =K24/K9 -> #DIV/0! | ... P25: =P24/P9 -> 0.36688961
A26: OPERATING EXPENSES
A27: Chemicals
A28: Chemical | B28: Rate(MK/kg)
A29: Chlorine | B29: 23929.1 | C29: kg | D29: 510.2 | E29: 525.19 | P29: =SUM(D29:O29) -> 1035.39
C30: kg/mg litre | D30: =D29/(D9/1000) -> 3.28257 | E30: =E29/(E9/1000) -> 3.4970469 | F30: =F29/(F9/1000) -> #DIV/0! | G30: =G29/(G9/1000) -> #DIV/0! | H30: =H29/(H9/1000) -> #DIV/0! | I30: =I29/(I9/1000) -> #DIV/0! | J30: =J29/(J9/1000) -> #DIV/0! | K30: =K29/(K9/1000) -> #DIV/0! | ... P30: =P29/(P9/1000) -> 3.3879676
A31: Aluminium sulphate | B31: 1090.4 | C31: kg | P31: =SUM(D31:O31) -> 0
C32: kg/mg litre | D32: =D31/(D9/1000) -> 0 | E32: =E31/(E9/1000) -> 0 | F32: =F31/(F9/1000) -> #DIV/0! | G32: =G31/(G9/1000) -> #DIV/0! | H32: =H31/(H9/1000) -> #DIV/0! | I32: =I31/(I9/1000) -> #DIV/0! | J32: =J31/(J9/1000) -> #DIV/0! | K32: =K31/(K9/1000) -> #DIV/0! | ... P32: =P31/(P9/1000) -> 0
A33: Soda | B33: 1228.2886 | C33: kg | P33: =SUM(D33:O33) -> 0
C34: kg/mg litre | D34: =D33/(D9/1000) -> 0 | E34: =E33/(E9/1000) -> 0 | F34: =F33/(F9/1000) -> #DIV/0! | G34: =G33/(G9/1000) -> #DIV/0! | H34: =H33/(H9/1000) -> #DIV/0! | I34: =I33/(I9/1000) -> #DIV/0! | J34: =J33/(J9/1000) -> #DIV/0! | K34: =K33/(K9/1000) -> #DIV/0! | ... P34: =P33/(P9/1000) -> 0
A35: Algae floc | B35: 3726.7258 | C35: litres
C36: litres/mg litre
A37: Sud floc | B37: 3951.5936 | C37: litres | D37: 0 | E37: 0 | F37: 0 | G37: 0 | H37: 0 | I37: 0 | J37: 0 | K37: 0 | L37: 0 | M37: 0 | N37: 0 | O37: 0 | P37: =SUM(D37:O37) -> 0
C38: litres/mg litre | D38: =D37/(D9/1000) -> 0 | E38: =E37/(E9/1000) -> 0 | F38: =F37/(F9/1000) -> #DIV/0! | G38: =G37/(G9/1000) -> #DIV/0! | H38: =H37/(H9/1000) -> #DIV/0! | I38: =I37/(I9/1000) -> #DIV/0! | J38: =J37/(J9/1000) -> #DIV/0! | K38: =K37/(K9/1000) -> #DIV/0! | ... P38: =P37/(P9/1000) -> 0
A39: Potasium permanganate | B39: 1950 | C39: kg | D39: 0 | E39: 0 | F39: 0 | G39: 0 | H39: 0 | I39: 0 | J39: 0 | K39: 0 | L39: 0 | M39: 0 | N39: 0 | O39: 0 | P39: =SUM(D39:O39) -> 0
C40: kg/mg litre | D40: =D39/(D9/1000) -> 0 | E40: =E39/(E9/1000) -> 0 | F40: =F39/(F9/1000) -> #DIV/0! | G40: =G39/(G9/1000) -> #DIV/0! | H40: =H39/(H9/1000) -> #DIV/0! | I40: =I39/(I9/1000) -> #DIV/0! | J40: =J39/(J9/1000) -> #DIV/0! | K40: =K39/(K9/1000) -> #DIV/0! | ... P40: =P39/(P9/1000) -> 0
A41: Cost of Chemicals | C41: Mk | D41: =(D29*$B29)+(D31*$B31)+(D33*$B33)+(D35*$B35)+(D37*$B37)+(D39*$B39) -> 12208627 | E41: =(E29*$B29)+(E31*$B31)+(E33*$B33)+(E35*$B35)+(E37*$B37)+(E39*$B39) -> 12567324 | F41: =(F29*$B29)+(F31*$B31)+(F33*$B33)+(F35*$B35)+(F37*$B37)+(F39*$B39) -> 0 | G41: =(G29*$B29)+(G31*$B31)+(G33*$B33)+(G35*$B35)+(G37*$B37)+(G39*$B39) -> 0 | H41: =(H29*$B29)+(H31*$B31)+(H33*$B33)+(H35*$B35)+(H37*$B37)+(H39*$B39) -> 0 | I41: =(I29*$B29)+(I31*$B31)+(I33*$B33)+(I35*$B35)+(I37*$B37)+(I39*$B39) -> 0 | J41: =(J29*$B29)+(J31*$B31)+(J33*$B33)+(J35*$B35)+(J37*$B37)+(J39*$B39) -> 0 | K41: =(K29*$B29)+(K31*$B31)+(K33*$B33)+(K35*$B35)+(K37*$B37)+(K39*$B39) -> 0 | ... O41: =(O29*$B29)+(O31*$B31)+(O33*$B33)+(O35*$B35)+(O37*$B37)+(O39*$B39) -> 0 | P41: =SUM(D41:O41) -> 24775951
A42: Cost/vol. Produced (chemicals) | C42: Mk/m3 | D42: =D41/D9 -> 78.548945 | E42: =E41/E9 -> 83.681185 | F42: =F41/F9 -> #DIV/0! | G42: =G41/G9 -> #DIV/0! | H42: =H41/H9 -> #DIV/0! | I42: =I41/I9 -> #DIV/0! | J42: =J41/J9 -> #DIV/0! | K42: =K41/K9 -> #DIV/0! | ... P42: =P41/P9 -> 81.071015
A43: Power
A44: Power Usage | C44: Kw | D44: 33903.91 | E44: 22944.25 | P44: =SUM(D44:O44) -> 56848.16
A45: Power/ Vol. Produced | C45: Kw/m3 | D45: =D44/D9 -> 0.21813398 | E45: =E44/E9 -> 0.15277732 | F45: =F44/F9 -> #DIV/0! | G45: =G44/G9 -> #DIV/0! | H45: =H44/H9 -> #DIV/0! | I45: =I44/I9 -> #DIV/0! | J45: =J44/J9 -> #DIV/0! | K45: =K44/K9 -> #DIV/0! | ... P45: =P44/P9 -> 0.1860166
A46: Cost of Power | C46: Mk | D46: =1.165*(16600+(D44*143.5)) -> 5687309.9 | E46: =1.165*(16600+(E44*143.5)) -> 3855101.4 | F46: =1.165*(16600+(F44*143.5)) -> 19339 | G46: =1.165*(16600+(G44*143.5)) -> 19339 | H46: =1.165*(16600+(H44*143.5)) -> 19339 | I46: =1.165*(16600+(I44*143.5)) -> 19339 | J46: =1.165*(16600+(J44*143.5)) -> 19339 | K46: =1.165*(16600+(K44*143.5)) -> 19339 | ... O46: =1.165*(16600+(O44*143.5)) -> 19339 | P46: =SUM(D46:O46) -> 9735801.3
A47: Cost/vol. Produced | C47: Mk/m3 | D47: =D46/D9 -> 36.591518 | E47: =E46/E9 -> 25.669701 | F47: =F46/F9 -> #DIV/0! | G47: =G46/G9 -> #DIV/0! | H47: =H46/H9 -> #DIV/0! | I47: =I46/I9 -> #DIV/0! | J47: =J46/J9 -> #DIV/0! | K47: =K46/K9 -> #DIV/0! | ... P47: =P46/P9 -> 31.857154
A48: Plant and Vehicle Maintenance
A49: Distances covered | C49: km | D49: 1948 | E49: 2481 | P49: =SUM(D49:O49) -> 4429
A50: Fuel Used (litres) | C50: litres | D50: 299.8 | E50: 245 | P50: =SUM(D50:O50) -> 544.8
A51: Cost of fuel | C51: Mk | D51: 2004462.6 | E51: 1626365 | P51: =SUM(D51:O51) -> 3630827.6
A52: Maintenance | C52: Mk | P52: =SUM(D52:O52) -> 0
A53: Salaries and Wages
A54: Staff Costs | C54: MK | D54: 32599951 | E54: 33032267 | P54: =SUM(D54:O54) -> 65632219
A55: Wages | C55: MK | D55: 4591888 | E55: 4739847.4 | P55: =SUM(D55:O55) -> 9331735.4
A56: Other Overhead Costs | C56: MK | D56: 3605140 | E56: 3707840 | P56: =SUM(D56:O56) -> 7312980
A57: Operating Costs
A58: Total Operating Costs | C58: MK | D58: =D41+D46+D51+D52+D54+D55+D56 -> 60697379 | E58: =E41+E46+E51+E52+E54+E55+E56 -> 59528745 | F58: =F41+F46+F51+F52+F54+F55+F56 -> 19339 | G58: =G41+G46+G51+G52+G54+G55+G56 -> 19339 | H58: =H41+H46+H51+H52+H54+H55+H56 -> 19339 | I58: =I41+I46+I51+I52+I54+I55+I56 -> 19339 | J58: =J41+J46+J51+J52+J54+J55+J56 -> 19339 | K58: =K41+K46+K51+K52+K54+K55+K56 -> 19339 | ... O58: =O41+O46+O51+O52+O54+O55+O56 -> 19339 | P58: =SUM(D58:O58) -> 1.2041951e+08
A59: Cost/Vol. Produced | C59: Mk/m3 | D59: =D58/D9 -> 390.52017 | E59: =E58/E9 -> 396.38 | F59: =F58/F9 -> #DIV/0! | G59: =G58/G9 -> #DIV/0! | H59: =H58/H9 -> #DIV/0! | I59: =I58/I9 -> #DIV/0! | J59: =J58/J9 -> #DIV/0! | K59: =K58/K9 -> #DIV/0! | ... P59: =P58/P9 -> 394.0326
A60: Cost/Vol. Billed | C60: Mk/m3 | D60: =D58/D22 -> 659.91766 | E60: =E58/E22 -> 586.45312 | F60: =F58/F22 -> #DIV/0! | G60: =G58/G22 -> #DIV/0! | H60: =H58/H22 -> #DIV/0! | I60: =I58/I22 -> #DIV/0! | J60: =J58/J22 -> #DIV/0! | K60: =K58/K22 -> #DIV/0! | ... P60: =P58/P22 -> 622.37582
A61: Permanent Staff Employed | C61: No | D61: 25 | E61: 25 | P61: =O61 -> 0
A62: Staff/Vol.1000m3 of Volume Produced/hour (12 hour day) | C62: No/1000m3 | D62: =(D61*1000*31)/D9 -> 4.9862636 | E62: =(E61*1000*31)/E9 -> 5.1604397 | F62: =(F61*1000*31)/F9 -> #DIV/0! | G62: =(G61*1000*31)/G9 -> #DIV/0! | H62: =(H61*1000*31)/H9 -> #DIV/0! | I62: =(I61*1000*31)/I9 -> #DIV/0! | J62: =(J61*1000*31)/J9 -> #DIV/0! | K62: =(K61*1000*31)/K9 -> #DIV/0! | ... P62: =(P61*1000*31)/P9 -> 0
A63: Temporary Staff Employed | C63: No | D63: 28 | E63: 28 | P63: =SUM(D63:O63) -> 56
A65: Water Connections and Disconnections
A66: New Individual Water Connections | B66: Brought Forward | C66: No | D66: 1978 | E66: 2018 | P66: =D66 -> 1978
B67: Applied this Month | C67: No | D67: 115 | E67: 138 | P67: =SUM(D67:O67) -> 253
B68: Done this Month Postpaid | C68: No | P68: =SUM(D68:O68) -> 0
B69: Done this Month Prepaid | C69: No | D69: 75 | E69: 109 | P69: =SUM(D69:O69) -> 184
B70: Total Done | C70: No | D70: =D68+D69 -> 75 | E70: =E68+E69 -> 109 | F70: =F68+F69 -> 0 | G70: =G68+G69 -> 0 | H70: =H68+H69 -> 0 | I70: =I68+I69 -> 0 | J70: =J68+J69 -> 0 | K70: =K68+K69 -> 0 | ... P70: =P68+P69 -> 184
B71: Carried Forward | C71: No | D71: =D66+D67-D70 -> 2018 | E71: =E66+E67-E70 -> 2047 | F71: =F66+F67-F70 -> 0 | G71: =G66+G67-G70 -> 0 | H71: =H66+H67-H70 -> 0 | I71: =I66+I67-I70 -> 0 | J71: =J66+J67-J70 -> 0 | K71: =K66+K67-K70 -> 0 | ... P71: =P66+P67-P70 -> 2047
A72: New Institutional Water Connections | B72: Brought Forward | C72: No | D72: 4 | E72: 4 | P72: =D72 -> 4
B73: Applied this Month | C73: No | P73: =SUM(D73:O73) -> 0
B74: Done this Month Postpaid | C74: No | P74: =SUM(D74:O74) -> 0
B75: Done this Month Prepaid | C75: No | P75: =SUM(D75:O75) -> 0
B76: Total Done | C76: No | D76: =D74+D75 -> 0 | E76: =E74+E75 -> 0 | F76: =F74+F75 -> 0 | G76: =G74+G75 -> 0 | H76: =H74+H75 -> 0 | I76: =I74+I75 -> 0 | J76: =J74+J75 -> 0 | K76: =K74+K75 -> 0 | ... P76: =P74+P75 -> 0
B77: Carried Forward | C77: No | D77: =D72+D73-D76 -> 4 | E77: =E72+E73-E76 -> 4 | F77: =F72+F73-F76 -> 0 | G77: =G72+G73-G76 -> 0 | H77: =H72+H73-H76 -> 0 | I77: =I72+I73-I76 -> 0 | J77: =J72+J73-J76 -> 0 | K77: =K72+K73-K76 -> 0 | ... P77: =P72+P73-P76 -> 4
A78: New Commercial/Industrial Water Connections | B78: Brought Forward | C78: No | P78: =D78 -> 0
B79: Applied this Month | C79: No | P79: =SUM(D79:O79) -> 0
B80: Done this Month Postpaid | C80: No | P80: =SUM(D80:O80) -> 0
B81: Done this Month Prepaid | C81: No | P81: =SUM(D81:O81) -> 0
B82: Total Done | C82: No | D82: =D80+D81 -> 0 | E82: =E80+E81 -> 0 | F82: =F80+F81 -> 0 | G82: =G80+G81 -> 0 | H82: =H80+H81 -> 0 | I82: =I80+I81 -> 0 | J82: =J80+J81 -> 0 | K82: =K80+K81 -> 0 | ... P82: =P80+P81 -> 0
B83: Carried Forward | C83: No | D83: =D78+D79-D82 -> 0 | E83: =E78+E79-E82 -> 0 | F83: =F78+F79-F82 -> 0 | G83: =G78+G79-G82 -> 0 | H83: =H78+H79-H82 -> 0 | I83: =I78+I79-I82 -> 0 | J83: =J78+J79-J82 -> 0 | K83: =K78+K79-K82 -> 0 | ... P83: =P78+P79-P82 -> 0
A84: New CWP | B84: Brought Forward | C84: No | D84: 10 | E84: 10 | P84: =D84 -> 10
B85: Applied this Month | C85: No | P85: =SUM(D85:O85) -> 0
B86: Done this Month Postpaid | C86: No | P86: =SUM(D86:O86) -> 0
B87: Done this Month Prepaid | C87: No | E87: 1 | P87: =SUM(D87:O87) -> 1
B88: Total Done | C88: No | D88: =D86+D87 -> 0 | E88: =E86+E87 -> 1 | F88: =F86+F87 -> 0 | G88: =G86+G87 -> 0 | H88: =H86+H87 -> 0 | I88: =I86+I87 -> 0 | J88: =J86+J87 -> 0 | K88: =K86+K87 -> 0 | ... O88: =O86+O87 -> 0 | P88: =SUM(D88:O88) -> 1
B89: Carried Forward | C89: No | D89: =D84+D85-D88 -> 10 | E89: =E84+E85-E88 -> 9 | F89: =F84+F85-F88 -> 0 | G89: =G84+G85-G88 -> 0 | H89: =H84+H85-H88 -> 0 | I89: =I84+I85-I88 -> 0 | J89: =J84+J85-J88 -> 0 | K89: =K84+K85-K88 -> 0 | ... O89: =O84+O85-O88 -> 0 | P89: =P84+P85-P86-P87 -> 9
A90: Aggregated New Water connections | B90: Brought Forward | C90: No | D90: =D66+D72+D78+D84 -> 1992 | E90: =E66+E72+E78+E84 -> 2032 | F90: =F66+F72+F78+F84 -> 0 | G90: =G66+G72+G78+G84 -> 0 | H90: =H66+H72+H78+H84 -> 0 | I90: =I66+I72+I78+I84 -> 0 | J90: =J66+J72+J78+J84 -> 0 | K90: =K66+K72+K78+K84 -> 0 | ... O90: =O66+O72+O78+O84 -> 0 | P90: =D90 -> 1992
B91: Applied this Month | C91: No | D91: =D67+D73+D79+D85 -> 115 | E91: =E67+E73+E79+E85 -> 138 | F91: =F67+F73+F79+F85 -> 0 | G91: =G67+G73+G79+G85 -> 0 | H91: =H67+H73+H79+H85 -> 0 | I91: =I67+I73+I79+I85 -> 0 | J91: =J67+J73+J79+J85 -> 0 | K91: =K67+K73+K79+K85 -> 0 | ... O91: =O67+O73+O79+O85 -> 0 | P91: =SUM(D91:O91) -> 253
B92: Done this Month Postpaid | C92: No | D92: =D68+D74+D80+D86 -> 0 | E92: =E68+E74+E80+E86 -> 0 | F92: =F68+F74+F80+F86 -> 0 | G92: =G68+G74+G80+G86 -> 0 | H92: =H68+H74+H80+H86 -> 0 | I92: =I68+I74+I80+I86 -> 0 | J92: =J68+J74+J80+J86 -> 0 | K92: =K68+K74+K80+K86 -> 0 | ... O92: =O68+O74+O80+O86 -> 0 | P92: =SUM(D92:O92) -> 0
B93: Done this Month Prepaid | D93: =D69+D75+D81+D87 -> 75 | E93: =E69+E75+E81+E87 -> 110 | F93: =F69+F75+F81+F87 -> 0 | G93: =G69+G75+G81+G87 -> 0 | H93: =H69+H75+H81+H87 -> 0 | I93: =I69+I75+I81+I87 -> 0 | J93: =J69+J75+J81+J87 -> 0 | K93: =K69+K75+K81+K87 -> 0 | ... O93: =O69+O75+O81+O87 -> 0 | P93: =SUM(D93:O93) -> 185
B94: Total Done | C94: No | D94: =D93+D92 -> 75 | E94: =E93+E92 -> 110 | F94: =F93+F92 -> 0 | G94: =G93+G92 -> 0 | H94: =H93+H92 -> 0 | I94: =I93+I92 -> 0 | J94: =J93+J92 -> 0 | K94: =K93+K92 -> 0 | ... P94: =P93+P92 -> 185
B95: Carried Forward | C95: No | D95: =D90+D91-D94 -> 2032 | E95: =E90+E91-E94 -> 2060 | F95: =F90+F91-F94 -> 0 | G95: =G90+G91-G94 -> 0 | H95: =H90+H91-H94 -> 0 | I95: =I90+I91-I94 -> 0 | J95: =J90+J91-J94 -> 0 | K95: =K90+K91-K94 -> 0 | ... P95: =P90+P91-P94 -> 2060
A97: Prepaid Metering
A98: Prepaid Meters Installed | C98: No | D98: 75 | E98: 110 | P98: =SUM(D98:O98) -> 185
A100: Active and Disconnected Accounts
A101: Disconnected Individual Accounts | C101: No | D101: 2079 | E101: 2042 | P101: =O101 -> 0
A102: Disconnected institutional Accounts | C102: No | D102: 55 | E102: 55 | P102: =O102 -> 0
A103: Disconnected Commercial/Industrial Accounts | C103: No | D103: 121 | E103: 120 | P103: =O103 -> 0
A104: Disconnected CWP | C104: No | D104: 10 | E104: 10 | P104: =O104 -> 0
A105: Total Disconnected Accounts | C105: No | D105: =SUM(D101:D104) -> 2265 | E105: =SUM(E101:E104) -> 2227 | F105: =SUM(F101:F104) -> 0 | G105: =SUM(G101:G104) -> 0 | H105: =SUM(H101:H104) -> 0 | I105: =SUM(I101:I104) -> 0 | J105: =SUM(J101:J104) -> 0 | K105: =SUM(K101:K104) -> 0 | ... O105: =SUM(O101:O104) -> 0 | P105: =O105 -> 0
A106: Postpaid Consumers
...

Sheet Monkey Bay
A1: SOUTHERN REGION WATER BOARD
A3: MONTHLY REPORTS - 2025/2026
A4: MANGOCHI ZONE
A5: MANGOCHI ZONE
A7: PARAMETERS | C7: UNITS | D7: APRIL | E7: MAY | F7: JUNE | G7: JULY | H7: AUGUST | I7: SEPTEMBER | J7: OCTOBER | K7: NOVEMBER | L7: DECEMBER | M7: JANUARY | N7: FEBRUARY | O7: MARCH | P7: TOTALS
A8: PRODUCTION
A9: Volume Produced | C9: m3 | D9: 55334 | E9: 60716 | P9: =SUM(D9:O9) -> 116050
A10: REVENUE WATER - POSTPAID
A11: Volume Billed Individuals | C11: m3 | D11: 16648 | E11: 19144 | P11: =SUM(D11:O11) -> 35792
A12: Volume Billed CWPs | C12: m3 | P12: =SUM(D12:O12) -> 0
A13: Volume Billed Institutions | C13: m3 | D13: 4296 | E13: 4619 | P13: =SUM(D13:O13) -> 8915
A14: Volume Billed Commercial/Industrial | C14: m3 | P14: =SUM(D14:O14) -> 0
A15: Total Volume Billed Post Paid | C15: m3 | D15: =SUM(D11:D14) -> 20944 | E15: =SUM(E11:E14) -> 23763 | F15: =SUM(F11:F14) -> 0 | G15: =SUM(G11:G14) -> 0 | H15: =SUM(H11:H14) -> 0 | I15: =SUM(I11:I14) -> 0 | J15: =SUM(J11:J14) -> 0 | K15: =SUM(K11:K14) -> 0 | ... P15: =SUM(P11:P14) -> 44707
A16: REVENUE WATER - PREPAID
A17: Individuals | C17: m3 | D17: 8292.7 | E17: 9882.4 | P17: =SUM(D17:O17) -> 18175.1
A18: CWPs | C18: m3 | D18: 1010.3 | E18: 1234.3 | P18: =SUM(D18:O18) -> 2244.6
A19: Institutions | C19: m3 | D19: 2460.9 | E19: 2137.6 | P19: =SUM(D19:O19) -> 4598.5
A20: Commercial/Industrial | C20: m3 | D20: 559.4 | E20: 608.4 | P20: =SUM(D20:O20) -> 1167.8
A21: Total Volume Prepaid | C21: m3 | D21: =SUM(D17:D20) -> 12323.3 | E21: =SUM(E17:E20) -> 13862.7 | F21: =SUM(F17:F20) -> 0 | G21: =SUM(G17:G20) -> 0 | H21: =SUM(H17:H20) -> 0 | I21: =SUM(I17:I20) -> 0 | J21: =SUM(J17:J20) -> 0 | K21: =SUM(K17:K20) -> 0 | ... P21: =SUM(P17:P20) -> 26186
A22: TOTAL REVENUE WATER | C22: m3 | D22: =D21+D15 -> 33267.3 | E22: =E21+E15 -> 37625.7 | F22: =F21+F15 -> 0 | G22: =G21+G15 -> 0 | H22: =H21+H15 -> 0 | I22: =I21+I15 -> 0 | J22: =J21+J15 -> 0 | K22: =K21+K15 -> 0 | ... P22: =P21+P15 -> 70893
A24: Non-Revenue Water (NRW) | B24: Volume | C24: m3 | D24: =D9-D22 -> 22066.7 | E24: =E9-E22 -> 23090.3 | F24: =F9-F22 -> 0 | G24: =G9-G22 -> 0 | H24: =H9-H22 -> 0 | I24: =I9-I22 -> 0 | J24: =J9-J22 -> 0 | K24: =K9-K22 -> 0 | ... P24: =P9-P22 -> 45157
B25: Percentage | C25: % | D25: =D24/D9 -> 0.39879098 | E25: =E24/E9 -> 0.38030009 | F25: =F24/F9 -> #DIV/0! | G25: =G24/G9 -> #DIV/0! | H25: =H24/H9 -> #DIV/0! | I25: =I24/I9 -> #DIV/0! | J25: =J24/J9 -> #DIV/0! | K25: =K24/K9 -> #DIV/0! | ... P25: =P24/P9 -> 0.38911676
A26: OPERATING EXPENSES
A27: Chemicals
A28: Chemical | B28: Rate(MK/kg)
A29: Chlorine | B29: 23929.1 | C29: kg | D29: 115 | E29: 115 | P29: =SUM(D29:O29) -> 230
C30: kg/mg litre | D30: =D29/(D9/1000) -> 2.0782882 | E30: =E29/(E9/1000) -> 1.8940642 | F30: =F29/(F9/1000) -> #DIV/0! | G30: =G29/(G9/1000) -> #DIV/0! | H30: =H29/(H9/1000) -> #DIV/0! | I30: =I29/(I9/1000) -> #DIV/0! | J30: =J29/(J9/1000) -> #DIV/0! | K30: =K29/(K9/1000) -> #DIV/0! | ... P30: =P29/(P9/1000) -> 1.9819044
A31: Aluminium sulphate | B31: 1090.4 | C31: kg | P31: =SUM(D31:O31) -> 0
C32: kg/mg litre | D32: =D31/(D9/1000) -> 0 | E32: =E31/(E9/1000) -> 0 | F32: =F31/(F9/1000) -> #DIV/0! | G32: =G31/(G9/1000) -> #DIV/0! | H32: =H31/(H9/1000) -> #DIV/0! | I32: =I31/(I9/1000) -> #DIV/0! | J32: =J31/(J9/1000) -> #DIV/0! | K32: =K31/(K9/1000) -> #DIV/0! | ... P32: =P31/(P9/1000) -> 0
A33: Soda | B33: 1228.2886 | C33: kg | P33: =SUM(D33:O33) -> 0
C34: kg/mg litre | D34: =D33/(D9/1000) -> 0 | E34: =E33/(E9/1000) -> 0 | F34: =F33/(F9/1000) -> #DIV/0! | G34: =G33/(G9/1000) -> #DIV/0! | H34: =H33/(H9/1000) -> #DIV/0! | I34: =I33/(I9/1000) -> #DIV/0! | J34: =J33/(J9/1000) -> #DIV/0! | K34: =K33/(K9/1000) -> #DIV/0! | ... P34: =P33/(P9/1000) -> 0
A35: Algae floc | B35: 3726.7258 | C35: litres
C36: litres/mg litre
A37: Sud floc | B37: 3951.5936 | C37: litres | D37: 0 | E37: 0 | F37: 0 | G37: 0 | H37: 0 | I37: 0 | J37: 0 | K37: 0 | L37: 0 | M37: 0 | N37: 0 | O37: 0 | P37: =SUM(D37:O37) -> 0
C38: litres/mg litre | D38: =D37/(D9/1000) -> 0 | E38: =E37/(E9/1000) -> 0 | F38: =F37/(F9/1000) -> #DIV/0! | G38: =G37/(G9/1000) -> #DIV/0! | H38: =H37/(H9/1000) -> #DIV/0! | I38: =I37/(I9/1000) -> #DIV/0! | J38: =J37/(J9/1000) -> #DIV/0! | K38: =K37/(K9/1000) -> #DIV/0! | ... P38: =P37/(P9/1000) -> 0
A39: Potasium permanganate | B39: 1950 | C39: kg | D39: 0 | E39: 0 | F39: 0 | G39: 0 | H39: 0 | I39: 0 | J39: 0 | K39: 0 | L39: 0 | M39: 0 | N39: 0 | O39: 0 | P39: =SUM(D39:O39) -> 0
C40: kg/mg litre | D40: =D39/(D9/1000) -> 0 | E40: =E39/(E9/1000) -> 0 | F40: =F39/(F9/1000) -> #DIV/0! | G40: =G39/(G9/1000) -> #DIV/0! | H40: =H39/(H9/1000) -> #DIV/0! | I40: =I39/(I9/1000) -> #DIV/0! | J40: =J39/(J9/1000) -> #DIV/0! | K40: =K39/(K9/1000) -> #DIV/0! | ... P40: =P39/(P9/1000) -> 0
A41: Cost of Chemicals | C41: Mk | D41: =(D29*$B29)+(D31*$B31)+(D33*$B33)+(D35*$B35)+(D37*$B37)+(D39*$B39) -> 2751846.5 | E41: =(E29*$B29)+(E31*$B31)+(E33*$B33)+(E35*$B35)+(E37*$B37)+(E39*$B39) -> 2751846.5 | F41: =(F29*$B29)+(F31*$B31)+(F33*$B33)+(F35*$B35)+(F37*$B37)+(F39*$B39) -> 0 | G41: =(G29*$B29)+(G31*$B31)+(G33*$B33)+(G35*$B35)+(G37*$B37)+(G39*$B39) -> 0 | H41: =(H29*$B29)+(H31*$B31)+(H33*$B33)+(H35*$B35)+(H37*$B37)+(H39*$B39) -> 0 | I41: =(I29*$B29)+(I31*$B31)+(I33*$B33)+(I35*$B35)+(I37*$B37)+(I39*$B39) -> 0 | J41: =(J29*$B29)+(J31*$B31)+(J33*$B33)+(J35*$B35)+(J37*$B37)+(J39*$B39) -> 0 | K41: =(K29*$B29)+(K31*$B31)+(K33*$B33)+(K35*$B35)+(K37*$B37)+(K39*$B39) -> 0 | ... O41: =(O29*$B29)+(O31*$B31)+(O33*$B33)+(O35*$B35)+(O37*$B37)+(O39*$B39) -> 0 | P41: =SUM(D41:O41) -> 5503693
A42: Cost/vol. Produced (chemicals) | C42: Mk/m3 | D42: =D41/D9 -> 49.731566 | E42: =E41/E9 -> 45.323251 | F42: =F41/F9 -> #DIV/0! | G42: =G41/G9 -> #DIV/0! | H42: =H41/H9 -> #DIV/0! | I42: =I41/I9 -> #DIV/0! | J42: =J41/J9 -> #DIV/0! | K42: =K41/K9 -> #DIV/0! | ... P42: =P41/P9 -> 47.425187
A43: Power
A44: Power Usage | C44: Kw | D44: 26954 | E44: 23960 | P44: =SUM(D44:O44) -> 50914
A45: Power/ Vol. Produced | C45: Kw/m3 | D45: =D44/D9 -> 0.48711461 | E45: =E44/E9 -> 0.39462415 | F45: =F44/F9 -> #DIV/0! | G45: =G44/G9 -> #DIV/0! | H45: =H44/H9 -> #DIV/0! | I45: =I44/I9 -> #DIV/0! | J45: =J44/J9 -> #DIV/0! | K45: =K44/K9 -> #DIV/0! | ... P45: =P44/P9 -> 0.43872469
A46: Cost of Power | C46: Mk | D46: =1.165*(16600+(D44*143.5)) -> 4525441.3 | E46: =1.165*(16600+(E44*143.5)) -> 4024911.9 | F46: =1.165*(16600+(F44*143.5)) -> 19339 | G46: =1.165*(16600+(G44*143.5)) -> 19339 | H46: =1.165*(16600+(H44*143.5)) -> 19339 | I46: =1.165*(16600+(I44*143.5)) -> 19339 | J46: =1.165*(16600+(J44*143.5)) -> 19339 | K46: =1.165*(16600+(K44*143.5)) -> 19339 | ... O46: =1.165*(16600+(O44*143.5)) -> 19339 | P46: =SUM(D46:O46) -> 8743743.2
A47: Cost/vol. Produced | C47: Mk/m3 | D47: =D46/D9 -> 81.784099 | E47: =E46/E9 -> 66.290795 | F47: =F46/F9 -> #DIV/0! | G47: =G46/G9 -> #DIV/0! | H47: =H46/H9 -> #DIV/0! | I47: =I46/I9 -> #DIV/0! | J47: =J46/J9 -> #DIV/0! | K47: =K46/K9 -> #DIV/0! | ... P47: =P46/P9 -> 75.344621
A48: Plant and Vehicle Maintenance
A49: Distances covered | C49: km | P49: =SUM(D49:O49) -> 0
A50: Fuel Used (litres) | C50: litres | P50: =SUM(D50:O50) -> 0
A51: Cost of fuel | C51: Mk | P51: =SUM(D51:O51) -> 0
A52: Maintenance | C52: Mk | P52: =SUM(D52:O52) -> 0
A53: Salaries and Wages
A54: Staff Costs | C54: MK | D54: 4012076.2 | E54: 4207141.8 | P54: =SUM(D54:O54) -> 8219217.9
A55: Wages | C55: MK | D55: 1563340.9 | E55: 1655720.9 | P55: =SUM(D55:O55) -> 3219061.8
A56: Other Overhead Costs | C56: MK | D56: 982120 | E56: 1026220 | P56: =SUM(D56:O56) -> 2008340
A57: Operating Costs
A58: Total Operating Costs | C58: MK | D58: =D41+D46+D51+D52+D54+D55+D56 -> 13834825 | E58: =E41+E46+E51+E52+E54+E55+E56 -> 13665841 | F58: =F41+F46+F51+F52+F54+F55+F56 -> 19339 | G58: =G41+G46+G51+G52+G54+G55+G56 -> 19339 | H58: =H41+H46+H51+H52+H54+H55+H56 -> 19339 | I58: =I41+I46+I51+I52+I54+I55+I56 -> 19339 | J58: =J41+J46+J51+J52+J54+J55+J56 -> 19339 | K58: =K41+K46+K51+K52+K54+K55+K56 -> 19339 | ... O58: =O41+O46+O51+O52+O54+O55+O56 -> 19339 | P58: =SUM(D58:O58) -> 27694056
A59: Cost/Vol. Produced | C59: Mk/m3 | D59: =D58/D9 -> 250.02394 | E59: =E58/E9 -> 225.07809 | F59: =F58/F9 -> #DIV/0! | G59: =G58/G9 -> #DIV/0! | H59: =H58/H9 -> #DIV/0! | I59: =I58/I9 -> #DIV/0! | J59: =J58/J9 -> #DIV/0! | K59: =K58/K9 -> #DIV/0! | ... P59: =P58/P9 -> 238.639
A60: Cost/Vol. Billed | C60: Mk/m3 | D60: =D58/D22 -> 415.86858 | E60: =E58/E22 -> 363.20496 | F60: =F58/F22 -> #DIV/0! | G60: =G58/G22 -> #DIV/0! | H60: =H58/H22 -> #DIV/0! | I60: =I58/I22 -> #DIV/0! | J60: =J58/J22 -> #DIV/0! | K60: =K58/K22 -> #DIV/0! | ... P60: =P58/P22 -> 390.64585
A61: Permanent Staff Employed | C61: No | D61: 4 | E61: 4 | P61: =O61 -> 0
A62: Staff/Vol.1000m3 of Volume Produced/hour (12 hour day) | C62: No/1000m3 | D62: =(D61*1000*31)/D9 -> 2.2409369 | E62: =(E61*1000*31)/E9 -> 2.0422953 | F62: =(F61*1000*31)/F9 -> #DIV/0! | G62: =(G61*1000*31)/G9 -> #DIV/0! | H62: =(H61*1000*31)/H9 -> #DIV/0! | I62: =(I61*1000*31)/I9 -> #DIV/0! | J62: =(J61*1000*31)/J9 -> #DIV/0! | K62: =(K61*1000*31)/K9 -> #DIV/0! | ... P62: =(P61*1000*31)/P9 -> 0
A63: Temporary Staff Employed | C63: No | D63: 13 | E63: 13 | P63: =SUM(D63:O63) -> 26
A65: Water Connections and Disconnections
A66: New Individual Water Connections | B66: Brought Forward | C66: No | D66: 77 | E66: 53 | P66: =D66 -> 77
B67: Applied this Month | C67: No | D67: 26 | E67: 31 | P67: =SUM(D67:O67) -> 57
B68: Done this Month Postpaid | C68: No | P68: =SUM(D68:O68) -> 0
B69: Done this Month Prepaid | C69: No | D69: 57 | E69: 50 | P69: =SUM(D69:O69) -> 107
B70: Total Done | C70: No | D70: =D68+D69 -> 57 | E70: =E68+E69 -> 50 | F70: =F68+F69 -> 0 | G70: =G68+G69 -> 0 | H70: =H68+H69 -> 0 | I70: =I68+I69 -> 0 | J70: =J68+J69 -> 0 | K70: =K68+K69 -> 0 | ... P70: =P68+P69 -> 107
B71: Carried Forward | C71: No | D71: =D66+D67-D70 -> 46 | E71: =E66+E67-E70 -> 34 | F71: =F66+F67-F70 -> 0 | G71: =G66+G67-G70 -> 0 | H71: =H66+H67-H70 -> 0 | I71: =I66+I67-I70 -> 0 | J71: =J66+J67-J70 -> 0 | K71: =K66+K67-K70 -> 0 | ... P71: =P66+P67-P70 -> 27
A72: New Institutional Water Connections | B72: Brought Forward | C72: No | P72: =D72 -> 0
B73: Applied this Month | C73: No | P73: =SUM(D73:O73) -> 0
B74: Done this Month Postpaid | C74: No | P74: =SUM(D74:O74) -> 0
B75: Done this Month Prepaid | C75: No | P75: =SUM(D75:O75) -> 0
B76: Total Done | C76: No | D76: =D74+D75 -> 0 | E76: =E74+E75 -> 0 | F76: =F74+F75 -> 0 | G76: =G74+G75 -> 0 | H76: =H74+H75 -> 0 | I76: =I74+I75 -> 0 | J76: =J74+J75 -> 0 | K76: =K74+K75 -> 0 | ... P76: =P74+P75 -> 0
B77: Carried Forward | C77: No | D77: =D72+D73-D76 -> 0 | E77: =E72+E73-E76 -> 0 | F77: =F72+F73-F76 -> 0 | G77: =G72+G73-G76 -> 0 | H77: =H72+H73-H76 -> 0 | I77: =I72+I73-I76 -> 0 | J77: =J72+J73-J76 -> 0 | K77: =K72+K73-K76 -> 0 | ... P77: =P72+P73-P76 -> 0
A78: New Commercial/Industrial Water Connections | B78: Brought Forward | C78: No | D78: 7 | E78: 7 | P78: =D78 -> 7
B79: Applied this Month | C79: No | P79: =SUM(D79:O79) -> 0
B80: Done this Month Postpaid | C80: No | P80: =SUM(D80:O80) -> 0
B81: Done this Month Prepaid | C81: No | D81: 1 | E81: 1 | P81: =SUM(D81:O81) -> 2
B82: Total Done | C82: No | D82: =D80+D81 -> 1 | E82: =E80+E81 -> 1 | F82: =F80+F81 -> 0 | G82: =G80+G81 -> 0 | H82: =H80+H81 -> 0 | I82: =I80+I81 -> 0 | J82: =J80+J81 -> 0 | K82: =K80+K81 -> 0 | ... P82: =P80+P81 -> 2
B83: Carried Forward | C83: No | D83: =D78+D79-D82 -> 6 | E83: =E78+E79-E82 -> 6 | F83: =F78+F79-F82 -> 0 | G83: =G78+G79-G82 -> 0 | H83: =H78+H79-H82 -> 0 | I83: =I78+I79-I82 -> 0 | J83: =J78+J79-J82 -> 0 | K83: =K78+K79-K82 -> 0 | ... P83: =P78+P79-P82 -> 5
A84: New CWP | B84: Brought Forward | C84: No | P84: =D84 -> 0
B85: Applied this Month | C85: No | P85: =SUM(D85:O85) -> 0
B86: Done this Month Postpaid | C86: No | P86: =SUM(D86:O86) -> 0
B87: Done this Month Prepaid | C87: No | P87: =SUM(D87:O87) -> 0
B88: Total Done | C88: No | D88: =D86+D87 -> 0 | E88: =E86+E87 -> 0 | F88: =F86+F87 -> 0 | G88: =G86+G87 -> 0 | H88: =H86+H87 -> 0 | I88: =I86+I87 -> 0 | J88: =J86+J87 -> 0 | K88: =K86+K87 -> 0 | ... O88: =O86+O87 -> 0 | P88: =SUM(D88:O88) -> 0
B89: Carried Forward | C89: No | D89: =D84+D85-D88 -> 0 | E89: =E84+E85-E88 -> 0 | F89: =F84+F85-F88 -> 0 | G89: =G84+G85-G88 -> 0 | H89: =H84+H85-H88 -> 0 | I89: =I84+I85-I88 -> 0 | J89: =J84+J85-J88 -> 0 | K89: =K84+K85-K88 -> 0 | ... O89: =O84+O85-O88 -> 0 | P89: =P84+P85-P86-P87 -> 0
A90: Aggregated New Water connections | B90: Brought Forward | C90: No | D90: =D66+D72+D78+D84 -> 84 | E90: =E66+E72+E78+E84 -> 60 | F90: =F66+F72+F78+F84 -> 0 | G90: =G66+G72+G78+G84 -> 0 | H90: =H66+H72+H78+H84 -> 0 | I90: =I66+I72+I78+I84 -> 0 | J90: =J66+J72+J78+J84 -> 0 | K90: =K66+K72+K78+K84 -> 0 | ... O90: =O66+O72+O78+O84 -> 0 | P90: =D90 -> 84
B91: Applied this Month | C91: No | D91: =D67+D73+D79+D85 -> 26 | E91: =E67+E73+E79+E85 -> 31 | F91: =F67+F73+F79+F85 -> 0 | G91: =G67+G73+G79+G85 -> 0 | H91: =H67+H73+H79+H85 -> 0 | I91: =I67+I73+I79+I85 -> 0 | J91: =J67+J73+J79+J85 -> 0 | K91: =K67+K73+K79+K85 -> 0 | ... O91: =O67+O73+O79+O85 -> 0 | P91: =SUM(D91:O91) -> 57
B92: Done this Month Postpaid | C92: No | D92: =D68+D74+D80+D86 -> 0 | E92: =E68+E74+E80+E86 -> 0 | F92: =F68+F74+F80+F86 -> 0 | G92: =G68+G74+G80+G86 -> 0 | H92: =H68+H74+H80+H86 -> 0 | I92: =I68+I74+I80+I86 -> 0 | J92: =J68+J74+J80+J86 -> 0 | K92: =K68+K74+K80+K86 -> 0 | ... O92: =O68+O74+O80+O86 -> 0 | P92: =SUM(D92:O92) -> 0
B93: Done this Month Prepaid | D93: =D69+D75+D81+D87 -> 58 | E93: =E69+E75+E81+E87 -> 51 | F93: =F69+F75+F81+F87 -> 0 | G93: =G69+G75+G81+G87 -> 0 | H93: =H69+H75+H81+H87 -> 0 | I93: =I69+I75+I81+I87 -> 0 | J93: =J69+J75+J81+J87 -> 0 | K93: =K69+K75+K81+K87 -> 0 | ... O93: =O69+O75+O81+O87 -> 0 | P93: =SUM(D93:O93) -> 109
B94: Total Done | C94: No | D94: =D93+D92 -> 58 | E94: =E93+E92 -> 51 | F94: =F93+F92 -> 0 | G94: =G93+G92 -> 0 | H94: =H93+H92 -> 0 | I94: =I93+I92 -> 0 | J94: =J93+J92 -> 0 | K94: =K93+K92 -> 0 | ... P94: =P93+P92 -> 109
B95: Carried Forward | C95: No | D95: =D90+D91-D94 -> 52 | E95: =E90+E91-E94 -> 40 | F95: =F90+F91-F94 -> 0 | G95: =G90+G91-G94 -> 0 | H95: =H90+H91-H94 -> 0 | I95: =I90+I91-I94 -> 0 | J95: =J90+J91-J94 -> 0 | K95: =K90+K91-K94 -> 0 | ... P95: =P90+P91-P94 -> 32
A97: Prepaid Metering
A98: Prepaid Meters Installed | C98: No | D98: 58 | E98: 51 | P98: =SUM(D98:O98) -> 109
A100: Active and Disconnected Accounts
A101: Disconnected Individual Accounts | C101: No | D101: 422 | E101: 397 | P101: =O101 -> 0
A102: Disconnected institutional Accounts | C102: No | D102: 18 | E102: 18 | P102: =O102 -> 0
A103: Disconnected Commercial/Industrial Accounts | C103: No | D103: 22 | E103: 22 | P103: =O103 -> 0
A104: Disconnected CWP | C104: No | D104: 3 | E104: 3 | P104: =O104 -> 0
A105: Total Disconnected Accounts | C105: No | D105: =SUM(D101:D104) -> 465 | E105: =SUM(E101:E104) -> 440 | F105: =SUM(F101:F104) -> 0 | G105: =SUM(G101:G104) -> 0 | H105: =SUM(H101:H104) -> 0 | I105: =SUM(I101:I104) -> 0 | J105: =SUM(J101:J104) -> 0 | K105: =SUM(K101:K104) -> 0 | ... O105: =SUM(O101:O104) -> 0 | P105: =O105 -> 0
A106: Postpaid Consumers
...

Sheet Namwera
A1: SOUTHERN REGION WATER BOARD
A3: MONTHLY REPORTS - 2025/2026
A4: MANGOCHI ZONE
A5: MANGOCHI ZONE
A7: PARAMETERS | C7: UNITS | D7: APRIL | E7: MAY | F7: JUNE | G7: JULY | H7: AUGUST | I7: SEPTEMBER | J7: OCTOBER | K7: NOVEMBER | L7: DECEMBER | M7: JANUARY | N7: FEBRUARY | O7: MARCH | P7: TOTALS
A8: PRODUCTION
A9: Volume Produced | C9: m3 | D9: 3422 | E9: 4964 | P9: =SUM(D9:O9) -> 8386
A10: REVENUE WATER - POSTPAID
A11: Volume Billed Individuals | C11: m3 | D11: 6 | E11: 15 | P11: =SUM(D11:O11) -> 21
A12: Volume Billed CWPs | C12: m3 | P12: =SUM(D12:O12) -> 0
A13: Volume Billed Institutions | C13: m3 | D13: 4 | E13: 3 | P13: =SUM(D13:O13) -> 7
A14: Volume Billed Commercial/Industrial | C14: m3 | P14: =SUM(D14:O14) -> 0
A15: Total Volume Billed Post Paid | C15: m3 | D15: =SUM(D11:D14) -> 10 | E15: =SUM(E11:E14) -> 18 | F15: =SUM(F11:F14) -> 0 | G15: =SUM(G11:G14) -> 0 | H15: =SUM(H11:H14) -> 0 | I15: =SUM(I11:I14) -> 0 | J15: =SUM(J11:J14) -> 0 | K15: =SUM(K11:K14) -> 0 | ... P15: =SUM(P11:P14) -> 28
A16: REVENUE WATER - PREPAID
A17: Individuals | C17: m3 | D17: 2707.1 | E17: 4142.7 | P17: =SUM(D17:O17) -> 6849.8
A18: CWPs | C18: m3 | P18: =SUM(D18:O18) -> 0
A19: Institutions | C19: m3 | D19: 580.3 | E19: 173.6 | P19: =SUM(D19:O19) -> 753.9
A20: Commercial/Industrial | C20: m3 | D20: 11.4 | E20: 16.4 | P20: =SUM(D20:O20) -> 27.8
A21: Total Volume Prepaid | C21: m3 | D21: =SUM(D17:D20) -> 3298.8 | E21: =SUM(E17:E20) -> 4332.7 | F21: =SUM(F17:F20) -> 0 | G21: =SUM(G17:G20) -> 0 | H21: =SUM(H17:H20) -> 0 | I21: =SUM(I17:I20) -> 0 | J21: =SUM(J17:J20) -> 0 | K21: =SUM(K17:K20) -> 0 | ... P21: =SUM(P17:P20) -> 7631.5
A22: TOTAL REVENUE WATER | C22: m3 | D22: =D21+D15 -> 3308.8 | E22: =E21+E15 -> 4350.7 | F22: =F21+F15 -> 0 | G22: =G21+G15 -> 0 | H22: =H21+H15 -> 0 | I22: =I21+I15 -> 0 | J22: =J21+J15 -> 0 | K22: =K21+K15 -> 0 | ... P22: =P21+P15 -> 7659.5
A24: Non-Revenue Water (NRW) | B24: Volume | C24: m3 | D24: =D9-D22 -> 113.2 | E24: =E9-E22 -> 613.3 | F24: =F9-F22 -> 0 | G24: =G9-G22 -> 0 | H24: =H9-H22 -> 0 | I24: =I9-I22 -> 0 | J24: =J9-J22 -> 0 | K24: =K9-K22 -> 0 | ... P24: =P9-P22 -> 726.5
B25: Percentage | C25: % | D25: =D24/D9 -> 0.03308007 | E25: =E24/E9 -> 0.12354956 | F25: =F24/F9 -> #DIV/0! | G25: =G24/G9 -> #DIV/0! | H25: =H24/H9 -> #DIV/0! | I25: =I24/I9 -> #DIV/0! | J25: =J24/J9 -> #DIV/0! | K25: =K24/K9 -> #DIV/0! | ... P25: =P24/P9 -> 0.086632483
A26: OPERATING EXPENSES
A27: Chemicals
A28: Chemical | B28: Rate(MK/kg)
A29: Chlorine | B29: 23929.1 | C29: kg | D29: 4.5 | E29: 4 | P29: =SUM(D29:O29) -> 8.5
C30: kg/mg litre | D30: =D29/(D9/1000) -> 1.3150205 | E30: =E29/(E9/1000) -> 0.80580177 | F30: =F29/(F9/1000) -> #DIV/0! | G30: =G29/(G9/1000) -> #DIV/0! | H30: =H29/(H9/1000) -> #DIV/0! | I30: =I29/(I9/1000) -> #DIV/0! | J30: =J29/(J9/1000) -> #DIV/0! | K30: =K29/(K9/1000) -> #DIV/0! | ... P30: =P29/(P9/1000) -> 1.0135941
A31: Aluminium sulphate | B31: 1090.4 | C31: kg | P31: =SUM(D31:O31) -> 0
C32: kg/mg litre | D32: =D31/(D9/1000) -> 0 | E32: =E31/(E9/1000) -> 0 | F32: =F31/(F9/1000) -> #DIV/0! | G32: =G31/(G9/1000) -> #DIV/0! | H32: =H31/(H9/1000) -> #DIV/0! | I32: =I31/(I9/1000) -> #DIV/0! | J32: =J31/(J9/1000) -> #DIV/0! | K32: =K31/(K9/1000) -> #DIV/0! | ... P32: =P31/(P9/1000) -> 0
A33: Soda | B33: 1228.2886 | C33: kg | P33: =SUM(D33:O33) -> 0
C34: kg/mg litre | D34: =D33/(D9/1000) -> 0 | E34: =E33/(E9/1000) -> 0 | F34: =F33/(F9/1000) -> #DIV/0! | G34: =G33/(G9/1000) -> #DIV/0! | H34: =H33/(H9/1000) -> #DIV/0! | I34: =I33/(I9/1000) -> #DIV/0! | J34: =J33/(J9/1000) -> #DIV/0! | K34: =K33/(K9/1000) -> #DIV/0! | ... P34: =P33/(P9/1000) -> 0
A35: Algae floc | B35: 3726.7258 | C35: litres
C36: litres/mg litre
A37: Sud floc | B37: 3951.5936 | C37: litres | D37: 0 | E37: 0 | F37: 0 | G37: 0 | H37: 0 | I37: 0 | J37: 0 | K37: 0 | L37: 0 | M37: 0 | N37: 0 | O37: 0 | P37: =SUM(D37:O37) -> 0
C38: litres/mg litre | D38: =D37/(D9/1000) -> 0 | E38: =E37/(E9/1000) -> 0 | F38: =F37/(F9/1000) -> #DIV/0! | G38: =G37/(G9/1000) -> #DIV/0! | H38: =H37/(H9/1000) -> #DIV/0! | I38: =I37/(I9/1000) -> #DIV/0! | J38: =J37/(J9/1000) -> #DIV/0! | K38: =K37/(K9/1000) -> #DIV/0! | ... P38: =P37/(P9/1000) -> 0
A39: Potasium permanganate | B39: 1950 | C39: kg | D39: 0 | E39: 0 | F39: 0 | G39: 0 | H39: 0 | I39: 0 | J39: 0 | K39: 0 | L39: 0 | M39: 0 | N39: 0 | O39: 0 | P39: =SUM(D39:O39) -> 0
C40: kg/mg litre | D40: =D39/(D9/1000) -> 0 | E40: =E39/(E9/1000) -> 0 | F40: =F39/(F9/1000) -> #DIV/0! | G40: =G39/(G9/1000) -> #DIV/0! | H40: =H39/(H9/1000) -> #DIV/0! | I40: =I39/(I9/1000) -> #DIV/0! | J40: =J39/(J9/1000) -> #DIV/0! | K40: =K39/(K9/1000) -> #DIV/0! | ... P40: =P39/(P9/1000) -> 0
A41: Cost of Chemicals | C41: Mk | D41: =(D29*$B29)+(D31*$B31)+(D33*$B33)+(D35*$B35)+(D37*$B37)+(D39*$B39) -> 107680.95 | E41: =(E29*$B29)+(E31*$B31)+(E33*$B33)+(E35*$B35)+(E37*$B37)+(E39*$B39) -> 95716.4 | F41: =(F29*$B29)+(F31*$B31)+(F33*$B33)+(F35*$B35)+(F37*$B37)+(F39*$B39) -> 0 | G41: =(G29*$B29)+(G31*$B31)+(G33*$B33)+(G35*$B35)+(G37*$B37)+(G39*$B39) -> 0 | H41: =(H29*$B29)+(H31*$B31)+(H33*$B33)+(H35*$B35)+(H37*$B37)+(H39*$B39) -> 0 | I41: =(I29*$B29)+(I31*$B31)+(I33*$B33)+(I35*$B35)+(I37*$B37)+(I39*$B39) -> 0 | J41: =(J29*$B29)+(J31*$B31)+(J33*$B33)+(J35*$B35)+(J37*$B37)+(J39*$B39) -> 0 | K41: =(K29*$B29)+(K31*$B31)+(K33*$B33)+(K35*$B35)+(K37*$B37)+(K39*$B39) -> 0 | ... O41: =(O29*$B29)+(O31*$B31)+(O33*$B33)+(O35*$B35)+(O37*$B37)+(O39*$B39) -> 0 | P41: =SUM(D41:O41) -> 203397.35
A42: Cost/vol. Produced (chemicals) | C42: Mk/m3 | D42: =D41/D9 -> 31.467256 | E42: =E41/E9 -> 19.282111 | F42: =F41/F9 -> #DIV/0! | G42: =G41/G9 -> #DIV/0! | H42: =H41/H9 -> #DIV/0! | I42: =I41/I9 -> #DIV/0! | J42: =J41/J9 -> #DIV/0! | K42: =K41/K9 -> #DIV/0! | ... P42: =P41/P9 -> 24.254394
A43: Power
A44: Power Usage | C44: Kw | D44: 3342 | E44: 5068 | P44: =SUM(D44:O44) -> 8410
A45: Power/ Vol. Produced | C45: Kw/m3 | D45: =D44/D9 -> 0.97662186 | E45: =E44/E9 -> 1.0209508 | F45: =F44/F9 -> #DIV/0! | G45: =G44/G9 -> #DIV/0! | H45: =H44/H9 -> #DIV/0! | I45: =I44/I9 -> #DIV/0! | J45: =J44/J9 -> #DIV/0! | K45: =K44/K9 -> #DIV/0! | ... P45: =P44/P9 -> 1.0028619
A46: Cost of Power | C46: Mk | D46: =1.165*(16600+(D44*143.5)) -> 578046.21 | E46: =1.165*(16600+(E44*143.5)) -> 866594.57 | F46: =1.165*(16600+(F44*143.5)) -> 19339 | G46: =1.165*(16600+(G44*143.5)) -> 19339 | H46: =1.165*(16600+(H44*143.5)) -> 19339 | I46: =1.165*(16600+(I44*143.5)) -> 19339 | J46: =1.165*(16600+(J44*143.5)) -> 19339 | K46: =1.165*(16600+(K44*143.5)) -> 19339 | ... O46: =1.165*(16600+(O44*143.5)) -> 19339 | P46: =SUM(D46:O46) -> 1638030.8
A47: Cost/vol. Produced | C47: Mk/m3 | D47: =D46/D9 -> 168.92057 | E47: =E46/E9 -> 174.57586 | F47: =F46/F9 -> #DIV/0! | G47: =G46/G9 -> #DIV/0! | H47: =H46/H9 -> #DIV/0! | I47: =I46/I9 -> #DIV/0! | J47: =J46/J9 -> #DIV/0! | K47: =K46/K9 -> #DIV/0! | ... P47: =P46/P9 -> 195.32921
A48: Plant and Vehicle Maintenance
A49: Distances covered | C49: km | P49: =SUM(D49:O49) -> 0
A50: Fuel Used (litres) | C50: litres | P50: =SUM(D50:O50) -> 0
A51: Cost of fuel | C51: Mk | P51: =SUM(D51:O51) -> 0
A52: Maintenance | C52: Mk | P52: =SUM(D52:O52) -> 0
A53: Salaries and Wages
A54: Staff Costs | C54: MK | D54: 4293180.9 | E54: 4203021.7 | P54: =SUM(D54:O54) -> 8496202.6
A55: Wages | C55: MK | D55: 919558.86 | E55: 934400.23 | P55: =SUM(D55:O55) -> 1853959.1
A56: Other Overhead Costs | C56: MK | D56: 239490 | E56: 244920 | P56: =SUM(D56:O56) -> 484410
A57: Operating Costs
A58: Total Operating Costs | C58: MK | D58: =D41+D46+D51+D52+D54+D55+D56 -> 6137956.9 | E58: =E41+E46+E51+E52+E54+E55+E56 -> 6344652.9 | F58: =F41+F46+F51+F52+F54+F55+F56 -> 19339 | G58: =G41+G46+G51+G52+G54+G55+G56 -> 19339 | H58: =H41+H46+H51+H52+H54+H55+H56 -> 19339 | I58: =I41+I46+I51+I52+I54+I55+I56 -> 19339 | J58: =J41+J46+J51+J52+J54+J55+J56 -> 19339 | K58: =K41+K46+K51+K52+K54+K55+K56 -> 19339 | ... O58: =O41+O46+O51+O52+O54+O55+O56 -> 19339 | P58: =SUM(D58:O58) -> 12676000
A59: Cost/Vol. Produced | C59: Mk/m3 | D59: =D58/D9 -> 1793.6753 | E59: =E58/E9 -> 1278.1331 | F59: =F58/F9 -> #DIV/0! | G59: =G58/G9 -> #DIV/0! | H59: =H58/H9 -> #DIV/0! | I59: =I58/I9 -> #DIV/0! | J59: =J58/J9 -> #DIV/0! | K59: =K58/K9 -> #DIV/0! | ... P59: =P58/P9 -> 1511.5669
A60: Cost/Vol. Billed | C60: Mk/m3 | D60: =D58/D22 -> 1855.0402 | E60: =E58/E22 -> 1458.3062 | F60: =F58/F22 -> #DIV/0! | G60: =G58/G22 -> #DIV/0! | H60: =H58/H22 -> #DIV/0! | I60: =I58/I22 -> #DIV/0! | J60: =J58/J22 -> #DIV/0! | K60: =K58/K22 -> #DIV/0! | ... P60: =P58/P22 -> 1654.9383
A61: Permanent Staff Employed | C61: No | D61: 3 | E61: 3 | P61: =O61 -> 0
A62: Staff/Vol.1000m3 of Volume Produced/hour (12 hour day) | C62: No/1000m3 | D62: =(D61*1000*31)/D9 -> 27.177089 | E62: =(E61*1000*31)/E9 -> 18.734891 | F62: =(F61*1000*31)/F9 -> #DIV/0! | G62: =(G61*1000*31)/G9 -> #DIV/0! | H62: =(H61*1000*31)/H9 -> #DIV/0! | I62: =(I61*1000*31)/I9 -> #DIV/0! | J62: =(J61*1000*31)/J9 -> #DIV/0! | K62: =(K61*1000*31)/K9 -> #DIV/0! | ... P62: =(P61*1000*31)/P9 -> 0
A63: Temporary Staff Employed | C63: No | D63: 6 | E63: 6 | P63: =SUM(D63:O63) -> 12
A65: Water Connections and Disconnections
A66: New Individual Water Connections | B66: Brought Forward | C66: No | D66: 76 | E66: 76 | P66: =D66 -> 76
B67: Applied this Month | C67: No | D67: 4 | E67: 13 | P67: =SUM(D67:O67) -> 17
B68: Done this Month Postpaid | C68: No | P68: =SUM(D68:O68) -> 0
B69: Done this Month Prepaid | C69: No | D69: 4 | E69: 5 | P69: =SUM(D69:O69) -> 9
B70: Total Done | C70: No | D70: =D68+D69 -> 4 | E70: =E68+E69 -> 5 | F70: =F68+F69 -> 0 | G70: =G68+G69 -> 0 | H70: =H68+H69 -> 0 | I70: =I68+I69 -> 0 | J70: =J68+J69 -> 0 | K70: =K68+K69 -> 0 | ... P70: =P68+P69 -> 9
B71: Carried Forward | C71: No | D71: =D66+D67-D70 -> 76 | E71: =E66+E67-E70 -> 84 | F71: =F66+F67-F70 -> 0 | G71: =G66+G67-G70 -> 0 | H71: =H66+H67-H70 -> 0 | I71: =I66+I67-I70 -> 0 | J71: =J66+J67-J70 -> 0 | K71: =K66+K67-K70 -> 0 | ... P71: =P66+P67-P70 -> 84
A72: New Institutional Water Connections | B72: Brought Forward | C72: No | P72: =D72 -> 0
B73: Applied this Month | C73: No | P73: =SUM(D73:O73) -> 0
B74: Done this Month Postpaid | C74: No | P74: =SUM(D74:O74) -> 0
B75: Done this Month Prepaid | C75: No | P75: =SUM(D75:O75) -> 0
B76: Total Done | C76: No | D76: =D74+D75 -> 0 | E76: =E74+E75 -> 0 | F76: =F74+F75 -> 0 | G76: =G74+G75 -> 0 | H76: =H74+H75 -> 0 | I76: =I74+I75 -> 0 | J76: =J74+J75 -> 0 | K76: =K74+K75 -> 0 | ... P76: =P74+P75 -> 0
B77: Carried Forward | C77: No | D77: =D72+D73-D76 -> 0 | E77: =E72+E73-E76 -> 0 | F77: =F72+F73-F76 -> 0 | G77: =G72+G73-G76 -> 0 | H77: =H72+H73-H76 -> 0 | I77: =I72+I73-I76 -> 0 | J77: =J72+J73-J76 -> 0 | K77: =K72+K73-K76 -> 0 | ... P77: =P72+P73-P76 -> 0
A78: New Commercial/Industrial Water Connections | B78: Brought Forward | C78: No | P78: =D78 -> 0
B79: Applied this Month | C79: No | P79: =SUM(D79:O79) -> 0
B80: Done this Month Postpaid | C80: No | P80: =SUM(D80:O80) -> 0
B81: Done this Month Prepaid | C81: No | P81: =SUM(D81:O81) -> 0
B82: Total Done | C82: No | D82: =D80+D81 -> 0 | E82: =E80+E81 -> 0 | F82: =F80+F81 -> 0 | G82: =G80+G81 -> 0 | H82: =H80+H81 -> 0 | I82: =I80+I81 -> 0 | J82: =J80+J81 -> 0 | K82: =K80+K81 -> 0 | ... P82: =P80+P81 -> 0
B83: Carried Forward | C83: No | D83: =D78+D79-D82 -> 0 | E83: =E78+E79-E82 -> 0 | F83: =F78+F79-F82 -> 0 | G83: =G78+G79-G82 -> 0 | H83: =H78+H79-H82 -> 0 | I83: =I78+I79-I82 -> 0 | J83: =J78+J79-J82 -> 0 | K83: =K78+K79-K82 -> 0 | ... P83: =P78+P79-P82 -> 0
A84: New CWP | B84: Brought Forward | C84: No | P84: =D84 -> 0
B85: Applied this Month | C85: No | P85: =SUM(D85:O85) -> 0
B86: Done this Month Postpaid | C86: No | P86: =SUM(D86:O86) -> 0
B87: Done this Month Prepaid | C87: No | P87: =SUM(D87:O87) -> 0
B88: Total Done | C88: No | D88: =D86+D87 -> 0 | E88: =E86+E87 -> 0 | F88: =F86+F87 -> 0 | G88: =G86+G87 -> 0 | H88: =H86+H87 -> 0 | I88: =I86+I87 -> 0 | J88: =J86+J87 -> 0 | K88: =K86+K87 -> 0 | ... O88: =O86+O87 -> 0 | P88: =SUM(D88:O88) -> 0
B89: Carried Forward | C89: No | D89: =D84+D85-D88 -> 0 | E89: =E84+E85-E88 -> 0 | F89: =F84+F85-F88 -> 0 | G89: =G84+G85-G88 -> 0 | H89: =H84+H85-H88 -> 0 | I89: =I84+I85-I88 -> 0 | J89: =J84+J85-J88 -> 0 | K89: =K84+K85-K88 -> 0 | ... O89: =O84+O85-O88 -> 0 | P89: =P84+P85-P86-P87 -> 0
A90: Aggregated New Water connections | B90: Brought Forward | C90: No | D90: =D66+D72+D78+D84 -> 76 | E90: =E66+E72+E78+E84 -> 76 | F90: =F66+F72+F78+F84 -> 0 | G90: =G66+G72+G78+G84 -> 0 | H90: =H66+H72+H78+H84 -> 0 | I90: =I66+I72+I78+I84 -> 0 | J90: =J66+J72+J78+J84 -> 0 | K90: =K66+K72+K78+K84 -> 0 | ... O90: =O66+O72+O78+O84 -> 0 | P90: =D90 -> 76
B91: Applied this Month | C91: No | D91: =D67+D73+D79+D85 -> 4 | E91: =E67+E73+E79+E85 -> 13 | F91: =F67+F73+F79+F85 -> 0 | G91: =G67+G73+G79+G85 -> 0 | H91: =H67+H73+H79+H85 -> 0 | I91: =I67+I73+I79+I85 -> 0 | J91: =J67+J73+J79+J85 -> 0 | K91: =K67+K73+K79+K85 -> 0 | ... O91: =O67+O73+O79+O85 -> 0 | P91: =SUM(D91:O91) -> 17
B92: Done this Month Postpaid | C92: No | D92: =D68+D74+D80+D86 -> 0 | E92: =E68+E74+E80+E86 -> 0 | F92: =F68+F74+F80+F86 -> 0 | G92: =G68+G74+G80+G86 -> 0 | H92: =H68+H74+H80+H86 -> 0 | I92: =I68+I74+I80+I86 -> 0 | J92: =J68+J74+J80+J86 -> 0 | K92: =K68+K74+K80+K86 -> 0 | ... O92: =O68+O74+O80+O86 -> 0 | P92: =SUM(D92:O92) -> 0
B93: Done this Month Prepaid | D93: =D69+D75+D81+D87 -> 4 | E93: =E69+E75+E81+E87 -> 5 | F93: =F69+F75+F81+F87 -> 0 | G93: =G69+G75+G81+G87 -> 0 | H93: =H69+H75+H81+H87 -> 0 | I93: =I69+I75+I81+I87 -> 0 | J93: =J69+J75+J81+J87 -> 0 | K93: =K69+K75+K81+K87 -> 0 | ... O93: =O69+O75+O81+O87 -> 0 | P93: =SUM(D93:O93) -> 9
B94: Total Done | C94: No | D94: =D93+D92 -> 4 | E94: =E93+E92 -> 5 | F94: =F93+F92 -> 0 | G94: =G93+G92 -> 0 | H94: =H93+H92 -> 0 | I94: =I93+I92 -> 0 | J94: =J93+J92 -> 0 | K94: =K93+K92 -> 0 | ... P94: =P93+P92 -> 9
B95: Carried Forward | C95: No | D95: =D90+D91-D94 -> 76 | E95: =E90+E91-E94 -> 84 | F95: =F90+F91-F94 -> 0 | G95: =G90+G91-G94 -> 0 | H95: =H90+H91-H94 -> 0 | I95: =I90+I91-I94 -> 0 | J95: =J90+J91-J94 -> 0 | K95: =K90+K91-K94 -> 0 | ... P95: =P90+P91-P94 -> 84
A97: Prepaid Metering
A98: Prepaid Meters Installed | C98: No | D98: 4 | E98: 5 | P98: =SUM(D98:O98) -> 9
A100: Active and Disconnected Accounts
A101: Disconnected Individual Accounts | C101: No | D101: 217 | E101: 217 | P101: =O101 -> 0
A102: Disconnected institutional Accounts | C102: No | P102: =O102 -> 0
A103: Disconnected Commercial/Industrial Accounts | C103: No | P103: =O103 -> 0
A104: Disconnected CWP | C104: No | P104: =O104 -> 0
A105: Total Disconnected Accounts | C105: No | D105: =SUM(D101:D104) -> 217 | E105: =SUM(E101:E104) -> 217 | F105: =SUM(F101:F104) -> 0 | G105: =SUM(G101:G104) -> 0 | H105: =SUM(H101:H104) -> 0 | I105: =SUM(I101:I104) -> 0 | J105: =SUM(J101:J104) -> 0 | K105: =SUM(K101:K104) -> 0 | ... O105: =SUM(O101:O104) -> 0 | P105: =O105 -> 0
A106: Postpaid Consumers
...

Sheet Nkhudzi
A1: SOUTHERN REGION WATER BOARD
A3: MONTHLY REPORTS - 2025/2026
A4: MANGOCHI ZONE
A5: MANGOCHI ZONE
A7: PARAMETERS | C7: UNITS | D7: APRIL | E7: MAY | F7: JUNE | G7: JULY | H7: AUGUST | I7: SEPTEMBER | J7: OCTOBER | K7: NOVEMBER | L7: DECEMBER | M7: JANUARY | N7: FEBRUARY | O7: MARCH | P7: TOTALS
A8: PRODUCTION
A9: Volume Produced | C9: m3 | D9: 33477 | E9: 40074 | P9: =SUM(D9:O9) -> 73551
A10: REVENUE WATER - POSTPAID
A11: Volume Billed Individuals | C11: m3 | D11: 100 | E11: 127 | P11: =SUM(D11:O11) -> 227
A12: Volume Billed CWPs | C12: m3 | P12: =SUM(D12:O12) -> 0
A13: Volume Billed Institutions | C13: m3 | D13: 71 | E13: 332 | P13: =SUM(D13:O13) -> 403
A14: Volume Billed Commercial/Industrial | C14: m3 | D14: 1 | E14: 1 | P14: =SUM(D14:O14) -> 2
A15: Total Volume Billed Post Paid | C15: m3 | D15: =SUM(D11:D14) -> 172 | E15: =SUM(E11:E14) -> 460 | F15: =SUM(F11:F14) -> 0 | G15: =SUM(G11:G14) -> 0 | H15: =SUM(H11:H14) -> 0 | I15: =SUM(I11:I14) -> 0 | J15: =SUM(J11:J14) -> 0 | K15: =SUM(K11:K14) -> 0 | ... P15: =SUM(P11:P14) -> 632
A16: REVENUE WATER - PREPAID
A17: Individuals | C17: m3 | D17: 22914.3 | E17: 25979.5 | P17: =SUM(D17:O17) -> 48893.8
A18: CWPs | C18: m3 | D18: 728.3 | E18: 631.3 | P18: =SUM(D18:O18) -> 1359.6
A19: Institutions | C19: m3 | D19: 628.5 | E19: 339.1 | P19: =SUM(D19:O19) -> 967.6
A20: Commercial/Industrial | C20: m3 | D20: 1261.1 | E20: 1023.9 | P20: =SUM(D20:O20) -> 2285
A21: Total Volume Prepaid | C21: m3 | D21: =SUM(D17:D20) -> 25532.2 | E21: =SUM(E17:E20) -> 27973.8 | F21: =SUM(F17:F20) -> 0 | G21: =SUM(G17:G20) -> 0 | H21: =SUM(H17:H20) -> 0 | I21: =SUM(I17:I20) -> 0 | J21: =SUM(J17:J20) -> 0 | K21: =SUM(K17:K20) -> 0 | ... P21: =SUM(P17:P20) -> 53506
A22: TOTAL REVENUE WATER | C22: m3 | D22: =D21+D15 -> 25704.2 | E22: =E21+E15 -> 28433.8 | F22: =F21+F15 -> 0 | G22: =G21+G15 -> 0 | H22: =H21+H15 -> 0 | I22: =I21+I15 -> 0 | J22: =J21+J15 -> 0 | K22: =K21+K15 -> 0 | ... P22: =P21+P15 -> 54138
A24: Non-Revenue Water (NRW) | B24: Volume | C24: m3 | D24: =D9-D22 -> 7772.8 | E24: =E9-E22 -> 11640.2 | F24: =F9-F22 -> 0 | G24: =G9-G22 -> 0 | H24: =H9-H22 -> 0 | I24: =I9-I22 -> 0 | J24: =J9-J22 -> 0 | K24: =K9-K22 -> 0 | ... P24: =P9-P22 -> 19413
B25: Percentage | C25: % | D25: =D24/D9 -> 0.23218329 | E25: =E24/E9 -> 0.29046763 | F25: =F24/F9 -> #DIV/0! | G25: =G24/G9 -> #DIV/0! | H25: =H24/H9 -> #DIV/0! | I25: =I24/I9 -> #DIV/0! | J25: =J24/J9 -> #DIV/0! | K25: =K24/K9 -> #DIV/0! | ... P25: =P24/P9 -> 0.26393931
A26: OPERATING EXPENSES
A27: Chemicals
A28: Chemical | B28: Rate(MK/kg)
A29: Chlorine | B29: 23929.1 | C29: kg | D29: 64.8 | E29: 74.31 | P29: =SUM(D29:O29) -> 139.11
C30: kg/mg litre | D30: =D29/(D9/1000) -> 1.9356573 | E30: =E29/(E9/1000) -> 1.8543195 | F30: =F29/(F9/1000) -> #DIV/0! | G30: =G29/(G9/1000) -> #DIV/0! | H30: =H29/(H9/1000) -> #DIV/0! | I30: =I29/(I9/1000) -> #DIV/0! | J30: =J29/(J9/1000) -> #DIV/0! | K30: =K29/(K9/1000) -> #DIV/0! | ... P30: =P29/(P9/1000) -> 1.8913407
A31: Aluminium sulphate | B31: 1090.4 | C31: kg | P31: =SUM(D31:O31) -> 0
C32: kg/mg litre | D32: =D31/(D9/1000) -> 0 | E32: =E31/(E9/1000) -> 0 | F32: =F31/(F9/1000) -> #DIV/0! | G32: =G31/(G9/1000) -> #DIV/0! | H32: =H31/(H9/1000) -> #DIV/0! | I32: =I31/(I9/1000) -> #DIV/0! | J32: =J31/(J9/1000) -> #DIV/0! | K32: =K31/(K9/1000) -> #DIV/0! | ... P32: =P31/(P9/1000) -> 0
A33: Soda | B33: 1228.2886 | C33: kg | P33: =SUM(D33:O33) -> 0
C34: kg/mg litre | D34: =D33/(D9/1000) -> 0 | E34: =E33/(E9/1000) -> 0 | F34: =F33/(F9/1000) -> #DIV/0! | G34: =G33/(G9/1000) -> #DIV/0! | H34: =H33/(H9/1000) -> #DIV/0! | I34: =I33/(I9/1000) -> #DIV/0! | J34: =J33/(J9/1000) -> #DIV/0! | K34: =K33/(K9/1000) -> #DIV/0! | ... P34: =P33/(P9/1000) -> 0
A35: Algae floc | B35: 3726.7258 | C35: litres
C36: litres/mg litre
A37: Sud floc | B37: 3951.5936 | C37: litres | D37: 0 | E37: 0 | F37: 0 | G37: 0 | H37: 0 | I37: 0 | J37: 0 | K37: 0 | L37: 0 | M37: 0 | N37: 0 | O37: 0 | P37: =SUM(D37:O37) -> 0
C38: litres/mg litre | D38: =D37/(D9/1000) -> 0 | E38: =E37/(E9/1000) -> 0 | F38: =F37/(F9/1000) -> #DIV/0! | G38: =G37/(G9/1000) -> #DIV/0! | H38: =H37/(H9/1000) -> #DIV/0! | I38: =I37/(I9/1000) -> #DIV/0! | J38: =J37/(J9/1000) -> #DIV/0! | K38: =K37/(K9/1000) -> #DIV/0! | ... P38: =P37/(P9/1000) -> 0
A39: Potasium permanganate | B39: 1950 | C39: kg | D39: 0 | E39: 0 | F39: 0 | G39: 0 | H39: 0 | I39: 0 | J39: 0 | K39: 0 | L39: 0 | M39: 0 | N39: 0 | O39: 0 | P39: =SUM(D39:O39) -> 0
C40: kg/mg litre | D40: =D39/(D9/1000) -> 0 | E40: =E39/(E9/1000) -> 0 | F40: =F39/(F9/1000) -> #DIV/0! | G40: =G39/(G9/1000) -> #DIV/0! | H40: =H39/(H9/1000) -> #DIV/0! | I40: =I39/(I9/1000) -> #DIV/0! | J40: =J39/(J9/1000) -> #DIV/0! | K40: =K39/(K9/1000) -> #DIV/0! | ... P40: =P39/(P9/1000) -> 0
A41: Cost of Chemicals | C41: Mk | D41: =(D29*$B29)+(D31*$B31)+(D33*$B33)+(D35*$B35)+(D37*$B37)+(D39*$B39) -> 1550605.7 | E41: =(E29*$B29)+(E31*$B31)+(E33*$B33)+(E35*$B35)+(E37*$B37)+(E39*$B39) -> 1778171.4 | F41: =(F29*$B29)+(F31*$B31)+(F33*$B33)+(F35*$B35)+(F37*$B37)+(F39*$B39) -> 0 | G41: =(G29*$B29)+(G31*$B31)+(G33*$B33)+(G35*$B35)+(G37*$B37)+(G39*$B39) -> 0 | H41: =(H29*$B29)+(H31*$B31)+(H33*$B33)+(H35*$B35)+(H37*$B37)+(H39*$B39) -> 0 | I41: =(I29*$B29)+(I31*$B31)+(I33*$B33)+(I35*$B35)+(I37*$B37)+(I39*$B39) -> 0 | J41: =(J29*$B29)+(J31*$B31)+(J33*$B33)+(J35*$B35)+(J37*$B37)+(J39*$B39) -> 0 | K41: =(K29*$B29)+(K31*$B31)+(K33*$B33)+(K35*$B35)+(K37*$B37)+(K39*$B39) -> 0 | ... O41: =(O29*$B29)+(O31*$B31)+(O33*$B33)+(O35*$B35)+(O37*$B37)+(O39*$B39) -> 0 | P41: =SUM(D41:O41) -> 3328777.1
A42: Cost/vol. Produced (chemicals) | C42: Mk/m3 | D42: =D41/D9 -> 46.318538 | E42: =E41/E9 -> 44.372197 | F42: =F41/F9 -> #DIV/0! | G42: =G41/G9 -> #DIV/0! | H42: =H41/H9 -> #DIV/0! | I42: =I41/I9 -> #DIV/0! | J42: =J41/J9 -> #DIV/0! | K42: =K41/K9 -> #DIV/0! | ... P42: =P41/P9 -> 45.258081
A43: Power
A44: Power Usage | C44: Kw | D44: 76587 | E44: 112937 | P44: =SUM(D44:O44) -> 189524
A45: Power/ Vol. Produced | C45: Kw/m3 | D45: =D44/D9 -> 2.2877498 | E45: =E44/E9 -> 2.8182113 | F45: =F44/F9 -> #DIV/0! | G45: =G44/G9 -> #DIV/0! | H45: =H44/H9 -> #DIV/0! | I45: =I44/I9 -> #DIV/0! | J45: =J44/J9 -> #DIV/0! | K45: =K44/K9 -> #DIV/0! | ... P45: =P44/P9 -> 2.5767699
A46: Cost of Power | C46: Mk | D46: =1.165*(16600+(D44*143.5)) -> 12822962 | E46: =1.165*(16600+(E44*143.5)) -> 18899864 | F46: =1.165*(16600+(F44*143.5)) -> 19339 | G46: =1.165*(16600+(G44*143.5)) -> 19339 | H46: =1.165*(16600+(H44*143.5)) -> 19339 | I46: =1.165*(16600+(I44*143.5)) -> 19339 | J46: =1.165*(16600+(J44*143.5)) -> 19339 | K46: =1.165*(16600+(K44*143.5)) -> 19339 | ... O46: =1.165*(16600+(O44*143.5)) -> 19339 | P46: =SUM(D46:O46) -> 31916217
A47: Cost/vol. Produced | C47: Mk/m3 | D47: =D46/D9 -> 383.03797 | E47: =E46/E9 -> 471.6241 | F47: =F46/F9 -> #DIV/0! | G47: =G46/G9 -> #DIV/0! | H47: =H46/H9 -> #DIV/0! | I47: =I46/I9 -> #DIV/0! | J47: =J46/J9 -> #DIV/0! | K47: =K46/K9 -> #DIV/0! | ... P47: =P46/P9 -> 433.93314
A48: Plant and Vehicle Maintenance
A49: Distances covered | C49: km | P49: =SUM(D49:O49) -> 0
A50: Fuel Used (litres) | C50: litres | P50: =SUM(D50:O50) -> 0
A51: Cost of fuel | C51: Mk | P51: =SUM(D51:O51) -> 0
A52: Maintenance | C52: Mk | P52: =SUM(D52:O52) -> 0
A53: Salaries and Wages
A54: Staff Costs | C54: MK | D54: 9184266 | E54: 8994697.1 | P54: =SUM(D54:O54) -> 18178963
A55: Wages | C55: MK | D55: 5882632.5 | E55: 5783892 | P55: =SUM(D55:O55) -> 11666524
A56: Other Overhead Costs | C56: MK | D56: 1222470 | E56: 1289470 | P56: =SUM(D56:O56) -> 2511940
A57: Operating Costs
A58: Total Operating Costs | C58: MK | D58: =D41+D46+D51+D52+D54+D55+D56 -> 30662936 | E58: =E41+E46+E51+E52+E54+E55+E56 -> 36746095 | F58: =F41+F46+F51+F52+F54+F55+F56 -> 19339 | G58: =G41+G46+G51+G52+G54+G55+G56 -> 19339 | H58: =H41+H46+H51+H52+H54+H55+H56 -> 19339 | I58: =I41+I46+I51+I52+I54+I55+I56 -> 19339 | J58: =J41+J46+J51+J52+J54+J55+J56 -> 19339 | K58: =K41+K46+K51+K52+K54+K55+K56 -> 19339 | ... O58: =O41+O46+O51+O52+O54+O55+O56 -> 19339 | P58: =SUM(D58:O58) -> 67602421
A59: Cost/Vol. Produced | C59: Mk/m3 | D59: =D58/D9 -> 915.94039 | E59: =E58/E9 -> 916.956 | F59: =F58/F9 -> #DIV/0! | G59: =G58/G9 -> #DIV/0! | H59: =H58/H9 -> #DIV/0! | I59: =I58/I9 -> #DIV/0! | J59: =J58/J9 -> #DIV/0! | K59: =K58/K9 -> #DIV/0! | ... P59: =P58/P9 -> 919.12307
A60: Cost/Vol. Billed | C60: Mk/m3 | D60: =D58/D22 -> 1192.9154 | E60: =E58/E22 -> 1292.3385 | F60: =F58/F22 -> #DIV/0! | G60: =G58/G22 -> #DIV/0! | H60: =H58/H22 -> #DIV/0! | I60: =I58/I22 -> #DIV/0! | J60: =J58/J22 -> #DIV/0! | K60: =K58/K22 -> #DIV/0! | ... P60: =P58/P22 -> 1248.7056
A61: Permanent Staff Employed | C61: No | D61: 9 | E61: 9 | P61: =O61 -> 0
A62: Staff/Vol.1000m3 of Volume Produced/hour (12 hour day) | C62: No/1000m3 | D62: =(D61*1000*31)/D9 -> 8.3340801 | E62: =(E61*1000*31)/E9 -> 6.9621201 | F62: =(F61*1000*31)/F9 -> #DIV/0! | G62: =(G61*1000*31)/G9 -> #DIV/0! | H62: =(H61*1000*31)/H9 -> #DIV/0! | I62: =(I61*1000*31)/I9 -> #DIV/0! | J62: =(J61*1000*31)/J9 -> #DIV/0! | K62: =(K61*1000*31)/K9 -> #DIV/0! | ... P62: =(P61*1000*31)/P9 -> 0
A63: Temporary Staff Employed | C63: No | D63: 42 | E63: 42 | P63: =SUM(D63:O63) -> 84
A65: Water Connections and Disconnections
A66: New Individual Water Connections | B66: Brought Forward | C66: No | D66: 2934 | E66: 2921 | P66: =D66 -> 2934
B67: Applied this Month | C67: No | D67: 40 | E67: 20 | P67: =SUM(D67:O67) -> 60
B68: Done this Month Postpaid | C68: No | P68: =SUM(D68:O68) -> 0
B69: Done this Month Prepaid | C69: No | D69: 53 | E69: 33 | P69: =SUM(D69:O69) -> 86
B70: Total Done | C70: No | D70: =D68+D69 -> 53 | E70: =E68+E69 -> 33 | F70: =F68+F69 -> 0 | G70: =G68+G69 -> 0 | H70: =H68+H69 -> 0 | I70: =I68+I69 -> 0 | J70: =J68+J69 -> 0 | K70: =K68+K69 -> 0 | ... P70: =P68+P69 -> 86
B71: Carried Forward | C71: No | D71: =D66+D67-D70 -> 2921 | E71: =E66+E67-E70 -> 2908 | F71: =F66+F67-F70 -> 0 | G71: =G66+G67-G70 -> 0 | H71: =H66+H67-H70 -> 0 | I71: =I66+I67-I70 -> 0 | J71: =J66+J67-J70 -> 0 | K71: =K66+K67-K70 -> 0 | ... P71: =P66+P67-P70 -> 2908
A72: New Institutional Water Connections | B72: Brought Forward | C72: No | D72: 10 | E72: 10 | P72: =D72 -> 10
B73: Applied this Month | C73: No | P73: =SUM(D73:O73) -> 0
B74: Done this Month Postpaid | C74: No | P74: =SUM(D74:O74) -> 0
B75: Done this Month Prepaid | C75: No | P75: =SUM(D75:O75) -> 0
B76: Total Done | C76: No | D76: =D74+D75 -> 0 | E76: =E74+E75 -> 0 | F76: =F74+F75 -> 0 | G76: =G74+G75 -> 0 | H76: =H74+H75 -> 0 | I76: =I74+I75 -> 0 | J76: =J74+J75 -> 0 | K76: =K74+K75 -> 0 | ... P76: =P74+P75 -> 0
B77: Carried Forward | C77: No | D77: =D72+D73-D76 -> 10 | E77: =E72+E73-E76 -> 10 | F77: =F72+F73-F76 -> 0 | G77: =G72+G73-G76 -> 0 | H77: =H72+H73-H76 -> 0 | I77: =I72+I73-I76 -> 0 | J77: =J72+J73-J76 -> 0 | K77: =K72+K73-K76 -> 0 | ... P77: =P72+P73-P76 -> 10
A78: New Commercial/Industrial Water Connections | B78: Brought Forward | C78: No | D78: 15 | E78: 15 | P78: =D78 -> 15
B79: Applied this Month | C79: No | P79: =SUM(D79:O79) -> 0
B80: Done this Month Postpaid | C80: No | P80: =SUM(D80:O80) -> 0
B81: Done this Month Prepaid | C81: No | P81: =SUM(D81:O81) -> 0
B82: Total Done | C82: No | D82: =D80+D81 -> 0 | E82: =E80+E81 -> 0 | F82: =F80+F81 -> 0 | G82: =G80+G81 -> 0 | H82: =H80+H81 -> 0 | I82: =I80+I81 -> 0 | J82: =J80+J81 -> 0 | K82: =K80+K81 -> 0 | ... P82: =P80+P81 -> 0
B83: Carried Forward | C83: No | D83: =D78+D79-D82 -> 15 | E83: =E78+E79-E82 -> 15 | F83: =F78+F79-F82 -> 0 | G83: =G78+G79-G82 -> 0 | H83: =H78+H79-H82 -> 0 | I83: =I78+I79-I82 -> 0 | J83: =J78+J79-J82 -> 0 | K83: =K78+K79-K82 -> 0 | ... P83: =P78+P79-P82 -> 15
A84: New CWP | B84: Brought Forward | C84: No | P84: =D84 -> 0
B85: Applied this Month | C85: No | P85: =SUM(D85:O85) -> 0
B86: Done this Month Postpaid | C86: No | P86: =SUM(D86:O86) -> 0
B87: Done this Month Prepaid | C87: No | P87: =SUM(D87:O87) -> 0
B88: Total Done | C88: No | D88: =D86+D87 -> 0 | E88: =E86+E87 -> 0 | F88: =F86+F87 -> 0 | G88: =G86+G87 -> 0 | H88: =H86+H87 -> 0 | I88: =I86+I87 -> 0 | J88: =J86+J87 -> 0 | K88: =K86+K87 -> 0 | ... O88: =O86+O87 -> 0 | P88: =SUM(D88:O88) -> 0
B89: Carried Forward | C89: No | D89: =D84+D85-D88 -> 0 | E89: =E84+E85-E88 -> 0 | F89: =F84+F85-F88 -> 0 | G89: =G84+G85-G88 -> 0 | H89: =H84+H85-H88 -> 0 | I89: =I84+I85-I88 -> 0 | J89: =J84+J85-J88 -> 0 | K89: =K84+K85-K88 -> 0 | ... O89: =O84+O85-O88 -> 0 | P89: =P84+P85-P86-P87 -> 0
A90: Aggregated New Water connections | B90: Brought Forward | C90: No | D90: =D66+D72+D78+D84 -> 2959 | E90: =E66+E72+E78+E84 -> 2946 | F90: =F66+F72+F78+F84 -> 0 | G90: =G66+G72+G78+G84 -> 0 | H90: =H66+H72+H78+H84 -> 0 | I90: =I66+I72+I78+I84 -> 0 | J90: =J66+J72+J78+J84 -> 0 | K90: =K66+K72+K78+K84 -> 0 | ... O90: =O66+O72+O78+O84 -> 0 | P90: =D90 -> 2959
B91: Applied this Month | C91: No | D91: =D67+D73+D79+D85 -> 40 | E91: =E67+E73+E79+E85 -> 20 | F91: =F67+F73+F79+F85 -> 0 | G91: =G67+G73+G79+G85 -> 0 | H91: =H67+H73+H79+H85 -> 0 | I91: =I67+I73+I79+I85 -> 0 | J91: =J67+J73+J79+J85 -> 0 | K91: =K67+K73+K79+K85 -> 0 | ... O91: =O67+O73+O79+O85 -> 0 | P91: =SUM(D91:O91) -> 60
B92: Done this Month Postpaid | C92: No | D92: =D68+D74+D80+D86 -> 0 | E92: =E68+E74+E80+E86 -> 0 | F92: =F68+F74+F80+F86 -> 0 | G92: =G68+G74+G80+G86 -> 0 | H92: =H68+H74+H80+H86 -> 0 | I92: =I68+I74+I80+I86 -> 0 | J92: =J68+J74+J80+J86 -> 0 | K92: =K68+K74+K80+K86 -> 0 | ... O92: =O68+O74+O80+O86 -> 0 | P92: =SUM(D92:O92) -> 0
B93: Done this Month Prepaid | D93: =D69+D75+D81+D87 -> 53 | E93: =E69+E75+E81+E87 -> 33 | F93: =F69+F75+F81+F87 -> 0 | G93: =G69+G75+G81+G87 -> 0 | H93: =H69+H75+H81+H87 -> 0 | I93: =I69+I75+I81+I87 -> 0 | J93: =J69+J75+J81+J87 -> 0 | K93: =K69+K75+K81+K87 -> 0 | ... O93: =O69+O75+O81+O87 -> 0 | P93: =SUM(D93:O93) -> 86
B94: Total Done | C94: No | D94: =D93+D92 -> 53 | E94: =E93+E92 -> 33 | F94: =F93+F92 -> 0 | G94: =G93+G92 -> 0 | H94: =H93+H92 -> 0 | I94: =I93+I92 -> 0 | J94: =J93+J92 -> 0 | K94: =K93+K92 -> 0 | ... P94: =P93+P92 -> 86
B95: Carried Forward | C95: No | D95: =D90+D91-D94 -> 2946 | E95: =E90+E91-E94 -> 2933 | F95: =F90+F91-F94 -> 0 | G95: =G90+G91-G94 -> 0 | H95: =H90+H91-H94 -> 0 | I95: =I90+I91-I94 -> 0 | J95: =J90+J91-J94 -> 0 | K95: =K90+K91-K94 -> 0 | ... P95: =P90+P91-P94 -> 2933
A97: Prepaid Metering
A98: Prepaid Meters Installed | C98: No | D98: 53 | E98: 33 | P98: =SUM(D98:O98) -> 86
A100: Active and Disconnected Accounts
A101: Disconnected Individual Accounts | C101: No | D101: 6 | E101: 6 | P101: =O101 -> 0
A102: Disconnected institutional Accounts | C102: No | D102: 3 | E102: 3 | P102: =O102 -> 0
A103: Disconnected Commercial/Industrial Accounts | C103: No | D103: 1 | E103: 1 | P103: =O103 -> 0
A104: Disconnected CWP | C104: No | P104: =O104 -> 0
A105: Total Disconnected Accounts | C105: No | D105: =SUM(D101:D104) -> 10 | E105: =SUM(E101:E104) -> 10 | F105: =SUM(F101:F104) -> 0 | G105: =SUM(G101:G104) -> 0 | H105: =SUM(H101:H104) -> 0 | I105: =SUM(I101:I104) -> 0 | J105: =SUM(J101:J104) -> 0 | K105: =SUM(K101:K104) -> 0 | ... O105: =SUM(O101:O104) -> 0 | P105: =O105 -> 0
A106: Postpaid Consumers
...

Sheet Zone Monthly
A1: SOUTHERN REGION WATER BOARD
A3: MONTHLY REPORTS - 2025/2026
A4: MANGOCHI ZONE
A5: MANGOCHI ZONE
A7: PARAMETERS | C7: UNITS | D7: APRIL | E7: MAY | F7: JUNE | G7: JULY | H7: AUGUST | I7: SEPTEMBER | J7: OCTOBER | K7: NOVEMBER | L7: DECEMBER | M7: JANUARY | N7: FEBRUARY | O7: MARCH | P7: TOTALS
A8: PRODUCTION
A9: Volume Produced | C9: m3 | D9: =Mangochi!D9+'Monkey Bay'!D9+Namwera!D9+Nkhudzi!D9 -> 247660 | E9: =Mangochi!E9+'Monkey Bay'!E9+Namwera!E9+Nkhudzi!E9 -> 255935 | F9: =Mangochi!F9+'Monkey Bay'!F9+Namwera!F9+Nkhudzi!F9 -> 0 | G9: =Mangochi!G9+'Monkey Bay'!G9+Namwera!G9+Nkhudzi!G9 -> 0 | H9: =Mangochi!H9+'Monkey Bay'!H9+Namwera!H9+Nkhudzi!H9 -> 0 | I9: =Mangochi!I9+'Monkey Bay'!I9+Namwera!I9+Nkhudzi!I9 -> 0 | J9: =Mangochi!J9+'Monkey Bay'!J9+Namwera!J9+Nkhudzi!J9 -> 0 | K9: =Mangochi!K9+'Monkey Bay'!K9+Namwera!K9+Nkhudzi!K9 -> 0 | ... O9: =Mangochi!O9+'Monkey Bay'!O9+Namwera!O9+Nkhudzi!O9 -> 0 | P9: =SUM(D9:O9) -> 503595
A10: REVENUE WATER - POSTPAID
A11: Volume Billed Individuals | C11: m3 | D11: =Mangochi!D11+'Monkey Bay'!D11+Namwera!D11+Nkhudzi!D11 -> 71261 | E11: =Mangochi!E11+'Monkey Bay'!E11+Namwera!E11+Nkhudzi!E11 -> 78663 | F11: =Mangochi!F11+'Monkey Bay'!F11+Namwera!F11+Nkhudzi!F11 -> 0 | G11: =Mangochi!G11+'Monkey Bay'!G11+Namwera!G11+Nkhudzi!G11 -> 0 | H11: =Mangochi!H11+'Monkey Bay'!H11+Namwera!H11+Nkhudzi!H11 -> 0 | I11: =Mangochi!I11+'Monkey Bay'!I11+Namwera!I11+Nkhudzi!I11 -> 0 | J11: =Mangochi!J11+'Monkey Bay'!J11+Namwera!J11+Nkhudzi!J11 -> 0 | K11: =Mangochi!K11+'Monkey Bay'!K11+Namwera!K11+Nkhudzi!K11 -> 0 | ... O11: =Mangochi!O11+'Monkey Bay'!O11+Namwera!O11+Nkhudzi!O11 -> 0 | P11: =SUM(D11:O11) -> 149924
A12: Volume Billed CWPs | C12: m3 | D12: =Mangochi!D12+'Monkey Bay'!D12+Namwera!D12+Nkhudzi!D12 -> 0 | E12: =Mangochi!E12+'Monkey Bay'!E12+Namwera!E12+Nkhudzi!E12 -> 0 | F12: =Mangochi!F12+'Monkey Bay'!F12+Namwera!F12+Nkhudzi!F12 -> 0 | G12: =Mangochi!G12+'Monkey Bay'!G12+Namwera!G12+Nkhudzi!G12 -> 0 | H12: =Mangochi!H12+'Monkey Bay'!H12+Namwera!H12+Nkhudzi!H12 -> 0 | I12: =Mangochi!I12+'Monkey Bay'!I12+Namwera!I12+Nkhudzi!I12 -> 0 | J12: =Mangochi!J12+'Monkey Bay'!J12+Namwera!J12+Nkhudzi!J12 -> 0 | K12: =Mangochi!K12+'Monkey Bay'!K12+Namwera!K12+Nkhudzi!K12 -> 0 | ... O12: =Mangochi!O12+'Monkey Bay'!O12+Namwera!O12+Nkhudzi!O12 -> 0 | P12: =SUM(D12:O12) -> 0
A13: Volume Billed Institutions | C13: m3 | D13: =Mangochi!D13+'Monkey Bay'!D13+Namwera!D13+Nkhudzi!D13 -> 4476 | E13: =Mangochi!E13+'Monkey Bay'!E13+Namwera!E13+Nkhudzi!E13 -> 5153 | F13: =Mangochi!F13+'Monkey Bay'!F13+Namwera!F13+Nkhudzi!F13 -> 0 | G13: =Mangochi!G13+'Monkey Bay'!G13+Namwera!G13+Nkhudzi!G13 -> 0 | H13: =Mangochi!H13+'Monkey Bay'!H13+Namwera!H13+Nkhudzi!H13 -> 0 | I13: =Mangochi!I13+'Monkey Bay'!I13+Namwera!I13+Nkhudzi!I13 -> 0 | J13: =Mangochi!J13+'Monkey Bay'!J13+Namwera!J13+Nkhudzi!J13 -> 0 | K13: =Mangochi!K13+'Monkey Bay'!K13+Namwera!K13+Nkhudzi!K13 -> 0 | ... O13: =Mangochi!O13+'Monkey Bay'!O13+Namwera!O13+Nkhudzi!O13 -> 0 | P13: =SUM(D13:O13) -> 9629
A14: Volume Billed Commercial/Industrial | C14: m3 | D14: =Mangochi!D14+'Monkey Bay'!D14+Namwera!D14+Nkhudzi!D14 -> 65 | E14: =Mangochi!E14+'Monkey Bay'!E14+Namwera!E14+Nkhudzi!E14 -> 80 | F14: =Mangochi!F14+'Monkey Bay'!F14+Namwera!F14+Nkhudzi!F14 -> 0 | G14: =Mangochi!G14+'Monkey Bay'!G14+Namwera!G14+Nkhudzi!G14 -> 0 | H14: =Mangochi!H14+'Monkey Bay'!H14+Namwera!H14+Nkhudzi!H14 -> 0 | I14: =Mangochi!I14+'Monkey Bay'!I14+Namwera!I14+Nkhudzi!I14 -> 0 | J14: =Mangochi!J14+'Monkey Bay'!J14+Namwera!J14+Nkhudzi!J14 -> 0 | K14: =Mangochi!K14+'Monkey Bay'!K14+Namwera!K14+Nkhudzi!K14 -> 0 | ... O14: =Mangochi!O14+'Monkey Bay'!O14+Namwera!O14+Nkhudzi!O14 -> 0 | P14: =SUM(D14:O14) -> 145
A15: Total Volume Billed Post Paid | C15: m3 | D15: =SUM(D11:D14) -> 75802 | E15: =SUM(E11:E14) -> 83896 | F15: =SUM(F11:F14) -> 0 | G15: =SUM(G11:G14) -> 0 | H15: =SUM(H11:H14) -> 0 | I15: =SUM(I11:I14) -> 0 | J15: =SUM(J11:J14) -> 0 | K15: =SUM(K11:K14) -> 0 | ... P15: =SUM(P11:P14) -> 159698
A16: REVENUE WATER - PREPAID
A17: Individuals | C17: m3 | D17: =Mangochi!D17+'Monkey Bay'!D17+Namwera!D17+Nkhudzi!D17 -> 59225.6 | E17: =Mangochi!E17+'Monkey Bay'!E17+Namwera!E17+Nkhudzi!E17 -> 69450.7 | F17: =Mangochi!F17+'Monkey Bay'!F17+Namwera!F17+Nkhudzi!F17 -> 0 | G17: =Mangochi!G17+'Monkey Bay'!G17+Namwera!G17+Nkhudzi!G17 -> 0 | H17: =Mangochi!H17+'Monkey Bay'!H17+Namwera!H17+Nkhudzi!H17 -> 0 | I17: =Mangochi!I17+'Monkey Bay'!I17+Namwera!I17+Nkhudzi!I17 -> 0 | J17: =Mangochi!J17+'Monkey Bay'!J17+Namwera!J17+Nkhudzi!J17 -> 0 | K17: =Mangochi!K17+'Monkey Bay'!K17+Namwera!K17+Nkhudzi!K17 -> 0 | ... O17: =Mangochi!O17+'Monkey Bay'!O17+Namwera!O17+Nkhudzi!O17 -> 0 | P17: =SUM(D17:O17) -> 128676.3
A18: CWPs | C18: m3 | D18: =Mangochi!D18+'Monkey Bay'!D18+Namwera!D18+Nkhudzi!D18 -> 6557.9 | E18: =Mangochi!E18+'Monkey Bay'!E18+Namwera!E18+Nkhudzi!E18 -> 6254.8 | F18: =Mangochi!F18+'Monkey Bay'!F18+Namwera!F18+Nkhudzi!F18 -> 0 | G18: =Mangochi!G18+'Monkey Bay'!G18+Namwera!G18+Nkhudzi!G18 -> 0 | H18: =Mangochi!H18+'Monkey Bay'!H18+Namwera!H18+Nkhudzi!H18 -> 0 | I18: =Mangochi!I18+'Monkey Bay'!I18+Namwera!I18+Nkhudzi!I18 -> 0 | J18: =Mangochi!J18+'Monkey Bay'!J18+Namwera!J18+Nkhudzi!J18 -> 0 | K18: =Mangochi!K18+'Monkey Bay'!K18+Namwera!K18+Nkhudzi!K18 -> 0 | ... O18: =Mangochi!O18+'Monkey Bay'!O18+Namwera!O18+Nkhudzi!O18 -> 0 | P18: =SUM(D18:O18) -> 12812.7
A19: Institutions | C19: m3 | D19: =Mangochi!D19+'Monkey Bay'!D19+Namwera!D19+Nkhudzi!D19 -> 9056.6 | E19: =Mangochi!E19+'Monkey Bay'!E19+Namwera!E19+Nkhudzi!E19 -> 8118.3 | F19: =Mangochi!F19+'Monkey Bay'!F19+Namwera!F19+Nkhudzi!F19 -> 0 | G19: =Mangochi!G19+'Monkey Bay'!G19+Namwera!G19+Nkhudzi!G19 -> 0 | H19: =Mangochi!H19+'Monkey Bay'!H19+Namwera!H19+Nkhudzi!H19 -> 0 | I19: =Mangochi!I19+'Monkey Bay'!I19+Namwera!I19+Nkhudzi!I19 -> 0 | J19: =Mangochi!J19+'Monkey Bay'!J19+Namwera!J19+Nkhudzi!J19 -> 0 | K19: =Mangochi!K19+'Monkey Bay'!K19+Namwera!K19+Nkhudzi!K19 -> 0 | ... O19: =Mangochi!O19+'Monkey Bay'!O19+Namwera!O19+Nkhudzi!O19 -> 0 | P19: =SUM(D19:O19) -> 17174.9
A20: Commercial/Industrial | C20: m3 | D20: =Mangochi!D20+'Monkey Bay'!D20+Namwera!D20+Nkhudzi!D20 -> 3615.4 | E20: =Mangochi!E20+'Monkey Bay'!E20+Namwera!E20+Nkhudzi!E20 -> 4196.8 | F20: =Mangochi!F20+'Monkey Bay'!F20+Namwera!F20+Nkhudzi!F20 -> 0 | G20: =Mangochi!G20+'Monkey Bay'!G20+Namwera!G20+Nkhudzi!G20 -> 0 | H20: =Mangochi!H20+'Monkey Bay'!H20+Namwera!H20+Nkhudzi!H20 -> 0 | I20: =Mangochi!I20+'Monkey Bay'!I20+Namwera!I20+Nkhudzi!I20 -> 0 | J20: =Mangochi!J20+'Monkey Bay'!J20+Namwera!J20+Nkhudzi!J20 -> 0 | K20: =Mangochi!K20+'Monkey Bay'!K20+Namwera!K20+Nkhudzi!K20 -> 0 | ... O20: =Mangochi!O20+'Monkey Bay'!O20+Namwera!O20+Nkhudzi!O20 -> 0 | P20: =SUM(D20:O20) -> 7812.2
A21: Total Volume Prepaid | C21: m3 | D21: =SUM(D17:D20) -> 78455.5 | E21: =SUM(E17:E20) -> 88020.6 | F21: =SUM(F17:F20) -> 0 | G21: =SUM(G17:G20) -> 0 | H21: =SUM(H17:H20) -> 0 | I21: =SUM(I17:I20) -> 0 | J21: =SUM(J17:J20) -> 0 | K21: =SUM(K17:K20) -> 0 | ... P21: =SUM(P17:P20) -> 166476.1
A22: TOTAL REVENUE WATER | C22: m3 | D22: =D21+D15 -> 154257.5 | E22: =E21+E15 -> 171916.6 | F22: =F21+F15 -> 0 | G22: =G21+G15 -> 0 | H22: =H21+H15 -> 0 | I22: =I21+I15 -> 0 | J22: =J21+J15 -> 0 | K22: =K21+K15 -> 0 | ... P22: =P21+P15 -> 326174.1
A24: Non-Revenue Water (NRW) | B24: Volume | C24: m3 | D24: =D9-D22 -> 93402.5 | E24: =E9-E22 -> 84018.4 | F24: =F9-F22 -> 0 | G24: =G9-G22 -> 0 | H24: =H9-H22 -> 0 | I24: =I9-I22 -> 0 | J24: =J9-J22 -> 0 | K24: =K9-K22 -> 0 | ... P24: =P9-P22 -> 177420.9
B25: Percentage | C25: % | D25: =D24/D9 -> 0.37714003 | E25: =E24/E9 -> 0.32828023 | F25: =F24/F9 -> #DIV/0! | G25: =G24/G9 -> #DIV/0! | H25: =H24/H9 -> #DIV/0! | I25: =I24/I9 -> #DIV/0! | J25: =J24/J9 -> #DIV/0! | K25: =K24/K9 -> #DIV/0! | ... P25: =P24/P9 -> 0.3523087
A26: OPERATING EXPENSES
A27: Chemicals
A28: Chemical | B28: Rate(MK/kg)
A29: Chlorine | B29: 23929.1 | C29: kg | D29: =Mangochi!D29+'Monkey Bay'!D29+Namwera!D29+Nkhudzi!D29 -> 694.5 | E29: =Mangochi!E29+'Monkey Bay'!E29+Namwera!E29+Nkhudzi!E29 -> 718.5 | F29: =Mangochi!F29+'Monkey Bay'!F29+Namwera!F29+Nkhudzi!F29 -> 0 | G29: =Mangochi!G29+'Monkey Bay'!G29+Namwera!G29+Nkhudzi!G29 -> 0 | H29: =Mangochi!H29+'Monkey Bay'!H29+Namwera!H29+Nkhudzi!H29 -> 0 | I29: =Mangochi!I29+'Monkey Bay'!I29+Namwera!I29+Nkhudzi!I29 -> 0 | J29: =Mangochi!J29+'Monkey Bay'!J29+Namwera!J29+Nkhudzi!J29 -> 0 | K29: =Mangochi!K29+'Monkey Bay'!K29+Namwera!K29+Nkhudzi!K29 -> 0 | ... O29: =Mangochi!O29+'Monkey Bay'!O29+Namwera!O29+Nkhudzi!O29 -> 0 | P29: =SUM(D29:O29) -> 1413
C30: kg/mg litre | D30: =Mangochi!D30+'Monkey Bay'!D30+Namwera!D30+Nkhudzi!D30 -> 8.6115359 | E30: =Mangochi!E30+'Monkey Bay'!E30+Namwera!E30+Nkhudzi!E30 -> 8.0512323 | F30: =Mangochi!F30+'Monkey Bay'!F30+Namwera!F30+Nkhudzi!F30 -> #DIV/0! | G30: =Mangochi!G30+'Monkey Bay'!G30+Namwera!G30+Nkhudzi!G30 -> #DIV/0! | H30: =Mangochi!H30+'Monkey Bay'!H30+Namwera!H30+Nkhudzi!H30 -> #DIV/0! | I30: =Mangochi!I30+'Monkey Bay'!I30+Namwera!I30+Nkhudzi!I30 -> #DIV/0! | J30: =Mangochi!J30+'Monkey Bay'!J30+Namwera!J30+Nkhudzi!J30 -> #DIV/0! | K30: =Mangochi!K30+'Monkey Bay'!K30+Namwera!K30+Nkhudzi!K30 -> #DIV/0! | ... O30: =Mangochi!O30+'Monkey Bay'!O30+Namwera!O30+Nkhudzi!O30 -> #DIV/0! | P30: =P29/(P9/1000) -> 2.8058261
A31: Aluminium sulphate | B31: 1090.4 | C31: kg | D31: =Mangochi!D31+'Monkey Bay'!D31+Namwera!D31+Nkhudzi!D31 -> 0 | E31: =Mangochi!E31+'Monkey Bay'!E31+Namwera!E31+Nkhudzi!E31 -> 0 | F31: =Mangochi!F31+'Monkey Bay'!F31+Namwera!F31+Nkhudzi!F31 -> 0 | G31: =Mangochi!G31+'Monkey Bay'!G31+Namwera!G31+Nkhudzi!G31 -> 0 | H31: =Mangochi!H31+'Monkey Bay'!H31+Namwera!H31+Nkhudzi!H31 -> 0 | I31: =Mangochi!I31+'Monkey Bay'!I31+Namwera!I31+Nkhudzi!I31 -> 0 | J31: =Mangochi!J31+'Monkey Bay'!J31+Namwera!J31+Nkhudzi!J31 -> 0 | K31: =Mangochi!K31+'Monkey Bay'!K31+Namwera!K31+Nkhudzi!K31 -> 0 | L31: =Mangochi!L31+'Monkey Bay'!L31+Namwera!L31+Nkhudzi!L31 -> 0 | M31: =Mangochi!M31+'Monkey Bay'!M31+Namwera!M31 -> 0 | N31: =Mangochi!N31+'Monkey Bay'!N31+Namwera!N31 -> 0 | O31: =Mangochi!O31+'Monkey Bay'!O31+Namwera!O31 -> 0 | P31: =SUM(D31:O31) -> 0
C32: kg/mg litre | D32: =Mangochi!D32+'Monkey Bay'!D32+Namwera!D32+Nkhudzi!D32 -> 0 | E32: =Mangochi!E32+'Monkey Bay'!E32+Namwera!E32+Nkhudzi!E32 -> 0 | F32: =Mangochi!F32+'Monkey Bay'!F32+Namwera!F32+Nkhudzi!F32 -> #DIV/0! | G32: =Mangochi!G32+'Monkey Bay'!G32+Namwera!G32+Nkhudzi!G32 -> #DIV/0! | H32: =Mangochi!H32+'Monkey Bay'!H32+Namwera!H32+Nkhudzi!H32 -> #DIV/0! | I32: =Mangochi!I32+'Monkey Bay'!I32+Namwera!I32+Nkhudzi!I32 -> #DIV/0! | J32: =Mangochi!J32+'Monkey Bay'!J32+Namwera!J32+Nkhudzi!J32 -> #DIV/0! | K32: =Mangochi!K32+'Monkey Bay'!K32+Namwera!K32+Nkhudzi!K32 -> #DIV/0! | L32: =Mangochi!L32+'Monkey Bay'!L32+Namwera!L32+Nkhudzi!L32 -> #DIV/0! | M32: =Mangochi!M32+'Monkey Bay'!M32+Namwera!M32 -> #DIV/0! | N32: =Mangochi!N32+'Monkey Bay'!N32+Namwera!N32 -> #DIV/0! | O32: =Mangochi!O32+'Monkey Bay'!O32+Namwera!O32 -> #DIV/0! | P32: =P31/(P9/1000) -> 0
A33: Soda | B33: 1228.2886 | C33: kg | D33: =Mangochi!D33+'Monkey Bay'!D33+Namwera!D33+Nkhudzi!D33 -> 0 | E33: =Mangochi!E33+'Monkey Bay'!E33+Namwera!E33+Nkhudzi!E33 -> 0 | F33: =Mangochi!F33+'Monkey Bay'!F33+Namwera!F33+Nkhudzi!F33 -> 0 | G33: =Mangochi!G33+'Monkey Bay'!G33+Namwera!G33+Nkhudzi!G33 -> 0 | H33: =Mangochi!H33+'Monkey Bay'!H33+Namwera!H33+Nkhudzi!H33 -> 0 | I33: =Mangochi!I33+'Monkey Bay'!I33+Namwera!I33+Nkhudzi!I33 -> 0 | J33: =Mangochi!J33+'Monkey Bay'!J33+Namwera!J33+Nkhudzi!J33 -> 0 | K33: =Mangochi!K33+'Monkey Bay'!K33+Namwera!K33+Nkhudzi!K33 -> 0 | L33: =Mangochi!L33+'Monkey Bay'!L33+Namwera!L33+Nkhudzi!L33 -> 0 | M33: =Mangochi!M33+'Monkey Bay'!M33+Namwera!M33 -> 0 | N33: =Mangochi!N33+'Monkey Bay'!N33+Namwera!N33 -> 0 | O33: =Mangochi!O33+'Monkey Bay'!O33+Namwera!O33 -> 0 | P33: =SUM(D33:O33) -> 0
C34: kg/mg litre | D34: =Mangochi!D34+'Monkey Bay'!D34+Namwera!D34+Nkhudzi!D34 -> 0 | E34: =Mangochi!E34+'Monkey Bay'!E34+Namwera!E34+Nkhudzi!E34 -> 0 | F34: =Mangochi!F34+'Monkey Bay'!F34+Namwera!F34+Nkhudzi!F34 -> #DIV/0! | G34: =Mangochi!G34+'Monkey Bay'!G34+Namwera!G34+Nkhudzi!G34 -> #DIV/0! | H34: =Mangochi!H34+'Monkey Bay'!H34+Namwera!H34+Nkhudzi!H34 -> #DIV/0! | I34: =Mangochi!I34+'Monkey Bay'!I34+Namwera!I34+Nkhudzi!I34 -> #DIV/0! | J34: =Mangochi!J34+'Monkey Bay'!J34+Namwera!J34+Nkhudzi!J34 -> #DIV/0! | K34: =Mangochi!K34+'Monkey Bay'!K34+Namwera!K34+Nkhudzi!K34 -> #DIV/0! | L34: =Mangochi!L34+'Monkey Bay'!L34+Namwera!L34+Nkhudzi!L34 -> #DIV/0! | M34: =Mangochi!M34+'Monkey Bay'!M34+Namwera!M34 -> #DIV/0! | N34: =Mangochi!N34+'Monkey Bay'!N34+Namwera!N34 -> #DIV/0! | O34: =Mangochi!O34+'Monkey Bay'!O34+Namwera!O34 -> #DIV/0! | P34: =P33/(P9/1000) -> 0
A35: Algae floc | B35: 3726.7258 | C35: litres | D35: =Mangochi!D35+'Monkey Bay'!D35+Namwera!D35+Nkhudzi!D35 -> 0 | E35: =Mangochi!E35+'Monkey Bay'!E35+Namwera!E35+Nkhudzi!E35 -> 0 | F35: =Mangochi!F35+'Monkey Bay'!F35+Namwera!F35+Nkhudzi!F35 -> 0 | G35: =Mangochi!G35+'Monkey Bay'!G35+Namwera!G35+Nkhudzi!G35 -> 0 | H35: =Mangochi!H35+'Monkey Bay'!H35+Namwera!H35+Nkhudzi!H35 -> 0 | I35: =Mangochi!I35+'Monkey Bay'!I35+Namwera!I35+Nkhudzi!I35 -> 0 | J35: =Mangochi!J35+'Monkey Bay'!J35+Namwera!J35+Nkhudzi!J35 -> 0 | K35: =Mangochi!K35+'Monkey Bay'!K35+Namwera!K35+Nkhudzi!K35 -> 0 | L35: =Mangochi!L35+'Monkey Bay'!L35+Namwera!L35+Nkhudzi!L35 -> 0 | M35: =Mangochi!M35+'Monkey Bay'!M35+Namwera!M35 -> 0 | N35: =Mangochi!N35+'Monkey Bay'!N35+Namwera!N35 -> 0 | O35: =Mangochi!O35+'Monkey Bay'!O35+Namwera!O35 -> 0
C36: litres/mg litre | D36: =Mangochi!D36+'Monkey Bay'!D36+Namwera!D36+Nkhudzi!D36 -> 0 | E36: =Mangochi!E36+'Monkey Bay'!E36+Namwera!E36+Nkhudzi!E36 -> 0 | F36: =Mangochi!F36+'Monkey Bay'!F36+Namwera!F36+Nkhudzi!F36 -> 0 | G36: =Mangochi!G36+'Monkey Bay'!G36+Namwera!G36+Nkhudzi!G36 -> 0 | H36: =Mangochi!H36+'Monkey Bay'!H36+Namwera!H36+Nkhudzi!H36 -> 0 | I36: =Mangochi!I36+'Monkey Bay'!I36+Namwera!I36+Nkhudzi!I36 -> 0 | J36: =Mangochi!J36+'Monkey Bay'!J36+Namwera!J36+Nkhudzi!J36 -> 0 | K36: =Mangochi!K36+'Monkey Bay'!K36+Namwera!K36+Nkhudzi!K36 -> 0 | L36: =Mangochi!L36+'Monkey Bay'!L36+Namwera!L36+Nkhudzi!L36 -> 0
A37: Sud floc | B37: 3951.5936 | C37: litres | D37: =Mangochi!D37+'Monkey Bay'!D37+Namwera!D37+Nkhudzi!D37 -> 0 | E37: =Mangochi!E37+'Monkey Bay'!E37+Namwera!E37+Nkhudzi!E37 -> 0 | F37: =Mangochi!F37+'Monkey Bay'!F37+Namwera!F37+Nkhudzi!F37 -> 0 | G37: =Mangochi!G37+'Monkey Bay'!G37+Namwera!G37+Nkhudzi!G37 -> 0 | H37: =Mangochi!H37+'Monkey Bay'!H37+Namwera!H37+Nkhudzi!H37 -> 0 | I37: =Mangochi!I37+'Monkey Bay'!I37+Namwera!I37+Nkhudzi!I37 -> 0 | J37: =Mangochi!J37+'Monkey Bay'!J37+Namwera!J37+Nkhudzi!J37 -> 0 | K37: =Mangochi!K37+'Monkey Bay'!K37+Namwera!K37+Nkhudzi!K37 -> 0 | L37: =Mangochi!L37+'Monkey Bay'!L37+Namwera!L37+Nkhudzi!L37 -> 0 | M37: =Mangochi!M37+'Monkey Bay'!M37+Namwera!M37 -> 0 | N37: =Mangochi!N37+'Monkey Bay'!N37+Namwera!N37 -> 0 | O37: =Mangochi!O37+'Monkey Bay'!O37+Namwera!O37 -> 0 | P37: =SUM(D37:O37) -> 0
C38: litres/mg litre | D38: =Mangochi!D38+'Monkey Bay'!D38+Namwera!D38+Nkhudzi!D38 -> 0 | E38: =Mangochi!E38+'Monkey Bay'!E38+Namwera!E38+Nkhudzi!E38 -> 0 | F38: =Mangochi!F38+'Monkey Bay'!F38+Namwera!F38+Nkhudzi!F38 -> #DIV/0! | G38: =Mangochi!G38+'Monkey Bay'!G38+Namwera!G38+Nkhudzi!G38 -> #DIV/0! | H38: =Mangochi!H38+'Monkey Bay'!H38+Namwera!H38+Nkhudzi!H38 -> #DIV/0! | I38: =Mangochi!I38+'Monkey Bay'!I38+Namwera!I38+Nkhudzi!I38 -> #DIV/0! | J38: =Mangochi!J38+'Monkey Bay'!J38+Namwera!J38+Nkhudzi!J38 -> #DIV/0! | K38: =Mangochi!K38+'Monkey Bay'!K38+Namwera!K38+Nkhudzi!K38 -> #DIV/0! | L38: =Mangochi!L38+'Monkey Bay'!L38+Namwera!L38+Nkhudzi!L38 -> #DIV/0! | M38: =Mangochi!M38+'Monkey Bay'!M38+Namwera!M38 -> #DIV/0! | N38: =Mangochi!N38+'Monkey Bay'!N38+Namwera!N38 -> #DIV/0! | O38: =Mangochi!O38+'Monkey Bay'!O38+Namwera!O38 -> #DIV/0! | P38: =P37/(P9/1000) -> 0
A39: Potasium permanganate | B39: 1950 | C39: kg | D39: =Mangochi!D39+'Monkey Bay'!D39+Namwera!D39+Nkhudzi!D39 -> 0 | E39: =Mangochi!E39+'Monkey Bay'!E39+Namwera!E39+Nkhudzi!E39 -> 0 | F39: =Mangochi!F39+'Monkey Bay'!F39+Namwera!F39+Nkhudzi!F39 -> 0 | G39: =Mangochi!G39+'Monkey Bay'!G39+Namwera!G39+Nkhudzi!G39 -> 0 | H39: =Mangochi!H39+'Monkey Bay'!H39+Namwera!H39+Nkhudzi!H39 -> 0 | I39: =Mangochi!I39+'Monkey Bay'!I39+Namwera!I39+Nkhudzi!I39 -> 0 | J39: =Mangochi!J39+'Monkey Bay'!J39+Namwera!J39+Nkhudzi!J39 -> 0 | K39: =Mangochi!K39+'Monkey Bay'!K39+Namwera!K39+Nkhudzi!K39 -> 0 | L39: =Mangochi!L39+'Monkey Bay'!L39+Namwera!L39+Nkhudzi!L39 -> 0 | M39: =Mangochi!M39+'Monkey Bay'!M39+Namwera!M39 -> 0 | N39: =Mangochi!N39+'Monkey Bay'!N39+Namwera!N39 -> 0 | O39: =Mangochi!O39+'Monkey Bay'!O39+Namwera!O39 -> 0 | P39: =SUM(D39:O39) -> 0
C40: kg/mg litre | D40: =Mangochi!D40+'Monkey Bay'!D40+Namwera!D40+Nkhudzi!D40 -> 0 | E40: =Mangochi!E40+'Monkey Bay'!E40+Namwera!E40+Nkhudzi!E40 -> 0 | F40: =Mangochi!F40+'Monkey Bay'!F40+Namwera!F40+Nkhudzi!F40 -> #DIV/0! | G40: =Mangochi!G40+'Monkey Bay'!G40+Namwera!G40+Nkhudzi!G40 -> #DIV/0! | H40: =Mangochi!H40+'Monkey Bay'!H40+Namwera!H40+Nkhudzi!H40 -> #DIV/0! | I40: =Mangochi!I40+'Monkey Bay'!I40+Namwera!I40+Nkhudzi!I40 -> #DIV/0! | J40: =Mangochi!J40+'Monkey Bay'!J40+Namwera!J40+Nkhudzi!J40 -> #DIV/0! | K40: =Mangochi!K40+'Monkey Bay'!K40+Namwera!K40+Nkhudzi!K40 -> #DIV/0! | L40: =Mangochi!L40+'Monkey Bay'!L40+Namwera!L40+Nkhudzi!L40 -> #DIV/0! | M40: =Mangochi!M40+'Monkey Bay'!M40+Namwera!M40 -> #DIV/0! | N40: =Mangochi!N40+'Monkey Bay'!N40+Namwera!N40 -> #DIV/0! | O40: =Mangochi!O40+'Monkey Bay'!O40+Namwera!O40 -> #DIV/0! | P40: =P39/(P9/1000) -> 0
A41: Cost of Chemicals | C41: Mk | D41: =Mangochi!D41+'Monkey Bay'!D41+Namwera!D41+Nkhudzi!D41 -> 16618760 | E41: =Mangochi!E41+'Monkey Bay'!E41+Namwera!E41+Nkhudzi!E41 -> 17193058 | F41: =Mangochi!F41+'Monkey Bay'!F41+Namwera!F41+Nkhudzi!F41 -> 0 | G41: =Mangochi!G41+'Monkey Bay'!G41+Namwera!G41+Nkhudzi!G41 -> 0 | H41: =Mangochi!H41+'Monkey Bay'!H41+Namwera!H41+Nkhudzi!H41 -> 0 | I41: =Mangochi!I41+'Monkey Bay'!I41+Namwera!I41+Nkhudzi!I41 -> 0 | J41: =Mangochi!J41+'Monkey Bay'!J41+Namwera!J41+Nkhudzi!J41 -> 0 | K41: =Mangochi!K41+'Monkey Bay'!K41+Namwera!K41+Nkhudzi!K41 -> 0 | ... O41: =Mangochi!O41+'Monkey Bay'!O41+Namwera!O41+Nkhudzi!O41 -> 0 | P41: =SUM(D41:O41) -> 33811818
A42: Cost/vol. Produced (chemicals) | C42: Mk/m3 | D42: =Mangochi!D42+'Monkey Bay'!D42+Namwera!D42+Nkhudzi!D42 -> 206.0663 | E42: =Mangochi!E42+'Monkey Bay'!E42+Namwera!E42+Nkhudzi!E42 -> 192.65874 | F42: =Mangochi!F42+'Monkey Bay'!F42+Namwera!F42+Nkhudzi!F42 -> #DIV/0! | G42: =Mangochi!G42+'Monkey Bay'!G42+Namwera!G42+Nkhudzi!G42 -> #DIV/0! | H42: =Mangochi!H42+'Monkey Bay'!H42+Namwera!H42+Nkhudzi!H42 -> #DIV/0! | I42: =Mangochi!I42+'Monkey Bay'!I42+Namwera!I42+Nkhudzi!I42 -> #DIV/0! | J42: =Mangochi!J42+'Monkey Bay'!J42+Namwera!J42+Nkhudzi!J42 -> #DIV/0! | K42: =Mangochi!K42+'Monkey Bay'!K42+Namwera!K42+Nkhudzi!K42 -> #DIV/0! | ... O42: =Mangochi!O42+'Monkey Bay'!O42+Namwera!O42+Nkhudzi!O42 -> #DIV/0! | P42: =P41/P9 -> 67.140894
A43: Power
A44: Power Usage | C44: Kw | D44: =Mangochi!D44+'Monkey Bay'!D44+Namwera!D44+Nkhudzi!D44 -> 140786.91 | E44: =Mangochi!E44+'Monkey Bay'!E44+Namwera!E44+Nkhudzi!E44 -> 164909.25 | F44: =Mangochi!F44+'Monkey Bay'!F44+Namwera!F44+Nkhudzi!F44 -> 0 | G44: =Mangochi!G44+'Monkey Bay'!G44+Namwera!G44+Nkhudzi!G44 -> 0 | H44: =Mangochi!H44+'Monkey Bay'!H44+Namwera!H44+Nkhudzi!H44 -> 0 | I44: =Mangochi!I44+'Monkey Bay'!I44+Namwera!I44+Nkhudzi!I44 -> 0 | J44: =Mangochi!J44+'Monkey Bay'!J44+Namwera!J44+Nkhudzi!J44 -> 0 | K44: =Mangochi!K44+'Monkey Bay'!K44+Namwera!K44+Nkhudzi!K44 -> 0 | ... O44: =Mangochi!O44+'Monkey Bay'!O44+Namwera!O44+Nkhudzi!O44 -> 0 | P44: =SUM(D44:O44) -> 305696.16
A45: Power/ Vol. Produced | C45: Kw/m3 | D45: =Mangochi!D45+'Monkey Bay'!D45+Namwera!D45+Nkhudzi!D45 -> 3.9696202 | E45: =Mangochi!E45+'Monkey Bay'!E45+Namwera!E45+Nkhudzi!E45 -> 4.3865636 | F45: =Mangochi!F45+'Monkey Bay'!F45+Namwera!F45+Nkhudzi!F45 -> #DIV/0! | G45: =Mangochi!G45+'Monkey Bay'!G45+Namwera!G45+Nkhudzi!G45 -> #DIV/0! | H45: =Mangochi!H45+'Monkey Bay'!H45+Namwera!H45+Nkhudzi!H45 -> #DIV/0! | I45: =Mangochi!I45+'Monkey Bay'!I45+Namwera!I45+Nkhudzi!I45 -> #DIV/0! | J45: =Mangochi!J45+'Monkey Bay'!J45+Namwera!J45+Nkhudzi!J45 -> #DIV/0! | K45: =Mangochi!K45+'Monkey Bay'!K45+Namwera!K45+Nkhudzi!K45 -> #DIV/0! | ... O45: =Mangochi!O45+'Monkey Bay'!O45+Namwera!O45+Nkhudzi!O45 -> #DIV/0! | P45: =P44/P9 -> 0.60702779
A46: Cost of Power | C46: Mk | D46: =Mangochi!D46+'Monkey Bay'!D46+Namwera!D46+Nkhudzi!D46 -> 23613760 | E46: =Mangochi!E46+'Monkey Bay'!E46+Namwera!E46+Nkhudzi!E46 -> 27646472 | F46: =Mangochi!F46+'Monkey Bay'!F46+Namwera!F46+Nkhudzi!F46 -> 77356 | G46: =Mangochi!G46+'Monkey Bay'!G46+Namwera!G46+Nkhudzi!G46 -> 77356 | H46: =Mangochi!H46+'Monkey Bay'!H46+Namwera!H46+Nkhudzi!H46 -> 77356 | I46: =Mangochi!I46+'Monkey Bay'!I46+Namwera!I46+Nkhudzi!I46 -> 77356 | J46: =Mangochi!J46+'Monkey Bay'!J46+Namwera!J46+Nkhudzi!J46 -> 77356 | K46: =Mangochi!K46+'Monkey Bay'!K46+Namwera!K46+Nkhudzi!K46 -> 77356 | ... O46: =Mangochi!O46+'Monkey Bay'!O46+Namwera!O46+Nkhudzi!O46 -> 77356 | P46: =SUM(D46:O46) -> 52033792
A47: Cost/vol. Produced | C47: Mk/m3 | D47: =Mangochi!D47+'Monkey Bay'!D47+Namwera!D47+Nkhudzi!D47 -> 670.33416 | E47: =Mangochi!E47+'Monkey Bay'!E47+Namwera!E47+Nkhudzi!E47 -> 738.16046 | F47: =Mangochi!F47+'Monkey Bay'!F47+Namwera!F47+Nkhudzi!F47 -> #DIV/0! | G47: =Mangochi!G47+'Monkey Bay'!G47+Namwera!G47+Nkhudzi!G47 -> #DIV/0! | H47: =Mangochi!H47+'Monkey Bay'!H47+Namwera!H47+Nkhudzi!H47 -> #DIV/0! | I47: =Mangochi!I47+'Monkey Bay'!I47+Namwera!I47+Nkhudzi!I47 -> #DIV/0! | J47: =Mangochi!J47+'Monkey Bay'!J47+Namwera!J47+Nkhudzi!J47 -> #DIV/0! | K47: =Mangochi!K47+'Monkey Bay'!K47+Namwera!K47+Nkhudzi!K47 -> #DIV/0! | ... O47: =Mangochi!O47+'Monkey Bay'!O47+Namwera!O47+Nkhudzi!O47 -> #DIV/0! | P47: =P46/P9 -> 103.32468
A48: Plant and Vehicle Maintenance
A49: Distances covered | C49: km | D49: =Mangochi!D49+'Monkey Bay'!D49+Namwera!D49+Nkhudzi!D49 -> 1948 | E49: =Mangochi!E49+'Monkey Bay'!E49+Namwera!E49+Nkhudzi!E49 -> 2481 | F49: =Mangochi!F49+'Monkey Bay'!F49+Namwera!F49+Nkhudzi!F49 -> 0 | G49: =Mangochi!G49+'Monkey Bay'!G49+Namwera!G49+Nkhudzi!G49 -> 0 | H49: =Mangochi!H49+'Monkey Bay'!H49+Namwera!H49+Nkhudzi!H49 -> 0 | I49: =Mangochi!I49+'Monkey Bay'!I49+Namwera!I49+Nkhudzi!I49 -> 0 | J49: =Mangochi!J49+'Monkey Bay'!J49+Namwera!J49+Nkhudzi!J49 -> 0 | K49: =Mangochi!K49+'Monkey Bay'!K49+Namwera!K49+Nkhudzi!K49 -> 0 | ... O49: =Mangochi!O49+'Monkey Bay'!O49+Namwera!O49+Nkhudzi!O49 -> 0 | P49: =SUM(D49:O49) -> 4429
A50: Fuel Used (litres) | C50: litres | D50: =Mangochi!D50+'Monkey Bay'!D50+Namwera!D50+Nkhudzi!D50 -> 299.8 | E50: =Mangochi!E50+'Monkey Bay'!E50+Namwera!E50+Nkhudzi!E50 -> 245 | F50: =Mangochi!F50+'Monkey Bay'!F50+Namwera!F50+Nkhudzi!F50 -> 0 | G50: =Mangochi!G50+'Monkey Bay'!G50+Namwera!G50+Nkhudzi!G50 -> 0 | H50: =Mangochi!H50+'Monkey Bay'!H50+Namwera!H50+Nkhudzi!H50 -> 0 | I50: =Mangochi!I50+'Monkey Bay'!I50+Namwera!I50+Nkhudzi!I50 -> 0 | J50: =Mangochi!J50+'Monkey Bay'!J50+Namwera!J50+Nkhudzi!J50 -> 0 | K50: =Mangochi!K50+'Monkey Bay'!K50+Namwera!K50+Nkhudzi!K50 -> 0 | ... O50: =Mangochi!O50+'Monkey Bay'!O50+Namwera!O50+Nkhudzi!O50 -> 0 | P50: =SUM(D50:O50) -> 544.8
A51: Cost of fuel | C51: Mk | D51: =Mangochi!D51+'Monkey Bay'!D51+Namwera!D51+Nkhudzi!D51 -> 2004462.6 | E51: =Mangochi!E51+'Monkey Bay'!E51+Namwera!E51+Nkhudzi!E51 -> 1626365 | F51: =Mangochi!F51+'Monkey Bay'!F51+Namwera!F51+Nkhudzi!F51 -> 0 | G51: =Mangochi!G51+'Monkey Bay'!G51+Namwera!G51+Nkhudzi!G51 -> 0 | H51: =Mangochi!H51+'Monkey Bay'!H51+Namwera!H51+Nkhudzi!H51 -> 0 | I51: =Mangochi!I51+'Monkey Bay'!I51+Namwera!I51+Nkhudzi!I51 -> 0 | J51: =Mangochi!J51+'Monkey Bay'!J51+Namwera!J51+Nkhudzi!J51 -> 0 | K51: =Mangochi!K51+'Monkey Bay'!K51+Namwera!K51+Nkhudzi!K51 -> 0 | ... O51: =Mangochi!O51+'Monkey Bay'!O51+Namwera!O51+Nkhudzi!O51 -> 0 | P51: =SUM(D51:O51) -> 3630827.6
A52: Maintenance | C52: Mk | D52: =Mangochi!D52+'Monkey Bay'!D52+Namwera!D52+Nkhudzi!D52 -> 0 | E52: =Mangochi!E52+'Monkey Bay'!E52+Namwera!E52+Nkhudzi!E52 -> 0 | F52: =Mangochi!F52+'Monkey Bay'!F52+Namwera!F52+Nkhudzi!F52 -> 0 | G52: =Mangochi!G52+'Monkey Bay'!G52+Namwera!G52+Nkhudzi!G52 -> 0 | H52: =Mangochi!H52+'Monkey Bay'!H52+Namwera!H52+Nkhudzi!H52 -> 0 | I52: =Mangochi!I52+'Monkey Bay'!I52+Namwera!I52+Nkhudzi!I52 -> 0 | J52: =Mangochi!J52+'Monkey Bay'!J52+Namwera!J52+Nkhudzi!J52 -> 0 | K52: =Mangochi!K52+'Monkey Bay'!K52+Namwera!K52+Nkhudzi!K52 -> 0 | L52: =Mangochi!L52+'Monkey Bay'!L52+Namwera!L52+Nkhudzi!L52 -> 0 | M52: =Mangochi!M52+'Monkey Bay'!M52+Namwera!M52 -> 0 | N52: =Mangochi!N52+'Monkey Bay'!N52+Namwera!N52 -> 0 | O52: =Mangochi!O52+'Monkey Bay'!O52+Namwera!O52 -> 0 | P52: =SUM(D52:O52) -> 0
A53: Salaries and Wages
A54: Staff Costs | C54: MK | D54: =Mangochi!D54+'Monkey Bay'!D54+Namwera!D54+Nkhudzi!D54 -> 50089474 | E54: =Mangochi!E54+'Monkey Bay'!E54+Namwera!E54+Nkhudzi!E54 -> 50437128 | F54: =Mangochi!F54+'Monkey Bay'!F54+Namwera!F54+Nkhudzi!F54 -> 0 | G54: =Mangochi!G54+'Monkey Bay'!G54+Namwera!G54+Nkhudzi!G54 -> 0 | H54: =Mangochi!H54+'Monkey Bay'!H54+Namwera!H54+Nkhudzi!H54 -> 0 | I54: =Mangochi!I54+'Monkey Bay'!I54+Namwera!I54+Nkhudzi!I54 -> 0 | J54: =Mangochi!J54+'Monkey Bay'!J54+Namwera!J54+Nkhudzi!J54 -> 0 | K54: =Mangochi!K54+'Monkey Bay'!K54+Namwera!K54+Nkhudzi!K54 -> 0 | ... O54: =Mangochi!O54+'Monkey Bay'!O54+Namwera!O54+Nkhudzi!O54 -> 0 | P54: =SUM(D54:O54) -> 1.005266e+08
A55: Wages | C55: MK | D55: =Mangochi!D55+'Monkey Bay'!D55+Namwera!D55+Nkhudzi!D55 -> 12957420 | E55: =Mangochi!E55+'Monkey Bay'!E55+Namwera!E55+Nkhudzi!E55 -> 13113860 | F55: =Mangochi!F55+'Monkey Bay'!F55+Namwera!F55+Nkhudzi!F55 -> 0 | G55: =Mangochi!G55+'Monkey Bay'!G55+Namwera!G55+Nkhudzi!G55 -> 0 | H55: =Mangochi!H55+'Monkey Bay'!H55+Namwera!H55+Nkhudzi!H55 -> 0 | I55: =Mangochi!I55+'Monkey Bay'!I55+Namwera!I55+Nkhudzi!I55 -> 0 | J55: =Mangochi!J55+'Monkey Bay'!J55+Namwera!J55+Nkhudzi!J55 -> 0 | K55: =Mangochi!K55+'Monkey Bay'!K55+Namwera!K55+Nkhudzi!K55 -> 0 | ... O55: =Mangochi!O55+'Monkey Bay'!O55+Namwera!O55+Nkhudzi!O55 -> 0 | P55: =SUM(D55:O55) -> 26071281
A56: Other Overhead Costs | C56: MK | D56: =Mangochi!D56+'Monkey Bay'!D56+Namwera!D56+Nkhudzi!D56 -> 6049220 | E56: =Mangochi!E56+'Monkey Bay'!E56+Namwera!E56+Nkhudzi!E56 -> 6268450 | F56: =Mangochi!F56+'Monkey Bay'!F56+Namwera!F56+Nkhudzi!F56 -> 0 | G56: =Mangochi!G56+'Monkey Bay'!G56+Namwera!G56+Nkhudzi!G56 -> 0 | H56: =Mangochi!H56+'Monkey Bay'!H56+Namwera!H56+Nkhudzi!H56 -> 0 | I56: =Mangochi!I56+'Monkey Bay'!I56+Namwera!I56+Nkhudzi!I56 -> 0 | J56: =Mangochi!J56+'Monkey Bay'!J56+Namwera!J56+Nkhudzi!J56 -> 0 | K56: =Mangochi!K56+'Monkey Bay'!K56+Namwera!K56+Nkhudzi!K56 -> 0 | ... O56: =Mangochi!O56+'Monkey Bay'!O56+Namwera!O56+Nkhudzi!O56 -> 0 | P56: =SUM(D56:O56) -> 12317670
A57: Operating Costs
A58: Total Operating Costs | C58: MK | D58: =D41+D46+D51+D52+D54+D55+D56 -> 1.113331e+08 | E58: =E41+E46+E51+E52+E54+E55+E56 -> 1.1628533e+08 | F58: =F41+F46+F51+F52+F54+F55+F56 -> 77356 | G58: =G41+G46+G51+G52+G54+G55+G56 -> 77356 | H58: =H41+H46+H51+H52+H54+H55+H56 -> 77356 | I58: =I41+I46+I51+I52+I54+I55+I56 -> 77356 | J58: =J41+J46+J51+J52+J54+J55+J56 -> 77356 | K58: =K41+K46+K51+K52+K54+K55+K56 -> 77356 | ... O58: =O41+O46+O51+O52+O54+O55+O56 -> 77356 | P58: =SUM(D58:O58) -> 2.2839199e+08
A59: Cost/Vol. Produced | C59: Mk/m3 | D59: =D58/D9 -> 449.54008 | E59: =E58/E9 -> 454.35495 | F59: =F58/F9 -> #DIV/0! | G59: =G58/G9 -> #DIV/0! | H59: =H58/H9 -> #DIV/0! | I59: =I58/I9 -> #DIV/0! | J59: =J58/J9 -> #DIV/0! | K59: =K58/K9 -> #DIV/0! | ... P59: =P58/P9 -> 453.52315
A60: Cost/Vol. Billed | C60: Mk/m3 | D60: =D58/D22 -> 721.73539 | E60: =E58/E22 -> 676.4055 | F60: =F58/F22 -> #DIV/0! | G60: =G58/G22 -> #DIV/0! | H60: =H58/H22 -> #DIV/0! | I60: =I58/I22 -> #DIV/0! | J60: =J58/J22 -> #DIV/0! | K60: =K58/K22 -> #DIV/0! | ... P60: =P58/P22 -> 700.21498
A61: Permanent Staff Employed | C61: No | D61: =Mangochi!D61+'Monkey Bay'!D61+Namwera!D61+Nkhudzi!D61 -> 41 | E61: =Mangochi!E61+'Monkey Bay'!E61+Namwera!E61+Nkhudzi!E61 -> 41 | F61: =Mangochi!F61+'Monkey Bay'!F61+Namwera!F61+Nkhudzi!F61 -> 0 | G61: =Mangochi!G61+'Monkey Bay'!G61+Namwera!G61+Nkhudzi!G61 -> 0 | H61: =Mangochi!H61+'Monkey Bay'!H61+Namwera!H61+Nkhudzi!H61 -> 0 | I61: =Mangochi!I61+'Monkey Bay'!I61+Namwera!I61+Nkhudzi!I61 -> 0 | J61: =Mangochi!J61+'Monkey Bay'!J61+Namwera!J61+Nkhudzi!J61 -> 0 | K61: =Mangochi!K61+'Monkey Bay'!K61+Namwera!K61+Nkhudzi!K61 -> 0 | ... O61: =Mangochi!O61+'Monkey Bay'!O61+Namwera!O61+Nkhudzi!O61 -> 0 | P61: =O61 -> 0
A62: Staff/Vol.1000m3 of Volume Produced/hour (12 hour day) | C62: No/1000m3 | D62: =Mangochi!D62+'Monkey Bay'!D62+Namwera!D62 -> 34.40429 | E62: =Mangochi!E62+'Monkey Bay'!E62+Namwera!E62 -> 25.937626 | F62: =Mangochi!F62+'Monkey Bay'!F62+Namwera!F62 -> #DIV/0! | G62: =Mangochi!G62+'Monkey Bay'!G62+Namwera!G62 -> #DIV/0! | H62: =Mangochi!H62+'Monkey Bay'!H62+Namwera!H62 -> #DIV/0! | I62: =Mangochi!I62+'Monkey Bay'!I62+Namwera!I62 -> #DIV/0! | J62: =Mangochi!J62+'Monkey Bay'!J62+Namwera!J62 -> #DIV/0! | K62: =Mangochi!K62+'Monkey Bay'!K62+Namwera!K62 -> #DIV/0! | L62: =Mangochi!L62+'Monkey Bay'!L62+Namwera!L62 -> #DIV/0! | M62: =Mangochi!M62+'Monkey Bay'!M62+Namwera!M62+Nkhudzi!M62 -> #DIV/0! | N62: =Mangochi!N62+'Monkey Bay'!N62+Namwera!N62+Nkhudzi!N62 -> #DIV/0! | O62: =Mangochi!O62+'Monkey Bay'!O62+Namwera!O62+Nkhudzi!O62 -> #DIV/0! | P62: =(P61*1000*31)/P9 -> 0
A63: Temporary Staff Employed | C63: No | D63: =Mangochi!D63+'Monkey Bay'!D63+Namwera!D63+Nkhudzi!D63 -> 89 | E63: =Mangochi!E63+'Monkey Bay'!E63+Namwera!E63+Nkhudzi!E63 -> 89 | F63: =Mangochi!F63+'Monkey Bay'!F63+Namwera!F63+Nkhudzi!F63 -> 0 | G63: =Mangochi!G63+'Monkey Bay'!G63+Namwera!G63+Nkhudzi!G63 -> 0 | H63: =Mangochi!H63+'Monkey Bay'!H63+Namwera!H63+Nkhudzi!H63 -> 0 | I63: =Mangochi!I63+'Monkey Bay'!I63+Namwera!I63+Nkhudzi!I63 -> 0 | J63: =Mangochi!J63+'Monkey Bay'!J63+Namwera!J63+Nkhudzi!J63 -> 0 | K63: =Mangochi!K63+'Monkey Bay'!K63+Namwera!K63+Nkhudzi!K63 -> 0 | ... O63: =Mangochi!O63+'Monkey Bay'!O63+Namwera!O63+Nkhudzi!O63 -> 0 | P63: =SUM(D63:O63) -> 178
A65: Water Connections and Disconnections
A66: New Individual Water Connections | B66: Brought Forward | C66: No | D66: =Mangochi!D66+'Monkey Bay'!D66+Namwera!D66+Nkhudzi!D66 -> 5065 | E66: =Mangochi!E66+'Monkey Bay'!E66+Namwera!E66+Nkhudzi!E66 -> 5068 | F66: =Mangochi!F66+'Monkey Bay'!F66+Namwera!F66+Nkhudzi!F66 -> 0 | G66: =Mangochi!G66+'Monkey Bay'!G66+Namwera!G66+Nkhudzi!G66 -> 0 | H66: =Mangochi!H66+'Monkey Bay'!H66+Namwera!H66+Nkhudzi!H66 -> 0 | I66: =Mangochi!I66+'Monkey Bay'!I66+Namwera!I66+Nkhudzi!I66 -> 0 | J66: =Mangochi!J66+'Monkey Bay'!J66+Namwera!J66+Nkhudzi!J66 -> 0 | K66: =Mangochi!K66+'Monkey Bay'!K66+Namwera!K66+Nkhudzi!K66 -> 0 | ... O66: =Mangochi!O66+'Monkey Bay'!O66+Namwera!O66+Nkhudzi!O66 -> 0 | P66: =Mangochi!P66+'Monkey Bay'!P66+Namwera!P66 -> 2131
B67: Applied this Month | C67: No | D67: =Mangochi!D67+'Monkey Bay'!D67+Namwera!D67+Nkhudzi!D67 -> 185 | E67: =Mangochi!E67+'Monkey Bay'!E67+Namwera!E67+Nkhudzi!E67 -> 202 | F67: =Mangochi!F67+'Monkey Bay'!F67+Namwera!F67+Nkhudzi!F67 -> 0 | G67: =Mangochi!G67+'Monkey Bay'!G67+Namwera!G67+Nkhudzi!G67 -> 0 | H67: =Mangochi!H67+'Monkey Bay'!H67+Namwera!H67+Nkhudzi!H67 -> 0 | I67: =Mangochi!I67+'Monkey Bay'!I67+Namwera!I67+Nkhudzi!I67 -> 0 | J67: =Mangochi!J67+'Monkey Bay'!J67+Namwera!J67+Nkhudzi!J67 -> 0 | K67: =Mangochi!K67+'Monkey Bay'!K67+Namwera!K67+Nkhudzi!K67 -> 0 | ... O67: =Mangochi!O67+'Monkey Bay'!O67+Namwera!O67+Nkhudzi!O67 -> 0 | P67: =Mangochi!P67+'Monkey Bay'!P67+Namwera!P67 -> 327
B68: Done this Month Postpaid | C68: No | D68: =Mangochi!D68+'Monkey Bay'!D68+Namwera!D68+Nkhudzi!D68 -> 0 | E68: =Mangochi!E68+'Monkey Bay'!E68+Namwera!E68+Nkhudzi!E68 -> 0 | F68: =Mangochi!F68+'Monkey Bay'!F68+Namwera!F68+Nkhudzi!F68 -> 0 | G68: =Mangochi!G68+'Monkey Bay'!G68+Namwera!G68+Nkhudzi!G68 -> 0 | H68: =Mangochi!H68+'Monkey Bay'!H68+Namwera!H68+Nkhudzi!H68 -> 0 | I68: =Mangochi!I68+'Monkey Bay'!I68+Namwera!I68+Nkhudzi!I68 -> 0 | J68: =Mangochi!J68+'Monkey Bay'!J68+Namwera!J68+Nkhudzi!J68 -> 0 | K68: =Mangochi!K68+'Monkey Bay'!K68+Namwera!K68+Nkhudzi!K68 -> 0 | ... O68: =Mangochi!O68+'Monkey Bay'!O68+Namwera!O68+Nkhudzi!O68 -> 0 | P68: =Mangochi!P68+'Monkey Bay'!P68+Namwera!P68 -> 0
B69: Done this Month Prepaid | C69: No | D69: =Mangochi!D69+'Monkey Bay'!D69+Namwera!D69+Nkhudzi!D69 -> 189 | E69: =Mangochi!E69+'Monkey Bay'!E69+Namwera!E69+Nkhudzi!E69 -> 197 | F69: =Mangochi!F69+'Monkey Bay'!F69+Namwera!F69+Nkhudzi!F69 -> 0 | G69: =Mangochi!G69+'Monkey Bay'!G69+Namwera!G69+Nkhudzi!G69 -> 0 | H69: =Mangochi!H69+'Monkey Bay'!H69+Namwera!H69+Nkhudzi!H69 -> 0 | I69: =Mangochi!I69+'Monkey Bay'!I69+Namwera!I69+Nkhudzi!I69 -> 0 | J69: =Mangochi!J69+'Monkey Bay'!J69+Namwera!J69+Nkhudzi!J69 -> 0 | K69: =Mangochi!K69+'Monkey Bay'!K69+Namwera!K69+Nkhudzi!K69 -> 0 | ... O69: =Mangochi!O69+'Monkey Bay'!O69+Namwera!O69+Nkhudzi!O69 -> 0 | P69: =Mangochi!P69+'Monkey Bay'!P69+Namwera!P69 -> 300
B70: Total Done | C70: No | D70: =Mangochi!D70+'Monkey Bay'!D70+Namwera!D70+Nkhudzi!D70 -> 189 | E70: =Mangochi!E70+'Monkey Bay'!E70+Namwera!E70+Nkhudzi!E70 -> 197 | F70: =Mangochi!F70+'Monkey Bay'!F70+Namwera!F70+Nkhudzi!F70 -> 0 | G70: =Mangochi!G70+'Monkey Bay'!G70+Namwera!G70+Nkhudzi!G70 -> 0 | H70: =Mangochi!H70+'Monkey Bay'!H70+Namwera!H70+Nkhudzi!H70 -> 0 | I70: =Mangochi!I70+'Monkey Bay'!I70+Namwera!I70+Nkhudzi!I70 -> 0 | J70: =Mangochi!J70+'Monkey Bay'!J70+Namwera!J70+Nkhudzi!J70 -> 0 | K70: =Mangochi!K70+'Monkey Bay'!K70+Namwera!K70+Nkhudzi!K70 -> 0 | ... O70: =Mangochi!O70+'Monkey Bay'!O70+Namwera!O70+Nkhudzi!O70 -> 0 | P70: =Mangochi!P70+'Monkey Bay'!P70+Namwera!P70 -> 300
B71: Carried Forward | C71: No | D71: =Mangochi!D71+'Monkey Bay'!D71+Namwera!D71+Nkhudzi!D71 -> 5061 | E71: =Mangochi!E71+'Monkey Bay'!E71+Namwera!E71+Nkhudzi!E71 -> 5073 | F71: =Mangochi!F71+'Monkey Bay'!F71+Namwera!F71+Nkhudzi!F71 -> 0 | G71: =Mangochi!G71+'Monkey Bay'!G71+Namwera!G71+Nkhudzi!G71 -> 0 | H71: =Mangochi!H71+'Monkey Bay'!H71+Namwera!H71+Nkhudzi!H71 -> 0 | I71: =Mangochi!I71+'Monkey Bay'!I71+Namwera!I71+Nkhudzi!I71 -> 0 | J71: =Mangochi!J71+'Monkey Bay'!J71+Namwera!J71+Nkhudzi!J71 -> 0 | K71: =Mangochi!K71+'Monkey Bay'!K71+Namwera!K71+Nkhudzi!K71 -> 0 | ... O71: =Mangochi!O71+'Monkey Bay'!O71+Namwera!O71+Nkhudzi!O71 -> 0 | P71: =Mangochi!P71+'Monkey Bay'!P71+Namwera!P71 -> 2158
A72: New Institutional Water Connections | B72: Brought Forward | C72: No | D72: =Mangochi!D72+'Monkey Bay'!D72+Namwera!D72+Nkhudzi!D72 -> 14 | E72: =Mangochi!E72+'Monkey Bay'!E72+Namwera!E72+Nkhudzi!E72 -> 14 | F72: =Mangochi!F72+'Monkey Bay'!F72+Namwera!F72+Nkhudzi!F72 -> 0 | G72: =Mangochi!G72+'Monkey Bay'!G72+Namwera!G72+Nkhudzi!G72 -> 0 | H72: =Mangochi!H72+'Monkey Bay'!H72+Namwera!H72+Nkhudzi!H72 -> 0 | I72: =Mangochi!I72+'Monkey Bay'!I72+Namwera!I72+Nkhudzi!I72 -> 0 | J72: =Mangochi!J72+'Monkey Bay'!J72+Namwera!J72+Nkhudzi!J72 -> 0 | K72: =Mangochi!K72+'Monkey Bay'!K72+Namwera!K72+Nkhudzi!K72 -> 0 | ... O72: =Mangochi!O72+'Monkey Bay'!O72+Namwera!O72+Nkhudzi!O72 -> 0 | P72: =Mangochi!P72+'Monkey Bay'!P72+Namwera!P72 -> 4
B73: Applied this Month | C73: No | D73: =Mangochi!D73+'Monkey Bay'!D73+Namwera!D73+Nkhudzi!D73 -> 0 | E73: =Mangochi!E73+'Monkey Bay'!E73+Namwera!E73+Nkhudzi!E73 -> 0 | F73: =Mangochi!F73+'Monkey Bay'!F73+Namwera!F73+Nkhudzi!F73 -> 0 | G73: =Mangochi!G73+'Monkey Bay'!G73+Namwera!G73+Nkhudzi!G73 -> 0 | H73: =Mangochi!H73+'Monkey Bay'!H73+Namwera!H73+Nkhudzi!H73 -> 0 | I73: =Mangochi!I73+'Monkey Bay'!I73+Namwera!I73+Nkhudzi!I73 -> 0 | J73: =Mangochi!J73+'Monkey Bay'!J73+Namwera!J73+Nkhudzi!J73 -> 0 | K73: =Mangochi!K73+'Monkey Bay'!K73+Namwera!K73+Nkhudzi!K73 -> 0 | ... O73: =Mangochi!O73+'Monkey Bay'!O73+Namwera!O73+Nkhudzi!O73 -> 0 | P73: =Mangochi!P73+'Monkey Bay'!P73+Namwera!P73 -> 0
B74: Done this Month Postpaid | C74: No | D74: =Mangochi!D74+'Monkey Bay'!D74+Namwera!D74+Nkhudzi!D74 -> 0 | E74: =Mangochi!E74+'Monkey Bay'!E74+Namwera!E74+Nkhudzi!E74 -> 0 | F74: =Mangochi!F74+'Monkey Bay'!F74+Namwera!F74+Nkhudzi!F74 -> 0 | G74: =Mangochi!G74+'Monkey Bay'!G74+Namwera!G74+Nkhudzi!G74 -> 0 | H74: =Mangochi!H74+'Monkey Bay'!H74+Namwera!H74+Nkhudzi!H74 -> 0 | I74: =Mangochi!I74+'Monkey Bay'!I74+Namwera!I74+Nkhudzi!I74 -> 0 | J74: =Mangochi!J74+'Monkey Bay'!J74+Namwera!J74+Nkhudzi!J74 -> 0 | K74: =Mangochi!K74+'Monkey Bay'!K74+Namwera!K74+Nkhudzi!K74 -> 0 | ... O74: =Mangochi!O74+'Monkey Bay'!O74+Namwera!O74+Nkhudzi!O74 -> 0 | P74: =Mangochi!P74+'Monkey Bay'!P74+Namwera!P74 -> 0
B75: Done this Month Prepaid | C75: No | D75: =Mangochi!D75+'Monkey Bay'!D75+Namwera!D75+Nkhudzi!D75 -> 0 | E75: =Mangochi!E75+'Monkey Bay'!E75+Namwera!E75+Nkhudzi!E75 -> 0 | F75: =Mangochi!F75+'Monkey Bay'!F75+Namwera!F75+Nkhudzi!F75 -> 0 | G75: =Mangochi!G75+'Monkey Bay'!G75+Namwera!G75+Nkhudzi!G75 -> 0 | H75: =Mangochi!H75+'Monkey Bay'!H75+Namwera!H75+Nkhudzi!H75 -> 0 | I75: =Mangochi!I75+'Monkey Bay'!I75+Namwera!I75+Nkhudzi!I75 -> 0 | J75: =Mangochi!J75+'Monkey Bay'!J75+Namwera!J75+Nkhudzi!J75 -> 0 | K75: =Mangochi!K75+'Monkey Bay'!K75+Namwera!K75+Nkhudzi!K75 -> 0 | ... O75: =Mangochi!O75+'Monkey Bay'!O75+Namwera!O75+Nkhudzi!O75 -> 0 | P75: =Mangochi!P75+'Monkey Bay'!P75+Namwera!P75 -> 0
B76: Total Done | C76: No | D76: =Mangochi!D76+'Monkey Bay'!D76+Namwera!D76+Nkhudzi!D76 -> 0 | E76: =Mangochi!E76+'Monkey Bay'!E76+Namwera!E76+Nkhudzi!E76 -> 0 | F76: =Mangochi!F76+'Monkey Bay'!F76+Namwera!F76+Nkhudzi!F76 -> 0 | G76: =Mangochi!G76+'Monkey Bay'!G76+Namwera!G76+Nkhudzi!G76 -> 0 | H76: =Mangochi!H76+'Monkey Bay'!H76+Namwera!H76+Nkhudzi!H76 -> 0 | I76: =Mangochi!I76+'Monkey Bay'!I76+Namwera!I76+Nkhudzi!I76 -> 0 | J76: =Mangochi!J76+'Monkey Bay'!J76+Namwera!J76+Nkhudzi!J76 -> 0 | K76: =Mangochi!K76+'Monkey Bay'!K76+Namwera!K76+Nkhudzi!K76 -> 0 | ... O76: =Mangochi!O76+'Monkey Bay'!O76+Namwera!O76+Nkhudzi!O76 -> 0 | P76: =Mangochi!P76+'Monkey Bay'!P76+Namwera!P76 -> 0
B77: Carried Forward | C77: No | D77: =Mangochi!D77+'Monkey Bay'!D77+Namwera!D77+Nkhudzi!D77 -> 14 | E77: =Mangochi!E77+'Monkey Bay'!E77+Namwera!E77+Nkhudzi!E77 -> 14 | F77: =Mangochi!F77+'Monkey Bay'!F77+Namwera!F77+Nkhudzi!F77 -> 0 | G77: =Mangochi!G77+'Monkey Bay'!G77+Namwera!G77+Nkhudzi!G77 -> 0 | H77: =Mangochi!H77+'Monkey Bay'!H77+Namwera!H77+Nkhudzi!H77 -> 0 | I77: =Mangochi!I77+'Monkey Bay'!I77+Namwera!I77+Nkhudzi!I77 -> 0 | J77: =Mangochi!J77+'Monkey Bay'!J77+Namwera!J77+Nkhudzi!J77 -> 0 | K77: =Mangochi!K77+'Monkey Bay'!K77+Namwera!K77+Nkhudzi!K77 -> 0 | ... O77: =Mangochi!O77+'Monkey Bay'!O77+Namwera!O77+Nkhudzi!O77 -> 0 | P77: =Mangochi!P77+'Monkey Bay'!P77+Namwera!P77 -> 4
A78: New Commercial/Industrial Water Connections | B78: Brought Forward | C78: No | D78: =Mangochi!D78+'Monkey Bay'!D78+Namwera!D78+Nkhudzi!D78 -> 22 | E78: =Mangochi!E78+'Monkey Bay'!E78+Namwera!E78+Nkhudzi!E78 -> 22 | F78: =Mangochi!F78+'Monkey Bay'!F78+Namwera!F78+Nkhudzi!F78 -> 0 | G78: =Mangochi!G78+'Monkey Bay'!G78+Namwera!G78+Nkhudzi!G78 -> 0 | H78: =Mangochi!H78+'Monkey Bay'!H78+Namwera!H78+Nkhudzi!H78 -> 0 | I78: =Mangochi!I78+'Monkey Bay'!I78+Namwera!I78+Nkhudzi!I78 -> 0 | J78: =Mangochi!J78+'Monkey Bay'!J78+Namwera!J78+Nkhudzi!J78 -> 0 | K78: =Mangochi!K78+'Monkey Bay'!K78+Namwera!K78+Nkhudzi!K78 -> 0 | ... O78: =Mangochi!O78+'Monkey Bay'!O78+Namwera!O78+Nkhudzi!O78 -> 0 | P78: =Mangochi!P78+'Monkey Bay'!P78+Namwera!P78 -> 7
B79: Applied this Month | C79: No | D79: =Mangochi!D79+'Monkey Bay'!D79+Namwera!D79+Nkhudzi!D79 -> 0 | E79: =Mangochi!E79+'Monkey Bay'!E79+Namwera!E79+Nkhudzi!E79 -> 0 | F79: =Mangochi!F79+'Monkey Bay'!F79+Namwera!F79+Nkhudzi!F79 -> 0 | G79: =Mangochi!G79+'Monkey Bay'!G79+Namwera!G79+Nkhudzi!G79 -> 0 | H79: =Mangochi!H79+'Monkey Bay'!H79+Namwera!H79+Nkhudzi!H79 -> 0 | I79: =Mangochi!I79+'Monkey Bay'!I79+Namwera!I79+Nkhudzi!I79 -> 0 | J79: =Mangochi!J79+'Monkey Bay'!J79+Namwera!J79+Nkhudzi!J79 -> 0 | K79: =Mangochi!K79+'Monkey Bay'!K79+Namwera!K79+Nkhudzi!K79 -> 0 | ... O79: =Mangochi!O79+'Monkey Bay'!O79+Namwera!O79+Nkhudzi!O79 -> 0 | P79: =Mangochi!P79+'Monkey Bay'!P79+Namwera!P79 -> 0
B80: Done this Month Postpaid | C80: No | D80: =Mangochi!D80+'Monkey Bay'!D80+Namwera!D80+Nkhudzi!D80 -> 0 | E80: =Mangochi!E80+'Monkey Bay'!E80+Namwera!E80+Nkhudzi!E80 -> 0 | F80: =Mangochi!F80+'Monkey Bay'!F80+Namwera!F80+Nkhudzi!F80 -> 0 | G80: =Mangochi!G80+'Monkey Bay'!G80+Namwera!G80+Nkhudzi!G80 -> 0 | H80: =Mangochi!H80+'Monkey Bay'!H80+Namwera!H80+Nkhudzi!H80 -> 0 | I80: =Mangochi!I80+'Monkey Bay'!I80+Namwera!I80+Nkhudzi!I80 -> 0 | J80: =Mangochi!J80+'Monkey Bay'!J80+Namwera!J80+Nkhudzi!J80 -> 0 | K80: =Mangochi!K80+'Monkey Bay'!K80+Namwera!K80+Nkhudzi!K80 -> 0 | ... O80: =Mangochi!O80+'Monkey Bay'!O80+Namwera!O80+Nkhudzi!O80 -> 0 | P80: =Mangochi!P80+'Monkey Bay'!P80+Namwera!P80 -> 0
B81: Done this Month Prepaid | C81: No | D81: =Mangochi!D81+'Monkey Bay'!D81+Namwera!D81+Nkhudzi!D81 -> 1 | E81: =Mangochi!E81+'Monkey Bay'!E81+Namwera!E81+Nkhudzi!E81 -> 1 | F81: =Mangochi!F81+'Monkey Bay'!F81+Namwera!F81+Nkhudzi!F81 -> 0 | G81: =Mangochi!G81+'Monkey Bay'!G81+Namwera!G81+Nkhudzi!G81 -> 0 | H81: =Mangochi!H81+'Monkey Bay'!H81+Namwera!H81+Nkhudzi!H81 -> 0 | I81: =Mangochi!I81+'Monkey Bay'!I81+Namwera!I81+Nkhudzi!I81 -> 0 | J81: =Mangochi!J81+'Monkey Bay'!J81+Namwera!J81+Nkhudzi!J81 -> 0 | K81: =Mangochi!K81+'Monkey Bay'!K81+Namwera!K81+Nkhudzi!K81 -> 0 | ... O81: =Mangochi!O81+'Monkey Bay'!O81+Namwera!O81+Nkhudzi!O81 -> 0 | P81: =Mangochi!P81+'Monkey Bay'!P81+Namwera!P81 -> 2
B82: Total Done | C82: No | D82: =Mangochi!D82+'Monkey Bay'!D82+Namwera!D82+Nkhudzi!D82 -> 1 | E82: =Mangochi!E82+'Monkey Bay'!E82+Namwera!E82+Nkhudzi!E82 -> 1 | F82: =Mangochi!F82+'Monkey Bay'!F82+Namwera!F82+Nkhudzi!F82 -> 0 | G82: =Mangochi!G82+'Monkey Bay'!G82+Namwera!G82+Nkhudzi!G82 -> 0 | H82: =Mangochi!H82+'Monkey Bay'!H82+Namwera!H82+Nkhudzi!H82 -> 0 | I82: =Mangochi!I82+'Monkey Bay'!I82+Namwera!I82+Nkhudzi!I82 -> 0 | J82: =Mangochi!J82+'Monkey Bay'!J82+Namwera!J82+Nkhudzi!J82 -> 0 | K82: =Mangochi!K82+'Monkey Bay'!K82+Namwera!K82+Nkhudzi!K82 -> 0 | ... O82: =Mangochi!O82+'Monkey Bay'!O82+Namwera!O82+Nkhudzi!O82 -> 0 | P82: =Mangochi!P82+'Monkey Bay'!P82+Namwera!P82 -> 2
B83: Carried Forward | C83: No | D83: =Mangochi!D83+'Monkey Bay'!D83+Namwera!D83+Nkhudzi!D83 -> 21 | E83: =Mangochi!E83+'Monkey Bay'!E83+Namwera!E83+Nkhudzi!E83 -> 21 | F83: =Mangochi!F83+'Monkey Bay'!F83+Namwera!F83+Nkhudzi!F83 -> 0 | G83: =Mangochi!G83+'Monkey Bay'!G83+Namwera!G83+Nkhudzi!G83 -> 0 | H83: =Mangochi!H83+'Monkey Bay'!H83+Namwera!H83+Nkhudzi!H83 -> 0 | I83: =Mangochi!I83+'Monkey Bay'!I83+Namwera!I83+Nkhudzi!I83 -> 0 | J83: =Mangochi!J83+'Monkey Bay'!J83+Namwera!J83+Nkhudzi!J83 -> 0 | K83: =Mangochi!K83+'Monkey Bay'!K83+Namwera!K83+Nkhudzi!K83 -> 0 | ... O83: =Mangochi!O83+'Monkey Bay'!O83+Namwera!O83+Nkhudzi!O83 -> 0 | P83: =Mangochi!P83+'Monkey Bay'!P83+Namwera!P83 -> 5
A84: New CWP | B84: Brought Forward | C84: No | D84: =Mangochi!D84+'Monkey Bay'!D84+Namwera!D84+Nkhudzi!D84 -> 10 | E84: =Mangochi!E84+'Monkey Bay'!E84+Namwera!E84+Nkhudzi!E84 -> 10 | F84: =Mangochi!F84+'Monkey Bay'!F84+Namwera!F84+Nkhudzi!F84 -> 0 | G84: =Mangochi!G84+'Monkey Bay'!G84+Namwera!G84+Nkhudzi!G84 -> 0 | H84: =Mangochi!H84+'Monkey Bay'!H84+Namwera!H84+Nkhudzi!H84 -> 0 | I84: =Mangochi!I84+'Monkey Bay'!I84+Namwera!I84+Nkhudzi!I84 -> 0 | J84: =Mangochi!J84+'Monkey Bay'!J84+Namwera!J84+Nkhudzi!J84 -> 0 | K84: =Mangochi!K84+'Monkey Bay'!K84+Namwera!K84+Nkhudzi!K84 -> 0 | ... O84: =Mangochi!O84+'Monkey Bay'!O84+Namwera!O84+Nkhudzi!O84 -> 0 | P84: =Mangochi!P84+'Monkey Bay'!P84+Namwera!P84 -> 10
B85: Applied this Month | C85: No | D85: =Mangochi!D85+'Monkey Bay'!D85+Namwera!D85+Nkhudzi!D85 -> 0 | E85: =Mangochi!E85+'Monkey Bay'!E85+Namwera!E85+Nkhudzi!E85 -> 0 | F85: =Mangochi!F85+'Monkey Bay'!F85+Namwera!F85+Nkhudzi!F85 -> 0 | G85: =Mangochi!G85+'Monkey Bay'!G85+Namwera!G85+Nkhudzi!G85 -> 0 | H85: =Mangochi!H85+'Monkey Bay'!H85+Namwera!H85+Nkhudzi!H85 -> 0 | I85: =Mangochi!I85+'Monkey Bay'!I85+Namwera!I85+Nkhudzi!I85 -> 0 | J85: =Mangochi!J85+'Monkey Bay'!J85+Namwera!J85+Nkhudzi!J85 -> 0 | K85: =Mangochi!K85+'Monkey Bay'!K85+Namwera!K85+Nkhudzi!K85 -> 0 | ... O85: =Mangochi!O85+'Monkey Bay'!O85+Namwera!O85+Nkhudzi!O85 -> 0 | P85: =Mangochi!P85+'Monkey Bay'!P85+Namwera!P85 -> 0
B86: Done this Month Postpaid | C86: No | D86: =Mangochi!D86+'Monkey Bay'!D86+Namwera!D86+Nkhudzi!D86 -> 0 | E86: =Mangochi!E86+'Monkey Bay'!E86+Namwera!E86+Nkhudzi!E86 -> 0 | F86: =Mangochi!F86+'Monkey Bay'!F86+Namwera!F86+Nkhudzi!F86 -> 0 | G86: =Mangochi!G86+'Monkey Bay'!G86+Namwera!G86+Nkhudzi!G86 -> 0 | H86: =Mangochi!H86+'Monkey Bay'!H86+Namwera!H86+Nkhudzi!H86 -> 0 | I86: =Mangochi!I86+'Monkey Bay'!I86+Namwera!I86+Nkhudzi!I86 -> 0 | J86: =Mangochi!J86+'Monkey Bay'!J86+Namwera!J86+Nkhudzi!J86 -> 0 | K86: =Mangochi!K86+'Monkey Bay'!K86+Namwera!K86+Nkhudzi!K86 -> 0 | ... O86: =Mangochi!O86+'Monkey Bay'!O86+Namwera!O86+Nkhudzi!O86 -> 0 | P86: =Mangochi!P86+'Monkey Bay'!P86+Namwera!P86 -> 0
B87: Done this Month Prepaid | C87: No | D87: =Mangochi!D87+'Monkey Bay'!D87+Namwera!D87+Nkhudzi!D87 -> 0 | E87: =Mangochi!E87+'Monkey Bay'!E87+Namwera!E87+Nkhudzi!E87 -> 1 | F87: =Mangochi!F87+'Monkey Bay'!F87+Namwera!F87+Nkhudzi!F87 -> 0 | G87: =Mangochi!G87+'Monkey Bay'!G87+Namwera!G87+Nkhudzi!G87 -> 0 | H87: =Mangochi!H87+'Monkey Bay'!H87+Namwera!H87+Nkhudzi!H87 -> 0 | I87: =Mangochi!I87+'Monkey Bay'!I87+Namwera!I87+Nkhudzi!I87 -> 0 | J87: =Mangochi!J87+'Monkey Bay'!J87+Namwera!J87+Nkhudzi!J87 -> 0 | K87: =Mangochi!K87+'Monkey Bay'!K87+Namwera!K87+Nkhudzi!K87 -> 0 | ... O87: =Mangochi!O87+'Monkey Bay'!O87+Namwera!O87+Nkhudzi!O87 -> 0 | P87: =Mangochi!P87+'Monkey Bay'!P87+Namwera!P87 -> 1
B88: Total Done | C88: No | D88: =Mangochi!D88+'Monkey Bay'!D88+Namwera!D88+Nkhudzi!D88 -> 0 | E88: =Mangochi!E88+'Monkey Bay'!E88+Namwera!E88+Nkhudzi!E88 -> 1 | F88: =Mangochi!F88+'Monkey Bay'!F88+Namwera!F88+Nkhudzi!F88 -> 0 | G88: =Mangochi!G88+'Monkey Bay'!G88+Namwera!G88+Nkhudzi!G88 -> 0 | H88: =Mangochi!H88+'Monkey Bay'!H88+Namwera!H88+Nkhudzi!H88 -> 0 | I88: =Mangochi!I88+'Monkey Bay'!I88+Namwera!I88+Nkhudzi!I88 -> 0 | J88: =Mangochi!J88+'Monkey Bay'!J88+Namwera!J88+Nkhudzi!J88 -> 0 | K88: =Mangochi!K88+'Monkey Bay'!K88+Namwera!K88+Nkhudzi!K88 -> 0 | ... O88: =Mangochi!O88+'Monkey Bay'!O88+Namwera!O88+Nkhudzi!O88 -> 0 | P88: =Mangochi!P88+'Monkey Bay'!P88+Namwera!P88 -> 1
B89: Carried Forward | C89: No | D89: =Mangochi!D89+'Monkey Bay'!D89+Namwera!D89+Nkhudzi!D89 -> 10 | E89: =Mangochi!E89+'Monkey Bay'!E89+Namwera!E89+Nkhudzi!E89 -> 9 | F89: =Mangochi!F89+'Monkey Bay'!F89+Namwera!F89+Nkhudzi!F89 -> 0 | G89: =Mangochi!G89+'Monkey Bay'!G89+Namwera!G89+Nkhudzi!G89 -> 0 | H89: =Mangochi!H89+'Monkey Bay'!H89+Namwera!H89+Nkhudzi!H89 -> 0 | I89: =Mangochi!I89+'Monkey Bay'!I89+Namwera!I89+Nkhudzi!I89 -> 0 | J89: =Mangochi!J89+'Monkey Bay'!J89+Namwera!J89+Nkhudzi!J89 -> 0 | K89: =Mangochi!K89+'Monkey Bay'!K89+Namwera!K89+Nkhudzi!K89 -> 0 | ... O89: =Mangochi!O89+'Monkey Bay'!O89+Namwera!O89+Nkhudzi!O89 -> 0 | P89: =Mangochi!P89+'Monkey Bay'!P89+Namwera!P89 -> 9
A90: Aggregated New Water connections | B90: Brought Forward | C90: No | D90: =Mangochi!D90+'Monkey Bay'!D90+Namwera!D90+Nkhudzi!D90 -> 5111 | E90: =Mangochi!E90+'Monkey Bay'!E90+Namwera!E90+Nkhudzi!E90 -> 5114 | F90: =Mangochi!F90+'Monkey Bay'!F90+Namwera!F90+Nkhudzi!F90 -> 0 | G90: =Mangochi!G90+'Monkey Bay'!G90+Namwera!G90+Nkhudzi!G90 -> 0 | H90: =Mangochi!H90+'Monkey Bay'!H90+Namwera!H90+Nkhudzi!H90 -> 0 | I90: =Mangochi!I90+'Monkey Bay'!I90+Namwera!I90+Nkhudzi!I90 -> 0 | J90: =Mangochi!J90+'Monkey Bay'!J90+Namwera!J90+Nkhudzi!J90 -> 0 | K90: =Mangochi!K90+'Monkey Bay'!K90+Namwera!K90+Nkhudzi!K90 -> 0 | ... O90: =Mangochi!O90+'Monkey Bay'!O90+Namwera!O90+Nkhudzi!O90 -> 0 | P90: =Mangochi!P90+'Monkey Bay'!P90+Namwera!P90 -> 2152
B91: Applied this Month | C91: No | D91: =Mangochi!D91+'Monkey Bay'!D91+Namwera!D91+Nkhudzi!D91 -> 185 | E91: =Mangochi!E91+'Monkey Bay'!E91+Namwera!E91+Nkhudzi!E91 -> 202 | F91: =Mangochi!F91+'Monkey Bay'!F91+Namwera!F91+Nkhudzi!F91 -> 0 | G91: =Mangochi!G91+'Monkey Bay'!G91+Namwera!G91+Nkhudzi!G91 -> 0 | H91: =Mangochi!H91+'Monkey Bay'!H91+Namwera!H91+Nkhudzi!H91 -> 0 | I91: =Mangochi!I91+'Monkey Bay'!I91+Namwera!I91+Nkhudzi!I91 -> 0 | J91: =Mangochi!J91+'Monkey Bay'!J91+Namwera!J91+Nkhudzi!J91 -> 0 | K91: =Mangochi!K91+'Monkey Bay'!K91+Namwera!K91+Nkhudzi!K91 -> 0 | ... O91: =Mangochi!O91+'Monkey Bay'!O91+Namwera!O91+Nkhudzi!O91 -> 0 | P91: =Mangochi!P91+'Monkey Bay'!P91+Namwera!P91 -> 327
B92: Done this Month Postpaid | C92: No | D92: =Mangochi!D92+'Monkey Bay'!D92+Namwera!D92+Nkhudzi!D92 -> 0 | E92: =Mangochi!E92+'Monkey Bay'!E92+Namwera!E92+Nkhudzi!E92 -> 0 | F92: =Mangochi!F92+'Monkey Bay'!F92+Namwera!F92+Nkhudzi!F92 -> 0 | G92: =Mangochi!G92+'Monkey Bay'!G92+Namwera!G92+Nkhudzi!G92 -> 0 | H92: =Mangochi!H92+'Monkey Bay'!H92+Namwera!H92+Nkhudzi!H92 -> 0 | I92: =Mangochi!I92+'Monkey Bay'!I92+Namwera!I92+Nkhudzi!I92 -> 0 | J92: =Mangochi!J92+'Monkey Bay'!J92+Namwera!J92+Nkhudzi!J92 -> 0 | K92: =Mangochi!K92+'Monkey Bay'!K92+Namwera!K92+Nkhudzi!K92 -> 0 | ... O92: =Mangochi!O92+'Monkey Bay'!O92+Namwera!O92+Nkhudzi!O92 -> 0 | P92: =Mangochi!P92+'Monkey Bay'!P92+Namwera!P92 -> 0
B93: Done this Month Prepaid | D93: =Mangochi!D93+'Monkey Bay'!D93+Namwera!D93+Nkhudzi!D93 -> 190 | E93: =Mangochi!E93+'Monkey Bay'!E93+Namwera!E93+Nkhudzi!E93 -> 199 | F93: =Mangochi!F93+'Monkey Bay'!F93+Namwera!F93+Nkhudzi!F93 -> 0 | G93: =Mangochi!G93+'Monkey Bay'!G93+Namwera!G93+Nkhudzi!G93 -> 0 | H93: =Mangochi!H93+'Monkey Bay'!H93+Namwera!H93+Nkhudzi!H93 -> 0 | I93: =Mangochi!I93+'Monkey Bay'!I93+Namwera!I93+Nkhudzi!I93 -> 0 | J93: =Mangochi!J93+'Monkey Bay'!J93+Namwera!J93+Nkhudzi!J93 -> 0 | K93: =Mangochi!K93+'Monkey Bay'!K93+Namwera!K93+Nkhudzi!K93 -> 0 | ... O93: =Mangochi!O93+'Monkey Bay'!O93+Namwera!O93+Nkhudzi!O93 -> 0 | P93: =Mangochi!P93+'Monkey Bay'!P93+Namwera!P93 -> 303
B94: Total Done | C94: No | D94: =Mangochi!D94+'Monkey Bay'!D94+Namwera!D94+Nkhudzi!D94 -> 190 | E94: =Mangochi!E94+'Monkey Bay'!E94+Namwera!E94+Nkhudzi!E94 -> 199 | F94: =Mangochi!F94+'Monkey Bay'!F94+Namwera!F94+Nkhudzi!F94 -> 0 | G94: =Mangochi!G94+'Monkey Bay'!G94+Namwera!G94+Nkhudzi!G94 -> 0 | H94: =Mangochi!H94+'Monkey Bay'!H94+Namwera!H94+Nkhudzi!H94 -> 0 | I94: =Mangochi!I94+'Monkey Bay'!I94+Namwera!I94+Nkhudzi!I94 -> 0 | J94: =Mangochi!J94+'Monkey Bay'!J94+Namwera!J94+Nkhudzi!J94 -> 0 | K94: =Mangochi!K94+'Monkey Bay'!K94+Namwera!K94+Nkhudzi!K94 -> 0 | ... O94: =Mangochi!O94+'Monkey Bay'!O94+Namwera!O94+Nkhudzi!O94 -> 0 | P94: =Mangochi!P94+'Monkey Bay'!P94+Namwera!P94 -> 303
B95: Carried Forward | C95: No | D95: =Mangochi!D95+'Monkey Bay'!D95+Namwera!D95+Nkhudzi!D95 -> 5106 | E95: =Mangochi!E95+'Monkey Bay'!E95+Namwera!E95+Nkhudzi!E95 -> 5117 | F95: =Mangochi!F95+'Monkey Bay'!F95+Namwera!F95+Nkhudzi!F95 -> 0 | G95: =Mangochi!G95+'Monkey Bay'!G95+Namwera!G95+Nkhudzi!G95 -> 0 | H95: =Mangochi!H95+'Monkey Bay'!H95+Namwera!H95+Nkhudzi!H95 -> 0 | I95: =Mangochi!I95+'Monkey Bay'!I95+Namwera!I95+Nkhudzi!I95 -> 0 | J95: =Mangochi!J95+'Monkey Bay'!J95+Namwera!J95+Nkhudzi!J95 -> 0 | K95: =Mangochi!K95+'Monkey Bay'!K95+Namwera!K95+Nkhudzi!K95 -> 0 | ... O95: =Mangochi!O95+'Monkey Bay'!O95+Namwera!O95+Nkhudzi!O95 -> 0 | P95: =Mangochi!P95+'Monkey Bay'!P95+Namwera!P95 -> 2176
M96: =Mangochi!M96+'Monkey Bay'!M96+Namwera!M96+Nkhudzi!M96 -> 0 | N96: =Mangochi!N96+'Monkey Bay'!N96+Namwera!N96+Nkhudzi!N96 -> 0 | O96: =Mangochi!O96+'Monkey Bay'!O96+Namwera!O96+Nkhudzi!O96 -> 0
A97: Prepaid Metering
A98: Prepaid Meters Installed | C98: No | D98: =Mangochi!D98+'Monkey Bay'!D98+Namwera!D98+Nkhudzi!D98 -> 190 | E98: =Mangochi!E98+'Monkey Bay'!E98+Namwera!E98+Nkhudzi!E98 -> 199 | F98: =Mangochi!F98+'Monkey Bay'!F98+Namwera!F98+Nkhudzi!F98 -> 0 | G98: =Mangochi!G98+'Monkey Bay'!G98+Namwera!G98+Nkhudzi!G98 -> 0 | H98: =Mangochi!H98+'Monkey Bay'!H98+Namwera!H98+Nkhudzi!H98 -> 0 | I98: =Mangochi!I98+'Monkey Bay'!I98+Namwera!I98+Nkhudzi!I98 -> 0 | J98: =Mangochi!J98+'Monkey Bay'!J98+Namwera!J98+Nkhudzi!J98 -> 0 | K98: =Mangochi!K98+'Monkey Bay'!K98+Namwera!K98+Nkhudzi!K98 -> 0 | ... O98: =Mangochi!O98+'Monkey Bay'!O98+Namwera!O98+Nkhudzi!O98 -> 0 | P98: =SUM(D98:O98) -> 389
A100: Active and Disconnected Accounts
A101: Disconnected Individual Accounts | C101: No | D101: =Mangochi!D101+'Monkey Bay'!D101+Namwera!D101+Nkhudzi!D101 -> 2724 | E101: =Mangochi!E101+'Monkey Bay'!E101+Namwera!E101+Nkhudzi!E101 -> 2662 | F101: =Mangochi!F101+'Monkey Bay'!F101+Namwera!F101+Nkhudzi!F101 -> 0 | G101: =Mangochi!G101+'Monkey Bay'!G101+Namwera!G101+Nkhudzi!G101 -> 0 | H101: =Mangochi!H101+'Monkey Bay'!H101+Namwera!H101+Nkhudzi!H101 -> 0 | I101: =Mangochi!I101+'Monkey Bay'!I101+Namwera!I101+Nkhudzi!I101 -> 0 | J101: =Mangochi!J101+'Monkey Bay'!J101+Namwera!J101+Nkhudzi!J101 -> 0 | K101: =Mangochi!K101+'Monkey Bay'!K101+Namwera!K101+Nkhudzi!K101 -> 0 | ... O101: =Mangochi!O101+'Monkey Bay'!O101+Namwera!O101+Nkhudzi!O101 -> 0 | P101: =O101 -> 0
A102: Disconnected institutional Accounts | C102: No | D102: =Mangochi!D102+'Monkey Bay'!D102+Namwera!D102+Nkhudzi!D102 -> 76 | E102: =Mangochi!E102+'Monkey Bay'!E102+Namwera!E102+Nkhudzi!E102 -> 76 | F102: =Mangochi!F102+'Monkey Bay'!F102+Namwera!F102+Nkhudzi!F102 -> 0 | G102: =Mangochi!G102+'Monkey Bay'!G102+Namwera!G102+Nkhudzi!G102 -> 0 | H102: =Mangochi!H102+'Monkey Bay'!H102+Namwera!H102+Nkhudzi!H102 -> 0 | I102: =Mangochi!I102+'Monkey Bay'!I102+Namwera!I102+Nkhudzi!I102 -> 0 | J102: =Mangochi!J102+'Monkey Bay'!J102+Namwera!J102+Nkhudzi!J102 -> 0 | K102: =Mangochi!K102+'Monkey Bay'!K102+Namwera!K102+Nkhudzi!K102 -> 0 | ... O102: =Mangochi!O102+'Monkey Bay'!O102+Namwera!O102+Nkhudzi!O102 -> 0 | P102: =O102 -> 0
A103: Disconnected Commercial/Industrial Accounts | C103: No | D103: =Mangochi!D103+'Monkey Bay'!D103+Namwera!D103+Nkhudzi!D103 -> 144 | E103: =Mangochi!E103+'Monkey Bay'!E103+Namwera!E103+Nkhudzi!E103 -> 143 | F103: =Mangochi!F103+'Monkey Bay'!F103+Namwera!F103+Nkhudzi!F103 -> 0 | G103: =Mangochi!G103+'Monkey Bay'!G103+Namwera!G103+Nkhudzi!G103 -> 0 | H103: =Mangochi!H103+'Monkey Bay'!H103+Namwera!H103+Nkhudzi!H103 -> 0 | I103: =Mangochi!I103+'Monkey Bay'!I103+Namwera!I103+Nkhudzi!I103 -> 0 | J103: =Mangochi!J103+'Monkey Bay'!J103+Namwera!J103+Nkhudzi!J103 -> 0 | K103: =Mangochi!K103+'Monkey Bay'!K103+Namwera!K103+Nkhudzi!K103 -> 0 | ... O103: =Mangochi!O103+'Monkey Bay'!O103+Namwera!O103+Nkhudzi!O103 -> 0 | P103: =O103 -> 0
A104: Disconnected CWP | C104: No | D104: =Mangochi!D104+'Monkey Bay'!D104+Namwera!D104+Nkhudzi!D104 -> 13 | E104: =Mangochi!E104+'Monkey Bay'!E104+Namwera!E104+Nkhudzi!E104 -> 13 | F104: =Mangochi!F104+'Monkey Bay'!F104+Namwera!F104+Nkhudzi!F104 -> 0 | G104: =Mangochi!G104+'Monkey Bay'!G104+Namwera!G104+Nkhudzi!G104 -> 0 | H104: =Mangochi!H104+'Monkey Bay'!H104+Namwera!H104+Nkhudzi!H104 -> 0 | I104: =Mangochi!I104+'Monkey Bay'!I104+Namwera!I104+Nkhudzi!I104 -> 0 | J104: =Mangochi!J104+'Monkey Bay'!J104+Namwera!J104+Nkhudzi!J104 -> 0 | K104: =Mangochi!K104+'Monkey Bay'!K104+Namwera!K104+Nkhudzi!K104 -> 0 | ... O104: =Mangochi!O104+'Monkey Bay'!O104+Namwera!O104+Nkhudzi!O104 -> 0 | P104: =O104 -> 0
A105: Total Disconnected Accounts | C105: No | D105: =SUM(D101:D104) -> 2957 | E105: =SUM(E101:E104) -> 2894 | F105: =SUM(F101:F104) -> 0 | G105: =SUM(G101:G104) -> 0 | H105: =SUM(H101:H104) -> 0 | I105: =SUM(I101:I104) -> 0 | J105: =SUM(J101:J104) -> 0 | K105: =SUM(K101:K104) -> 0 | ... O105: =SUM(O101:O104) -> 0 | P105: =O105 -> 0
...

Sheet 1st QTR
A1: SOUTHERN REGION WATER BOARD
A3: MONTHLY REPORTS - 2025/2026
A4: MANGOCHI ZONE
A5: MANGOCHI ZONE
A7: PARAMETERS | C7: UNITS | D7: Mangochi | E7: Monkey Bay | F7: Namwera | G7: Nkhudzi | H7: TOTALS
A8: PRODUCTION
A9: Volume Produced | C9: m3 | D9: =Mangochi!D9+Mangochi!E9+Mangochi!F9 -> 305608 | E9: ='Monkey Bay'!D9+'Monkey Bay'!E9+'Monkey Bay'!F9 -> 116050 | F9: =Namwera!D9+Namwera!E9+Namwera!F9 -> 8386 | G9: =Nkhudzi!D9+Nkhudzi!E9+Nkhudzi!F9 -> 73551 | H9: =SUM(D9:G9) -> 503595
A10: REVENUE WATER - POSTPAID
A11: Volume Billed Individuals | C11: m3 | D11: =Mangochi!D11+Mangochi!E11+Mangochi!F11 -> 113884 | E11: ='Monkey Bay'!D11+'Monkey Bay'!E11+'Monkey Bay'!F11 -> 35792 | F11: =Namwera!D11+Namwera!E11+Namwera!F11 -> 21 | G11: =Nkhudzi!D11+Nkhudzi!E11+Nkhudzi!F11 -> 227 | H11: =SUM(D11:G11) -> 149924
A12: Volume Billed CWPs | C12: m3 | D12: =Mangochi!D12+Mangochi!E12+Mangochi!F12 -> 0 | E12: ='Monkey Bay'!D12+'Monkey Bay'!E12+'Monkey Bay'!F12 -> 0 | F12: =Namwera!D12+Namwera!E12+Namwera!F12 -> 0 | G12: =Nkhudzi!D12+Nkhudzi!E12+Nkhudzi!F12 -> 0 | H12: =SUM(D12:G12) -> 0
A13: Volume Billed Institutions | C13: m3 | D13: =Mangochi!D13+Mangochi!E13+Mangochi!F13 -> 304 | E13: ='Monkey Bay'!D13+'Monkey Bay'!E13+'Monkey Bay'!F13 -> 8915 | F13: =Namwera!D13+Namwera!E13+Namwera!F13 -> 7 | G13: =Nkhudzi!D13+Nkhudzi!E13+Nkhudzi!F13 -> 403 | H13: =SUM(D13:G13) -> 9629
A14: Volume Billed Commercial/Industrial | C14: m3 | D14: =Mangochi!D14+Mangochi!E14+Mangochi!F14 -> 143 | E14: ='Monkey Bay'!D14+'Monkey Bay'!E14+'Monkey Bay'!F14 -> 0 | F14: =Namwera!D14+Namwera!E14+Namwera!F14 -> 0 | G14: =Nkhudzi!D14+Nkhudzi!E14+Nkhudzi!F14 -> 2 | H14: =SUM(D14:G14) -> 145
A15: Total Volume Billed Post Paid | C15: m3 | D15: =SUM(D11:D14) -> 114331 | E15: =SUM(E11:E14) -> 44707 | F15: =SUM(F11:F14) -> 28 | G15: =SUM(G11:G14) -> 632 | H15: =SUM(D15:G15) -> 159698
A16: REVENUE WATER - PREPAID
A17: Individuals | C17: m3 | D17: =Mangochi!D17+Mangochi!E17+Mangochi!F17 -> 54757.6 | E17: ='Monkey Bay'!D17+'Monkey Bay'!E17+'Monkey Bay'!F17 -> 18175.1 | F17: =Namwera!D17+Namwera!E17+Namwera!F17 -> 6849.8 | G17: =Nkhudzi!D17+Nkhudzi!E17+Nkhudzi!F17 -> 48893.8 | H17: =SUM(D17:G17) -> 128676.3
A18: CWPs | C18: m3 | D18: =Mangochi!D18+Mangochi!E18+Mangochi!F18 -> 9208.5 | E18: ='Monkey Bay'!D18+'Monkey Bay'!E18+'Monkey Bay'!F18 -> 2244.6 | F18: =Namwera!D18+Namwera!E18+Namwera!F18 -> 0 | G18: =Nkhudzi!D18+Nkhudzi!E18+Nkhudzi!F18 -> 1359.6 | H18: =SUM(D18:G18) -> 12812.7
A19: Institutions | C19: m3 | D19: =Mangochi!D19+Mangochi!E19+Mangochi!F19 -> 10854.9 | E19: ='Monkey Bay'!D19+'Monkey Bay'!E19+'Monkey Bay'!F19 -> 4598.5 | F19: =Namwera!D19+Namwera!E19+Namwera!F19 -> 753.9 | G19: =Nkhudzi!D19+Nkhudzi!E19+Nkhudzi!F19 -> 967.6 | H19: =SUM(D19:G19) -> 17174.9
A20: Commercial/Industrial | C20: m3 | D20: =Mangochi!D20+Mangochi!E20+Mangochi!F20 -> 4331.6 | E20: ='Monkey Bay'!D20+'Monkey Bay'!E20+'Monkey Bay'!F20 -> 1167.8 | F20: =Namwera!D20+Namwera!E20+Namwera!F20 -> 27.8 | G20: =Nkhudzi!D20+Nkhudzi!E20+Nkhudzi!F20 -> 2285 | H20: =SUM(D20:G20) -> 7812.2
A21: Total Volume Prepaid | C21: m3 | D21: =SUM(D17:D20) -> 79152.6 | E21: =SUM(E17:E20) -> 26186 | F21: =SUM(F17:F20) -> 7631.5 | G21: =SUM(G17:G20) -> 53506 | H21: =SUM(D21:G21) -> 166476.1
A22: TOTAL REVENUE WATER | C22: m3 | D22: =D21+D15 -> 193483.6 | E22: =E21+E15 -> 70893 | F22: =F21+F15 -> 7659.5 | G22: =G21+G15 -> 54138 | H22: =SUM(D22:G22) -> 326174.1
A23: NON-REVENUE WATER (NRW)
A24: Non-Revenue Water (NRW) | B24: Volume | C24: m3 | D24: =D9-D22 -> 112124.4 | E24: =E9-E22 -> 45157 | F24: =F9-F22 -> 726.5 | G24: =G9-G22 -> 19413 | H24: =H9-H22 -> 177420.9
B25: Percentage | C25: % | D25: =D24/D9 -> 0.36688961 | E25: =E24/E9 -> 0.38911676 | F25: =F24/F9 -> 0.086632483 | G25: =G24/G9 -> 0.26393931 | H25: =H24/H9 -> 0.3523087
A26: OPERATING EXPENSES
A27: Chemicals
A28: Chemical | B28: Rate(MK/kg)
A29: Chlorine | B29: 3525.29 | C29: kg | D29: =Mangochi!D29+Mangochi!E29+Mangochi!F29 -> 1035.39 | E29: ='Monkey Bay'!D29+'Monkey Bay'!E29+'Monkey Bay'!F29 -> 230 | F29: =Namwera!D29+Namwera!E29+Namwera!F29 -> 8.5 | G29: =Nkhudzi!D29+Nkhudzi!E29+Nkhudzi!F29 -> 139.11 | H29: =SUM(D29:G29) -> 1413
C30: kg/mg litre | D30: =D29/(D9/1000) -> 3.3879676 | E30: =E29/(E9/1000) -> 1.9819044 | F30: =F29/(F9/1000) -> 1.0135941 | G30: =G29/(G9/1000) -> 1.8913407 | H30: =H29/(H9/1000) -> 2.8058261
A31: Aluminium sulphate | B31: 1060.0102 | C31: kg | D31: =Mangochi!D31+Mangochi!E31+Mangochi!F31 -> 0 | E31: ='Monkey Bay'!D31+'Monkey Bay'!E31+'Monkey Bay'!F31 -> 0 | F31: =Namwera!D31+Namwera!E31+Namwera!F31 -> 0 | G31: =Nkhudzi!D31+Nkhudzi!E31+Nkhudzi!F31 -> 0 | H31: =SUM(D31:G31) -> 0
C32: kg/mg litre | D32: =D31/(D9/1000) -> 0 | E32: =E31/(E9/1000) -> 0 | F32: =F31/(F9/1000) -> 0 | G32: =Nkhudzi!D32+Nkhudzi!E32+Nkhudzi!F32 -> #DIV/0! | H32: =H31/(H9/1000) -> 0
A33: Soda | B33: 1228.2886 | C33: kg | D33: =Mangochi!D33+Mangochi!E33+Mangochi!F33 -> 0 | E33: ='Monkey Bay'!D33+'Monkey Bay'!E33+'Monkey Bay'!F33 -> 0 | F33: =Namwera!D33+Namwera!E33+Namwera!F33 -> 0 | G33: =Nkhudzi!D33+Nkhudzi!E33+Nkhudzi!F33 -> 0 | H33: =SUM(D33:F33) -> 0
C34: kg/mg litre | D34: =D33/(D9/1000) -> 0 | E34: =E33/(E9/1000) -> 0 | F34: =F33/(F9/1000) -> 0 | G34: =Nkhudzi!D34+Nkhudzi!E34+Nkhudzi!F34 -> #DIV/0! | H34: =H33/(H9/1000) -> 0
A35: Algae floc | B35: 3726.7258 | C35: litres | D35: =Mangochi!D35+Mangochi!E35+Mangochi!F35 -> 0 | E35: ='Monkey Bay'!D35+'Monkey Bay'!E35+'Monkey Bay'!F35 -> 0 | F35: =Namwera!D35+Namwera!E35+Namwera!F35 -> 0 | G35: =Nkhudzi!D35+Nkhudzi!E35+Nkhudzi!F35 -> 0
C36: litres/mg litre | D36: =D35/(D11/1000) -> 0 | E36: =E35/(E11/1000) -> 0 | F36: =F35/(F11/1000) -> 0 | G36: =Nkhudzi!D36+Nkhudzi!E36+Nkhudzi!F36 -> 0
A37: Sud floc | B37: 3951.5936 | C37: litres | D37: =Mangochi!D37+Mangochi!E37+Mangochi!F37 -> 0 | E37: ='Monkey Bay'!D37+'Monkey Bay'!E37+'Monkey Bay'!F37 -> 0 | F37: =Namwera!D37+Namwera!E37+Namwera!F37 -> 0 | G37: =Nkhudzi!D37+Nkhudzi!E37+Nkhudzi!F37 -> 0 | H37: =SUM(D37:F37) -> 0
C38: litres/mg litre | D38: =D37/(D13/1000) -> 0 | E38: =E37/(E13/1000) -> 0 | F38: =F37/(F13/1000) -> 0 | G38: =Nkhudzi!D38+Nkhudzi!E38+Nkhudzi!F38 -> #DIV/0! | H38: =H37/(H9/1000) -> 0
A39: Potasium permanganate | B39: 1950 | C39: kg | D39: =Mangochi!D39+Mangochi!E39+Mangochi!F39 -> 0 | E39: ='Monkey Bay'!D39+'Monkey Bay'!E39+'Monkey Bay'!F39 -> 0 | F39: =Namwera!D39+Namwera!E39+Namwera!F39 -> 0 | G39: =Nkhudzi!D39+Nkhudzi!E39+Nkhudzi!F39 -> 0 | H39: =SUM(D39:F39) -> 0
C40: kg/mg litre | D40: =D39/(D9/1000) -> 0 | E40: =E39/(E9/1000) -> 0 | F40: =F39/(F9/1000) -> 0 | G40: =Nkhudzi!D40+Nkhudzi!E40+Nkhudzi!F40 -> #DIV/0! | H40: =H39/(H9/1000) -> 0
A41: Cost of Chemicals | C41: Mk | D41: =(D29*$B29)+(D31*$B31)+(D33*$B33)+(D35*$B35)+(D37*$B37)+(D39*$B39) -> 3650050 | E41: =(E29*$B29)+(E31*$B31)+(E33*$B33)+(E35*$B35)+(E37*$B37)+(E39*$B39) -> 810816.7 | F41: =(F29*$B29)+(F31*$B31)+(F33*$B33)+(F35*$B35)+(F37*$B37)+(F39*$B39) -> 29964.965 | G41: =(G29*$B29)+(G31*$B31)+(G33*$B33)+(G35*$B35)+(G37*$B37)+(G39*$B39) -> 490403.09 | H41: =SUM(D41:G41) -> 4981234.8
A42: Cost/vol. Produced (chemicals) | C42: Mk/m3 | D42: =D41/D9 -> 11.943568 | E42: =E41/E9 -> 6.9867876 | F42: =F41/F9 -> 3.5732131 | G42: =G41/G9 -> 6.6675245 | H42: =H41/H9 -> 9.8913507
A43: Power
A44: Power Usage | C44: Kw | D44: =Mangochi!D44+Mangochi!E44+Mangochi!F44 -> 56848.16 | E44: ='Monkey Bay'!D44+'Monkey Bay'!E44+'Monkey Bay'!F44 -> 50914 | F44: =Namwera!D44+Namwera!E44+Namwera!F44 -> 8410 | G44: =Nkhudzi!D44+Nkhudzi!E44+Nkhudzi!F44 -> 189524 | H44: =SUM(D44:G44) -> 305696.16
A45: Power/ Vol. Produced | C45: Kw/m3 | D45: =D44/D9 -> 0.1860166 | E45: =E44/E9 -> 0.43872469 | F45: =F44/F9 -> 1.0028619 | G45: =G44/G9 -> 2.5767699 | H45: =H44/H9 -> 0.60702779
A46: Cost of Power | C46: Mk | D46: =Mangochi!D46+Mangochi!E46+Mangochi!F46 -> 9561750.3 | E46: ='Monkey Bay'!D46+'Monkey Bay'!E46+'Monkey Bay'!F46 -> 8569692.2 | F46: =Namwera!D46+Namwera!E46+Namwera!F46 -> 1463979.8 | G46: =Nkhudzi!D46+Nkhudzi!E46+Nkhudzi!F46 -> 31742166 | H46: =SUM(D46:G46) -> 51337588
A47: Cost/vol. Produced | C47: Mk/m3 | D47: =D46/D9 -> 31.287631 | E47: =E46/E9 -> 73.844828 | F47: =F46/F9 -> 174.57426 | G47: =G46/G9 -> 431.56674 | H47: =H46/H9 -> 101.94221
A48: Plant and Vehicle Maintenance
A49: Distances covered | C49: km | D49: =Mangochi!D49+Mangochi!E49+Mangochi!F49 -> 4429 | E49: ='Monkey Bay'!D49+'Monkey Bay'!E49+'Monkey Bay'!F49 -> 0 | F49: =Namwera!D49+Namwera!E49+Namwera!F49 -> 0 | G49: =Nkhudzi!D49+Nkhudzi!E49+Nkhudzi!F49 -> 0 | H49: =SUM(D49:G49) -> 4429
A50: Fuel Used (litres) | C50: litres | D50: =Mangochi!D50+Mangochi!E50+Mangochi!F50 -> 544.8 | E50: ='Monkey Bay'!D50+'Monkey Bay'!E50+'Monkey Bay'!F50 -> 0 | F50: =Namwera!D50+Namwera!E50+Namwera!F50 -> 0 | G50: =Nkhudzi!D50+Nkhudzi!E50+Nkhudzi!F50 -> 0 | H50: =SUM(D50:G50) -> 544.8
A51: Cost of fuel | C51: Mk | D51: =Mangochi!D51+Mangochi!E51+Mangochi!F51 -> 3630827.6 | E51: ='Monkey Bay'!D51+'Monkey Bay'!E51+'Monkey Bay'!F51 -> 0 | F51: =Namwera!D51+Namwera!E51+Namwera!F51 -> 0 | G51: =Nkhudzi!D51+Nkhudzi!E51+Nkhudzi!F51 -> 0 | H51: =SUM(D51:G51) -> 3630827.6
A52: Maintenance | C52: Mk | D52: =Mangochi!D52+Mangochi!E52+Mangochi!F52 -> 0 | E52: ='Monkey Bay'!D52+'Monkey Bay'!E52+'Monkey Bay'!F52 -> 0 | F52: =Namwera!D52+Namwera!E52+Namwera!F52 -> 0 | G52: =Nkhudzi!D52+Nkhudzi!E52+Nkhudzi!F52 -> 0 | H52: =SUM(D52:G52) -> 0
A53: Salaries and Wages
A54: Staff Costs | C54: MK | D54: =Mangochi!D54+Mangochi!E54+Mangochi!F54 -> 65632219 | E54: ='Monkey Bay'!D54+'Monkey Bay'!E54+'Monkey Bay'!F54 -> 8219217.9 | F54: =Namwera!D54+Namwera!E54+Namwera!F54 -> 8496202.6 | G54: =Nkhudzi!D54+Nkhudzi!E54+Nkhudzi!F54 -> 18178963 | H54: =SUM(D54:G54) -> 1.005266e+08
A55: Wages | C55: MK | D55: =Mangochi!D55+Mangochi!E55+Mangochi!F55 -> 9331735.4 | E55: ='Monkey Bay'!D55+'Monkey Bay'!E55+'Monkey Bay'!F55 -> 3219061.8 | F55: =Namwera!D55+Namwera!E55+Namwera!F55 -> 1853959.1 | G55: =Nkhudzi!D55+Nkhudzi!E55+Nkhudzi!F55 -> 11666524 | H55: =SUM(D55:G55) -> 26071281
A56: Other Overhead Costs | C56: MK | D56: =Mangochi!D56+Mangochi!E56+Mangochi!F56 -> 7312980 | E56: ='Monkey Bay'!D56+'Monkey Bay'!E56+'Monkey Bay'!F56 -> 2008340 | F56: =Namwera!D56+Namwera!E56+Namwera!F56 -> 484410 | G56: =Nkhudzi!D56+Nkhudzi!E56+Nkhudzi!F56 -> 2511940 | H56: =SUM(D56:G56) -> 12317670
A57: Operating Costs
A58: Total Operating Costs | C58: MK | D58: =D41+D46+D51+D52+D54+D55+D56 -> 99119562 | E58: =E41+E46+E51+E52+E54+E55+E56 -> 22827129 | F58: =F41+F46+F51+F52+F54+F55+F56 -> 12328516 | G58: =G41+G46+G51+G52+G54+G55+G56 -> 64589996 | H58: =SUM(D58:G58) -> 1.988652e+08
A59: Cost/Vol. Produced | C59: Mk/m3 | D59: =D58/D9 -> 324.33563 | E59: =E58/E9 -> 196.70081 | F59: =F58/F9 -> 1470.1307 | G59: =G58/G9 -> 878.16612 | H59: =H58/H9 -> 394.89114
A60: Cost/Vol. Billed | C60: Mk/m3 | D60: =D58/D22 -> 512.28922 | E60: =E58/E22 -> 321.99411 | F60: =F58/F22 -> 1609.572 | G60: =G58/G22 -> 1193.0621 | H60: =H58/H22 -> 609.69036
A61: Permanent Staff Employed | C61: No | D61: =Mangochi!F61 -> 0 | E61: ='Monkey Bay'!F61 -> 0 | F61: =Namwera!F61 -> 0 | G61: =Nkhudzi!F61 -> 0 | H61: =SUM(D61:G61) -> 0
A62: Staff/Vol.1000m3 of Volume Produced/hour (12 hour day) | C62: No/1000m3 | D62: =(D61*1000*31)/D9 -> 0 | E62: =(E61*1000*31)/E9 -> 0 | F62: =(F61*1000*31)/F9 -> 0 | G62: =(G61*1000*31)/G9 -> 0 | H62: =(H61*1000*31)/H9 -> 0
A63: Temporary Staff Employed | C63: No | D63: =Mangochi!F63 -> 0 | E63: ='Monkey Bay'!F63 -> 0 | F63: =Namwera!F63 -> 0 | G63: =Nkhudzi!F63 -> 0 | H63: =SUM(D63:G63) -> 0
A65: Water Connections and Disconnections
A66: New Individual Water Connections | B66: Brought Forward | C66: No | D66: =Mangochi!D66 -> 1978 | E66: ='Monkey Bay'!D66 -> 77 | F66: =Namwera!D66 -> 76 | G66: =Nkhudzi!D66 -> 2934 | H66: =SUM(D66:G66) -> 5065
B67: Applied this Month | C67: No | D67: =Mangochi!D67+Mangochi!E67+Mangochi!F67 -> 253 | E67: ='Monkey Bay'!D67+'Monkey Bay'!E67+'Monkey Bay'!F67 -> 57 | F67: =Namwera!D67+Namwera!E67+Namwera!F67 -> 17 | G67: =Nkhudzi!D67+Nkhudzi!E67+Nkhudzi!F67 -> 60 | H67: =SUM(D67:G67) -> 387
B68: Done this Month Postpaid | C68: No | D68: =Mangochi!D68+Mangochi!E68+Mangochi!F68 -> 0 | E68: ='Monkey Bay'!D68+'Monkey Bay'!E68+'Monkey Bay'!F68 -> 0 | F68: =Namwera!D68+Namwera!E68+Namwera!F68 -> 0 | G68: =Nkhudzi!D68+Nkhudzi!E68+Nkhudzi!F68 -> 0 | H68: =SUM(D68:G68) -> 0
B69: Done this Month Prepaid | C69: No | D69: =Mangochi!D69+Mangochi!E69+Mangochi!F69 -> 184 | E69: ='Monkey Bay'!D69+'Monkey Bay'!E69+'Monkey Bay'!F69 -> 107 | F69: =Namwera!D69+Namwera!E69+Namwera!F69 -> 9 | G69: =Nkhudzi!D69+Nkhudzi!E69+Nkhudzi!F69 -> 86 | H69: =SUM(D69:G69) -> 386
B70: Total Done | C70: No | D70: =D68+D69 -> 184 | E70: =E68+E69 -> 107 | F70: =F68+F69 -> 9 | G70: =Nkhudzi!D70+Nkhudzi!E70+Nkhudzi!F70 -> 86 | H70: =SUM(D70:G70) -> 386
B71: Carried Forward | C71: No | D71: =D66+D67-D70 -> 2047 | E71: =E66+E67-E70 -> 27 | F71: =F66+F67-F70 -> 84 | G71: =G66+G67-G70 -> 2908 | H71: =H66+H67-H70 -> 5066
A72: New Institutional Water Connections | B72: Brought Forward | C72: No | D72: =Mangochi!D72 -> 4 | E72: ='Monkey Bay'!D72 -> 0 | F72: =Namwera!D72 -> 0 | G72: =Nkhudzi!D72+Nkhudzi!E72+Nkhudzi!F72 -> 20 | H72: =SUM(D72:G72) -> 24
B73: Applied this Month | C73: No | D73: =Mangochi!D73+Mangochi!E73+Mangochi!F73 -> 0 | E73: ='Monkey Bay'!D73+'Monkey Bay'!E73+'Monkey Bay'!F73 -> 0 | F73: =Namwera!D73+Namwera!E73+Namwera!F73 -> 0 | G73: =Nkhudzi!D73+Nkhudzi!E73+Nkhudzi!F73 -> 0 | H73: =SUM(D73:G73) -> 0
B74: Done this Month Postpaid | C74: No | D74: =Mangochi!D74+Mangochi!E74+Mangochi!F74 -> 0 | E74: ='Monkey Bay'!D74+'Monkey Bay'!E74+'Monkey Bay'!F74 -> 0 | F74: =Namwera!D74+Namwera!E74+Namwera!F74 -> 0 | G74: =Nkhudzi!D74+Nkhudzi!E74+Nkhudzi!F74 -> 0 | H74: =SUM(D74:G74) -> 0
B75: Done this Month Prepaid | C75: No | D75: =Mangochi!D75+Mangochi!E75+Mangochi!F75 -> 0 | E75: ='Monkey Bay'!D75+'Monkey Bay'!E75+'Monkey Bay'!F75 -> 0 | F75: =Namwera!D75+Namwera!E75+Namwera!F75 -> 0 | G75: =Nkhudzi!D75+Nkhudzi!E75+Nkhudzi!F75 -> 0 | H75: =SUM(D75:G75) -> 0
B76: Total Done | C76: No | D76: =D74+D75 -> 0 | E76: =E74+E75 -> 0 | F76: =F74+F75 -> 0 | G76: =Nkhudzi!D76+Nkhudzi!E76+Nkhudzi!F76 -> 0 | H76: =SUM(D76:G76) -> 0
B77: Carried Forward | C77: No | D77: =D73+D74-D76 -> 0 | E77: =E73+E74-E76 -> 0 | F77: =F73+F74-F76 -> 0 | G77: =G73+G74-G76 -> 0 | H77: =H72+H73-H76 -> 24
A78: New Commercial/Industrial Water Connections | B78: Brought Forward | C78: No | D78: =Mangochi!D78 -> 0 | E78: ='Monkey Bay'!D78 -> 7 | F78: =Namwera!D78 -> 0 | G78: =Nkhudzi!D78+Nkhudzi!E78+Nkhudzi!F78 -> 30 | H78: =SUM(D78:F78) -> 7
B79: Applied this Month | C79: No | D79: =Mangochi!D79+Mangochi!E79+Mangochi!F79 -> 0 | E79: ='Monkey Bay'!D79+'Monkey Bay'!E79+'Monkey Bay'!F79 -> 0 | F79: =Namwera!D79+Namwera!E79+Namwera!F79 -> 0 | G79: =Nkhudzi!D79+Nkhudzi!E79+Nkhudzi!F79 -> 0 | H79: =SUM(D79:G79) -> 0
B80: Done this Month Postpaid | C80: No | D80: =Mangochi!D80+Mangochi!E80+Mangochi!F80 -> 0 | E80: ='Monkey Bay'!D80+'Monkey Bay'!E80+'Monkey Bay'!F80 -> 0 | F80: =Namwera!D80+Namwera!E80+Namwera!F80 -> 0 | G80: =Nkhudzi!D80+Nkhudzi!E80+Nkhudzi!F80 -> 0 | H80: =SUM(D80:G80) -> 0
B81: Done this Month Prepaid | C81: No | D81: =Mangochi!D81+Mangochi!E81+Mangochi!F81 -> 0 | E81: ='Monkey Bay'!D81+'Monkey Bay'!E81+'Monkey Bay'!F81 -> 2 | F81: =Namwera!D81+Namwera!E81+Namwera!F81 -> 0 | G81: =Nkhudzi!D81+Nkhudzi!E81+Nkhudzi!F81 -> 0 | H81: =SUM(D81:G81) -> 2
B82: Total Done | C82: No | D82: =D81+D80 -> 0 | E82: =E81+E80 -> 2 | F82: =F81+F80 -> 0 | G82: =Nkhudzi!D82+Nkhudzi!E82+Nkhudzi!F82 -> 0 | H82: =SUM(D82:G82) -> 2
B83: Carried Forward | C83: No | D83: =D78+D79-D82 -> 0 | E83: =E78+E79-E82 -> 5 | F83: =F78+F79-F82 -> 0 | G83: =Nkhudzi!D83+Nkhudzi!E83+Nkhudzi!F83 -> 30 | H83: =H78+H79-H82 -> 5
A84: New CWP | B84: Brought Forward | C84: No | D84: =Mangochi!D84 -> 10 | E84: ='Monkey Bay'!D84 -> 0 | F84: =Namwera!D84 -> 0 | G84: =Nkhudzi!D84+Nkhudzi!E84+Nkhudzi!F84 -> 0 | H84: =SUM(D84:G84) -> 10
B85: Applied this Month | C85: No | D85: =Mangochi!D85+Mangochi!E85+Mangochi!F85 -> 0 | E85: ='Monkey Bay'!D85+'Monkey Bay'!E85+'Monkey Bay'!F85 -> 0 | F85: =Namwera!D85+Namwera!E85+Namwera!F85 -> 0 | G85: =Nkhudzi!D85+Nkhudzi!E85+Nkhudzi!F85 -> 0 | H85: =SUM(D85:G85) -> 0
B86: Done this Month Postpaid | C86: No | D86: =Mangochi!D86+Mangochi!E86+Mangochi!F86 -> 0 | E86: ='Monkey Bay'!D86+'Monkey Bay'!E86+'Monkey Bay'!F86 -> 0 | F86: =Namwera!D86+Namwera!E86+Namwera!F86 -> 0 | G86: =Nkhudzi!D86+Nkhudzi!E86+Nkhudzi!F86 -> 0 | H86: =SUM(D86:G86) -> 0
B87: Done this Month Prepaid | C87: No | D87: =Mangochi!D87+Mangochi!E87+Mangochi!F87 -> 1 | E87: ='Monkey Bay'!D87+'Monkey Bay'!E87+'Monkey Bay'!F87 -> 0 | F87: =Namwera!D87+Namwera!E87+Namwera!F87 -> 0 | G87: =Nkhudzi!D87+Nkhudzi!E87+Nkhudzi!F87 -> 0 | H87: =SUM(D87:G87) -> 1
B88: Total Done | C88: No | D88: =D87+D86 -> 1 | E88: =E87+E86 -> 0 | F88: =F87+F86 -> 0 | G88: =Nkhudzi!D88+Nkhudzi!E88+Nkhudzi!F88 -> 0 | H88: =SUM(D88:G88) -> 1
B89: Carried Forward | C89: No | D89: =D84+D85-D88 -> 9 | E89: =E84+E85-E88 -> 0 | F89: =F84+F85-F88 -> 0 | G89: =Nkhudzi!D89+Nkhudzi!E89+Nkhudzi!F89 -> 0 | H89: =H84+H85-H88 -> 9
A90: Aggregated New Water connections | B90: Brought Forward | C90: No | D90: =D66+D72+D78+D84 -> 1992 | E90: =E66+E72+E78+E84 -> 84 | F90: =F66+F72+F78+F84 -> 76 | G90: =G66+G72+G78+G84 -> 2984 | H90: =SUM(D90:G90) -> 5136
B91: Applied this Month | C91: No | D91: =D67+D73+D79+D85 -> 253 | E91: =E67+E73+E79+E85 -> 57 | F91: =F67+F73+F79+F85 -> 17 | G91: =G67+G73+G79+G85 -> 60 | H91: =SUM(D91:G91) -> 387
B92: Done this Month Postpaid | C92: No | D92: =D68+D74+D80+D86 -> 0 | E92: =E68+E74+E80+E86 -> 0 | F92: =F68+F74+F80+F86 -> 0 | G92: =G68+G74+G80+G86 -> 0 | H92: =SUM(D92:G92) -> 0
B93: Done this Month Prepaid | D93: =D69+D75+D81+D87 -> 185 | E93: =E69+E75+E81+E87 -> 109 | F93: =F69+F75+F81+F87 -> 9 | G93: =G69+G75+G81+G87 -> 86 | H93: =SUM(D93:G93) -> 389
B94: Total Done | C94: No | D94: =D93+D92 -> 185 | E94: =E93+E92 -> 109 | F94: =F93+F92 -> 9 | G94: =G93+G92 -> 86 | H94: =SUM(D94:G94) -> 389
B95: Carried Forward | C95: No | D95: =D90+D91-D94 -> 2060 | E95: =E90+E91-E94 -> 32 | F95: =F90+F91-F94 -> 84 | G95: =G90+G91-G94 -> 2958 | H95: =H90+H91-H94 -> 5134
A97: Prepaid Metering
A98: Prepaid Meters Installed | C98: No | D98: =Mangochi!D98+Mangochi!E98+Mangochi!F98 -> 185 | E98: ='Monkey Bay'!D98+'Monkey Bay'!E98+'Monkey Bay'!F98 -> 109 | F98: =Namwera!D98+Namwera!E98+Namwera!F98 -> 9 | G98: =Nkhudzi!D98+Nkhudzi!E98+Nkhudzi!F98 -> 86 | H98: =SUM(D98:G98) -> 389
A100: Active and Disconnected Accounts
A101: Disconnected Individual Accounts | C101: No | D101: =Mangochi!F101 -> 0 | E101: ='Monkey Bay'!F101 -> 0 | F101: =Namwera!F101 -> 0 | G101: =Nkhudzi!F101 -> 0 | H101: =SUM(D101:G101) -> 0
A102: Disconnected institutional Accounts | C102: No | D102: =Mangochi!F102 -> 0 | E102: ='Monkey Bay'!F102 -> 0 | F102: =Namwera!F102 -> 0 | G102: =Nkhudzi!F102 -> 0 | H102: =SUM(D102:G102) -> 0
A103: Disconnected Commercial/Industrial Accounts | C103: No | D103: =Mangochi!F103 -> 0 | E103: ='Monkey Bay'!F103 -> 0 | F103: =Namwera!F103 -> 0 | G103: =Nkhudzi!F103 -> 0 | H103: =SUM(D103:G103) -> 0
A104: Disconnected CWP | C104: No | D104: =Mangochi!F104 -> 0 | E104: ='Monkey Bay'!F104 -> 0 | F104: =Namwera!F104 -> 0 | G104: =Nkhudzi!F104 -> 0 | H104: =SUM(D104:G104) -> 0
A105: Total Disconnected Accounts | C105: No | D105: =SUM(D101:D104) -> 0 | E105: =SUM(E101:E104) -> 0 | F105: =SUM(F101:F104) -> 0 | G105: =SUM(G101:G104) -> 0 | H105: =SUM(H101:H104) -> 0
...

Sheet 2nd QTR 
A1: SOUTHERN REGION WATER BOARD
A3: MONTHLY REPORTS - 2025/2026
A4: MANGOCHI ZONE
A5: MANGOCHI ZONE
A7: PARAMETERS | C7: UNITS | D7: Mangochi | E7: Monkey Bay | F7: Namwera | G7: Nkhudzi | H7: TOTALS
A8: PRODUCTION
A9: Volume Produced | C9: m3 | D9: =Mangochi!G9+Mangochi!H9+Mangochi!I9 -> 0 | E9: ='Monkey Bay'!G9+'Monkey Bay'!H9+'Monkey Bay'!I9 -> 0 | F9: =Namwera!G9+Namwera!H9+Namwera!I9 -> 0 | G9: =Nkhudzi!G9+Nkhudzi!H9+Nkhudzi!I9 -> 0 | H9: =SUM(D9:G9) -> 0
A10: REVENUE WATER - POSTPAID
A11: Volume Billed Individuals | C11: m3 | D11: =Mangochi!G11+Mangochi!H11+Mangochi!I11 -> 0 | E11: ='Monkey Bay'!G11+'Monkey Bay'!H11+'Monkey Bay'!I11 -> 0 | F11: =Namwera!G11+Namwera!H11+Namwera!I11 -> 0 | G11: =Nkhudzi!G11+Nkhudzi!H11+Nkhudzi!I11 -> 0 | H11: =SUM(D11:G11) -> 0
A12: Volume Billed CWPs | C12: m3 | D12: =Mangochi!G12+Mangochi!H12+Mangochi!I12 -> 0 | E12: ='Monkey Bay'!G12+'Monkey Bay'!H12+'Monkey Bay'!I12 -> 0 | F12: =Namwera!G12+Namwera!H12+Namwera!I12 -> 0 | G12: =Nkhudzi!G12+Nkhudzi!H12+Nkhudzi!I12 -> 0 | H12: =SUM(D12:G12) -> 0
A13: Volume Billed Institutions | C13: m3 | D13: =Mangochi!G13+Mangochi!H13+Mangochi!I13 -> 0 | E13: ='Monkey Bay'!G13+'Monkey Bay'!H13+'Monkey Bay'!I13 -> 0 | F13: =Namwera!G13+Namwera!H13+Namwera!I13 -> 0 | G13: =Nkhudzi!G13+Nkhudzi!H13+Nkhudzi!I13 -> 0 | H13: =SUM(D13:G13) -> 0
A14: Volume Billed Commercial/Industrial | C14: m3 | D14: =Mangochi!G14+Mangochi!H14+Mangochi!I14 -> 0 | E14: ='Monkey Bay'!G14+'Monkey Bay'!H14+'Monkey Bay'!I14 -> 0 | F14: =Namwera!G14+Namwera!H14+Namwera!I14 -> 0 | G14: =Nkhudzi!G14+Nkhudzi!H14+Nkhudzi!I14 -> 0 | H14: =SUM(D14:G14) -> 0
A15: Total Volume Billed Post Paid | C15: m3 | D15: =SUM(D11:D14) -> 0 | E15: =SUM(E11:E14) -> 0 | F15: =SUM(F11:F14) -> 0 | G15: =SUM(G11:G14) -> 0 | H15: =SUM(D15:G15) -> 0
A16: REVENUE WATER - PREPAID
A17: Individuals | C17: m3 | D17: =Mangochi!G17+Mangochi!H17+Mangochi!I17 -> 0 | E17: ='Monkey Bay'!G17+'Monkey Bay'!H17+'Monkey Bay'!I17 -> 0 | F17: =Namwera!G17+Namwera!H17+Namwera!I17 -> 0 | G17: =Nkhudzi!G17+Nkhudzi!H17+Nkhudzi!I17 -> 0 | H17: =SUM(D17:G17) -> 0
A18: CWPs | C18: m3 | D18: =Mangochi!G18+Mangochi!H18+Mangochi!I18 -> 0 | E18: ='Monkey Bay'!G18+'Monkey Bay'!H18+'Monkey Bay'!I18 -> 0 | F18: =Namwera!G18+Namwera!H18+Namwera!I18 -> 0 | G18: =Nkhudzi!G18+Nkhudzi!H18+Nkhudzi!I18 -> 0 | H18: =SUM(D18:G18) -> 0
A19: Institutions | C19: m3 | D19: =Mangochi!G19+Mangochi!H19+Mangochi!I19 -> 0 | E19: ='Monkey Bay'!G19+'Monkey Bay'!H19+'Monkey Bay'!I19 -> 0 | F19: =Namwera!G19+Namwera!H19+Namwera!I19 -> 0 | G19: =Nkhudzi!G19+Nkhudzi!H19+Nkhudzi!I19 -> 0 | H19: =SUM(D19:G19) -> 0
A20: Commercial/Industrial | C20: m3 | D20: =Mangochi!G20+Mangochi!H20+Mangochi!I20 -> 0 | E20: ='Monkey Bay'!G20+'Monkey Bay'!H20+'Monkey Bay'!I20 -> 0 | F20: =Namwera!G20+Namwera!H20+Namwera!I20 -> 0 | G20: =Nkhudzi!G20+Nkhudzi!H20+Nkhudzi!I20 -> 0 | H20: =SUM(D20:G20) -> 0
A21: Total Volume Prepaid | C21: m3 | D21: =SUM(D17:D20) -> 0 | E21: =SUM(E17:E20) -> 0 | F21: =SUM(F17:F20) -> 0 | G21: =SUM(G17:G20) -> 0 | H21: =SUM(D21:G21) -> 0
A22: TOTAL REVENUE WATER | C22: m3 | D22: =D21+D15 -> 0 | E22: =E21+E15 -> 0 | F22: =F21+F15 -> 0 | G22: =G21+G15 -> 0 | H22: =SUM(D22:G22) -> 0
A23: NON-REVENUE WATER (NRW)
A24: Non-Revenue Water (NRW) | B24: Volume | C24: m3 | D24: =D9-D22 -> 0 | E24: =E9-E22 -> 0 | F24: =F9-F22 -> 0 | G24: =G9-G22 -> 0 | H24: =H9-H22 -> 0
B25: Percentage | C25: % | D25: =D24/D9 -> #DIV/0! | E25: =E24/E9 -> #DIV/0! | F25: =F24/F9 -> #DIV/0! | G25: =G24/G9 -> #DIV/0! | H25: =H24/H9 -> #DIV/0!
A26: OPERATING EXPENSES
A27: Chemicals
A28: Chemical | B28: Rate(MK/kg)
A29: Chlorine | B29: 3525.29 | C29: kg | D29: =Mangochi!G29+Mangochi!H29+Mangochi!I29 -> 0 | E29: ='Monkey Bay'!G29+'Monkey Bay'!H29+'Monkey Bay'!I29 -> 0 | F29: =Namwera!G29+Namwera!H29+Namwera!I29 -> 0 | G29: =Nkhudzi!G29+Nkhudzi!H29+Nkhudzi!I29 -> 0 | H29: =SUM(D29:G29) -> 0
C30: kg/mg litre | D30: =D29/(D9/1000) -> #DIV/0! | E30: =E29/(E9/1000) -> #DIV/0! | F30: =F29/(F9/1000) -> #DIV/0! | G30: =G29/(G9/1000) -> #DIV/0! | H30: =H29/(H9/1000) -> #DIV/0!
A31: Aluminium sulphate | B31: 1060.0102 | C31: kg | D31: =Mangochi!G31+Mangochi!H31+Mangochi!I31 -> 0 | E31: ='Monkey Bay'!G31+'Monkey Bay'!H31+'Monkey Bay'!I31 -> 0 | F31: =Namwera!G31+Namwera!H31+Namwera!I31 -> 0 | G31: =Nkhudzi!G31+Nkhudzi!H31+Nkhudzi!I31 -> 0 | H31: =SUM(D31:G31) -> 0
C32: kg/mg litre | D32: =D31/(D9/1000) -> #DIV/0! | E32: =E31/(E9/1000) -> #DIV/0! | F32: =F31/(F9/1000) -> #DIV/0! | G32: =Nkhudzi!J32+Nkhudzi!K32+Nkhudzi!L32 -> #DIV/0! | H32: =H31/(H9/1000) -> #DIV/0!
A33: Soda | B33: 1228.2886 | C33: kg | D33: =Mangochi!G33+Mangochi!H33+Mangochi!I33 -> 0 | E33: ='Monkey Bay'!G33+'Monkey Bay'!H33+'Monkey Bay'!I33 -> 0 | F33: =Namwera!G33+Namwera!H33+Namwera!I33 -> 0 | G33: =Nkhudzi!G33+Nkhudzi!H33+Nkhudzi!I33 -> 0 | H33: =SUM(D33:F33) -> 0
C34: kg/mg litre | D34: =D33/(D9/1000) -> #DIV/0! | E34: =E33/(E9/1000) -> #DIV/0! | F34: =F33/(F9/1000) -> #DIV/0! | G34: =Nkhudzi!J34+Nkhudzi!K34+Nkhudzi!L34 -> #DIV/0! | H34: =H33/(H9/1000) -> #DIV/0!
A35: Algae floc | B35: 3726.7258 | C35: litres | D35: =Mangochi!G35+Mangochi!H35+Mangochi!I35 -> 0 | E35: ='Monkey Bay'!G35+'Monkey Bay'!H35+'Monkey Bay'!I35 -> 0 | F35: =Namwera!G35+Namwera!H35+Namwera!I35 -> 0 | G35: =Nkhudzi!G35+Nkhudzi!H35+Nkhudzi!I35 -> 0
C36: litres/mg litre | G36: =Nkhudzi!G36+Nkhudzi!H36+Nkhudzi!I36 -> 0
A37: Sud floc | B37: 3951.5936 | C37: litres | D37: =Mangochi!G37+Mangochi!H37+Mangochi!I37 -> 0 | E37: ='Monkey Bay'!G37+'Monkey Bay'!H37+'Monkey Bay'!I37 -> 0 | F37: =Namwera!G37+Namwera!H37+Namwera!I37 -> 0 | G37: =Nkhudzi!G37+Nkhudzi!H37+Nkhudzi!I37 -> 0 | H37: =SUM(D37:F37) -> 0
C38: litres/mg litre | D38: =D37/(D9/1000) -> #DIV/0! | E38: =E37/(E9/1000) -> #DIV/0! | F38: =F37/(F9/1000) -> #DIV/0! | G38: =Nkhudzi!J38+Nkhudzi!K38+Nkhudzi!L38 -> #DIV/0! | H38: =H37/(H9/1000) -> #DIV/0!
A39: Potasium permanganate | B39: 1950 | C39: kg | D39: =Mangochi!G39+Mangochi!H39+Mangochi!I39 -> 0 | E39: ='Monkey Bay'!G39+'Monkey Bay'!H39+'Monkey Bay'!I39 -> 0 | F39: =Namwera!G39+Namwera!H39+Namwera!I39 -> 0 | G39: =Nkhudzi!G39+Nkhudzi!H39+Nkhudzi!I39 -> 0 | H39: =SUM(D39:F39) -> 0
C40: kg/mg litre | D40: =D39/(D9/1000) -> #DIV/0! | E40: =E39/(E9/1000) -> #DIV/0! | F40: =F39/(F9/1000) -> #DIV/0! | G40: =Nkhudzi!J40+Nkhudzi!K40+Nkhudzi!L40 -> #DIV/0! | H40: =H39/(H9/1000) -> #DIV/0!
A41: Cost of Chemicals | C41: Mk | D41: =(D29*$B29)+(D31*$B31)+(D33*$B33)+(D35*$B35)+(D37*$B37)+(D39*$B39) -> 0 | E41: =(E29*$B29)+(E31*$B31)+(E33*$B33)+(E35*$B35)+(E37*$B37)+(E39*$B39) -> 0 | F41: =(F29*$B29)+(F31*$B31)+(F33*$B33)+(F35*$B35)+(F37*$B37)+(F39*$B39) -> 0 | G41: =(G29*$B29)+(G31*$B31)+(G33*$B33)+(G35*$B35)+(G37*$B37)+(G39*$B39) -> 0 | H41: =SUM(D41:G41) -> 0
A42: Cost/vol. Produced (chemicals) | C42: Mk/m3 | D42: =D41/D9 -> #DIV/0! | E42: =E41/E9 -> #DIV/0! | F42: =F41/F9 -> #DIV/0! | G42: =G41/G9 -> #DIV/0! | H42: =H41/H9 -> #DIV/0!
A43: Power
A44: Power Usage | C44: Kw | D44: =Mangochi!G44+Mangochi!H44+Mangochi!I44 -> 0 | E44: ='Monkey Bay'!G44+'Monkey Bay'!H44+'Monkey Bay'!I44 -> 0 | F44: =Namwera!G44+Namwera!H44+Namwera!I44 -> 0 | G44: =Nkhudzi!G44+Nkhudzi!H44+Nkhudzi!I44 -> 0 | H44: =SUM(D44:G44) -> 0
A45: Power/ Vol. Produced | C45: Kw/m3 | D45: =D44/D9 -> #DIV/0! | E45: =E44/E9 -> #DIV/0! | F45: =F44/F9 -> #DIV/0! | G45: =G44/G9 -> #DIV/0! | H45: =H44/H9 -> #DIV/0!
A46: Cost of Power | C46: Mk | D46: =Mangochi!G46+Mangochi!H46+Mangochi!I46 -> 58017 | E46: ='Monkey Bay'!G46+'Monkey Bay'!H46+'Monkey Bay'!I46 -> 58017 | F46: =Namwera!G46+Namwera!H46+Namwera!I46 -> 58017 | G46: =Nkhudzi!G46+Nkhudzi!H46+Nkhudzi!I46 -> 58017 | H46: =SUM(D46:G46) -> 232068
A47: Cost/vol. Produced | C47: Mk/m3 | D47: =D46/D9 -> #DIV/0! | E47: =E46/E9 -> #DIV/0! | F47: =F46/F9 -> #DIV/0! | G47: =G46/G9 -> #DIV/0! | H47: =H46/H9 -> #DIV/0!
A48: Plant and Vehicle Maintenance
A49: Distances covered | C49: km | D49: =Mangochi!G49+Mangochi!H49+Mangochi!I49 -> 0 | E49: ='Monkey Bay'!G49+'Monkey Bay'!H49+'Monkey Bay'!I49 -> 0 | F49: =Namwera!G49+Namwera!H49+Namwera!I49 -> 0 | G49: =Nkhudzi!G49+Nkhudzi!H49+Nkhudzi!I49 -> 0 | H49: =SUM(D49:G49) -> 0
A50: Fuel Used (litres) | C50: litres | D50: =Mangochi!G50+Mangochi!H50+Mangochi!I50 -> 0 | E50: ='Monkey Bay'!G50+'Monkey Bay'!H50+'Monkey Bay'!I50 -> 0 | F50: =Namwera!G50+Namwera!H50+Namwera!I50 -> 0 | G50: =Nkhudzi!G50+Nkhudzi!H50+Nkhudzi!I50 -> 0 | H50: =SUM(D50:G50) -> 0
A51: Cost of fuel | C51: Mk | D51: =Mangochi!G51+Mangochi!H51+Mangochi!I51 -> 0 | E51: ='Monkey Bay'!G51+'Monkey Bay'!H51+'Monkey Bay'!I51 -> 0 | F51: =Namwera!G51+Namwera!H51+Namwera!I51 -> 0 | G51: =Nkhudzi!G51+Nkhudzi!H51+Nkhudzi!I51 -> 0 | H51: =SUM(D51:G51) -> 0
A52: Maintenance | C52: Mk | D52: =Mangochi!G52+Mangochi!H52+Mangochi!I52 -> 0 | E52: ='Monkey Bay'!G52+'Monkey Bay'!H52+'Monkey Bay'!I52 -> 0 | F52: =Namwera!G52+Namwera!H52+Namwera!I52 -> 0 | G52: =Nkhudzi!M52+Nkhudzi!N52+Nkhudzi!O52 -> 0 | H52: =SUM(D52:G52) -> 0
A53: Salaries and Wages
A54: Staff Costs | C54: MK | D54: =Mangochi!G54+Mangochi!H54+Mangochi!I54 -> 0 | E54: ='Monkey Bay'!G54+'Monkey Bay'!H54+'Monkey Bay'!I54 -> 0 | F54: =Namwera!G54+Namwera!H54+Namwera!I54 -> 0 | G54: =Nkhudzi!G54+Nkhudzi!H54+Nkhudzi!I54 -> 0 | H54: =SUM(D54:G54) -> 0
A55: Wages | C55: MK | D55: =Mangochi!G55+Mangochi!H55+Mangochi!I55 -> 0 | E55: ='Monkey Bay'!G55+'Monkey Bay'!H55+'Monkey Bay'!I55 -> 0 | F55: =Namwera!G55+Namwera!H55+Namwera!I55 -> 0 | G55: =Nkhudzi!G55+Nkhudzi!H55+Nkhudzi!I55 -> 0 | H55: =SUM(D55:G55) -> 0
A56: Other Overhead Costs | C56: MK | D56: =Mangochi!G56+Mangochi!H56+Mangochi!I56 -> 0 | E56: ='Monkey Bay'!G56+'Monkey Bay'!H56+'Monkey Bay'!I56 -> 0 | F56: =Namwera!G56+Namwera!H56+Namwera!I56 -> 0 | G56: =Nkhudzi!G56+Nkhudzi!H56+Nkhudzi!I56 -> 0 | H56: =SUM(D56:G56) -> 0
A57: Operating Costs
A58: Total Operating Costs | C58: MK | D58: =D41+D46+D51+D52+D54+D55+D56 -> 58017 | E58: =E41+E46+E51+E52+E54+E55+E56 -> 58017 | F58: =F41+F46+F51+F52+F54+F55+F56 -> 58017 | G58: =G41+G46+G51+G52+G54+G55+G56 -> 58017 | H58: =SUM(D58:G58) -> 232068
A59: Cost/Vol. Produced | C59: Mk/m3 | D59: =D58/D9 -> #DIV/0! | E59: =E58/E9 -> #DIV/0! | F59: =F58/F9 -> #DIV/0! | G59: =G58/G9 -> #DIV/0! | H59: =H58/H9 -> #DIV/0!
A60: Cost/Vol. Billed | C60: Mk/m3 | D60: =D58/D22 -> #DIV/0! | E60: =E58/E22 -> #DIV/0! | F60: =F58/F22 -> #DIV/0! | G60: =G58/G22 -> #DIV/0! | H60: =H58/H22 -> #DIV/0!
A61: Permanent Staff Employed | C61: No | D61: =Mangochi!I61 -> 0 | E61: ='Monkey Bay'!I61 -> 0 | F61: =Namwera!I61 -> 0 | G61: =Nkhudzi!I61 -> 0 | H61: =SUM(D61:G61) -> 0
A62: Staff/Vol.1000m3 of Volume Produced/hour (12 hour day) | C62: No/1000m3 | D62: =(D61*1000*31)/D9 -> #DIV/0! | E62: =(E61*1000*31)/E9 -> #DIV/0! | F62: =(F61*1000*31)/F9 -> #DIV/0! | G62: =(G61*1000*31)/G9 -> #DIV/0! | H62: =(H61*1000*31)/H9 -> #DIV/0!
A63: Temporary Staff Employed | C63: No | D63: =Mangochi!I63 -> 0 | E63: ='Monkey Bay'!I63 -> 0 | F63: =Namwera!I63 -> 0 | G63: =Nkhudzi!I63 -> 0 | H63: =SUM(D63:G63) -> 0
A65: Water Connections and Disconnections
A66: New Individual Water Connections | B66: Brought Forward | C66: No | D66: =Mangochi!G66 -> 0 | E66: ='Monkey Bay'!G66 -> 0 | F66: =Namwera!G66 -> 0 | G66: =Nkhudzi!G66 -> 0 | H66: =SUM(D66:G66) -> 0
B67: Applied this Month | C67: No | D67: =Mangochi!G67+Mangochi!H67+Mangochi!I67 -> 0 | E67: ='Monkey Bay'!G67+'Monkey Bay'!H67+'Monkey Bay'!I67 -> 0 | F67: =Namwera!G67+Namwera!H67+Namwera!I67 -> 0 | G67: =Nkhudzi!G67+Nkhudzi!H67+Nkhudzi!I67 -> 0 | H67: =SUM(D67:G67) -> 0
B68: Done this Month Postpaid | C68: No | D68: =Mangochi!G68+Mangochi!H68+Mangochi!I68 -> 0 | E68: ='Monkey Bay'!G68+'Monkey Bay'!H68+'Monkey Bay'!I68 -> 0 | F68: =Namwera!G68+Namwera!H68+Namwera!I68 -> 0 | G68: =Nkhudzi!G68+Nkhudzi!H68+Nkhudzi!I68 -> 0 | H68: =SUM(D68:G68) -> 0
B69: Done this Month Prepaid | C69: No | D69: =Mangochi!G69+Mangochi!H69+Mangochi!I69 -> 0 | E69: ='Monkey Bay'!G69+'Monkey Bay'!H69+'Monkey Bay'!I69 -> 0 | F69: =Namwera!G69+Namwera!H69+Namwera!I69 -> 0 | G69: =Nkhudzi!G69+Nkhudzi!H69+Nkhudzi!I69 -> 0 | H69: =SUM(D69:G69) -> 0
B70: Total Done | C70: No | D70: =D68+D69 -> 0 | E70: =E68+E69 -> 0 | F70: =F68+F69 -> 0 | G70: =Nkhudzi!G70+Nkhudzi!H70+Nkhudzi!I70 -> 0 | H70: =SUM(D70:G70) -> 0
B71: Carried Forward | C71: No | D71: =D66+D67-D70 -> 0 | E71: =E66+E67-E70 -> 0 | F71: =F66+F67-F70 -> 0 | G71: =G66+G67-G70 -> 0 | H71: =H66+H67-H70 -> 0
A72: New Institutional Water Connections | B72: Brought Forward | C72: No | D72: =Mangochi!G72 -> 0 | E72: ='Monkey Bay'!G72 -> 0 | F72: =Namwera!G72 -> 0 | G72: =Namwera!H72 -> 0 | H72: =SUM(D72:G72) -> 0
B73: Applied this Month | C73: No | D73: =Mangochi!G73+Mangochi!H73+Mangochi!I73 -> 0 | E73: ='Monkey Bay'!G73+'Monkey Bay'!H73+'Monkey Bay'!I73 -> 0 | F73: =Namwera!G73+Namwera!H73+Namwera!I73 -> 0 | G73: =Nkhudzi!G73+Nkhudzi!H73+Nkhudzi!I73 -> 0 | H73: =SUM(D73:G73) -> 0
B74: Done this Month Postpaid | C74: No | D74: =Mangochi!G74+Mangochi!H74+Mangochi!I74 -> 0 | E74: ='Monkey Bay'!G74+'Monkey Bay'!H74+'Monkey Bay'!I74 -> 0 | F74: =Namwera!G74+Namwera!H74+Namwera!I74 -> 0 | G74: =Nkhudzi!G74+Nkhudzi!H74+Nkhudzi!I74 -> 0 | H74: =SUM(D74:G74) -> 0
B75: Done this Month Prepaid | C75: No | D75: =Mangochi!G75+Mangochi!H75+Mangochi!I75 -> 0 | E75: ='Monkey Bay'!G75+'Monkey Bay'!H75+'Monkey Bay'!I75 -> 0 | F75: =Namwera!G75+Namwera!H75+Namwera!I75 -> 0 | G75: =Nkhudzi!G75+Nkhudzi!H75+Nkhudzi!I75 -> 0 | H75: =SUM(D75:G75) -> 0
B76: Total Done | C76: No | D76: =D74+D75 -> 0 | E76: =E74+E75 -> 0 | F76: =F74+F75 -> 0 | G76: =G74+G75 -> 0 | H76: =SUM(D76:G76) -> 0
B77: Carried Forward | C77: No | D77: =D73+D74-D76 -> 0 | E77: =E73+E74-E76 -> 0 | F77: =F73+F74-F76 -> 0 | G77: =G73+G74-G76 -> 0 | H77: =H72+H73-H76 -> 0
A78: New Commercial/Industrial Water Connections | B78: Brought Forward | C78: No | D78: =Mangochi!G78 -> 0 | E78: ='Monkey Bay'!G78 -> 0 | F78: =Namwera!G78 -> 0 | G78: =Nkhudzi!G78+Nkhudzi!H78+Nkhudzi!I78 -> 0 | H78: =SUM(D78:F78) -> 0
B79: Applied this Month | C79: No | D79: =Mangochi!G79+Mangochi!H79+Mangochi!I79 -> 0 | E79: ='Monkey Bay'!G79+'Monkey Bay'!H79+'Monkey Bay'!I79 -> 0 | F79: =Namwera!G79+Namwera!H79+Namwera!I79 -> 0 | G79: =Nkhudzi!G79+Nkhudzi!H79+Nkhudzi!I79 -> 0 | H79: =SUM(D79:G79) -> 0
B80: Done this Month Postpaid | C80: No | D80: =Mangochi!G80+Mangochi!H80+Mangochi!I80 -> 0 | E80: ='Monkey Bay'!G80+'Monkey Bay'!H80+'Monkey Bay'!I80 -> 0 | F80: =Namwera!G80+Namwera!H80+Namwera!I80 -> 0 | G80: =Nkhudzi!G80+Nkhudzi!H80+Nkhudzi!I80 -> 0 | H80: =SUM(D80:G80) -> 0
B81: Done this Month Prepaid | C81: No | D81: =Mangochi!G81+Mangochi!H81+Mangochi!I81 -> 0 | E81: ='Monkey Bay'!G81+'Monkey Bay'!H81+'Monkey Bay'!I81 -> 0 | F81: =Namwera!G81+Namwera!H81+Namwera!I81 -> 0 | G81: =Nkhudzi!G81+Nkhudzi!H81+Nkhudzi!I81 -> 0 | H81: =SUM(D81:G81) -> 0
B82: Total Done | C82: No | D82: =D81+D80 -> 0 | E82: =E81+E80 -> 0 | F82: =F81+F80 -> 0 | G82: =G81+G80 -> 0 | H82: =SUM(D82:G82) -> 0
B83: Carried Forward | C83: No | D83: =D78+D79-D82 -> 0 | E83: =E78+E79-E82 -> 0 | F83: =F78+F79-F82 -> 0 | G83: =G78+G79-G82 -> 0 | H83: =H78+H79-H82 -> 0
A84: New CWP | B84: Brought Forward | C84: No | D84: =Mangochi!G84 -> 0 | E84: ='Monkey Bay'!G84 -> 0 | F84: =Namwera!G84 -> 0 | G84: =Nkhudzi!G84 -> 0 | H84: =SUM(D84:G84) -> 0
B85: Applied this Month | C85: No | D85: =Mangochi!G85+Mangochi!H85+Mangochi!I85 -> 0 | E85: ='Monkey Bay'!G85+'Monkey Bay'!H85+'Monkey Bay'!I85 -> 0 | F85: =Namwera!G85+Namwera!H85+Namwera!I85 -> 0 | G85: =Nkhudzi!G85+Nkhudzi!H85+Nkhudzi!I85 -> 0 | H85: =SUM(D85:G85) -> 0
B86: Done this Month Postpaid | C86: No | D86: =Mangochi!G86+Mangochi!H86+Mangochi!I86 -> 0 | E86: ='Monkey Bay'!G86+'Monkey Bay'!H86+'Monkey Bay'!I86 -> 0 | F86: =Namwera!G86+Namwera!H86+Namwera!I86 -> 0 | G86: =Nkhudzi!G86+Nkhudzi!H86+Nkhudzi!I86 -> 0 | H86: =SUM(D86:G86) -> 0
B87: Done this Month Prepaid | C87: No | D87: =Mangochi!G87+Mangochi!H87+Mangochi!I87 -> 0 | E87: ='Monkey Bay'!G87+'Monkey Bay'!H87+'Monkey Bay'!I87 -> 0 | F87: =Namwera!G87+Namwera!H87+Namwera!I87 -> 0 | G87: =Nkhudzi!G87+Nkhudzi!H87+Nkhudzi!I87 -> 0 | H87: =SUM(D87:G87) -> 0
B88: Total Done | C88: No | D88: =D87+D86 -> 0 | E88: =E87+E86 -> 0 | F88: =F87+F86 -> 0 | G88: =G87+G86 -> 0 | H88: =SUM(D88:G88) -> 0
B89: Carried Forward | C89: No | D89: =D84+D85-D88 -> 0 | E89: =E84+E85-E88 -> 0 | F89: =F84+F85-F88 -> 0 | G89: =G84+G85-G88 -> 0 | H89: =H84+H85-H88 -> 0
A90: Aggregated New Water connections | B90: Brought Forward | C90: No | D90: =D66+D72+D78+D84 -> 0 | E90: =E66+E72+E78+E84 -> 0 | F90: =F66+F72+F78+F84 -> 0 | G90: =G66+G72+G78+G84 -> 0 | H90: =SUM(D90:G90) -> 0
B91: Applied this Month | C91: No | D91: =D67+D73+D79+D85 -> 0 | E91: =E67+E73+E79+E85 -> 0 | F91: =F67+F73+F79+F85 -> 0 | G91: =G67+G73+G79+G85 -> 0 | H91: =SUM(D91:G91) -> 0
B92: Done this Month Postpaid | C92: No | D92: =D68+D74+D80+D86 -> 0 | E92: =E68+E74+E80+E86 -> 0 | F92: =F68+F74+F80+F86 -> 0 | G92: =G68+G74+G80+G86 -> 0 | H92: =SUM(D92:G92) -> 0
B93: Done this Month Prepaid | D93: =D69+D75+D81+D87 -> 0 | E93: =E69+E75+E81+E87 -> 0 | F93: =F69+F75+F81+F87 -> 0 | G93: =G69+G75+G81+G87 -> 0 | H93: =SUM(D93:G93) -> 0
B94: Total Done | C94: No | D94: =D93+D92 -> 0 | E94: =E93+E92 -> 0 | F94: =F93+F92 -> 0 | G94: =G93+G92 -> 0 | H94: =SUM(D94:G94) -> 0
B95: Carried Forward | C95: No | D95: =D90+D91-D94 -> 0 | E95: =E90+E91-E94 -> 0 | F95: =F90+F91-F94 -> 0 | G95: =G90+G91-G94 -> 0 | H95: =H90+H91-H94 -> 0
A97: Prepaid Metering
A98: Prepaid Meters Installed | C98: No | D98: =Mangochi!G98+Mangochi!H98+Mangochi!I98 -> 0 | E98: ='Monkey Bay'!G98+'Monkey Bay'!H98+'Monkey Bay'!I98 -> 0 | F98: =Namwera!G98+Namwera!H98+Namwera!I98 -> 0 | G98: =Nkhudzi!G98+Nkhudzi!H98+Nkhudzi!I98 -> 0 | H98: =SUM(D98:G98) -> 0
A100: Active and Disconnected Accounts
A101: Disconnected Individual Accounts | C101: No | D101: =Mangochi!I101 -> 0 | E101: ='Monkey Bay'!I101 -> 0 | F101: =Namwera!I101 -> 0 | G101: =Nkhudzi!I101 -> 0 | H101: =SUM(D101:G101) -> 0
A102: Disconnected institutional Accounts | C102: No | D102: =Mangochi!I102 -> 0 | E102: ='Monkey Bay'!I102 -> 0 | F102: =Namwera!I102 -> 0 | G102: =Nkhudzi!I102 -> 0 | H102: =SUM(D102:G102) -> 0
A103: Disconnected Commercial/Industrial Accounts | C103: No | D103: =Mangochi!I103 -> 0 | E103: ='Monkey Bay'!I103 -> 0 | F103: =Namwera!I103 -> 0 | G103: =Nkhudzi!I103 -> 0 | H103: =SUM(D103:G103) -> 0
A104: Disconnected CWP | C104: No | D104: =Mangochi!I104 -> 0 | E104: ='Monkey Bay'!I104 -> 0 | F104: =Namwera!I104 -> 0 | G104: =Nkhudzi!I104 -> 0 | H104: =SUM(D104:G104) -> 0
A105: Total Disconnected Accounts | C105: No | D105: =SUM(D101:D104) -> 0 | E105: =SUM(E101:E104) -> 0 | F105: =SUM(F101:F104) -> 0 | G105: =SUM(G101:G104) -> 0 | H105: =SUM(H101:H104) -> 0
...

Sheet Midyear Summary
A1: SOUTHERN REGION WATER BOARD
A3: MONTHLY REPORTS - 2025/2026
A4: MANGOCHI ZONE
A5: MANGOCHI ZONE
A7: PARAMETERS | C7: UNITS | D7: Mangochi | E7: Monkey Bay | F7: Namwera | G7: Nkhudzi | H7: TOTALS
A8: PRODUCTION
A9: Volume Produced | C9: m3 | D9: =Mangochi!D9+Mangochi!E9+Mangochi!F9+Mangochi!G9+Mangochi!H9+Mangochi!I9 -> 305608 | E9: ='Monkey Bay'!D9+'Monkey Bay'!E9+'Monkey Bay'!F9+'Monkey Bay'!G9+'Monkey Bay'!H9+'Monkey Bay'!I9 -> 116050 | F9: =Namwera!D9+Namwera!E9+Namwera!F9+Namwera!G9+Namwera!H9+Namwera!I9 -> 8386 | G9: =Nkhudzi!D9+Nkhudzi!E9+Nkhudzi!F9+Nkhudzi!G9+Nkhudzi!H9+Nkhudzi!I9 -> 73551 | H9: =SUM(D9:G9) -> 503595
A10: REVENUE WATER - POSTPAID
A11: Volume Billed Individuals | C11: m3 | D11: =Mangochi!D11+Mangochi!E11+Mangochi!F11+Mangochi!G11+Mangochi!H11+Mangochi!I11 -> 113884 | E11: ='Monkey Bay'!D11+'Monkey Bay'!E11+'Monkey Bay'!F11+'Monkey Bay'!G11+'Monkey Bay'!H11+'Monkey Bay'!I11 -> 35792 | F11: =Namwera!D11+Namwera!E11+Namwera!F11+Namwera!G11+Namwera!H11+Namwera!I11 -> 21 | G11: =Nkhudzi!D11+Nkhudzi!E11+Nkhudzi!F11+Nkhudzi!G11+Nkhudzi!H11+Nkhudzi!I11 -> 227 | H11: =SUM(D11:G11) -> 149924
A12: Volume Billed CWPs | C12: m3 | D12: =Mangochi!D12+Mangochi!E12+Mangochi!F12+Mangochi!G12+Mangochi!H12+Mangochi!I12 -> 0 | E12: ='Monkey Bay'!D12+'Monkey Bay'!E12+'Monkey Bay'!F12+'Monkey Bay'!G12+'Monkey Bay'!H12+'Monkey Bay'!I12 -> 0 | F12: =Namwera!D12+Namwera!E12+Namwera!F12+Namwera!G12+Namwera!H12+Namwera!I12 -> 0 | G12: =Nkhudzi!D12+Nkhudzi!E12+Nkhudzi!F12+Nkhudzi!G12+Nkhudzi!H12+Nkhudzi!I12 -> 0 | H12: =SUM(D12:G12) -> 0
A13: Volume Billed Institutions | C13: m3 | D13: =Mangochi!D13+Mangochi!E13+Mangochi!F13+Mangochi!G13+Mangochi!H13+Mangochi!I13 -> 304 | E13: ='Monkey Bay'!D13+'Monkey Bay'!E13+'Monkey Bay'!F13+'Monkey Bay'!G13+'Monkey Bay'!H13+'Monkey Bay'!I13 -> 8915 | F13: =Namwera!D13+Namwera!E13+Namwera!F13+Namwera!G13+Namwera!H13+Namwera!I13 -> 7 | G13: =Nkhudzi!D13+Nkhudzi!E13+Nkhudzi!F13+Nkhudzi!G13+Nkhudzi!H13+Nkhudzi!I13 -> 403 | H13: =SUM(D13:G13) -> 9629
A14: Volume Billed Commercial/Industrial | C14: m3 | D14: =Mangochi!D14+Mangochi!E14+Mangochi!F14+Mangochi!G14+Mangochi!H14+Mangochi!I14 -> 143 | E14: ='Monkey Bay'!D14+'Monkey Bay'!E14+'Monkey Bay'!F14+'Monkey Bay'!G14+'Monkey Bay'!H14+'Monkey Bay'!I14 -> 0 | F14: =Namwera!D14+Namwera!E14+Namwera!F14+Namwera!G14+Namwera!H14+Namwera!I14 -> 0 | G14: =Nkhudzi!D14+Nkhudzi!E14+Nkhudzi!F14+Nkhudzi!G14+Nkhudzi!H14+Nkhudzi!I14 -> 2 | H14: =SUM(D14:G14) -> 145
A15: Total Volume Billed Post Paid | C15: m3 | D15: =SUM(D11:D14) -> 114331 | E15: =SUM(E11:E14) -> 44707 | F15: =SUM(F11:F14) -> 28 | G15: =SUM(G11:G14) -> 632 | H15: =SUM(D15:G15) -> 159698
A16: REVENUE WATER - PREPAID
A17: Individuals | C17: m3 | D17: =Mangochi!D17+Mangochi!E17+Mangochi!F17+Mangochi!G17+Mangochi!H17+Mangochi!I17 -> 54757.6 | E17: ='Monkey Bay'!D17+'Monkey Bay'!E17+'Monkey Bay'!F17+'Monkey Bay'!G17+'Monkey Bay'!H17+'Monkey Bay'!I17 -> 18175.1 | F17: =Namwera!D17+Namwera!E17+Namwera!F17+Namwera!G17+Namwera!H17+Namwera!I17 -> 6849.8 | G17: =Nkhudzi!D17+Nkhudzi!E17+Nkhudzi!F17+Nkhudzi!G17+Nkhudzi!H17+Nkhudzi!I17 -> 48893.8 | H17: =SUM(D17:G17) -> 128676.3
A18: CWPs | C18: m3 | D18: =Mangochi!D18+Mangochi!E18+Mangochi!F18+Mangochi!G18+Mangochi!H18+Mangochi!I18 -> 9208.5 | E18: ='Monkey Bay'!D18+'Monkey Bay'!E18+'Monkey Bay'!F18+'Monkey Bay'!G18+'Monkey Bay'!H18+'Monkey Bay'!I18 -> 2244.6 | F18: =Namwera!D18+Namwera!E18+Namwera!F18+Namwera!G18+Namwera!H18+Namwera!I18 -> 0 | G18: =Nkhudzi!M18+Nkhudzi!N18+Nkhudzi!O18 -> 0 | H18: =SUM(D18:G18) -> 11453.1
A19: Institutions | C19: m3 | D19: =Mangochi!D19+Mangochi!E19+Mangochi!F19+Mangochi!G19+Mangochi!H19+Mangochi!I19 -> 10854.9 | E19: ='Monkey Bay'!D19+'Monkey Bay'!E19+'Monkey Bay'!F19+'Monkey Bay'!G19+'Monkey Bay'!H19+'Monkey Bay'!I19 -> 4598.5 | F19: =Namwera!D19+Namwera!E19+Namwera!F19+Namwera!G19+Namwera!H19+Namwera!I19 -> 753.9 | G19: =Nkhudzi!M19+Nkhudzi!N19+Nkhudzi!O19 -> 0 | H19: =SUM(D19:G19) -> 16207.3
A20: Commercial/Industrial | C20: m3 | D20: =Mangochi!D20+Mangochi!E20+Mangochi!F20+Mangochi!G20+Mangochi!H20+Mangochi!I20 -> 4331.6 | E20: ='Monkey Bay'!D20+'Monkey Bay'!E20+'Monkey Bay'!F20+'Monkey Bay'!G20+'Monkey Bay'!H20+'Monkey Bay'!I20 -> 1167.8 | F20: =Namwera!D20+Namwera!E20+Namwera!F20+Namwera!G20+Namwera!H20+Namwera!I20 -> 27.8 | G20: =Nkhudzi!M20+Nkhudzi!N20+Nkhudzi!O20 -> 0 | H20: =SUM(D20:G20) -> 5527.2
A21: Total Volume Prepaid | C21: m3 | D21: =SUM(D17:D20) -> 79152.6 | E21: =SUM(E17:E20) -> 26186 | F21: =SUM(F17:F20) -> 7631.5 | G21: =SUM(G17:G20) -> 48893.8 | H21: =SUM(D21:G21) -> 161863.9
A22: TOTAL REVENUE WATER | C22: m3 | D22: =D21+D15 -> 193483.6 | E22: =E21+E15 -> 70893 | F22: =F21+F15 -> 7659.5 | G22: =G21+G15 -> 49525.8 | H22: =SUM(D22:G22) -> 321561.9
A23: NON-REVENUE WATER (NRW)
A24: Non-Revenue Water (NRW) | B24: Volume | C24: m3 | D24: =D9-D22 -> 112124.4 | E24: =E9-E22 -> 45157 | F24: =F9-F22 -> 726.5 | G24: =G9-G22 -> 24025.2 | H24: =H9-H22 -> 182033.1
B25: Percentage | C25: % | D25: =D24/D9 -> 0.36688961 | E25: =E24/E9 -> 0.38911676 | F25: =F24/F9 -> 0.086632483 | G25: =G24/G9 -> 0.32664682 | H25: =H24/H9 -> 0.36146725
A26: OPERATING EXPENSES
A27: Chemicals
A28: Chemical | B28: Rate(MK/kg)
A29: Chlorine | B29: 3525.29 | C29: kg | D29: =Mangochi!D29+Mangochi!E29+Mangochi!F29+Mangochi!G29+Mangochi!H29+Mangochi!I29 -> 1035.39 | E29: ='Monkey Bay'!D29+'Monkey Bay'!E29+'Monkey Bay'!F29+'Monkey Bay'!G29+'Monkey Bay'!H29+'Monkey Bay'!I29 -> 230 | F29: =Namwera!D29+Namwera!E29+Namwera!F29+Namwera!G29+Namwera!H29+Namwera!I29 -> 8.5 | G29: =Nkhudzi!D29+Nkhudzi!E29+Nkhudzi!F29+Nkhudzi!G29+Nkhudzi!H29+Nkhudzi!I29 -> 139.11 | H29: =SUM(D29:G29) -> 1413
C30: kg/mg litre | D30: =D29/(D9/1000) -> 3.3879676 | E30: =E29/(E9/1000) -> 1.9819044 | F30: =F29/(F9/1000) -> 1.0135941 | G30: =G29/(G9/1000) -> 1.8913407 | H30: =H29/(H9/1000) -> 2.8058261
A31: Aluminium sulphate | B31: 1060.0102 | C31: kg | D31: =Mangochi!D31+Mangochi!E31+Mangochi!F31+Mangochi!G31+Mangochi!H31+Mangochi!I31 -> 0 | E31: ='Monkey Bay'!D31+'Monkey Bay'!E31+'Monkey Bay'!F31+'Monkey Bay'!G31+'Monkey Bay'!H31+'Monkey Bay'!I31 -> 0 | F31: =Namwera!D31+Namwera!E31+Namwera!F31+Namwera!G31+Namwera!H31+Namwera!I31 -> 0 | G31: =Nkhudzi!D31+Nkhudzi!E31+Nkhudzi!F31+Nkhudzi!G31+Nkhudzi!H31+Nkhudzi!I31 -> 0 | H31: =SUM(D31:G31) -> 0
C32: kg/mg litre | D32: =D31/(D9/1000) -> 0 | E32: =E31/(E9/1000) -> 0 | F32: =F31/(F9/1000) -> 0 | G32: =Nkhudzi!D32+Nkhudzi!E32+Nkhudzi!F32+Nkhudzi!G32+Nkhudzi!H32+Nkhudzi!I32 -> #DIV/0! | H32: =H31/(H9/1000) -> 0
A33: Soda | B33: 1228.2886 | C33: kg | D33: =Mangochi!D33+Mangochi!E33+Mangochi!F33+Mangochi!G33+Mangochi!H33+Mangochi!I33 -> 0 | E33: ='Monkey Bay'!D33+'Monkey Bay'!E33+'Monkey Bay'!F33+'Monkey Bay'!G33+'Monkey Bay'!H33+'Monkey Bay'!I33 -> 0 | F33: =Namwera!D33+Namwera!E33+Namwera!F33+Namwera!G33+Namwera!H33+Namwera!I33 -> 0 | G33: =Nkhudzi!J33+Nkhudzi!K33+Nkhudzi!L33 -> 0 | H33: =SUM(D33:F33) -> 0
C34: kg/mg litre | D34: =D33/(D9/1000) -> 0 | E34: =E33/(E9/1000) -> 0 | F34: =F33/(F9/1000) -> 0 | G34: =Nkhudzi!D34+Nkhudzi!E34+Nkhudzi!F34+Nkhudzi!G34+Nkhudzi!H34+Nkhudzi!I34 -> #DIV/0! | H34: =H33/(H9/1000) -> 0
A35: Algae floc | B35: 3726.7258 | C35: litres | D35: =Mangochi!D35+Mangochi!E35+Mangochi!F35+Mangochi!G35+Mangochi!H35+Mangochi!I35 -> 0 | E35: ='Monkey Bay'!D35+'Monkey Bay'!E35+'Monkey Bay'!F35+'Monkey Bay'!G35+'Monkey Bay'!H35+'Monkey Bay'!I35 -> 0 | F35: =Namwera!D35+Namwera!E35+Namwera!F35+Namwera!G35+Namwera!H35+Namwera!I35 -> 0 | G35: =Nkhudzi!D35+Nkhudzi!E35+Nkhudzi!F35+Nkhudzi!G35+Nkhudzi!H35+Nkhudzi!I35 -> 0
C36: litres/mg litre | G36: =Nkhudzi!D36+Nkhudzi!E36+Nkhudzi!F36+Nkhudzi!G36+Nkhudzi!H36+Nkhudzi!I36 -> 0
A37: Sud floc | B37: 3951.5936 | C37: litres | D37: =Mangochi!D37+Mangochi!E37+Mangochi!F37+Mangochi!G37+Mangochi!H37+Mangochi!I37 -> 0 | E37: ='Monkey Bay'!D37+'Monkey Bay'!E37+'Monkey Bay'!F37+'Monkey Bay'!G37+'Monkey Bay'!H37+'Monkey Bay'!I37 -> 0 | F37: =Namwera!D37+Namwera!E37+Namwera!F37+Namwera!G37+Namwera!H37+Namwera!I37 -> 0 | G37: =Nkhudzi!D37+Nkhudzi!E37+Nkhudzi!F37+Nkhudzi!G37+Nkhudzi!H37+Nkhudzi!I37 -> 0 | H37: =SUM(D37:F37) -> 0
C38: litres/mg litre | D38: =D37/(D9/1000) -> 0 | E38: =E37/(E9/1000) -> 0 | F38: =F37/(F9/1000) -> 0 | G38: =Nkhudzi!D38+Nkhudzi!E38+Nkhudzi!F38+Nkhudzi!G38+Nkhudzi!H38+Nkhudzi!I38 -> #DIV/0! | H38: =H37/(H9/1000) -> 0
A39: Potasium permanganate | B39: 1950 | C39: kg | D39: =Mangochi!D39+Mangochi!E39+Mangochi!F39+Mangochi!G39+Mangochi!H39+Mangochi!I39 -> 0 | E39: ='Monkey Bay'!D39+'Monkey Bay'!E39+'Monkey Bay'!F39+'Monkey Bay'!G39+'Monkey Bay'!H39+'Monkey Bay'!I39 -> 0 | F39: =Namwera!D39+Namwera!E39+Namwera!F39+Namwera!G39+Namwera!H39+Namwera!I39 -> 0 | G39: =Nkhudzi!D39+Nkhudzi!E39+Nkhudzi!F39+Nkhudzi!G39+Nkhudzi!H39+Nkhudzi!I39 -> 0 | H39: =SUM(D39:F39) -> 0
C40: kg/mg litre | D40: =D39/(D9/1000) -> 0 | E40: =E39/(E9/1000) -> 0 | F40: =F39/(F9/1000) -> 0 | G40: =Nkhudzi!D40+Nkhudzi!E40+Nkhudzi!F40+Nkhudzi!G40+Nkhudzi!H40+Nkhudzi!I40 -> #DIV/0! | H40: =H39/(H9/1000) -> 0
A41: Cost of Chemicals | C41: Mk | D41: =(D29*$B29)+(D31*$B31)+(D33*$B33)+(D35*$B35)+(D37*$B37)+(D39*$B39) -> 3650050 | E41: =(E29*$B29)+(E31*$B31)+(E33*$B33)+(E35*$B35)+(E37*$B37)+(E39*$B39) -> 810816.7 | F41: =(F29*$B29)+(F31*$B31)+(F33*$B33)+(F35*$B35)+(F37*$B37)+(F39*$B39) -> 29964.965 | G41: =(G29*$B29)+(G31*$B31)+(G33*$B33)+(G35*$B35)+(G37*$B37)+(G39*$B39) -> 490403.09 | H41: =SUM(D41:G41) -> 4981234.8
A42: Cost/vol. Produced (chemicals) | C42: Mk/m3 | D42: =D41/D9 -> 11.943568 | E42: =E41/E9 -> 6.9867876 | F42: =F41/F9 -> 3.5732131 | G42: =G41/G9 -> 6.6675245 | H42: =H41/H9 -> 9.8913507
A43: Power
A44: Power Usage | C44: Kw | D44: =Mangochi!D44+Mangochi!E44+Mangochi!F44+Mangochi!G44+Mangochi!H44+Mangochi!I44 -> 56848.16 | E44: ='Monkey Bay'!D44+'Monkey Bay'!E44+'Monkey Bay'!F44+'Monkey Bay'!G44+'Monkey Bay'!H44+'Monkey Bay'!I44 -> 50914 | F44: =Namwera!D44+Namwera!E44+Namwera!F44+Namwera!G44+Namwera!H44+Namwera!I44 -> 8410 | G44: =Nkhudzi!D44+Nkhudzi!E44+Nkhudzi!F44+Nkhudzi!G44+Nkhudzi!H44+Nkhudzi!I44 -> 189524 | H44: =SUM(D44:G44) -> 305696.16
A45: Power/ Vol. Produced | C45: Kw/m3 | D45: =D44/D9 -> 0.1860166 | E45: =E44/E9 -> 0.43872469 | F45: =F44/F9 -> 1.0028619 | G45: =G44/G9 -> 2.5767699 | H45: =H44/H9 -> 0.60702779
A46: Cost of Power | C46: Mk | D46: =Mangochi!D46+Mangochi!E46+Mangochi!F46+Mangochi!G46+Mangochi!H46+Mangochi!I46 -> 9619767.3 | E46: ='Monkey Bay'!D46+'Monkey Bay'!E46+'Monkey Bay'!F46+'Monkey Bay'!G46+'Monkey Bay'!H46+'Monkey Bay'!I46 -> 8627709.2 | F46: =Namwera!D46+Namwera!E46+Namwera!F46+Namwera!G46+Namwera!H46+Namwera!I46 -> 1521996.8 | G46: =Nkhudzi!D46+Nkhudzi!E46+Nkhudzi!F46+Nkhudzi!G46+Nkhudzi!H46+Nkhudzi!I46 -> 31800183 | H46: =SUM(D46:G46) -> 51569656
A47: Cost/vol. Produced | C47: Mk/m3 | D47: =D46/D9 -> 31.477472 | E47: =E46/E9 -> 74.344759 | F47: =F46/F9 -> 181.49258 | G47: =G46/G9 -> 432.35554 | H47: =H46/H9 -> 102.40303
A48: Plant and Vehicle Maintenance
A49: Distances covered | C49: km | D49: =Mangochi!D49+Mangochi!E49+Mangochi!F49+Mangochi!G49+Mangochi!H49+Mangochi!I49 -> 4429 | E49: ='Monkey Bay'!D49+'Monkey Bay'!E49+'Monkey Bay'!F49+'Monkey Bay'!G49+'Monkey Bay'!H49+'Monkey Bay'!I49 -> 0 | F49: =Namwera!D49+Namwera!E49+Namwera!F49+Namwera!G49+Namwera!H49+Namwera!I49 -> 0 | G49: =Nkhudzi!D49+Nkhudzi!E49+Nkhudzi!F49+Nkhudzi!G49+Nkhudzi!H49+Nkhudzi!I49 -> 0 | H49: =SUM(D49:G49) -> 4429
A50: Fuel Used (litres) | C50: litres | D50: =Mangochi!D50+Mangochi!E50+Mangochi!F50+Mangochi!G50+Mangochi!H50+Mangochi!I50 -> 544.8 | E50: ='Monkey Bay'!D50+'Monkey Bay'!E50+'Monkey Bay'!F50+'Monkey Bay'!G50+'Monkey Bay'!H50+'Monkey Bay'!I50 -> 0 | F50: =Namwera!D50+Namwera!E50+Namwera!F50+Namwera!G50+Namwera!H50+Namwera!I50 -> 0 | G50: =Nkhudzi!D50+Nkhudzi!E50+Nkhudzi!F50+Nkhudzi!G50+Nkhudzi!H50+Nkhudzi!I50 -> 0 | H50: =SUM(D50:G50) -> 544.8
A51: Cost of fuel | C51: Mk | D51: =Mangochi!D51+Mangochi!E51+Mangochi!F51+Mangochi!G51+Mangochi!H51+Mangochi!I51 -> 3630827.6 | E51: ='Monkey Bay'!D51+'Monkey Bay'!E51+'Monkey Bay'!F51+'Monkey Bay'!G51+'Monkey Bay'!H51+'Monkey Bay'!I51 -> 0 | F51: =Namwera!D51+Namwera!E51+Namwera!F51+Namwera!G51+Namwera!H51+Namwera!I51 -> 0 | G51: =Nkhudzi!D51+Nkhudzi!E51+Nkhudzi!F51+Nkhudzi!G51+Nkhudzi!H51+Nkhudzi!I51 -> 0 | H51: =SUM(D51:G51) -> 3630827.6
A52: Maintenance | C52: Mk | D52: =Mangochi!D52+Mangochi!E52+Mangochi!F52+Mangochi!G52+Mangochi!H52+Mangochi!I52 -> 0 | E52: =Mangochi!E52+Mangochi!F52+Mangochi!G52+Mangochi!H52+Mangochi!I52+Mangochi!J52 -> 0 | F52: =Mangochi!F52+Mangochi!G52+Mangochi!H52+Mangochi!I52+Mangochi!J52+Mangochi!K52 -> 0 | G52: =Nkhudzi!D52+Nkhudzi!E52+Nkhudzi!F52+Nkhudzi!G52+Nkhudzi!H52+Nkhudzi!I52 -> 0 | H52: =SUM(D52:G52) -> 0
A53: Salaries and Wages
A54: Staff Costs | C54: MK | D54: =Mangochi!D54+Mangochi!E54+Mangochi!F54+Mangochi!G54+Mangochi!H54+Mangochi!I54 -> 65632219 | E54: ='Monkey Bay'!D54+'Monkey Bay'!E54+'Monkey Bay'!F54+'Monkey Bay'!G54+'Monkey Bay'!H54+'Monkey Bay'!I54 -> 8219217.9 | F54: =Namwera!D54+Namwera!E54+Namwera!F54+Namwera!G54+Namwera!H54+Namwera!I54 -> 8496202.6 | G54: =Nkhudzi!D54+Nkhudzi!E54+Nkhudzi!F54+Nkhudzi!G54+Nkhudzi!H54+Nkhudzi!I54 -> 18178963 | H54: =SUM(D54:G54) -> 1.005266e+08
A55: Wages | C55: MK | D55: =Mangochi!D55+Mangochi!E55+Mangochi!F55+Mangochi!G55+Mangochi!H55+Mangochi!I55 -> 9331735.4 | E55: ='Monkey Bay'!D55+'Monkey Bay'!E55+'Monkey Bay'!F55+'Monkey Bay'!G55+'Monkey Bay'!H55+'Monkey Bay'!I55 -> 3219061.8 | F55: =Namwera!D55+Namwera!E55+Namwera!F55+Namwera!G55+Namwera!H55+Namwera!I55 -> 1853959.1 | G55: =Nkhudzi!D55+Nkhudzi!E55+Nkhudzi!F55+Nkhudzi!G55+Nkhudzi!H55+Nkhudzi!I55 -> 11666524 | H55: =SUM(D55:G55) -> 26071281
A56: Other Overhead Costs | C56: MK | D56: =Mangochi!D56+Mangochi!E56+Mangochi!F56+Mangochi!G56+Mangochi!H56+Mangochi!I56 -> 7312980 | E56: ='Monkey Bay'!D56+'Monkey Bay'!E56+'Monkey Bay'!F56+'Monkey Bay'!G56+'Monkey Bay'!H56+'Monkey Bay'!I56 -> 2008340 | F56: =Namwera!D56+Namwera!E56+Namwera!F56+Namwera!G56+Namwera!H56+Namwera!I56 -> 484410 | G56: =Nkhudzi!D56+Nkhudzi!E56+Nkhudzi!F56+Nkhudzi!G56+Nkhudzi!H56+Nkhudzi!I56 -> 2511940 | H56: =SUM(D56:G56) -> 12317670
A57: Operating Costs
A58: Total Operating Costs | C58: MK | D58: =D41+D46+D51+D52+D54+D55+D56 -> 99177579 | E58: =E41+E46+E51+E52+E54+E55+E56 -> 22885146 | F58: =F41+F46+F51+F52+F54+F55+F56 -> 12386533 | G58: =G41+G46+G51+G52+G54+G55+G56 -> 64648013 | H58: =SUM(D58:G58) -> 1.9909727e+08
A59: Cost/Vol. Produced | C59: Mk/m3 | D59: =D58/D9 -> 324.52547 | E59: =E58/E9 -> 197.20074 | F59: =F58/F9 -> 1477.0491 | G59: =G58/G9 -> 878.95492 | H59: =H58/H9 -> 395.35196
A60: Cost/Vol. Billed | C60: Mk/m3 | D60: =D58/D22 -> 512.58907 | E60: =E58/E22 -> 322.81249 | F60: =F58/F22 -> 1617.1465 | G60: =G58/G22 -> 1305.3401 | H60: =H58/H22 -> 619.15691
A61: Permanent Staff Employed | C61: No | D61: =Mangochi!I61 -> 0 | E61: ='Monkey Bay'!I61 -> 0 | F61: =Namwera!I61 -> 0 | G61: =Nkhudzi!I61 -> 0 | H61: =SUM(D61:G61) -> 0
A62: Staff/Vol.1000m3 of Volume Produced/hour (12 hour day) | C62: No/1000m3 | D62: =(D61*1000*31)/D9 -> 0 | E62: =(E61*1000*31)/E9 -> 0 | F62: =(F61*1000*31)/F9 -> 0 | G62: =(G61*1000*31)/G9 -> 0 | H62: =(H61*1000*31)/H9 -> 0
A63: Temporary Staff Employed | C63: No | D63: =Mangochi!I63 -> 0 | E63: ='Monkey Bay'!I63 -> 0 | F63: =Namwera!I63 -> 0 | G63: =Nkhudzi!I63 -> 0 | H63: =SUM(D63:G63) -> 0
A65: Water Connections and Disconnections
A66: New Individual Water Connections | B66: Brought Forward | C66: No | D66: =Mangochi!D66 -> 1978 | E66: ='Monkey Bay'!D66 -> 77 | F66: =Namwera!D66 -> 76 | G66: =Nkhudzi!M66 -> 0 | H66: =SUM(D66:G66) -> 2131
B67: Applied this Month | C67: No | D67: =Mangochi!D67+Mangochi!E67+Mangochi!F67+Mangochi!G67+Mangochi!H67+Mangochi!I67 -> 253 | E67: ='Monkey Bay'!D67+'Monkey Bay'!E67+'Monkey Bay'!F67+'Monkey Bay'!G67+'Monkey Bay'!H67+'Monkey Bay'!I67 -> 57 | F67: =Namwera!D67+Namwera!E67+Namwera!F67+Namwera!G67+Namwera!H67+Namwera!I67 -> 17 | G67: =Nkhudzi!M67+Nkhudzi!N67+Nkhudzi!O67 -> 0 | H67: =SUM(D67:G67) -> 327
B68: Done this Month Postpaid | C68: No | D68: =Mangochi!D68+Mangochi!E68+Mangochi!F68+Mangochi!G68+Mangochi!H68+Mangochi!I68 -> 0 | E68: ='Monkey Bay'!D68+'Monkey Bay'!E68+'Monkey Bay'!F68+'Monkey Bay'!G68+'Monkey Bay'!H68+'Monkey Bay'!I68 -> 0 | F68: =Namwera!D68+Namwera!E68+Namwera!F68+Namwera!G68+Namwera!H68+Namwera!I68 -> 0 | G68: =Nkhudzi!M68+Nkhudzi!N68+Nkhudzi!O68 -> 0 | H68: =SUM(D68:G68) -> 0
B69: Done this Month Prepaid | C69: No | D69: =Mangochi!D69+Mangochi!E69+Mangochi!F69+Mangochi!G69+Mangochi!H69+Mangochi!I69 -> 184 | E69: ='Monkey Bay'!D69+'Monkey Bay'!E69+'Monkey Bay'!F69+'Monkey Bay'!G69+'Monkey Bay'!H69+'Monkey Bay'!I69 -> 107 | F69: =Namwera!D69+Namwera!E69+Namwera!F69+Namwera!G69+Namwera!H69+Namwera!I69 -> 9 | G69: =Nkhudzi!M69+Nkhudzi!N69+Nkhudzi!O69 -> 0 | H69: =SUM(D69:G69) -> 300
B70: Total Done | C70: No | D70: =D68+D69 -> 184 | E70: =E68+E69 -> 107 | F70: =F68+F69 -> 9 | G70: =Nkhudzi!M70+Nkhudzi!N70+Nkhudzi!O70 -> 0 | H70: =SUM(D70:G70) -> 300
B71: Carried Forward | C71: No | D71: =D66+D67-D70 -> 2047 | E71: =E66+E67-E70 -> 27 | F71: =F66+F67-F70 -> 84 | G71: =G66+G67-G70 -> 0 | H71: =H66+H67-H70 -> 2158
A72: New Institutional Water Connections | B72: Brought Forward | C72: No | D72: =Mangochi!D72 -> 4 | E72: ='Monkey Bay'!D72 -> 0 | F72: =Namwera!D72 -> 0 | G72: =Nkhudzi!M72+Nkhudzi!N72+Nkhudzi!O72 -> 0 | H72: =SUM(D72:G72) -> 4
B73: Applied this Month | C73: No | D73: =Mangochi!D73+Mangochi!E73+Mangochi!F73+Mangochi!G73+Mangochi!H73+Mangochi!I73 -> 0 | E73: ='Monkey Bay'!D73+'Monkey Bay'!E73+'Monkey Bay'!F73+'Monkey Bay'!G73+'Monkey Bay'!H73+'Monkey Bay'!I73 -> 0 | F73: =Namwera!D73+Namwera!E73+Namwera!F73+Namwera!G73+Namwera!H73+Namwera!I73 -> 0 | G73: =Nkhudzi!M73+Nkhudzi!N73+Nkhudzi!O73 -> 0 | H73: =SUM(D73:G73) -> 0
B74: Done this Month Postpaid | C74: No | D74: =Mangochi!D74+Mangochi!E74+Mangochi!F74+Mangochi!G74+Mangochi!H74+Mangochi!I74 -> 0 | E74: ='Monkey Bay'!D74+'Monkey Bay'!E74+'Monkey Bay'!F74+'Monkey Bay'!G74+'Monkey Bay'!H74+'Monkey Bay'!I74 -> 0 | F74: =Namwera!D74+Namwera!E74+Namwera!F74+Namwera!G74+Namwera!H74+Namwera!I74 -> 0 | G74: =Nkhudzi!M74+Nkhudzi!N74+Nkhudzi!O74 -> 0 | H74: =SUM(D74:G74) -> 0
B75: Done this Month Prepaid | C75: No | D75: =Mangochi!D75+Mangochi!E75+Mangochi!F75+Mangochi!G75+Mangochi!H75+Mangochi!I75 -> 0 | E75: ='Monkey Bay'!D75+'Monkey Bay'!E75+'Monkey Bay'!F75+'Monkey Bay'!G75+'Monkey Bay'!H75+'Monkey Bay'!I75 -> 0 | F75: =Namwera!D75+Namwera!E75+Namwera!F75+Namwera!G75+Namwera!H75+Namwera!I75 -> 0 | G75: =Nkhudzi!M75+Nkhudzi!N75+Nkhudzi!O75 -> 0 | H75: =SUM(D75:G75) -> 0
B76: Total Done | C76: No | D76: =D74+D75 -> 0 | E76: =E74+E75 -> 0 | F76: =F74+F75 -> 0 | G76: =Nkhudzi!M76+Nkhudzi!N76+Nkhudzi!O76 -> 0 | H76: =SUM(D76:G76) -> 0
B77: Carried Forward | C77: No | D77: =D73+D74-D76 -> 0 | E77: =E73+E74-E76 -> 0 | F77: =F73+F74-F76 -> 0 | G77: =G73+G74-G76 -> 0 | H77: =H72+H73-H76 -> 4
A78: New Commercial/Industrial Water Connections | B78: Brought Forward | C78: No | D78: =Mangochi!D78 -> 0 | E78: ='Monkey Bay'!D78 -> 7 | F78: =Namwera!D78 -> 0 | G78: =Nkhudzi!M78+Nkhudzi!N78+Nkhudzi!O78 -> 0 | H78: =SUM(D78:F78) -> 7
B79: Applied this Month | C79: No | D79: =Mangochi!D79+Mangochi!E79+Mangochi!F79+Mangochi!G79+Mangochi!H79+Mangochi!I79 -> 0 | E79: ='Monkey Bay'!D79+'Monkey Bay'!E79+'Monkey Bay'!F79+'Monkey Bay'!G79+'Monkey Bay'!H79+'Monkey Bay'!I79 -> 0 | F79: =Namwera!D79+Namwera!E79+Namwera!F79+Namwera!G79+Namwera!H79+Namwera!I79 -> 0 | G79: =Nkhudzi!M79+Nkhudzi!N79+Nkhudzi!O79 -> 0 | H79: =SUM(D79:G79) -> 0
B80: Done this Month Postpaid | C80: No | D80: =Mangochi!D80+Mangochi!E80+Mangochi!F80+Mangochi!G80+Mangochi!H80+Mangochi!I80 -> 0 | E80: ='Monkey Bay'!D80+'Monkey Bay'!E80+'Monkey Bay'!F80+'Monkey Bay'!G80+'Monkey Bay'!H80+'Monkey Bay'!I80 -> 0 | F80: =Namwera!D80+Namwera!E80+Namwera!F80+Namwera!G80+Namwera!H80+Namwera!I80 -> 0 | G80: =Nkhudzi!M80+Nkhudzi!N80+Nkhudzi!O80 -> 0 | H80: =SUM(D80:G80) -> 0
B81: Done this Month Prepaid | C81: No | D81: =Mangochi!D81+Mangochi!E81+Mangochi!F81+Mangochi!G81+Mangochi!H81+Mangochi!I81 -> 0 | E81: ='Monkey Bay'!D81+'Monkey Bay'!E81+'Monkey Bay'!F81+'Monkey Bay'!G81+'Monkey Bay'!H81+'Monkey Bay'!I81 -> 2 | F81: =Namwera!D81+Namwera!E81+Namwera!F81+Namwera!G81+Namwera!H81+Namwera!I81 -> 0 | G81: =Nkhudzi!M81+Nkhudzi!N81+Nkhudzi!O81 -> 0 | H81: =SUM(D81:G81) -> 2
B82: Total Done | C82: No | D82: =D81+D80 -> 0 | E82: =E81+E80 -> 2 | F82: =F81+F80 -> 0 | G82: =Nkhudzi!M82+Nkhudzi!N82+Nkhudzi!O82 -> 0 | H82: =SUM(D82:G82) -> 2
B83: Carried Forward | C83: No | D83: =D78+D79-D82 -> 0 | E83: =E78+E79-E82 -> 5 | F83: =F78+F79-F82 -> 0 | G83: =Nkhudzi!M83+Nkhudzi!N83+Nkhudzi!O83 -> 0 | H83: =H78+H79-H82 -> 5
A84: New CWP | B84: Brought Forward | C84: No | D84: =Mangochi!D84 -> 10 | E84: ='Monkey Bay'!D84 -> 0 | F84: =Namwera!D84 -> 0 | G84: =Nkhudzi!M84+Nkhudzi!N84+Nkhudzi!O84 -> 0 | H84: =SUM(D84:G84) -> 10
B85: Applied this Month | C85: No | D85: =Mangochi!D85+Mangochi!E85+Mangochi!F85+Mangochi!G85+Mangochi!H85+Mangochi!I85 -> 0 | E85: ='Monkey Bay'!D85+'Monkey Bay'!E85+'Monkey Bay'!F85+'Monkey Bay'!G85+'Monkey Bay'!H85+'Monkey Bay'!I85 -> 0 | F85: =Namwera!D85+Namwera!E85+Namwera!F85+Namwera!G85+Namwera!H85+Namwera!I85 -> 0 | G85: =Nkhudzi!M85+Nkhudzi!N85+Nkhudzi!O85 -> 0 | H85: =SUM(D85:G85) -> 0
B86: Done this Month Postpaid | C86: No | D86: =Mangochi!D86+Mangochi!E86+Mangochi!F86+Mangochi!G86+Mangochi!H86+Mangochi!I86 -> 0 | E86: ='Monkey Bay'!D86+'Monkey Bay'!E86+'Monkey Bay'!F86+'Monkey Bay'!G86+'Monkey Bay'!H86+'Monkey Bay'!I86 -> 0 | F86: =Namwera!D86+Namwera!E86+Namwera!F86+Namwera!G86+Namwera!H86+Namwera!I86 -> 0 | G86: =Nkhudzi!M86+Nkhudzi!N86+Nkhudzi!O86 -> 0 | H86: =SUM(D86:G86) -> 0
B87: Done this Month Prepaid | C87: No | D87: =Mangochi!D87+Mangochi!E87+Mangochi!F87+Mangochi!G87+Mangochi!H87+Mangochi!I87 -> 1 | E87: ='Monkey Bay'!D87+'Monkey Bay'!E87+'Monkey Bay'!F87+'Monkey Bay'!G87+'Monkey Bay'!H87+'Monkey Bay'!I87 -> 0 | F87: =Namwera!D87+Namwera!E87+Namwera!F87+Namwera!G87+Namwera!H87+Namwera!I87 -> 0 | G87: =Nkhudzi!M87+Nkhudzi!N87+Nkhudzi!O87 -> 0 | H87: =SUM(D87:G87) -> 1
B88: Total Done | C88: No | D88: =D87+D86 -> 1 | E88: =E87+E86 -> 0 | F88: =F87+F86 -> 0 | G88: =Nkhudzi!M88+Nkhudzi!N88+Nkhudzi!O88 -> 0 | H88: =SUM(D88:G88) -> 1
B89: Carried Forward | C89: No | D89: =D84+D85-D88 -> 9 | E89: =E84+E85-E88 -> 0 | F89: =F84+F85-F88 -> 0 | G89: =Nkhudzi!M89+Nkhudzi!N89+Nkhudzi!O89 -> 0 | H89: =H84+H85-H88 -> 9
A90: Aggregated New Water connections | B90: Brought Forward | C90: No | D90: =D66+D72+D78+D84 -> 1992 | E90: =E66+E72+E78+E84 -> 84 | F90: =F66+F72+F78+F84 -> 76 | G90: =G66+G72+G78+G84 -> 0 | H90: =SUM(D90:G90) -> 2152
B91: Applied this Month | C91: No | D91: =D67+D73+D79+D85 -> 253 | E91: =E67+E73+E79+E85 -> 57 | F91: =F67+F73+F79+F85 -> 17 | G91: =G67+G73+G79+G85 -> 0 | H91: =SUM(D91:G91) -> 327
B92: Done this Month Postpaid | C92: No | D92: =D68+D74+D80+D86 -> 0 | E92: =E68+E74+E80+E86 -> 0 | F92: =F68+F74+F80+F86 -> 0 | G92: =G68+G74+G80+G86 -> 0 | H92: =SUM(D92:G92) -> 0
B93: Done this Month Prepaid | D93: =D69+D75+D81+D87 -> 185 | E93: =E69+E75+E81+E87 -> 109 | F93: =F69+F75+F81+F87 -> 9 | G93: =G69+G75+G81+G87 -> 0 | H93: =SUM(D93:G93) -> 303
B94: Total Done | C94: No | D94: =D93+D92 -> 185 | E94: =E93+E92 -> 109 | F94: =F93+F92 -> 9 | G94: =G93+G92 -> 0 | H94: =SUM(D94:G94) -> 303
B95: Carried Forward | C95: No | D95: =D90+D91-D94 -> 2060 | E95: =E90+E91-E94 -> 32 | F95: =F90+F91-F94 -> 84 | G95: =G90+G91-G94 -> 0 | H95: =H90+H91-H94 -> 2176
A97: Prepaid Metering
A98: Prepaid Meters Installed | C98: No | D98: =Mangochi!D98+Mangochi!E98+Mangochi!F98+Mangochi!G98+Mangochi!H98+Mangochi!I98 -> 185 | E98: ='Monkey Bay'!D98+'Monkey Bay'!E98+'Monkey Bay'!F98+'Monkey Bay'!G98+'Monkey Bay'!H98+'Monkey Bay'!I98 -> 109 | F98: =Namwera!D98+Namwera!E98+Namwera!F98+Namwera!G98+Namwera!H98+Namwera!I98 -> 9 | G98: =Nkhudzi!M98+Nkhudzi!N98+Nkhudzi!O98 -> 0 | H98: =SUM(D98:G98) -> 303
A100: Active and Disconnected Accounts
A101: Disconnected Individual Accounts | C101: No | D101: =Mangochi!I101 -> 0 | E101: ='Monkey Bay'!I101 -> 0 | F101: =Namwera!I101 -> 0 | G101: =Nkhudzi!O101 -> 0 | H101: =SUM(D101:G101) -> 0
A102: Disconnected institutional Accounts | C102: No | D102: =Mangochi!I102 -> 0 | E102: ='Monkey Bay'!I102 -> 0 | F102: =Namwera!I102 -> 0 | G102: =Nkhudzi!O102 -> 0 | H102: =SUM(D102:G102) -> 0
A103: Disconnected Commercial/Industrial Accounts | C103: No | D103: =Mangochi!I103 -> 0 | E103: ='Monkey Bay'!I103 -> 0 | F103: =Namwera!I103 -> 0 | G103: =Nkhudzi!O103 -> 0 | H103: =SUM(D103:G103) -> 0
A104: Disconnected CWP | C104: No | D104: =Mangochi!I104 -> 0 | E104: ='Monkey Bay'!I104 -> 0 | F104: =Namwera!I104 -> 0 | G104: =Nkhudzi!O104 -> 0 | H104: =SUM(D104:G104) -> 0
A105: Total Disconnected Accounts | C105: No | D105: =SUM(D101:D104) -> 0 | E105: =SUM(E101:E104) -> 0 | F105: =SUM(F101:F104) -> 0 | G105: =SUM(G101:G104) -> 0 | H105: =SUM(H101:H104) -> 0
...

Sheet 3rd QTR
A1: SOUTHERN REGION WATER BOARD
A3: MONTHLY REPORTS - 2025/2026
A4: MANGOCHI ZONE
A5: MANGOCHI ZONE
A7: PARAMETERS | C7: UNITS | D7: Mangochi | E7: Monkey Bay | F7: Namwera | G7: Nkhudzi | H7: TOTALS
A8: PRODUCTION
A9: Volume Produced | C9: m3 | D9: =Mangochi!J9+Mangochi!K9+Mangochi!L9 -> 0 | E9: ='Monkey Bay'!J9+'Monkey Bay'!K9+'Monkey Bay'!L9 -> 0 | F9: =Namwera!J9+Namwera!K9+Namwera!L9 -> 0 | G9: =Nkhudzi!J9+Nkhudzi!K9+Nkhudzi!L9 -> 0 | H9: =SUM(D9:G9) -> 0
A10: REVENUE WATER - POSTPAID
A11: Volume Billed Individuals | C11: m3 | D11: =Mangochi!J11+Mangochi!K11+Mangochi!L11 -> 0 | E11: ='Monkey Bay'!J11+'Monkey Bay'!K11+'Monkey Bay'!L11 -> 0 | F11: =Namwera!J11+Namwera!K11+Namwera!L11 -> 0 | G11: =Nkhudzi!J11+Nkhudzi!K11+Nkhudzi!L11 -> 0 | H11: =SUM(D11:G11) -> 0
A12: Volume Billed CWPs | C12: m3 | D12: =Mangochi!J12+Mangochi!K12+Mangochi!L12 -> 0 | E12: ='Monkey Bay'!J12+'Monkey Bay'!K12+'Monkey Bay'!L12 -> 0 | F12: =Namwera!J12+Namwera!K12+Namwera!L12 -> 0 | G12: =Nkhudzi!J12+Nkhudzi!K12+Nkhudzi!L12 -> 0 | H12: =SUM(D12:G12) -> 0
A13: Volume Billed Institutions | C13: m3 | D13: =Mangochi!J13+Mangochi!K13+Mangochi!L13 -> 0 | E13: ='Monkey Bay'!J13+'Monkey Bay'!K13+'Monkey Bay'!L13 -> 0 | F13: =Namwera!J13+Namwera!K13+Namwera!L13 -> 0 | G13: =Nkhudzi!J13+Nkhudzi!K13+Nkhudzi!L13 -> 0 | H13: =SUM(D13:G13) -> 0
A14: Volume Billed Commercial/Industrial | C14: m3 | D14: =Mangochi!J14+Mangochi!K14+Mangochi!L14 -> 0 | E14: ='Monkey Bay'!J14+'Monkey Bay'!K14+'Monkey Bay'!L14 -> 0 | F14: =Namwera!J14+Namwera!K14+Namwera!L14 -> 0 | G14: =Nkhudzi!J14+Nkhudzi!K14+Nkhudzi!L14 -> 0 | H14: =SUM(D14:G14) -> 0
A15: Total Volume Billed Post Paid | C15: m3 | D15: =SUM(D11:D14) -> 0 | E15: =SUM(E11:E14) -> 0 | F15: =SUM(F11:F14) -> 0 | G15: =SUM(G11:G14) -> 0 | H15: =SUM(D15:G15) -> 0
A16: REVENUE WATER - PREPAID
A17: Individuals | C17: m3 | D17: =Mangochi!J17+Mangochi!K17+Mangochi!L17 -> 0 | E17: ='Monkey Bay'!J17+'Monkey Bay'!K17+'Monkey Bay'!L17 -> 0 | F17: =Namwera!J17+Namwera!K17+Namwera!L17 -> 0 | G17: =Nkhudzi!J17+Nkhudzi!K17+Nkhudzi!L17 -> 0 | H17: =SUM(D17:G17) -> 0
A18: CWPs | C18: m3 | D18: =Mangochi!J18+Mangochi!K18+Mangochi!L18 -> 0 | E18: ='Monkey Bay'!J18+'Monkey Bay'!K18+'Monkey Bay'!L18 -> 0 | F18: =Namwera!J18+Namwera!K18+Namwera!L18 -> 0 | G18: =Nkhudzi!J18+Nkhudzi!K18+Nkhudzi!L18 -> 0 | H18: =SUM(D18:G18) -> 0
A19: Institutions | C19: m3 | D19: =Mangochi!J19+Mangochi!K19+Mangochi!L19 -> 0 | E19: ='Monkey Bay'!J19+'Monkey Bay'!K19+'Monkey Bay'!L19 -> 0 | F19: =Namwera!J19+Namwera!K19+Namwera!L19 -> 0 | G19: =Nkhudzi!J19+Nkhudzi!K19+Nkhudzi!L19 -> 0 | H19: =SUM(D19:G19) -> 0
A20: Commercial/Industrial | C20: m3 | D20: =Mangochi!J20+Mangochi!K20+Mangochi!L20 -> 0 | E20: ='Monkey Bay'!J20+'Monkey Bay'!K20+'Monkey Bay'!L20 -> 0 | F20: =Namwera!J20+Namwera!K20+Namwera!L20 -> 0 | G20: =Nkhudzi!J20+Nkhudzi!K20+Nkhudzi!L20 -> 0 | H20: =SUM(D20:G20) -> 0
A21: Total Volume Prepaid | C21: m3 | D21: =SUM(D17:D20) -> 0 | E21: =SUM(E17:E20) -> 0 | F21: =SUM(F17:F20) -> 0 | G21: =SUM(G17:G20) -> 0 | H21: =SUM(D21:G21) -> 0
A22: TOTAL REVENUE WATER | C22: m3 | D22: =D21+D15 -> 0 | E22: =E21+E15 -> 0 | F22: =F21+F15 -> 0 | G22: =G21+G15 -> 0 | H22: =SUM(D22:G22) -> 0
A23: NON-REVENUE WATER (NRW)
A24: Non-Revenue Water (NRW) | B24: Volume | C24: m3 | D24: =D9-D22 -> 0 | E24: =E9-E22 -> 0 | F24: =F9-F22 -> 0 | G24: =G9-G22 -> 0 | H24: =H9-H22 -> 0
B25: Percentage | C25: % | D25: =D24/D9 -> #DIV/0! | E25: =E24/E9 -> #DIV/0! | F25: =F24/F9 -> #DIV/0! | G25: =G24/G9 -> #DIV/0! | H25: =H24/H9 -> #DIV/0!
A26: OPERATING EXPENSES
A27: Chemicals
A28: Chemical | B28: Rate(MK/kg)
A29: Chlorine | B29: 3525.29 | C29: kg | D29: =Mangochi!J29+Mangochi!K29+Mangochi!L29 -> 0 | E29: ='Monkey Bay'!J29+'Monkey Bay'!K29+'Monkey Bay'!L29 -> 0 | F29: =Namwera!J29+Namwera!K29+Namwera!L29 -> 0 | G29: =Nkhudzi!J29+Nkhudzi!K29+Nkhudzi!L29 -> 0 | H29: =SUM(D29:G29) -> 0
C30: kg/mg litre | D30: =D29/(D9/1000) -> #DIV/0! | E30: =E29/(E9/1000) -> #DIV/0! | F30: =F29/(F9/1000) -> #DIV/0! | G30: =G29/(G9/1000) -> #DIV/0! | H30: =H29/(H9/1000) -> #DIV/0!
A31: Aluminium sulphate | B31: 1060.0102 | C31: kg | D31: =Mangochi!J31+Mangochi!K31+Mangochi!L31 -> 0 | E31: ='Monkey Bay'!J31+'Monkey Bay'!K31+'Monkey Bay'!L31 -> 0 | F31: =Namwera!J31+Namwera!K31+Namwera!L31 -> 0 | G31: =Nkhudzi!J31+Nkhudzi!K31+Nkhudzi!L31 -> 0 | H31: =SUM(D31:F31) -> 0
C32: kg/mg litre | D32: =D31/(D9/1000) -> #DIV/0! | E32: =E31/(E9/1000) -> #DIV/0! | F32: =F31/(F9/1000) -> #DIV/0! | G32: =Nkhudzi!J32+Nkhudzi!K32+Nkhudzi!L32 -> #DIV/0! | H32: =H31/(H9/1000) -> #DIV/0!
A33: Soda | B33: 1228.2886 | C33: kg | D33: =Mangochi!J33+Mangochi!K33+Mangochi!L33 -> 0 | E33: ='Monkey Bay'!J33+'Monkey Bay'!K33+'Monkey Bay'!L33 -> 0 | F33: =Namwera!J33+Namwera!K33+Namwera!L33 -> 0 | G33: =Nkhudzi!J33+Nkhudzi!K33+Nkhudzi!L33 -> 0 | H33: =SUM(D33:F33) -> 0
C34: kg/mg litre | D34: =D33/(D9/1000) -> #DIV/0! | E34: =E33/(E9/1000) -> #DIV/0! | F34: =F33/(F9/1000) -> #DIV/0! | G34: =Nkhudzi!J34+Nkhudzi!K34+Nkhudzi!L34 -> #DIV/0! | H34: =H33/(H9/1000) -> #DIV/0!
A35: Algae floc | B35: 3726.7258 | C35: litres | D35: =Mangochi!J35+Mangochi!K35+Mangochi!L35 -> 0 | E35: ='Monkey Bay'!J35+'Monkey Bay'!K35+'Monkey Bay'!L35 -> 0 | F35: =Namwera!J35+Namwera!K35+Namwera!L35 -> 0 | G35: =Nkhudzi!J35+Nkhudzi!K35+Nkhudzi!L35 -> 0
C36: litres/mg litre | G36: =Nkhudzi!J36+Nkhudzi!K36+Nkhudzi!L36 -> 0
A37: Sud floc | B37: 3951.5936 | C37: litres | D37: =Mangochi!J37+Mangochi!K37+Mangochi!L37 -> 0 | E37: ='Monkey Bay'!J37+'Monkey Bay'!K37+'Monkey Bay'!L37 -> 0 | F37: =Namwera!J37+Namwera!K37+Namwera!L37 -> 0 | G37: =Nkhudzi!J37+Nkhudzi!K37+Nkhudzi!L37 -> 0 | H37: =SUM(D37:F37) -> 0
C38: litres/mg litre | D38: =D37/(D9/1000) -> #DIV/0! | E38: =E37/(E9/1000) -> #DIV/0! | F38: =F37/(F9/1000) -> #DIV/0! | G38: =Nkhudzi!J38+Nkhudzi!K38+Nkhudzi!L38 -> #DIV/0! | H38: =H37/(H9/1000) -> #DIV/0!
A39: Potasium permanganate | B39: 1950 | C39: kg | D39: =Mangochi!J39+Mangochi!K39+Mangochi!L39 -> 0 | E39: ='Monkey Bay'!J39+'Monkey Bay'!K39+'Monkey Bay'!L39 -> 0 | F39: =Namwera!J39+Namwera!K39+Namwera!L39 -> 0 | G39: =Nkhudzi!J39+Nkhudzi!K39+Nkhudzi!L39 -> 0 | H39: =SUM(D39:F39) -> 0
C40: kg/mg litre | D40: =D39/(D9/1000) -> #DIV/0! | E40: =E39/(E9/1000) -> #DIV/0! | F40: =F39/(F9/1000) -> #DIV/0! | G40: =Nkhudzi!J40+Nkhudzi!K40+Nkhudzi!L40 -> #DIV/0! | H40: =H39/(H9/1000) -> #DIV/0!
A41: Cost of Chemicals | C41: Mk | D41: =(D29*$B29)+(D31*$B31)+(D33*$B33)+(D35*$B35)+(D37*$B37)+(D39*$B39) -> 0 | E41: =(E29*$B29)+(E31*$B31)+(E33*$B33)+(E35*$B35)+(E37*$B37)+(E39*$B39) -> 0 | F41: =(F29*$B29)+(F31*$B31)+(F33*$B33)+(F35*$B35)+(F37*$B37)+(F39*$B39) -> 0 | G41: =(G29*$B29)+(G31*$B31)+(G33*$B33)+(G35*$B35)+(G37*$B37)+(G39*$B39) -> 0 | H41: =SUM(D41:G41) -> 0
A42: Cost/vol. Produced (chemicals) | C42: Mk/m3 | D42: =D41/D9 -> #DIV/0! | E42: =E41/E9 -> #DIV/0! | F42: =F41/F9 -> #DIV/0! | G42: =G41/G9 -> #DIV/0! | H42: =H41/H9 -> #DIV/0!
A43: Power
A44: Power Usage | C44: Kw | D44: =Mangochi!J44+Mangochi!K44+Mangochi!L44 -> 0 | E44: ='Monkey Bay'!J44+'Monkey Bay'!K44+'Monkey Bay'!L44 -> 0 | F44: =Namwera!J44+Namwera!K44+Namwera!L44 -> 0 | G44: =Nkhudzi!J44+Nkhudzi!K44+Nkhudzi!L44 -> 0 | H44: =SUM(D44:G44) -> 0
A45: Power/ Vol. Produced | C45: Kw/m3 | D45: =D44/D9 -> #DIV/0! | E45: =E44/E9 -> #DIV/0! | F45: =F44/F9 -> #DIV/0! | G45: =G44/G9 -> #DIV/0! | H45: =H44/H9 -> #DIV/0!
A46: Cost of Power | C46: Mk | D46: =Mangochi!J46+Mangochi!K46+Mangochi!L46 -> 58017 | E46: ='Monkey Bay'!J46+'Monkey Bay'!K46+'Monkey Bay'!L46 -> 58017 | F46: =Namwera!J46+Namwera!K46+Namwera!L46 -> 58017 | G46: =Nkhudzi!J46+Nkhudzi!K46+Nkhudzi!L46 -> 58017 | H46: =SUM(D46:G46) -> 232068
A47: Cost/vol. Produced | C47: Mk/m3 | D47: =D46/D9 -> #DIV/0! | E47: =E46/E9 -> #DIV/0! | F47: =F46/F9 -> #DIV/0! | G47: =G46/G9 -> #DIV/0! | H47: =H46/H9 -> #DIV/0!
A48: Plant and Vehicle Maintenance
A49: Distances covered | C49: km | D49: =Mangochi!J49+Mangochi!K49+Mangochi!L49 -> 0 | E49: ='Monkey Bay'!J49+'Monkey Bay'!K49+'Monkey Bay'!L49 -> 0 | F49: =Namwera!J49+Namwera!K49+Namwera!L49 -> 0 | G49: =Nkhudzi!J49+Nkhudzi!K49+Nkhudzi!L49 -> 0 | H49: =SUM(D49:G49) -> 0
A50: Fuel Used (litres) | C50: litres | D50: =Mangochi!J50+Mangochi!K50+Mangochi!L50 -> 0 | E50: ='Monkey Bay'!J50+'Monkey Bay'!K50+'Monkey Bay'!L50 -> 0 | F50: =Namwera!J50+Namwera!K50+Namwera!L50 -> 0 | G50: =Nkhudzi!J50+Nkhudzi!K50+Nkhudzi!L50 -> 0 | H50: =SUM(D50:G50) -> 0
A51: Cost of fuel | C51: Mk | D51: =Mangochi!J51+Mangochi!K51+Mangochi!L51 -> 0 | E51: ='Monkey Bay'!J51+'Monkey Bay'!K51+'Monkey Bay'!L51 -> 0 | F51: =Namwera!J51+Namwera!K51+Namwera!L51 -> 0 | G51: =Nkhudzi!J51+Nkhudzi!K51+Nkhudzi!L51 -> 0 | H51: =SUM(D51:G51) -> 0
A52: Maintenance | C52: Mk | D52: =Mangochi!J52+Mangochi!K52+Mangochi!L52 -> 0 | E52: ='Monkey Bay'!J52+'Monkey Bay'!K52+'Monkey Bay'!L52 -> 0 | F52: =Namwera!J52+Namwera!K52+Namwera!L52 -> 0 | G52: =Nkhudzi!J52+Nkhudzi!K52+Nkhudzi!L52 -> 0 | H52: =SUM(D52:G52) -> 0
A53: Salaries and Wages
A54: Staff Costs | C54: MK | D54: =Mangochi!J54+Mangochi!K54+Mangochi!L54 -> 0 | E54: ='Monkey Bay'!J54+'Monkey Bay'!K54+'Monkey Bay'!L54 -> 0 | F54: =Namwera!J54+Namwera!K54+Namwera!L54 -> 0 | G54: =Nkhudzi!J54+Nkhudzi!K54+Nkhudzi!L54 -> 0 | H54: =SUM(D54:G54) -> 0
A55: Wages | C55: MK | D55: =Mangochi!J55+Mangochi!K55+Mangochi!L55 -> 0 | E55: ='Monkey Bay'!J55+'Monkey Bay'!K55+'Monkey Bay'!L55 -> 0 | F55: =Namwera!J55+Namwera!K55+Namwera!L55 -> 0 | G55: =Nkhudzi!J55+Nkhudzi!K55+Nkhudzi!L55 -> 0 | H55: =SUM(D55:G55) -> 0
A56: Other Overhead Costs | C56: MK | D56: =Mangochi!J56+Mangochi!K56+Mangochi!L56 -> 0 | E56: ='Monkey Bay'!J56+'Monkey Bay'!K56+'Monkey Bay'!L56 -> 0 | F56: =Namwera!J56+Namwera!K56+Namwera!L56 -> 0 | G56: =Nkhudzi!J56+Nkhudzi!K56+Nkhudzi!L56 -> 0 | H56: =SUM(D56:G56) -> 0
A57: Operating Costs
A58: Total Operating Costs | C58: MK | D58: =D41+D46+D51+D52+D54+D55+D56 -> 58017 | E58: =E41+E46+E51+E52+E54+E55+E56 -> 58017 | F58: =F41+F46+F51+F52+F54+F55+F56 -> 58017 | G58: =G41+G46+G51+G52+G54+G55+G56 -> 58017 | H58: =SUM(D58:G58) -> 232068
A59: Cost/Vol. Produced | C59: Mk/m3 | D59: =D58/D9 -> #DIV/0! | E59: =E58/E9 -> #DIV/0! | F59: =F58/F9 -> #DIV/0! | G59: =G58/G9 -> #DIV/0! | H59: =H58/H9 -> #DIV/0!
A60: Cost/Vol. Billed | C60: Mk/m3 | D60: =D58/D22 -> #DIV/0! | E60: =E58/E22 -> #DIV/0! | F60: =F58/F22 -> #DIV/0! | G60: =G58/G22 -> #DIV/0! | H60: =H58/H22 -> #DIV/0!
A61: Permanent Staff Employed | C61: No | D61: =Mangochi!L61 -> 0 | E61: ='Monkey Bay'!L61 -> 0 | F61: =Namwera!L61 -> 0 | G61: =Nkhudzi!L61 -> 0 | H61: =SUM(D61:G61) -> 0
A62: Staff/Vol.1000m3 of Volume Produced/hour (12 hour day) | C62: No/1000m3 | D62: =(D61*1000*31)/D9 -> #DIV/0! | E62: =(E61*1000*31)/E9 -> #DIV/0! | F62: =(F61*1000*31)/F9 -> #DIV/0! | G62: =(G61*1000*31)/G9 -> #DIV/0! | H62: =(H61*1000*31)/H9 -> #DIV/0!
A63: Temporary Staff Employed | C63: No | D63: =Mangochi!L63 -> 0 | E63: ='Monkey Bay'!L63 -> 0 | F63: =Namwera!L63 -> 0 | G63: =Nkhudzi!L63 -> 0 | H63: =SUM(D63:G63) -> 0
A65: Water Connections and Disconnections
A66: New Individual Water Connections | B66: Brought Forward | C66: No | D66: =Mangochi!J66 -> 0 | E66: ='Monkey Bay'!J66 -> 0 | F66: =Namwera!J66 -> 0 | G66: =Nkhudzi!J66 -> 0 | H66: =SUM(D66:G66) -> 0
B67: Applied this Month | C67: No | D67: =Mangochi!J67+Mangochi!K67+Mangochi!L67 -> 0 | E67: ='Monkey Bay'!J67+'Monkey Bay'!K67+'Monkey Bay'!L67 -> 0 | F67: =Namwera!J67+Namwera!K67+Namwera!L67 -> 0 | G67: =Nkhudzi!J67+Nkhudzi!K67+Nkhudzi!L67 -> 0 | H67: =SUM(D67:G67) -> 0
B68: Done this Month Postpaid | C68: No | D68: =Mangochi!J68+Mangochi!K68+Mangochi!L68 -> 0 | E68: ='Monkey Bay'!J68+'Monkey Bay'!K68+'Monkey Bay'!L68 -> 0 | F68: =Namwera!J68+Namwera!K68+Namwera!L68 -> 0 | G68: =Nkhudzi!J68+Nkhudzi!K68+Nkhudzi!L68 -> 0 | H68: =SUM(D68:G68) -> 0
B69: Done this Month Prepaid | C69: No | D69: =Mangochi!J69+Mangochi!K69+Mangochi!L69 -> 0 | E69: ='Monkey Bay'!J69+'Monkey Bay'!K69+'Monkey Bay'!L69 -> 0 | F69: =Namwera!J69+Namwera!K69+Namwera!L69 -> 0 | G69: =Nkhudzi!J69+Nkhudzi!K69+Nkhudzi!L69 -> 0 | H69: =SUM(D69:G69) -> 0
B70: Total Done | C70: No | D70: =D68+D69 -> 0 | E70: =E68+E69 -> 0 | F70: =F68+F69 -> 0 | G70: =Nkhudzi!J70+Nkhudzi!K70+Nkhudzi!L70 -> 0 | H70: =SUM(D70:G70) -> 0
B71: Carried Forward | C71: No | D71: =D66+D67-D70 -> 0 | E71: =E66+E67-E70 -> 0 | F71: =F66+F67-F70 -> 0 | G71: =G66+G67-G70 -> 0 | H71: =H66+H67-H70 -> 0
A72: New Institutional Water Connections | B72: Brought Forward | C72: No | D72: =Mangochi!J72 -> 0 | E72: ='Monkey Bay'!J72 -> 0 | F72: =Namwera!J72 -> 0 | G72: =Nkhudzi!J72+Nkhudzi!K72+Nkhudzi!L72 -> 0 | H72: =SUM(D72:G72) -> 0
B73: Applied this Month | C73: No | D73: =Mangochi!J73+Mangochi!K73+Mangochi!L73 -> 0 | E73: ='Monkey Bay'!J73+'Monkey Bay'!K73+'Monkey Bay'!L73 -> 0 | F73: =Namwera!J73+Namwera!K73+Namwera!L73 -> 0 | G73: =Nkhudzi!J73+Nkhudzi!K73+Nkhudzi!L73 -> 0 | H73: =SUM(D73:G73) -> 0
B74: Done this Month Postpaid | C74: No | D74: =Mangochi!J74+Mangochi!K74+Mangochi!L74 -> 0 | E74: ='Monkey Bay'!J74+'Monkey Bay'!K74+'Monkey Bay'!L74 -> 0 | F74: =Namwera!J74+Namwera!K74+Namwera!L74 -> 0 | G74: =Nkhudzi!J74+Nkhudzi!K74+Nkhudzi!L74 -> 0 | H74: =SUM(D74:G74) -> 0
B75: Done this Month Prepaid | C75: No | D75: =Mangochi!J75+Mangochi!K75+Mangochi!L75 -> 0 | E75: ='Monkey Bay'!J75+'Monkey Bay'!K75+'Monkey Bay'!L75 -> 0 | F75: =Namwera!J75+Namwera!K75+Namwera!L75 -> 0 | G75: =Nkhudzi!J75+Nkhudzi!K75+Nkhudzi!L75 -> 0 | H75: =SUM(D75:G75) -> 0
B76: Total Done | C76: No | D76: =D74+D75 -> 0 | E76: =E74+E75 -> 0 | F76: =F74+F75 -> 0 | G76: =Nkhudzi!J76+Nkhudzi!K76+Nkhudzi!L76 -> 0 | H76: =SUM(D76:G76) -> 0
B77: Carried Forward | C77: No | D77: =D73+D74-D76 -> 0 | E77: =E73+E74-E76 -> 0 | F77: =F73+F74-F76 -> 0 | G77: =G73+G74-G76 -> 0 | H77: =H72+H73-H76 -> 0
A78: New Commercial/Industrial Water Connections | B78: Brought Forward | C78: No | D78: =Mangochi!J78 -> 0 | E78: ='Monkey Bay'!J78 -> 0 | F78: =Namwera!J78 -> 0 | G78: =Nkhudzi!J78+Nkhudzi!K78+Nkhudzi!L78 -> 0 | H78: =SUM(D78:F78) -> 0
B79: Applied this Month | C79: No | D79: =Mangochi!J79+Mangochi!K79+Mangochi!L79 -> 0 | E79: ='Monkey Bay'!J79+'Monkey Bay'!K79+'Monkey Bay'!L79 -> 0 | F79: =Namwera!J79+Namwera!K79+Namwera!L79 -> 0 | G79: =Nkhudzi!J79+Nkhudzi!K79+Nkhudzi!L79 -> 0 | H79: =SUM(D79:G79) -> 0
B80: Done this Month Postpaid | C80: No | D80: =Mangochi!J80+Mangochi!K80+Mangochi!L80 -> 0 | E80: ='Monkey Bay'!J80+'Monkey Bay'!K80+'Monkey Bay'!L80 -> 0 | F80: =Namwera!J80+Namwera!K80+Namwera!L80 -> 0 | G80: =Nkhudzi!J80+Nkhudzi!K80+Nkhudzi!L80 -> 0 | H80: =SUM(D80:G80) -> 0
B81: Done this Month Prepaid | C81: No | D81: =Mangochi!J81+Mangochi!K81+Mangochi!L81 -> 0 | E81: ='Monkey Bay'!J81+'Monkey Bay'!K81+'Monkey Bay'!L81 -> 0 | F81: =Namwera!J81+Namwera!K81+Namwera!L81 -> 0 | G81: =Nkhudzi!J81+Nkhudzi!K81+Nkhudzi!L81 -> 0 | H81: =SUM(D81:G81) -> 0
B82: Total Done | C82: No | D82: =D81+D80 -> 0 | E82: =E81+E80 -> 0 | F82: =F81+F80 -> 0 | G82: =Nkhudzi!J82+Nkhudzi!K82+Nkhudzi!L82 -> 0 | H82: =SUM(D82:G82) -> 0
B83: Carried Forward | C83: No | D83: =D78+D79-D82 -> 0 | E83: ='Monkey Bay'!J83+'Monkey Bay'!K83+'Monkey Bay'!L83 -> 0 | F83: =F78+F79-F82 -> 0 | G83: =G78+G79-G82 -> 0 | H83: =H78+H79-H82 -> 0
A84: New CWP | B84: Brought Forward | C84: No | D84: =Mangochi!J84 -> 0 | E84: ='Monkey Bay'!J84 -> 0 | F84: =Namwera!J84 -> 0 | G84: =Nkhudzi!J84+Nkhudzi!K84+Nkhudzi!L84 -> 0 | H84: =SUM(D84:G84) -> 0
B85: Applied this Month | C85: No | D85: =Mangochi!J85+Mangochi!K85+Mangochi!L85 -> 0 | E85: ='Monkey Bay'!J85+'Monkey Bay'!K85+'Monkey Bay'!L85 -> 0 | F85: =Namwera!J85+Namwera!K85+Namwera!L85 -> 0 | G85: =Nkhudzi!J85+Nkhudzi!K85+Nkhudzi!L85 -> 0 | H85: =SUM(D85:G85) -> 0
B86: Done this Month Postpaid | C86: No | D86: =Mangochi!J86+Mangochi!K86+Mangochi!L86 -> 0 | E86: ='Monkey Bay'!J86+'Monkey Bay'!K86+'Monkey Bay'!L86 -> 0 | F86: =Namwera!J86+Namwera!K86+Namwera!L86 -> 0 | G86: =Nkhudzi!J86+Nkhudzi!K86+Nkhudzi!L86 -> 0 | H86: =SUM(D86:G86) -> 0
B87: Done this Month Prepaid | C87: No | D87: =Mangochi!J87+Mangochi!K87+Mangochi!L87 -> 0 | E87: ='Monkey Bay'!J87+'Monkey Bay'!K87+'Monkey Bay'!L87 -> 0 | F87: =Namwera!J87+Namwera!K87+Namwera!L87 -> 0 | G87: =Nkhudzi!J87+Nkhudzi!K87+Nkhudzi!L87 -> 0 | H87: =SUM(D87:G87) -> 0
B88: Total Done | C88: No | D88: =D87+D86 -> 0 | E88: =E87+E86 -> 0 | F88: =F87+F86 -> 0 | G88: =Nkhudzi!J88+Nkhudzi!K88+Nkhudzi!L88 -> 0 | H88: =SUM(D88:G88) -> 0
B89: Carried Forward | C89: No | D89: =D84+D85-D88 -> 0 | E89: =E84+E85-E88 -> 0 | F89: =F84+F85-F88 -> 0 | G89: =G84+G85-G88 -> 0 | H89: =H84+H85-H88 -> 0
A90: Aggregated New Water connections | B90: Brought Forward | C90: No | D90: =D66+D72+D78+D84 -> 0 | E90: =E66+E72+E78+E84 -> 0 | F90: =F66+F72+F78+F84 -> 0 | G90: =G66+G72+G78+G84 -> 0 | H90: =SUM(D90:G90) -> 0
B91: Applied this Month | C91: No | D91: =D67+D73+D79+D85 -> 0 | E91: =E67+E73+E79+E85 -> 0 | F91: =F67+F73+F79+F85 -> 0 | G91: =G67+G73+G79+G85 -> 0 | H91: =SUM(D91:G91) -> 0
B92: Done this Month Postpaid | C92: No | D92: =D68+D74+D80+D86 -> 0 | E92: =E68+E74+E80+E86 -> 0 | F92: =F68+F74+F80+F86 -> 0 | G92: =G68+G74+G80+G86 -> 0 | H92: =SUM(D92:G92) -> 0
B93: Done this Month Prepaid | D93: =D69+D75+D81+D87 -> 0 | E93: =E69+E75+E81+E87 -> 0 | F93: =F69+F75+F81+F87 -> 0 | G93: =G69+G75+G81+G87 -> 0 | H93: =SUM(D93:G93) -> 0
B94: Total Done | C94: No | D94: =D93+D92 -> 0 | E94: =E93+E92 -> 0 | F94: =F93+F92 -> 0 | G94: =G93+G92 -> 0 | H94: =SUM(D94:G94) -> 0
B95: Carried Forward | C95: No | D95: =D90+D91-D94 -> 0 | E95: =E90+E91-E94 -> 0 | F95: =F90+F91-F94 -> 0 | G95: =G90+G91-G94 -> 0 | H95: =H90+H91-H94 -> 0
A97: Prepaid Metering
A98: Prepaid Meters Installed | C98: No | D98: =Mangochi!J98+Mangochi!K98+Mangochi!L98 -> 0 | E98: ='Monkey Bay'!J98+'Monkey Bay'!K98+'Monkey Bay'!L98 -> 0 | F98: =Namwera!J98+Namwera!K98+Namwera!L98 -> 0 | G98: =Nkhudzi!J98+Nkhudzi!K98+Nkhudzi!L98 -> 0 | H98: =SUM(D98:G98) -> 0
A100: Active and Disconnected Accounts
A101: Disconnected Individual Accounts | C101: No | D101: =Mangochi!L101 -> 0 | E101: ='Monkey Bay'!L101 -> 0 | F101: =Namwera!L101 -> 0 | G101: =Nkhudzi!L101 -> 0 | H101: =SUM(D101:G101) -> 0
A102: Disconnected institutional Accounts | C102: No | D102: =Mangochi!L102 -> 0 | E102: ='Monkey Bay'!L102 -> 0 | F102: =Namwera!L102 -> 0 | G102: =Nkhudzi!L102 -> 0 | H102: =SUM(D102:G102) -> 0
A103: Disconnected Commercial/Industrial Accounts | C103: No | D103: =Mangochi!L103 -> 0 | E103: ='Monkey Bay'!L103 -> 0 | F103: =Namwera!L103 -> 0 | G103: =Nkhudzi!L103 -> 0 | H103: =SUM(D103:G103) -> 0
A104: Disconnected CWP | C104: No | D104: =Mangochi!L104 -> 0 | E104: ='Monkey Bay'!L104 -> 0 | F104: =Namwera!L104 -> 0 | G104: =Nkhudzi!L104 -> 0 | H104: =SUM(D104:G104) -> 0
A105: Total Disconnected Accounts | C105: No | D105: =SUM(D101:D104) -> 0 | E105: =SUM(E101:E104) -> 0 | F105: =SUM(F101:F104) -> 0 | G105: =SUM(G101:G104) -> 0 | H105: =SUM(H101:H104) -> 0
...

Sheet 4th QTR
A1: SOUTHERN REGION WATER BOARD
A3: MONTHLY REPORTS - 2025/2026
A4: MANGOCHI ZONE
A5: MANGOCHI ZONE
A7: PARAMETERS | C7: UNITS | D7: Mangochi | E7: Monkey Bay | F7: Namwera | G7: Nkhudzi | H7: TOTALS
A8: PRODUCTION
A9: Volume Produced | C9: m3 | D9: =Mangochi!M9+Mangochi!N9+Mangochi!O9 -> 0 | E9: ='Monkey Bay'!M9+'Monkey Bay'!N9+'Monkey Bay'!O9 -> 0 | F9: =Namwera!M9+Namwera!N9+Namwera!O9 -> 0 | G9: =Nkhudzi!M9+Nkhudzi!N9+Nkhudzi!O9 -> 0 | H9: =SUM(D9:G9) -> 0
A10: REVENUE WATER - POSTPAID
A11: Volume Billed Individuals | C11: m3 | D11: =Mangochi!M11+Mangochi!N11+Mangochi!O11 -> 0 | E11: ='Monkey Bay'!M11+'Monkey Bay'!N11+'Monkey Bay'!O11 -> 0 | F11: =Namwera!M11+Namwera!N11+Namwera!O11 -> 0 | G11: =Nkhudzi!M11+Nkhudzi!N11+Nkhudzi!O11 -> 0 | H11: =SUM(D11:G11) -> 0
A12: Volume Billed CWPs | C12: m3 | D12: =Mangochi!M12+Mangochi!N12+Mangochi!O12 -> 0 | E12: ='Monkey Bay'!M12+'Monkey Bay'!N12+'Monkey Bay'!O12 -> 0 | F12: =Namwera!M12+Namwera!N12+Namwera!O12 -> 0 | G12: =Nkhudzi!M12+Nkhudzi!N12+Nkhudzi!O12 -> 0 | H12: =SUM(D12:G12) -> 0
A13: Volume Billed Institutions | C13: m3 | D13: =Mangochi!M13+Mangochi!N13+Mangochi!O13 -> 0 | E13: ='Monkey Bay'!M13+'Monkey Bay'!N13+'Monkey Bay'!O13 -> 0 | F13: =Namwera!M13+Namwera!N13+Namwera!O13 -> 0 | G13: =Nkhudzi!M13+Nkhudzi!N13+Nkhudzi!O13 -> 0 | H13: =SUM(D13:G13) -> 0
A14: Volume Billed Commercial/Industrial | C14: m3 | D14: =Mangochi!M14+Mangochi!N14+Mangochi!O14 -> 0 | E14: ='Monkey Bay'!M14+'Monkey Bay'!N14+'Monkey Bay'!O14 -> 0 | F14: =Namwera!M14+Namwera!N14+Namwera!O14 -> 0 | G14: =Nkhudzi!M14+Nkhudzi!N14+Nkhudzi!O14 -> 0 | H14: =SUM(D14:G14) -> 0
A15: Total Volume Billed Post Paid | C15: m3 | D15: =SUM(D11:D14) -> 0 | E15: =SUM(E11:E14) -> 0 | F15: =SUM(F11:F14) -> 0 | G15: =SUM(G11:G14) -> 0 | H15: =SUM(D15:G15) -> 0
A16: REVENUE WATER - PREPAID
